Workbook

Sheet Лист1
A1: Этап | B1: № | C1: Название критерия | D1: Prompt
A2: Установление контакта | B2: 1 | C2: 1. Приветствие и установление контакта | D2: Проверь, сказал ли Продавец в начале звонка фразы, близкие по смыслу к следующему: - «Здравствуйте, [Имя клиента], это [Имя Продавца] из Sternmeister», я менеджер приемной комиссии SternMeister» Структура и точное совпадение с фразами из примеров неважны, главное, чтобы было приветствие [1] – Всё названное соблюдено. [0] – Приветствия не было. [Пусто] – Начало разговора отсутствует. Важно: перед оценкой проверь корректность ролей. Продавец — сотрудник компании Sternmeister (в транскрипции может быть “Стармейстер”, “Стернмейстер”, “Стенмейстер”), предлагающий и продающий Клиенту курс обучения на бухгалтера в Германии.
B3: 2 | C3: 2. Озвучен план разговора (программирование) | D3: Проверь, дал ли Продавец Клиенту чёткое понимание, как будет строиться разговор. Он должен был проговорить следующие три смысловых блока (не обязательно дословно, главное — по смыслу): – Задам несколько вопросов, чтобы понять, насколько подходим друг другу – Расскажу про курс – Договоримся, что если всё подойдёт, определимся по дальнейшим шагам [1] – Все три смысловых блока озвучены или переформулированы близко по смыслу. Продавец озвучил продолжительность разговора, дал структуру разговора, подготовил Клиента к последующим этапам. [0] – Один или несколько смысловых блоков не были сказаны, либо структура программирования нарушена. В ответе опиши, какие части были пропущены, искажены или недостаточно выражены. [Пусто] – Если в транскрипции отсутствует момент, когда Продавец мог бы озвучить план разговора (например, звонок прервался раньше этого момента). Важно: перед оценкой проверь корректность ролей. Продавец — сотрудник компании Sternmeister (в транскрипции может быть “Стармейстер”, “Стернмейстер”, “Стенмейстер”), предлагающий и продающий Клиенту курс обучения на бухгалтера в Германии.
B4: 3 | C4: 3. Корректная отработка вопроса о стоимости (если он прозвучал) | D4: Проверь, задал ли Клиент вопрос о стоимости до того, как Продавец выяснил его потребности, запрос или цели, и если да — как Продавец отреагировал. По скрипту Sternmeister, в начале звонка Продавец не должен сразу озвучивать цену, а мягко “отложить” этот вопрос, чтобы сначала понять потребности, запрос, цели Клиента. [1] – Клиент задал вопрос о цене до этапа выяснения запроса, и Продавец корректно отработал его: перенёс обсуждение стоимости на потом, мотивировав это необходимостью сначала разобраться в ситуации Клиента. Формулировки могут быть любыми по смыслу. [0] – Продавец начал обсуждать цену сразу или допустил обсуждение возражений на этом этапе. Либо проигнорировал вопрос без осознанного переноса. В ответе укажи, как прозвучал вопрос, как отреагировал на него Продавец и как отреагировал Клиент. [Пусто] – Вопрос о стоимости не поднимался в начале разговора. Важно: перед оценкой проверь корректность ролей. Продавец — сотрудник компании Sternmeister (в транскрипции может быть “Стармейстер”, “Стернмейстер”, “Стенмейстер”), предлагающий и продающий Клиенту курс обучения на бухгалтера в Германии.
B5: 4 | C5: 4. Корректная отработка вопроса о JobCenter (если он прозвучал) | D5: Проверь, во всем разговоре задал ли Клиент вопрос в любой форме о финансировании оплаты курсов через Jobcenter (например, спросил про Gutschein, Berater, субсидию и т. п.), и если задал — как Продавец отреагировал. [1] – Продавец корректно отреагировал: – подтвердил, что можно получить финансирование на курс SternMeister – отметил, что для получения финансирования необходимо подходить под следующие критерии: - готовность заниматься фольцайт (полный день от 12:00 до 20:00), - уровень языка В1+, - среднее специальное образование - возраст до 55 лет - стоять на учете в Джоб Центре или в Агентур фюр Арбайт - обязательно, чтобы человек не работал - доход в семье был не больше 3000 евро – и задал уточняющий вопрос о том, подходит ли Клиент под эти критерии, тем самым, дав возможность Клиенту самому сказать, что он не подходит (в случае, если это так) [0] – Продавец допустил некорректную реакцию: – сказал, что компания Продавца не работает с JobCenter или, что Клиенту не одобрят финансирование, например: “нет возможности через Jobcenter”, “мы с ними не работаем”, "вы не подходите под требования, вам не одобрят финансирование" [Пусто] – Тема Jobcenter и финансирования через субсидии не поднималась в разговоре. Важно: перед оценкой проверь корректность ролей. Продавец — сотрудник компании Sternmeister (в транскрипции может быть “Стармейстер”, “Стернмейстер”, “Стенмейстер”), предлагающий и продающий Клиенту курс обучения на бухгалтера в Германии.
A6: Выявление потребностей | B6: 5 | C6: 5. Small talk и установление контакта | D6: Проверь, выяснил ли Продавец, чем Клиент занимается сейчас и кем работал раньше. Этот этап помогает наладить контакт и запустить диалог. Продавец должен был задать вопросы, или Клиент мог сам рассказать об этом в начале разговора. Пример по скрипту: «Расскажите, пожалуйста, немного о себе». [1] – Продавец задал общие вопросы, установил контакт с клиентом, перед тем, как перейти к вопросам по Точке А и Точке В или Клиент сообщил сам: чем он занимается сейчас, кем работал раньше, сколько уже в Германии, в какой сфере. Допускаются любые формулировки по смыслу. [0] – Продавец не задал таких вопросов и не проявил интереса к опыту Клиента, а сам Клиент об этом ничего не рассказал. В ответе опиши, что именно выяснено, а что было упущено. [Пусто] – Разговор не дошёл до момента знакомства и обсуждения опыта. Важно: перед оценкой проверь корректность ролей. Продавец — сотрудник компании Sternmeister (в транскрипции может быть “Стармейстер”, “Стернмейстер”, “Стенмейстер”), предлагающий и продающий Клиенту курс обучения на бухгалтера в Германии.
B7: 6 | C7: 6. Точка А (выявить и усилить боль) | D7: Проверь, выяснил ли Продавец ключевые элементы Точки А, задавая вопросы или активно слушая Клиента. Структура Точки А включает: – опыт Клиента – текущая ситуация Клиента и что именно в ней не устраивает Клиента – какие попытки уже предпринимались Клиентом, чтобы изменить ситуацию – каким Клиент видит идеальное решение Важно: Продавец может задавать любые вопросы, которые помогают выявить эти пункты. Допустима ситуация, когда Клиент сам обо всём рассказывает — в этом случае Продавец должен проявить активное слушание. [1] – Продавец получил ответы на все 4 элемента фрейма Точки А: опыт, текущая ситуация, попытки изменить ситуацию, идеальное решение. Информация может быть получена как в результате вопросов, так и из рассказа Клиента. [0] – Продавец не проявил интереса к опыту Клиента, не задал ни одного вопроса, который выявил бы ответы на названные пункты, и сам Клиент ничего о себе не рассказал. [Пусто] – Разговор не дошёл до этапа знакомства и обсуждения ситуации Клиента (например, прервался раньше). Важно: перед оценкой проверь корректность ролей. Продавец — сотрудник компании Sternmeister (в транскрипции может быть “Стармейстер”, “Стернмейстер”, “Стенмейстер”), предлагающий и продающий Клиенту курс обучения на бухгалтера в Германии.
B8: 7 | C8: 7. Ситуативные вопросы в Точке А | D8: Проверь, задал ли Продавец вопрос про текущую ситуацию Клиента и о том, какие попытки были изменить текущую ситуацию. В данном критерии, мы проверяем задал ли Продавец уточнящющие вопросы про влияние текущей ситуации Клиента на его жизнь или отношения с семьей, если да, то спросил ли продавец в каких ситуациях и как это проявляется: [1] – Продавец, для уточнения влияния текущей ситуации Клиента на жизнь Клиента, задал вопросы близкие по смыслу в любой формулировке, например: "Как текущая ситуация сказывается на жизни/на ваши отношения с семьей/женой/мужем/детьми (в зависимости от ситуации)" или "Если и в течение следующего года ничего не поменяется - вы к этому готовы Или внутри уже нет сил ждать еще, пока все сдвинется" [0] – Продавец не задал вопросы на уточнениие влияния текущей ситуации Клиента на жизнь Клиента или не спросил готов ли Клиент к тому, чтобы в течение следующего года ничего не поменялось [Пусто] – Разговор не дошёл до этапа знакомства и обсуждения ситуации Клиента (например, прервался раньше). Важно: перед оценкой проверь корректность ролей. Продавец — сотрудник компании Sternmeister (в транскрипции может быть “Стармейстер”, “Стернмейстер”, “Стенмейстер”), предлагающий и продающий Клиенту курс обучения на бухгалтера в Германии.
B9: 8 | C9: 8. Точка В (ожидания, готовность, срочность) | D9: Проверь, выяснил ли Продавец ключевые элементы Точки В, задавая вопросы или активно слушая Клиента. Структура Точки В должна соответствовать технике SMART и включать: – конкретную цель Клиента – измеримый результат — уровень дохода, который хочет получать Клиент – значимость цели — вторичные цели Клиента, например: «чтобы стать финансово независимой», «чтобы чувствовать себя полноценной», «чтобы уйти от быта и выйти на работу», «чтобы контролировать лучше свой бизнес и не допускать потерь», «чтобы обеспечить себе и/или семье и/или своему ребенку лучшее будущее», «чтобы поменять параграф и получить ВНЖ/ПМЖ в Германии» и т.д. – срок достижения цели — когда Клиент хочет выйти на результат Продавец может задавать любые вопросы, которые помогают выявить пункты фрейма Точки Б. Допустима ситуация, когда Клиент сам обо всём рассказывает — в этом случае Продавец должен проявить активное слушание. Также проверь, использовал ли Продавец в этом блоке реплики-презентации, показывая, что курс компании Sternmeister помогает достичь заявленной цели (например: “вот именно поэтому у нас предусмотрена стажировка, чтобы вы быстрее нашли работу”). [1] – Продавец получил ответы на все 4 элемента SMART-структуры: цель, доход, значимость и срок. Информация может быть получена как в результате вопросов, так и из рассказа Клиента. [0] – Продавец не получил информацию хотя бы по одному из четырёх пунктов фрейма Точки Б по технике SMART. [Пусто] – Разговор не дошёл до этапа обсуждения целей Клиента (например, прервался раньше). Важно: перед оценкой проверь корректность ролей. Продавец — сотрудник компании Sternmeister (в транскрипции может быть “Стармейстер”, “Стернмейстер”, “Стенмейстер”), предлагающий и продающий Клиенту курс обучения на бухгалтера в Германии.
B10: 9 | C10: 9. Уточнение SMART-целей Клиента | D10: Проверь, как Продавец отреагировал, если Клиент дал расплывчатый ответ хотя бы по одному из пунктов SMART-структуры: – конкретная цель (например: «не знаю», «просто хочу что-то поменять», «ну как получится») – измеримый результат — уровень дохода (например: «чем больше, тем лучше», «не думал(а)», «не знаю») – значимость цели — мотивация и вторичные цели (например: «просто интересно», «ну как у всех», «да не знаю зачем») – срок достижения цели (например: «не ставила себе такие цели», «не задумывалась», «как получится», «чем скорее, тем лучше») Продавец должен мягко уточнить и помочь Клиенту сформулировать цель конкретно. Допускаются любые формулировки по смыслу. Примеры корректных уточнений: – “Чтобы понять, насколько вам подходит курс, давайте прикинем хотя бы ориентир...” – “Это поможет построить чёткий карьерный план...” – “Давайте представим, что всё получилось — как скоро вы бы хотели выйти на такой результат” – “Понимаю, что хочется всё и сразу, но всё же — какой уровень дохода будет для вас реальным и комфортным” [1] – Продавец получил расплывчатый ответ хотя бы по одному из пунктов SMART и помог Клиенту его уточнить. В ответе опиши: – по каким пунктам SMART ответ Клиента был неконкретным – как именно Продавец уточнил – удалось ли прийти к конкретной формулировке [0] – Продавец принял расплывчатый ответ без попытки уточнить, не довёл до конкретики ни один из пунктов. [Пусто] – Цели Клиента и Точка Б не обсуждались (например, разговор прервался раньше). Важно: перед оценкой проверь корректность ролей. Продавец — сотрудник компании Sternmeister (в транскрипции может быть “Стармейстер”, “Стернмейстер”, “Стенмейстер”), предлагающий и продающий Клиенту курс обучения на бухгалтера в Германии.
B11: 10 | C11: 10. Преимущества профессии Бухгалтера | D11: Проверь, рассказал ли продавец на этапе выяснения Точки Б (цель клиента, результат который хочет клиент, сроки) о преимуществах профессии Бухгалтера в Германии, о социальном пакете, возможном карьерном росте и зарплатах, продавец обрисовал картину лучшего будущего и спросил что Клиент будет чувствовать, когда все это произойдет: [1] - Если продавец рассказал о преимуществах профессии Бухгалтера в Германии, минимум две из фраз ниже (или близкие по смыслу или своими словами): - "Годовой доход начинающих бухгалтеров составляет в среднем €47 000, а уже через 3 года на позиции финансового директора €69000 в год" - "Квалификация бухгалтера даст вам возможность найти работу как фестангештельте (штатный сотрудник), таким образом вы получите все преимущества поддержки от государства, итак, что изменилось в вашей жизни к лучшему или какие эмоции вы испытываете" - "У вас будут оплачиваемые больничные, премии, отпускные и уверенность, что вас точно не сократят в случае кризиса, а при банкротстве компании вы будете получать зарплату еще 6 месяцев, итак, что изменилось в вашей жизни к лучшему или какие эмоции вы испытываете" - "Давайте представим: у вас на руках немецкий диплом бухгалтера, вы выходите на новую работу. Вы работаете бухгалтером с 9 до 5 часов дня, с 2 полноценными выходными, с бесплатной медициной в хороших клиниках и с отпуском целый месяц в году, итак, что изменилось в вашей жизни к лучшему или какие эмоции вы испытываете" [0] – Продавец не рассказал про социальный пакет Бухгалтера в Германии или применил лишь одну из необходимых фраз (или близких по смыслу). [Пусто] – Разговор не дошёл до этапа обсуждения целей Клиента (например, прервался раньше). В обоснование выпиши какие именно фразы применил Продавец, как конкретно он их произнес и в каком контексте. Если Продавец применил лишь одну фразу - выпиши какую именно и в каком контексте. Укажи какие из необходимых фраз также были применимы в контексте диалога, но не были использованы Продавцом. Важно: перед оценкой проверь корректность ролей. Продавец — сотрудник компании Sternmeister (в транскрипции может быть “Стармейстер”, “Стернмейстер”, “Стенмейстер”), предлагающий и продающий Клиенту курс обучения на бухгалтера в Германии.
B12: 11 | C12: 11. Резюмирование целей и сроков перед презентацией | D12: Проверь, резюмировал ли Продавец ключевые моменты, которые обсудил с Клиентом: его текущую ситуацию (точка А), цели и желания (точка Б), а также сроки достижения результата. После резюмирования Продавец должен был получить подтверждение от Клиента, что всё верно, и только затем переходить к презентации курса. [1] – Продавец сказал, что хочет подытожить или проверить, правильно ли понял. Озвучил хотя бы в общем: – с какой ситуацией сейчас сталкивается Клиент – к чему он хочет прийти (цель, желаемая работа/доход) – обозначил или уточнил сроки (например, «в течение этого года») – задал вопрос, всё ли верно и/или предложил Клиенту дополнить Формулировки могут быть любыми по смыслу. [0] – Продавец не резюмировал ключевые точки, не подвёл итоги разговора и не получил подтверждение от Клиента. В ответе опиши, обсуждалась ли точка А и точка Б, и были ли предприняты попытки их подытожить. [Пусто] – Разговор не дошёл до момента перед презентацией, либо обрывается на этапе выявления потребностей. Важно: перед оценкой проверь корректность ролей. Продавец — сотрудник компании Sternmeister (в транскрипции может быть “Стармейстер”, “Стернмейстер”, “Стенмейстер”), предлагающий и продающий Клиенту курс обучения на бухгалтера в Германии.
A13: Презентация продукта | B13: 12 | C13: 12. Презентация проведена с опорой на цели и запрос Клиента | D13: Проверь, адаптировал ли Продавец презентацию курса под цели и запросы Клиента. Презентация должна отвечать на вопрос: почему именно этот курс помогает именно этому Клиенту достичь его цели. Продавец мог использовать любые формулировки, которые связывают содержание курса с ранее озвученными потребностями Клиента (например: «вы говорили, что хотите контролировать бухгалтерию в своём бизнесе — у нас есть модуль, где разбираем это», «вам важно понимать законы — поэтому у нас есть юридический блок» и т. п.). [1] – Продавец выяснил цели Клиента до начала презентации и в рассказе о курсе делал явные или неявные отсылки к ним. Использовал формулировки по смыслу: «вы говорили, что...», «в вашем случае...», «вам важно...», и связал контекст Клиента с содержанием программы курса. [0] – Продавец не выяснил цели Клиента до презентации или рассказывал про курс без привязки к его задачам, целям и пожеланиям. Презентация звучала обобщённо, без попытки показать, как курс помогает в конкретной ситуации Клиента. [Пусто] – Презентация курса не проводилась или разговор завершился до этого момента, (например, прервался раньше). Важно: перед оценкой проверь корректность ролей. Продавец — сотрудник компании Sternmeister (в транскрипции может быть “Стармейстер”, “Стернмейстер”, “Стенмейстер”), предлагающий и продающий Клиенту курс обучения на бухгалтера в Германии.
B14: 13 | C14: 13. Презентация проведена в формате диалога, с вовлечением Клиента | D14: Проверь, рассказывал ли Продавец о курсе в живом диалоге с Клиентом, а не в виде монолога. Он должен был задавать уточняющие или вовлекающие вопросы по ходу презентации, проверять интерес Клиента к отдельным темам, делать паузы для реакции. [1] – Презентация проходила в диалоге: Продавец задавал Клиенту вопросы по ходу рассказа, уточнял, что откликается, предлагал комментировать или делился примерами с вопросами типа “Вам бы это было полезно”, “А у вас было что-то похожее”. Формулировки могли быть разными по стилю. [0] – Продавец проводил презентацию в формате монолога, не задавая ни одного вопроса по ходу рассказа, не вовлекая Клиента и не создавая ощущение диалога. В ответе опиши, как именно шла подача — были ли реплики Клиента, на что Продавец реагировал. [Пусто] – Презентация курса не проводилась или разговор оборвался до неё. Важно: перед оценкой проверь корректность ролей. Продавец — сотрудник компании Sternmeister (в транскрипции может быть “Стармейстер”, “Стернмейстер”, “Стенмейстер”), предлагающий и продающий Клиенту курс обучения на бухгалтера в Германии.
A15: Предзакрытие и ФОМО | B15: 14 | C15: 14. Что откликнулось Клиенту в презентации и готовность клиента начать | D15: Проверь, задал ли Продавец вопрос о том, что из презентации оказалось наиболее важным или интересным для Клиента. [1] – Продавец задал любой из уточняющих вопросов (в любой формулировке, своими словами) из представленнных вопросов ниже: – “Что вам особенно откликнулось” – “Что показалось полезным или интересным” – "Что больше всего запомнилось" – ИЛИ Клиент сам по ходу презентации несколько раз проявлял интерес, называл, что именно ему подходит, говорил, что это про него. [0] – Продавец не задал уточняющий вопрос о том, что понравилось Клиенту В ответе опиши, звучала ли обратная связь или какая. [Пусто] – Презентация курса не проводилась или разговор прервался до этого момента. Важно: перед оценкой проверь корректность ролей. Продавец — сотрудник компании Sternmeister (в транскрипции может быть “Стармейстер”, “Стернмейстер”, “Стенмейстер”), предлагающий и продающий Клиенту курс обучения на бухгалтера в Германии."
B16: 15 | C16: 15. Предзакрытие, FOMO и тактика дефицита | D16: Проверь, как Продавец использует срочность и дефицит: создаёт обоснованное, правдоподобное, мягкое давление или давит агрессивно и неправдоподобно. [1] – Продавец создал FOMO эффект для Клиента (ощущение упущенной выгоды) через дефицит с отсылкой на реальные факты, сказав любую фразу создающую ограниченность предложения. Продавец не давит на страх или чувство вины. Давление воспринимается как мягкое и аргументированное. Вот несколько примеров подобных фраз, которые продавец может произнести близко по смыслу или своими словами, или сказав вообще другую фразу, но которая также создает эффект FOMO для Клиента: – «Сейчас у нас набирается группа, это последний поток перед перерывом. Если не попадете, следующая группа стартует только где-то через 3-4 месяца - это минус 4 месяца до вашей цели. В денежном эквиваленте это потеря €16 000» – «Дефицит бухгалтеров в Германии на максимуме сейчас, все рвутся, нужно успеть найти свое место, а то будет как в IT - кто не успел 10 лет назад, сейчас с 0 практически не может внедриться в эту сферу, а те, кто начали, сейчас получают по 10-15 тыс евро в месяц. Если начать сейчас в сфере бухгалтерии в Германии, через несколько лет можно будет вырасти до финансового директора и получать 10 000 евро в месяц» – «Стоимость следующего потока будет на 20% дороже, а на текущий осталось только определенное количество мест (например: 2 места или 3 места или 5 мест)» [0] – Продавец завершил презентацию не создав эффект FOMO для Клиента. Перешёл сразу к обсуждению цены и стоимости, к возражениям или просто завершил презентацию без предзакрытия. ИЛИ – Продавец использует жёсткое, неправдоподобное давление. Нет прозрачных оснований, происходит давление на страх, стыд или чувство неполноценности. Давление воспринимается как агрессивное и манипулятивное, Продавец пугает или торопит Клиента фразами вида: – «Вы так и хотите все жизнь сидеть на обеспечении от государства» – «Вы же не хотите так и работать на своей работе, время идёт» – «Пора уже решаться, а то поезд уйдёт» [Пусто] – Разговор не дошёл до конца презентации курса (например, прервался раньше) или тема сроков, повышения цен, набора в группу, количества мест и т.п. не обсуждается. В обосновании опиши, какие именно аргументы о срочности/дефиците использовал Продавец, выглядели ли они правдоподобно или манипулятивно, как реагировал Клиент, приведи 2–4 цитаты, где лучше всего слышно это давление или его отсутствие. Важно: перед оценкой проверь корректность ролей. Продавец — сотрудник компании Sternmeister (в транскрипции название может звучать как «Стармейстер», «Стернмейстер», «Стенмейстер»), предлагающий Клиенту курс обучения на бухгалтера в Германии.
B17: 16 | C17: 16. Реферальная программа | D17: Проверь, рассказал ли Продавец Клиенту о реферальной программе SternMeister и донёс ли ключевые условия. Учитывай эквиваленты по смыслу, даже если формулировки отличаются от скрипта. [1] – Продавец презентовал реферальную программу SternMeister. В разговоре прозвучали ключевые смысловые элементы: – Клиент получает вознаграждение за каждого приведённого друга/знакомого, который купит курс (с суммой 300 евро, выплачивается в течение 3 месяцев) – Продавец предложил конкретный следующий шаг (зафиксировать контакты сразу или отправить их сообщением позже). [0] – В разговоре реферальная программа упоминалась, но с существенными пробелами: – нет упоминания суммы вознаграждения – или не сказано, что реферал должен купить курс – или не объяснено, что делать Клиенту (нет предложения зафиксировать данные сейчас или отправить позже) – либо Продавец вообще не упомянул реферальную программу, хотя разговор дошёл до логичного завершения презентации курса и продажи. [Пусто] – Разговор закончился или оборвался до этапа презентации и продажи курса и у Продавца не было естественной возможности перейти к теме реферальной программы. В обосновании укажи – прозвучала ли реферальная программа и как именно её описал Продавец – была ли названа сумма вознаграждения и условие, что реферал должен купить курс – предлагал ли Продавец зафиксировать контакты сразу или отправить их позже и как на это отреагировал Клиент – общий вывод, насколько Клиент понял выгоду и конкретный следующий шаг по реферальной программе Важно: перед оценкой проверь корректность ролей. Продавец — сотрудник компании Sternmeister (в транскрипции может быть Стармейстер, Стернмейстер, Стенмейстер), предлагающий и продающий Клиенту курс обучения на бухгалтера в Германии.
A18: Отработка возражений | B18: 17 | C18: 17. Какие возражения озвучил Клиент (теги) | D18: [Тег] — данный критерий исключение. В качестве оценки, вместо [Тег], напиши все возражения, которые озвучил Клиент в разговоре, в виде списка тегов через запятую. Используй список тегов ниже. Если какое-то возражение не подходит ни под один из предложенных тегов — придумай новый тег, который точно отражает суть, и включи его в общий список. Если возражений не было, напиши: Тегов нет. В поле reasons укажи для каждого тега: – в какой момент прозвучало возражение (на каком этапе разговора) – как именно Клиент его сформулировал (дословно или по смыслу) – в каком тоне это прозвучало (уверенно, сомневаясь, с интересом, с раздражением и т.д.) Список тегов: дорого — клиент считает, что курс стоит слишком много нет времени — клиент не может начать из-за загруженности или нестабильного графика немецкий язык — клиент беспокоится, что не знает язык и не сможет пройти обучение или работать онлайн обучение — клиент не доверяет формату онлайн-обучения или считает его неудобным подумаю — клиент не готов принять решение и говорит, что подумает посоветуюсь — клиент говорит, что нужно посоветоваться (с супругом, семьёй и т.д.) не сейчас — клиент говорит, что не планирует начинать обучение в ближайшее время неуверенность в себе — клиент сомневается в своих силах или способностях не подходит программа — клиенту не подходит содержание курса, предметы, длительность и т.д. сомнения в трудоустройстве — клиент не верит, что после обучения сможет найти работу уже есть опыт — клиент говорит, что уже работает бухгалтером или имеет нужные знания нет уверенности в компании — клиент не доверяет Sternmeister, говорит, что не нашёл отзывов, сайта и т.д. сравнивает с конкурентами — клиент упоминает, что рассматривает другие курсы формат не подходит — клиенту не подходит график занятий, записи, онлайн-встречи не хочет менять профессию — клиент говорит, что передумал менять сферу или не уверен мало информации — клиент говорит, что недостаточно информации, чтобы принять решение сомнения в сертификате — клиент не понимает или не уверен в ценности сертификата AZAV нет денег — клиент говорит, что сейчас не может позволить себе оплату курса всё понятно — клиент говорит, что уже всё знает, ему не интересны объяснения причины не названы — клиент возражает, но не может объяснить причину, уклоняется от ответа
B19: 18 | C19: 18. Отработка возражений по структуре | D19: Проверь, отработал ли Продавец возражения Клиента по структуре: сначала уточнение, затем аргументация, и попытка определить, какое из возражений является ключевым. Для первого возражения важно, чтобы Продавец начал отработку с уточняющего вопроса о том, является ли это единственным препятствием для принятия решения. Примеры вопросов по смыслу: – «[Имя клиента], это единственный момент, который сейчас мешает начать» – «[Имя клиента], это основная причина, по которой сейчас сложно принять решение» Точное совпадение формулировок не требуется. Главное — Продавец по смыслу уточнил, является ли это возражение единственным и решающим. Если в разговоре возникало несколько возражений, дальнейшая отработка должна начинаться с уточнения, какое из них является ключевым. Примеры по смыслу: – «[Имя клиента], а что для вас сейчас важнее — [первое возражение] или [второе возражение]» Формулировки могут быть любыми. Важно, чтобы Продавец пытался определить главное возражение, а не отрабатывал их хаотично. [1] – Продавец отработал все возражения Клиента по структуре: – при первом возражении уточнил, является ли это единственной причиной, мешающей принятию решения; – при появлении последующих возражений попытался выяснить, какое из них ключевое; – дал аргументацию в ответ на слова Клиента, направленную на снятие сомнений или опасений. [0] – Продавец не отработал возражения по структуре: не уточнил, является ли возражение ключевым, не попытался определить главное ограничение или не дал аргументации для снятия сомнений Клиента. [Пусто] – Возражений со стороны Клиента не было. Важно: в обосновании выпиши: – какие возражения прозвучали; – как именно на них реагировал Продавец; – как отреагировал Клиент. Важно: перед оценкой проверь корректность ролей. Продавец — сотрудник компании Sternmeister (в транскрипции может быть «Стармейстер», «Стернмейстер», «Стенмейстер»), предлагающий и продающий Клиенту курс обучения на бухгалтера в Германии.
B20: 19 | C20: 19. Продавец корректно отработал ложные возражения (“подумаю”, “посоветуюсь”, “не сейчас”) | D20: Проверь, как Продавец отреагировал на так называемые ложные возражения — “подумаю”, “посоветуюсь”, “не сейчас” и т. д. По скрипту Sternmeister, в таких случаях нужно использовать технику “искренность” — спокойно и честно задать уточняющий вопрос, чтобы вскрыть настоящую причину сомнений Клиента. При отработке каждого возражения в конце Продавец должен делать персонализированный призыв к действию (например: “в этом случае могу предложить…”, “тогда предлагаю такой вариант, чтобы было комфортно”, "давайте тогда договоримся так...", "предлагаю согласовать ...", и т.д., в зависимости от цели данного конкретного клиента, допустимо в вопросительной форме) [1] – Продавец отреагировал на ложное возражение по структуре: – не ушёл от темы и не закрыл разговор – задал уточняющий вопрос (“что именно смущает”, “в чём именно хотите посоветоваться”, “что бы позволило вам принять решение сейчас”) – попытался вывести Клиента на настоящее возражение – В конце отработки возражения Продавец сделал персонализированный призыв Клиента к действию Если Клиент назвал настоящую причину — выпиши её. [0] – Продавец проигнорировал или быстро закрыл тему, не задал уточняющий вопрос, не попробовал прояснить, что стоит за фразой “подумаю” и т. д. В ответе укажи: – какие ложные возражения прозвучали – как Продавец на них отреагировал – удалось ли перейти к реальному возражению [Пусто] – Ложных возражений не было в разговоре. Важно: перед оценкой проверь корректность ролей. Продавец — сотрудник компании Sternmeister (в транскрипции может быть “Стармейстер”, “Стернмейстер”, “Стенмейстер”), предлагающий и продающий Клиенту курс обучения на бухгалтера в Германии.
B21: 20 | C21: 20. Какие техники отработки возражений стоило бы применить Продавцу | D21: [Рекомендация] - данный критерий исключение, в качестве оценки напиши слово Рекомендация, а в обосновании оценки reason напиши следующее: А) Проанализируй, как Продавец отрабатывал возражения в этом звонке: – какие конкретно возражения звучали – как на них реагировал Продавец – какие ошибки или недочёты он допустил (например, отсутствие присоединения, уточнения, слабые аргументы, уход от темы) Б) Разбери звонок с точки зрения 2–3 современных международных методик продаж (актуальных на 2025 год): – выбери подходящие модели (например: SPIN, Challenger, GAP, NEAT, Sandler) – объясни, как каждая из них помогает понять слабые места в отработке – укажи, какие принципы этих методик были не соблюдены и как это повлияло на реакцию Клиента В) Для каждой из выбранных методик предложи 1–2 примера фраз или вопросов, которые мог бы использовать Продавец в этой ситуации. Для каждой фразы укажи: – на какое возражение она направлена – к какой методике относится – почему эта формулировка была бы эффективнее (объясни с опорой на метод) Заверши ответ объяснением, как предложенные подходы могли бы помочь Продавцу: – укрепить доверие Клиента – выявить настоящую причину отказа – продвинуть диалог к принятию решения Важно: перед оценкой проверь корректность ролей. Продавец — сотрудник компании Sternmeister (в транскрипции может быть “Стармейстер”, “Стернмейстер”, “Стенмейстер”), предлагающий и продающий Клиенту курс обучения на бухгалтера в Германии.
B22: 21 | C22: 21. Как Продавец отработал вопросы Клиента (не только возражения) | D22: [Рекомендация] - данный критерий исключение, в качестве оценки напиши слово Рекомендация, а в обосновании оценки reason напиши следующее: А) Выпиши все вопросы, которые задал Клиент по ходу разговора (если были). Укажи, на каком этапе они прозвучали и с чем были связаны (цена, формат, сертификат, длительность и т. д.) Б) Для каждого вопроса укажи, дал ли Продавец понятный, конкретный и прямой ответ. Если ответ был неполным, не по сути или отложен "на потом", укажи это. В) Если какие-либо вопросы остались без ответа — выпиши их и предложи, как бы Продавец мог ответить на них лучше. Сформулируй ответную реплику, которая могла бы: – развеять сомнение – дать конкретику – или перевести Клиента к следующему шагу Оцени, повлияли ли неотвеченные вопросы на дальнейший ход разговора. Важно: перед оценкой проверь корректность ролей. Продавец — сотрудник компании Sternmeister (в транскрипции может быть “Стармейстер”, “Стернмейстер”, “Стенмейстер”), предлагающий и продающий Клиенту курс обучения на бухгалтера в Германии.
A23: Этап оплаты | B23: 22 | C23: 22. Продавец порекомендовал вариант оплаты и дал аргументацию | D23: Проверь, как Продавец рекомендовал вариант оплаты: обозначил ли ценность курса перед озвучиванием цены, предложил ли оплату от большего к меньшему, и аргументировал ли своё предложение. [1] – Продавец соблюдал алгоритм презентации цены (описан ниже) [0] – Продавец не соблюдал алгоритм презентации цены (описан ниже) Алгоритм презентации цены: 1. озвучил ценность курса до того, как назвать цену (например: на выходе после курса Бухгалтер у нас вы получаете гарантированную помощь в трудоустройстве, бесплатную практику в программах Datev и Lexware, знания узкопрофильного немецкого, необходимого для работы, знания по Искусственному Интеллекту, живые уроки с преподавателями с возможностью задавать вопросы, 6 проектов в портфолио и сертификат гос. образца за 4300 евро) 2. порекомендовал оплату от большего к меньшему (сначала 3900 евро целиком при единовременной оплате, затем рассрочка 3900 на 5 месяцев, далее 4300 на 7 месяцев, и только в исключительном случае — 4300 на 10 месяцев) 3. аргументировал выбор (например: “при полной оплате скидка 400 евро, так сможете максимально сэкономить”, “при рассрочке в 5 платежей скидочная стоимость сохраняется, что позволяет неплохо сэкономить” и т.д.) Рекомендации могут быть адаптированы под ситуацию Клиента, но логика ""от большего к меньшему"" должна сохраняться. 4. если в разговоре выяснилось, что Клиент заведомо не может оплатить всю сумму, допускается, что Продавец сразу перешёл к рассрочке, но всё равно Продавец должен начать с варианта 3900 евро на 5 месяцев, а не сразу с 4300 евро на 10 месяцев. [Пусто] – Разговор не дошёл до этапа обсуждения оплаты. Важно: перед оценкой проверь корректность ролей. Продавец — сотрудник компании Sternmeister (в транскрипции может быть “Стармейстер”, “Стернмейстер”, “Стенмейстер”), предлагающий и продающий Клиенту курс обучения на бухгалтера в Германии.
B24: 23 | C24: 23. Продавец узнал, подходит ли предложенный вариант оплаты Клиенту | D24: Проверь, задал ли Продавец вопрос о том, насколько Клиенту подходит предложенный вариант оплаты, и уточнил, что нужно, если Клиент не дал чёткого ответа. [1] – Продавец: – задал вопрос: “Этот вариант вам подходит”, “Какой способ оплаты вам удобнее”, “Готовы оплатить в таком формате” или аналогичный – выслушал ответ – если Клиент сомневался или ответил “не подходит” — Продавец задал уточняющий вопрос или предложил альтернативу, предварительно уточнив, единственный ли фактор — это стоимость, или есть другие причины. Если Клиент назвал другие причины, Продавец вернулся к отработке возражения по структуре: Присоединение → уточнение → аргумент → призыв к действию. [0] – Продавец не задал вопроса о предпочтении Клиента, не уточнил, подходит ли предложенный способ, или проигнорировал сомнение Клиента. В ответе укажи, как Продавец перешёл к оплате и была ли реакция на ответ Клиента. [Пусто] – Обсуждение оплаты не началось или прервалось до этого момента. Важно: перед оценкой проверь корректность ролей. Продавец — сотрудник компании Sternmeister (в транскрипции может быть “Стармейстер”, “Стернмейстер”, “Стенмейстер”), предлагающий и продающий Клиенту курс обучения на бухгалтера в Германии.
B25: 24 | C25: 24. Продавец предложил приступить к обучению | D25: Проверь, сделал ли Продавец прямое предложение зачислиться и начать обучение. [1] – Продавец: – задал финальный вопрос, например: “Вы готовы начать обучение”, “Давайте я помогу вам тогда оформиться”, “Готовы начать обучение сейчас” или аналогичную формулировку по смыслу [0] – Продавец не предложил приступить к обучению, не узнал о готовности Клиента. В ответе укажи, как завершился этот этап подробно. [Пусто] – Разговор прервался до попытки закрытия сделки. Структура и точное совпадение с фразами из примеров неважны, главное, чтобы было приветствие Важно: перед оценкой проверь корректность ролей. Продавец — сотрудник компании Sternmeister (в транскрипции может быть “Стармейстер”, “Стернмейстер”, “Стенмейстер”), предлагающий и продающий Клиенту курс обучения на бухгалтера в Германии.
B26: 25 | C26: 25. Следующие шаги | D26: Проверь, закрепил ли Продавец договоренности о конкретных дальнейших шагах, вне зависимости от того, обсуждалась оплата курса или нет: [1] – Если Клиент изъявил готовность оплатить или если Клиент не изъявлял готовности оплатить, в любом случае Продавец закрепил четкие договоренности о следующих шагах: проговорил когда будет следующий звонок в соответствии с договоренностью с клиентом. [0] – Продавец не закрепил четких договоренностей о следующих шагах с Клиентом, не назначил следующий звонок. [Пусто] – Разговор не дошёл до обсуждения оплаты. В обосновании выпиши, какие следующие шаги были зафиксированы. Важно: перед оценкой проверь корректность ролей. Продавец — сотрудник компании Sternmeister (в транскрипции может быть “Стармейстер”, “Стернмейстер”, “Стенмейстер”), предлагающий и продающий Клиенту курс обучения на бухгалтера в Германии.
A27: Стандарты общения | B27: 26 | C27: 26. Применение сторителлинга | D27: Проверь, применил ли Продавец сторителлинг в любой части разговора, например Продавец рассказал успешную историю одного из клиентов, как пример и мотивацию для Клиента в звонке. [1] – Продавец применил сторителлинг и рассказал, в любой части разговора с Клиентом, успешную историю-пример одного из текущих клиентов курсов Sternmeister или любую историю. Например, Продавец своими словами рассказал свою историю, историю какого-то знакомого, члена семьи или одну из историй предлагаемых скриптом: Пример 1 - Гульнара из Украины. У Гульнары в Украине была насыщенная профессиональная жизнь: высшее образование и работа бухгалтера, а потом — собственный бизнес (салон красоты, в который было вложено все и силы и финансы). Но война перечеркнула все. Ради безопасности сыновей ей пришлось приехать сюда, в Германию. Первые месяцы у нее были такие же проблемы и ограничения, что у вас: языковой барьер, ощущение, что жизнь остановилась и т.д. Гульнара устроилась на книжный склад, но внутри понимала, что она способна на большее. В итоге она записалась к нам на курс, хотя у неё были те же страхи, что не получится, но сейчас она говорит, что ни капли не жалеет и учеба ее вдохновляет на каждом шагу. Вообще все наши студенты отмечают, что главное — не бояться сделать первый шаг. Пример 2 - Виктория, приехала в Германию из Украины в 2022 году. Виктория более 20 лет работала главным бухгалтером в разных компаниях. После переезда она подрабатывала на разных работах, но поняла, что очень хочет снова заниматься тем, что любит и умеет — бухгалтерией. Виктория начала искать курсы, которые могли бы помочь ей адаптировать опыт к немецкой системе. Очень важно было, чтобы обучение было понятным, с поддержкой, на русском языке, и в то же время с ориентацией на реальные требования работодателей. Она долго не верила, что справится с обучением, но нашла нас и сейчас отмечает, что больше всего ей нравится в обучении практическая направленность и то, как поддерживают преподаватели. Главное, как отмечает Виктория, что она снова чувствует, что двигается к своей профессии. [0] – Продавец не применил сторителлинг и не рассказал историю-пример. [Пусто] – Если разговор оборвался или прервался не завершившись, и в нем продавец не успел применить сторителлинг. Важно: перед оценкой проверь корректность ролей. Продавец — сотрудник компании Sternmeister (в транскрипции может быть “Стармейстер”, “Стернмейстер”, “Стенмейстер”), предлагающий и продающий Клиенту курс обучения на бухгалтера в Германии.
B28: 27 | C28: 27. Общая доброжелательность и вежливость Продавца | D28: Проверь, был ли Продавец вежлив, внимателен и доброжелателен по ходу разговора. Учитывай: обращение по имени, интонацию по тексту, стиль общения и эмоциональный фон. [1] – Продавец: – минимум 3 раза обратился к Клиенту по имени (в любой части разговора) – использовал вежливые слова: “спасибо”, “пожалуйста”, “извините”, “будьте добры”, “разрешите уточнить” и т. д. – общался уважительно и с теплотой: без снисходительности, без высокомерия – подстраивал тональность под Клиента: – если Клиент был спокоен — Продавец вежлив и доброжелателен – если Клиент был доброжелателен — Продавец тоже – если Клиент раздражён — Продавец сохранил уважительный, спокойный стиль [0] – Продавец не обращался по имени, не использовал вежливую лексику, был сухим, механическим, игнорировал тональность Клиента, либо звучал холодно или напряжённо. В ответе укажи, какие фразы использовались, какой был стиль общения и как он сочетался с эмоциональным фоном Клиента. [Пусто] – Разговор прервался до момента, где можно было оценить стиль общения. Важно: перед оценкой проверь корректность ролей. Продавец — сотрудник компании Sternmeister (в транскрипции может быть “Стармейстер”, “Стернмейстер”, “Стенмейстер”), предлагающий и продающий Клиенту курс обучения на бухгалтера в Германии.
B29: 28 | C29: 28. Продавец использовал активное слушание и отзеркаливание Клиента | D29: Проверь, поддерживал ли Продавец контакт с Клиентом, показывал ли, что слушает и понимает, и повторял ли важные мысли Клиента своими словами. [1] – Продавец: – использовал фразы активного слушания: “да”, “угу”, “понял(а)”, “согласен”, “точно” и т. д. – реагировал на высказывания Клиента (комментарии, уточнения, мини-рефреймы) – перефразировал важные мысли Клиента и зеркалил последние ключевые слова из речи клиента: “Вы сказали, что уже работали бухгалтером…”, “Правильно понимаю, что для вас важно начать в этом году” и т.д. – поддерживал диалог в живом темпе, не уходил в монолог [0] – Продавец не проявлял признаков активного слушания, игнорировал реплики Клиента, не перефразировал важные мысли, общался шаблонно. В ответе укажи, как Продавец реагировал на реплики Клиента и было ли отзеркаливание. [Пусто] – Разговор был слишком коротким или прервался до момента активного диалога. Важно: перед оценкой проверь корректность ролей. Продавец — сотрудник компании Sternmeister (в транскрипции может быть “Стармейстер”, “Стернмейстер”, “Стенмейстер”), предлагающий и продающий Клиенту курс обучения на бухгалтера в Германии.
B30: 29 | C30: 29. Продавец был корректен и сохранял самоконтроль | D30: Проверь, проявлял ли Продавец уважение и терпение в разговоре, не перебивал, не раздражался, не говорил грубостей или пассивно-агрессивных фраз. [1] – Продавец: – не перебивал Клиента, либо перебил вежливо и один раз, с извинением (“простите, что перебиваю…”) – не проявлял раздражения или агрессии, даже если Клиент был негативен – не говорил фраз вроде: “я уже объяснял”, “ну я же сказал”, “вам непонятно что ли”, “я уже отвечал” – сохранял спокойный, профессиональный тон до конца разговора [0] – Продавец перебивал, давил, использовал раздражённый или пассивно-агрессивный стиль общения. В ответе укажи: – какие фразы звучали – как реагировал на паузы или сомнения Клиента – создавал ли ощущение давления или дискомфорта [Пусто] – Разговор прервался до момента, где можно было оценить корректность общения. Важно: перед оценкой проверь корректность ролей. Продавец — сотрудник компании Sternmeister (в транскрипции может быть “Стармейстер”, “Стернмейстер”, “Стенмейстер”), предлагающий и продающий Клиенту курс обучения на бухгалтера в Германии.
A31: Критические ошибки | B31: 30 | C31: 30. Критические ошибки с точки зрения компании | D31: Проверь, допускались ли критичиские ошибки в ходе разговора: [1] – В разговоре были зафиксированы одна или несколько ошибок, критичных для репутации и эффективности работы компании Sternmeister. Укажи, что именно произошло: А) Продавец негативно высказывался о компании или курсе Примеры: “у нас с этим часто проблемы”, “я сам не до конца понимаю, как это устроено”, “мне это тоже не нравится”, “ну, не знаю, кто этим занимается, разберётесь потом” Б) Продавец отговаривал Клиента от покупки или сам проявлял сомнение Примеры: “может, это не для вас”, “если не уверены — не надо идти на наше обучение” В) Продавец ввел Клиента в заблуждение относительно лицензии AZAV, сертификата, который получит клиент по окончанию курса или любых других составляющих курса и/или процессов компании. Например, Продавец сказал: – что у Sternmeister нет лицензии AZAV от Декры – что сертификат от Sternmeister не признается в Германии и не является достаточным основанием найти работу бухгалтера в Германии. – говорит, что лицензию нельзя никак проверить – говорит, что возможно подобрать индивидуальный график, если Клиенту не удобен презентованный Продавцом график Г) Продавец сынициировал разговор о возврате, его условиях, первым озвучил, что у Клиента есть возможность сделать возврат, если не понравится урок, хотя Клиент не задавал вопросов о возможносятх возврата. Продавец сказал фразы или близкие по смыслу: – вы ничего не теряете, можете оплатить сейчас, а потом потребовать возврат – оплатите сейчас, посетите 1 урок, если не понравится, сделаем возврат – вы ничем не рискуете, если оплатите сейчас за курс, все равно у нас есть возврат В ответе укажи: – какая фраза или действие вызвало риск и в каком контексте – почему это может быть воспринято как введение в заблуждение и чем может быть чревато для компании – какие из ошибок были допущены – как Продавец завершил разговор – был ли шанс продолжить работу с Клиентом — и использовал ли его Продавец [0] – Продавец не допустил критических ошибок: не высказывался негативно, не отговаривал Клиента, не дезинформировал Клиента, не заговаривал о возврате первым и закрепил следующий шаг с конкретикой - дата, время или способ связи. [Пусто] – Разговор прервался слишком рано, и оценка невозможна. Важно: перед оценкой проверь корректность ролей. Продавец — сотрудник компании Sternmeister (в транскрипции может быть “Стармейстер”, “Стернмейстер”, “Стенмейстер”), предлагающий и продающий Клиенту курс обучения на бухгалтера в Германии.
B32: 31 | C32: 31. Критические ошибки с точки зрения клиента | D32: [1] – В разговоре были допущены одна или несколько ошибок, которые могли нарушить доверие Клиента, ввести его в заблуждение или создать негативное впечатление. Укажи, что именно произошло: А) Продавец дал ложную или искаженную информацию Ошибка фиксируется, если сказанное противоречит следующим официальным данным о курсе Sternmeister: Формат и структура курса: – Длительность курса: 7 месяцев (31 неделя, включая каникулы) – Объём: 630 часов обучения и 150 академических часов узкопрофильного немецкого – Формат: онлайн – 70% курса — это практика – 6 практических кейсов, включая финальный проект – Язык обучения: русский Кто ведёт курс: – Преподаватели — русскоязычные специалисты бухгалтеры, живущие в Германии – Sternmeister работает в Германии, имеет право на образовательную деятельность, выдает официальные сертификаты вайтербильдунг с лицензией в соответствии с AZAV от Декра Что входит в обучение: – Узкопрофильный немецкий язык для бухгалтеров 150 часов – Карьерный центр — помогает с резюме, профилем LinkedIn, собеседованиями, стажировками – Soft skills — коммуникация, критическое мышление, адаптация – AI-инструменты и GPT Co-pilot — помогает в обучении и собеседованиях – Трекинг прогресса, LMS-платформа – Персонализированная мотивация — анкетирование, отслеживание вовлечённости – Спиралевидная модель обучения — постепенное углубление тем – Data-driven подход — адаптация контента и обратная связь на основе данных Документы и сертификация: – Клиент получает Сертификат о прохождении программы государственного образца, выданный по окончании курса. Он может называться: А. Weiterbildung – сертификат о дополнительном образовании (произносится как вайтербилдунг, вайсарбилдунг, вайсер-гилдзунг и др.) Б. Abschlusszertifikat – сертификат об окончании обучения (абшлусццертификат, абшлосс-цеттификат, абслус-сертификат и т. п.) В. Оба названия допустимы и взаимозаменяемы. AZAV — это государственная аккредитация организаций, обучающих в системе содействия занятости в Германии. Произносится как (Ацетафау, азав, ацэав, а-зав) У Sternmeister есть эта лицензия, и её наличие гарантировано на момент окончания обучения Клиента. Допустимые произношения и искажения AZAV и её расшифровки (не считаются ошибкой, если по смыслу понятно): AZAV – Ацетафау, азав, ацэав, а-зав, а если расшифровать аббревеатуру, то: Akkreditierung – аккредитирунг, аккредитерунг, акредетерунг, акритирунг, Zulassung – зуласунг, зуласинг, цулязунг, зюляссен, зулажундс, Verordnung – ферорднунг, ферарднунг, верорнунг, верортнунг, Arbeitsförderung – арбайтсфердерунг, арбайтсфордерунг, арбайцфорнунг, арбаитсфёрунг Ошибка если Продавец: – Утверждает, что у SternMeister нет лицензии в соответствии с AZAV – Умалчивает про сертификат, либо говорит, что он неофициальный – Говорит, что SternMeister не имеет лицензию от Декра Б) Продавец сказал “я не знаю” по вопросу, который обязан знать Такие темы включают: стоимость, формат, язык, старт потока, способы оплаты, наличие сертификата, продолжительность курса, возможность рассрочки и т. д. Если Продавец не знает, но обещает уточнить — это не ошибка. В) Продавец грубил, обвинял или перебивал Клиента Даже нейтральные фразы вроде “ну это же очевидно”, “я уже объяснял”, “вы не поняли” — в контексте могут быть восприняты как давление или снисходительность. В ответе укажи: – какая ошибка была допущена – цитаты и контекст – как это могло повлиять на доверие Клиента и желание продолжать разговор [0] – Продавец не допустил критических ошибок. Информация соответствовала действительности, поведение было уважительным, ответы — корректные и ясные. [Пусто] – Разговор прервался слишком рано, и оценка невозможна. Важно: перед оценкой проверь корректность ролей. Продавец — сотрудник компании Sternmeister (в транскрипции может быть “Стармейстер”, “Стернмейстер”, “Стенмейстер”), предлагающий и продающий Клиенту курс обучения на бухгалтера в Германии.
B33: 32 | C33: 32. Критические ошибки с точки зрения закона | D33: [1] – В разговоре были допущены действия или фразы, которые могут нарушать законодательство Германии или создать юридические риски для компании Sternmeister. Укажи, что именно произошло: А) Разглашение внутренней информации Продавец рассказал о: – доступах, правах и действиях сотрудников в CRM – финансовых показателях, зарплатах или схемах – внутренних документах, переписках, стратегиях – учебных материалах, к которым Клиент не должен получать доступ заранее Если это не было частью официальной презентации курса — это нарушение. Б) Неправомерные обещания Запрещено: – давать гарантии трудоустройства (например: “вы 100% получите работу”) – обещать отправить запись реального урока – угрожать клиенту, использовать нецензурную лексику [0] – Критических нарушений с точки зрения закона не зафиксировано. Продавец не давал ложных гарантий, не нарушал рамки диалога и не выходил за рамки допустимого в B2C-продаже образовательных услуг в Германии стандарта. [Пусто] – Разговор прервался слишком рано, и оценка невозможна. Важно: перед оценкой проверь корректность ролей. Продавец — сотрудник компании Sternmeister (в транскрипции может быть “Стармейстер”, “Стернмейстер”, “Стенмейстер”), предлагающий и продающий Клиенту курс обучения на бухгалтера в Германии.
A34: Экспертный блок | B34: 33 | C34: 33. Talk ratio Продавца | D34: [Число] — укажи, сколько процентов времени от общего активного диалога говорил Продавец в процентах. Расчёт нужно производить на основе таймкодов транскрипции. Укажи результат округлённым до целого числа (например: 48). 1. Определи длительность активного диалога — от первой реплики Продавца или Клиента до последней. Не учитывай автоответчик, тишину, заставки и паузы до начала разговора. 2. Суммируй длительность всех реплик Продавца в этом интервале (используй таймкоды начала и конца(или вместо конца таймкод начала следующей реплики клиента)). 3. Раздели суммарное время речи Продавца на общее время активного диалога, умножь на 100 и округли до целого. Важно: – Продавец — сотрудник Sternmeister (в транскрипции может быть “Стармейстер”, “Стернмейстер”, “Стенмейстер”). – Если Продавец говорит более 95% времени, обязательно проверь корректность ролей. – Если во всей транскрипции только один говорящий или второй сказал менее 3 слов, это не считается диалогом — поставь [Пусто]. – Используй секунды для всех расчётов. В поле reasons укажи: – Сколько секунд длился активный диалог – Сколько времени говорил Продавец – Сколько времени говорил Клиент – Количество реплик каждого – Итоговое соотношение Пример ответа: Score: 61 Reasons: Диалог длился 366 секунд. Продавец говорил 224 секунды, Клиент — 142. У Продавца — 28 реплик, у Клиента — 19. Соотношение: 224 / 366 = 61%. Важно: перед оценкой проверь корректность ролей. Продавец — сотрудник компании Sternmeister (в транскрипции может быть “Стармейстер”, “Стернмейстер”, “Стенмейстер”), предлагающий и продающий Клиенту курс обучения на бухгалтера в Германии.
B35: 34 | C35: 34. Оценка звонка по международным методологиям | D35: [Число] — в качестве оценки укажи итоговую сумму баллов по всем методологиям продаж. Для этого проанализируй весь звонок и оцени его по следующим пяти международным методологиям продаж. Для каждой методологии в поле обоснования укажи: А) Название методологии Б) Оценку звонка по данной методологии от 1 до 10 В) Почему была поставлена именно эта оценка (с примерами фраз из звонка, ситуаций и реакции Клиента) Г) Что нужно было сделать, чтобы получить 10 из 10 по этой методологии — приведи 2–3 конкретных примера фраз, вопросов или приёмов, которые нужно было использовать в этом разговоре После оценки всех методологий укажи сумму всех пяти оценок как итоговый балл по данному критерию, показав расчёт в обосновании, например: 7 + 8 + 5 + 6 + 9 = 35 (максимум — 50, минимум — 0). Пример оценки критерия: 35 Важно: перед оценкой проверь корректность ролей. Продавец — сотрудник компании Sternmeister (в транскрипции может быть “Стармейстер”, “Стернмейстер”, “Стенмейстер”), предлагающий и продающий Клиенту курс обучения на бухгалтера в Германии. Методологии: 1. Консультативные продажи 2.0 (Consultative Selling 2.0) Фокус: Продавец выступает как консультант, помогая Клиенту выбрать наилучшее решение под его задачи. Не «продаёт», а помогает. Ключевые шаги: – Построение доверия и открытого диалога – Выявление глубинных потребностей и приоритетов – Прояснение ограничений (бюджет, сроки, ожидания) – Презентация решения как персонального ответа – Подтверждение пользы и принятие решения Оцени: – Слушал ли Продавец больше, чем говорил – Задавал ли вопросы, раскрывающие личные цели Клиента – Связывал ли преимущества продукта с потребностями покупателя 2. Продажа через эмоциональный резонанс (Emotional Resonance Selling) Фокус: Продавец находит и усиливает эмоции Клиента, связанные с его потребностями или мечтами, и строит аргументацию на этом. Ключевые шаги: – Определение эмоциональной мотивации: «зачем это вам» – Настройка: интонация, ритм, эмпатия – Сторителлинг (аналогии, примеры) – Акцент на чувства от результата, а не на свойства – Закрытие сделки через воображение результата Оцени: – Выявил ли Продавец эмоциональную мотивацию Клиента (например: безопасность, статус, забота) – Подстроился ли под стиль Клиента – Использовал ли образы, истории или примеры, вызывающие эмоции 3. Продажи на основе потребностей (Needs-Based Selling, NBS) Фокус: Продавец выявляет конкретные потребности Клиента и классифицирует их, чтобы предложить точное решение. Ключевые шаги: – Сбор информации: зачем, для кого, с какими ожиданиями – Классификация запроса: рациональный / эмоциональный / срочный – Презентация продукта как идеального ответа – Устранение несоответствий и сомнений – Финализация покупки, подтверждение соответствия ожиданиям Оцени: – Были ли чётко выявлены потребности Клиента – Был ли выделен главный приоритет – Связал ли Продавец характеристики продукта с этими приоритетами 4. Продажа через истории (Story-Based Selling) Фокус: Продавец рассказывает правдоподобные и релевантные истории, помогающие Клиенту «увидеть себя» в успешной ситуации. Ключевые шаги: – Начало с проблемной ситуации, схожей с ситуацией Клиента – Показ процесса решения и выбора продукта – Завершение результатом — довольный клиент – Прямая или косвенная аналогия с текущим покупателем – Призыв к действию как логичное завершение истории Оцени: – Рассказывал ли Продавец истории – Были ли они релевантны ситуации Клиента – Вызвала ли история интерес, уточняющие вопросы или реакцию 5. Продажа по модели 4P (Problem–Promise–Proof–Proposal) Фокус: Структурированное убеждение Клиента через 4 шага — от боли к решению. Ключевые шаги: – Проблема: чётко обозначить боль Клиента – Обещание: пообещать результат («как станет лучше») – Доказательство: привести факты (цифры, кейсы, отзывы) – Предложение: конкретное предложение с призывом к действию Оцени: – Была ли чётко определена «болевая точка» – Сформулировал ли Продавец обещание результата – Привёл ли он доказательства – Сделал ли конкретное предложение (и какое именно)
B36: 35 | C36: 35. Структура звонка: фактический скрипт, который применил Продавец | D36: [1] – Разговор приблизил Клиента к покупке: Клиент ясно выразил интерес, согласие, дал позитивный сигнал (готов оплатить, захотел пойти на курс, договорились о следующем шаге). [0] – Разговор не привёл к результату: Клиент отказался, остался в сомнении, не проявил интерес, разговор завершился без конкретного решения. В поле reasons напиши: А) Восстанови фактический скрипт, который применил Продавец в этом звонке – Какие шаги он прошёл – В каком порядке – Как он переходил между темами – Что сказал на каждом этапе (цитаты или смысл фраз) Б) Зафиксируй особенности этого скрипта — что делал иначе были ли нестандартные шаги что пропустил В) Укажи, какие элементы скрипта сработали: где Клиент проявил интерес, задавал вопросы, реагировал позитивно Г) Укажи, какие элементы не сработали: где Клиент замолчал, ушёл в сомнение, дал возражение, или не дал ответа Задача критерия — восстановить реальную модель поведения Продавца, зафиксировать её логику и результат. Это позволит в будущем сравнивать “сильные” и “слабые” сценарии на основе 100+ звонков. Важно: перед оценкой проверь корректность ролей. Продавец — сотрудник компании Sternmeister (в транскрипции может быть “Стармейстер”, “Стернмейстер”, “Стенмейстер”), предлагающий и продающий Клиенту курс обучения на бухгалтера в Германии.
B37: 36 | C37: 36. Что заставит этого Клиента купить (тип, реакция и болеутоляющая формула) | D37: [Тип клиента] — укажи, к какому типу относится Клиент в этом разговоре. Выбери один из вариантов: Рациональный, Эмоциональный, Сравниватель (смотрит другие варианты), Осторожный (боится ошибки, ищет уверенность), Мечтатель (ориентирован на будущее, образ жизни), Недоверчивый, Убеждённый (уже почти готов), Иной (укажи). В поле reasons напиши: А) Что уже сработало – Какие фразы, темы или реакции Продавца вызвали позитивную реакцию – Где Клиент оживился, согласился, стал говорить больше Б) Что могло бы сработать сильнее – Где Продавец упустил момент – Какая информация, тактика или эмоция могла бы усилить мотивацию В) Pain-killer line – Придумай одну сильную фразу, которая могла бы снять ключевое сомнение Клиента – Объясни, почему она сработает именно для этого типа Клиента – Укажи, в какой момент разговора её стоило сказать Г) Что можно предпринять на следующем контакте – Какие темы напомнить – Какой формат диалога выбрать – Что НЕ стоит повторять Этот критерий помогает понять, как “дожать” клиента с учётом его типа мышления и мотивации, и собрать библиотеку стратегий под каждый тип. Важно: перед оценкой проверь корректность ролей. Продавец — сотрудник компании Sternmeister (в транскрипции может быть “Стармейстер”, “Стернмейстер”, “Стенмейстер”), предлагающий и продающий Клиенту курс обучения на бухгалтера в Германии.
B38: 37 | C38: 37. Неиспользованные УТП, которые могли бы повлиять | D38: [Рекомендация] - данный критерий исключение, в качестве оценки напиши слово Рекомендация, а в обосновании оценки reason напиши следующее: Проанализируй разговор и выпиши, какие УТП могли бы повлиять на решение Клиента, но не были использованы или были раскрыты недостаточно. Также оцени, не возникла ли в разговоре потребность в таком УТП, которого вообще нет в текущем продукте — если да, предложи, что стоило бы добавить в программу, чтобы закрыть этот запрос. А) Какие боли, сомнения или интересы выразил Клиент — и какие УТП могли бы на это сработать Б) Какие УТП были упомянуты, но не раскрыты или раскрыты поверхностно В) Какие УТП стоило бы добавить в разговор — как их можно было подать и почему эти УТП могли бы сработать именно для этого Клиента Г) Если Клиент озвучил конкретный запрос, а соответствующего УТП нет — предложи, какого УТП не хватает продукту и как его можно было бы сформулировать Список УТП курса “Бухгалтер” от Sternmeister: – Преподаватели — практикующие бухгалтеры уровня Middle+ – AI-инструменты для автоматизации и анализа – Карьерный центр + бот GPT Co-pilot: для помощи в подготовке и тренировок интервью – Полный пакет шаблонов: резюме, письма, тестовые задания – Soft skills: коммуникация, логика, аналитика – Немецкий язык для бухгалтеров – Современная методика обучения + LMS-платформа – Персонализированная система мотивации (по типу памяти) – 70% практики (реальные кейсы и инструменты) – Группа поддержки + сопровождение – Дашборд с прогрессом и аттестацией Документы и сертификация: – По окончании курса Клиент получает Сертификат о прохождении программы государственного образца с лицензией от Декра, который называется Weiterbildung — сертификат о дополнительном образовании (допустимые распознавания: вайсер-гилдзунг, вайсарбилдунг, вайтабилдунг, вайзер-билдунг и т. п.) – Сертификат выдаётся лицензированной организацией, обладающей лицензией AZAV — Akkreditierungs- und Zulassungsverordnung Arbeitsförderung (государственная лицензия, подтверждающая право обучать в системе содействия занятости в Германии) Допустимые искажения и распознавания: AZAV — ацетафау, азав, ацэав, а-зав Akkreditierung — аккредитирунг, аккредитерунг, акритирунг Zulassung — зуласунг, зуласинг, зюляссен Verordnung — ферорднунг, верортнунг Arbeitsförderung — арбайтсфердерунг, арбайтсфёрунг и т. п. Если ИИ по смыслу понимает, что речь о правильном документе — это допустимо. Цель критерия — зафиксировать не только неиспользованные, но и недостающие УТП, чтобы в будущем адаптировать продукт и скрипты под реальные ожидания клиентов. Важно: перед оценкой проверь корректность ролей. Продавец — сотрудник компании Sternmeister (в транскрипции может быть “Стармейстер”, “Стернмейстер”, “Стенмейстер”), предлагающий и продающий Клиенту курс обучения на бухгалтера в Германии.
B39: 38 | C39: 38. Потеря клиента на этапе оплаты | D39: [1] – Разговор шёл позитивно, но на этапе оплаты Клиент отказался, отложил решение или ушёл в неопределённость. [0] – Клиент дал согласие, проявил готовность к оплате или согласовал понятный следующий шаг, ведущий к продаже (например: обсудили формат, договорились о звонке для оплаты, зафиксировали план действий). В поле reasons напиши: А) Как завершился разговор Прозвучал ли отказ, сомнение или отложенное решение Б) Что именно Клиент сказал на этапе оплаты — сформулируй дословно или по смыслу В) Что сделал или не сделал Продавец: – были ли ошибки (не озвучил выгоды оплаты, не уточнил комфортный способ, не зафиксировал шаг) – чего не хватило: аргумента, поддержки, срочности Г) Придумай одну тактику, фразу или шаг, который мог бы изменить ситуацию (например: “если бы Продавец уточнил, какие именно условия оплаты вызывают сомнение…”) Если оценка [0], то в reasons напиши: – Почему Клиент согласился (что сработало) – Что сделал Продавец правильно Этот критерий показывает, где “падает” горячий клиент — из-за нерешённого возражения, неуверенности в стоимости, неготовности к оплате, неудачного дожима или просто отсутствия закрывающего вопроса. Важно: перед оценкой проверь корректность ролей. Продавец — сотрудник компании Sternmeister (в транскрипции может быть “Стармейстер”, “Стернмейстер”, “Стенмейстер”), предлагающий и продающий Клиенту курс обучения на бухгалтера в Германии.
B40: 39 | C40: 39. Экспертный стиль установновления раппорта | D40: Проверь, как Продавец устанавливает раппорт с Клиентом: через спокойный «терпеливый авторитет» и активное слушание или через жалобы/обесценивание, которые снижают его статус. [1] – Продавец строит раппорт через уверенный и экспертный стиль. Использует активное слушание и короткие поддерживающие реплики по делу («поняла», «верно», «я вас услышала»), интересуется ситуацией Клиента, не жалуется на свою занятость или личные проблемы, не переводит фокус на себя. Если Клиент уводит разговор в сторону в ответ на конкретный вопрос Продавца, Продавец вежливо возвращает Клиента к актуальной теме/вопросу и удерживает структуру диалога. Возникает ощущение спокойной, авторитетной связи. [0] – Продавец пытается установить раппорт через жалобы на занятость, количество клиентов, нехватку времени или другие сложности («я весь день на звонках», «у меня очередь желающих» и т.п.), либо чрезмерную фамильярность, что звучит непрофессионально и снижает его статус. Также сюда отнеси случаи, когда раппорт не выстраивается: Продавец звучит холодно, формально, не проявляет интереса к человеку; либо не возвращает Клиента к теме и теряет управление разговором. [Пусто] – звонок слишком короткий или технический (например, только перенос времени), нет реальной возможности установить раппорт, по фрагменту нельзя сделать вывод о стиле общения. В обосновании опиши, какими фразами и приёмами Продавец устанавливал (или не устанавливал) раппорт, было ли активное слушание или жалобы на занятость, как Продавец возвращал Клиента к теме (если уводил), приведи 2–4 цитаты, которые лучше всего показывают его стиль и то, как это могло влиять на восприятие Клиентом. Важно: перед оценкой проверь корректность ролей. Продавец — сотрудник компании Sternmeister (в транскрипции может быть “Стармейстер”, “Стернмейстер”, “Стенмейстер”), предлагающий и продающий Клиенту курс обучения на бухгалтера в Германии.
A41: Рекомендации | B41: 40 | C41: 40. Краткое резюме звонка | D41: [Резюме] - данный критерий исключение, в качестве оценки напиши слово Резюме, а в обосновании оценки reason напиши следующее: Cоставь краткое и структурированное резюме звонка. Оно должно быть лаконичным, понятным и отражать только ключевые моменты. Обязательно включи: А) Содержание звонка – Какие темы и блоки были затронуты – Обсуждалась ли мотивация, цели, сложности, презентация курса, этап оплаты и т.д. Б) Реакция Клиента на ключевые моменты – Была ли она заинтересованной, сомневающейся, позитивной, нейтральной или негативной – Как Клиент реагировал на презентацию, УТП и предложения В) Достигнутые договорённости – Были ли зафиксированы следующие шаги, созвон, выбор даты, интерес к оплате – Уточни, была ли попытка зафиксировать следующий шаг со стороны Продавца Это резюме должно помогать быстро понять суть разговора без прослушивания записи. Важно: перед оценкой проверь корректность ролей. Продавец — сотрудник компании Sternmeister (в транскрипции может быть “Стармейстер”, “Стернмейстер”, “Стенмейстер”), предлагающий и продающий Клиенту курс обучения на бухгалтера в Германии.
B42: 41 | C42: 41. Упоминание конкурентов и реакция Продавца | D42: [1] – В разговоре были упомянуты конкуренты (прямо или косвенно), и это повлияло на восприятие Клиентом курса. [0] – Упоминаний конкурентов в разговоре не было. В поле reasons напиши: А) Название конкурента — если было (например, “DeutschAkademie”), или укажи “Безымянный конкурент”, если прозвучало в виде “другая компания”, “там”, “у них”, “дешевле, чем у вас” и т.п. Б) Причина упоминания — что именно сказал Клиент о конкурентах: цена, формат, гарантии, длительность, отзывы, результаты В) Как это можно было обыграть — какой аргумент Sternmeister мог бы использовать Г) Придумай фразу Продавца, которая могла бы перевернуть мнение Клиента Д) Как бы эта фраза повлияла на решение Клиента (например, снизила тревожность, усилила доверие, добавила выгоду) Важно: перед оценкой проверь корректность ролей. Продавец — сотрудник компании Sternmeister (в транскрипции может быть “Стармейстер”, “Стернмейстер”, “Стенмейстер”), предлагающий и продающий Клиенту курс обучения на бухгалтера в Германии.
B43: 42 | C43: 42. Рекомендации Продавцу: зоны роста | D43: [Рекомендация] - данный критерий исключение, в качестве оценки напиши слово Рекомендация, а в обосновании оценки reason напиши следующее: Выяви ключевые ошибки Продавца, которые негативно повлияли на ход переговоров, вызвали отказ, снижали интерес или мешали продаже. Выпиши минимум 3 (если есть). Для каждой ошибки укажи: – Фраза Продавца – приведи дословную цитату или суть фразы – Контекст – когда это прозвучало, что сказал Клиент, как отреагировал, к чему это привело – Как следовало сказать – предложи лучший вариант формулировки – Ожидаемый эффект – что бы изменилось в разговоре, какую технику ты использовал, как это улучшает восприятие у Клиента Ошибкой также считается упущение — если Продавец не задал важный вопрос, не сделал дожим, не резюмировал или не уточнил ключевое. Важно: Игнорируй незначительные мелочи (например, слова-паразиты, оговорки), если они не повлияли на исход. Важно: перед оценкой проверь корректность ролей. Продавец — сотрудник компании Sternmeister (в транскрипции может быть “Стармейстер”, “Стернмейстер”, “Стенмейстер”), предлагающий и продающий Клиенту курс обучения на бухгалтера в Германии.
B44: 43 | C44: 43. Рекомендации Продавцу: лучшие практики | D44: [Рекомендация] - данный критерий исключение, в качестве оценки напиши слово Рекомендация, а в обосновании оценки reason напиши следующее: Выдели минимум 3 удачные техники или приёма (если есть), которые реально помогли Продавцу продвинуть диалог: снизить сопротивление, вызвать интерес, удержать Клиента, перевернуть сомнение или приблизиться к продаже. Если таких приемов нет — напиши: «Выраженных удачных техник не выявлено». Для каждой практики укажи: – Фраза Продавца – приведи дословную цитату или суть – Контекст – когда сказано, что было до и после, как отреагировал Клиент – Почему это сработало – за счёт чего фраза или приём были эффективны – Техника – какая методология или приём использован (например: "SPIN", "градация приоритетов", "storytelling", "вопрос-ловушка") – Тип практики: – Массовая техника – её можно учить других – Индивидуальная техника – уникальная находка, харизма, удачная интонация, нестандартная логика Отмечай только то, что действительно изменило ход разговора в пользу Продавца (удачные шутки или яркие моменты тоже можно отмечать). Важно: перед оценкой проверь корректность ролей. Продавец — сотрудник компании Sternmeister (в транскрипции может быть “Стармейстер”, “Стернмейстер”, “Стенмейстер”), предлагающий и продающий Клиенту курс обучения на бухгалтера в Германии.
B45: 44 | C45: 44. Портрет клиента | D45: [Рекомендация] - данный критерий исключение, в качестве оценки напиши слово Рекомендация, а в обосновании оценки reason напиши следующее: На основе всей транскрипции составь подробный, но лаконичный портрет Клиента. Сконцентрируйся на том, что можно использовать для улучшения продаж, продукта и маркетинга. Структура ответа обязательна. А) Психологический и демографический портрет Клиента – Какой у Клиента темперамент, стиль принятия решений, степень уверенности – Проявлял ли инициативу, сомнение, страх, интерес — приведи цитаты – Есть ли особенности поведения: уточняет, игнорирует и тп – Укажи имя Клиента и любые контактные данные, если были озвучены Б) Цели и приоритеты Клиента – Какие задачи он хочет решить: смена профессии, повышение дохода, стабильность, уверенность – Какие боли и страхи звучали — страх не справиться, не найти работу, зря потратить деньги – Что он хочет получить от курса и в какие сроки – Приведи цитаты, подтверждающие мотивацию В) Дополнительные характеристики и предложения – Что можно извлечь из этого кейса для маркетинга (например, формулировки, триггеры, термины, каналы) – Какие УТП сработали бы сильнее – Какие фичи, бонусы, способы оплаты, форматы сопровождения могли бы повлиять – Что это говорит о сегменте/персоне/рынке — можно ли масштабировать Используй этот критерий как исследовательскую сводку: он помогает находить точки роста для всего бизнеса — от скрипта до упаковки продукта. Важно: перед оценкой проверь корректность ролей. Продавец — сотрудник компании Sternmeister (в транскрипции может быть “Стармейстер”, “Стернмейстер”, “Стенмейстер”), предлагающий и продающий Клиенту курс обучения на бухгалтера в Германии.
A46: Фильтры | B46: 45 | C46: 45. Сбой или прерывание разговора | D46: [1] – если звонок был прерван до логического завершения. Сюда относятся случаи, когда: – разговор закончился резко, не было логичного прощания вроде "до свидания, всего хорошего" и финальных фраз – видно, что диалог ещё шёл, но внезапно прервался – Клиент сказал, что сейчас не может говорить или попросил перезвонить позже – слышны сбои связи, обрывы, долгие паузы, и разговор завершился неестественно [0] – если разговор был полноценным и завершился логично. Сюда относятся ситуации, когда: – участники попрощались – разговор завершён финальной фразой, даже если Клиент отказался от покупки – в разговоре не было технических сбоев и он шёл до конца Важно: перед оценкой проверь корректность ролей. Продавец — сотрудник компании Sternmeister (в транскрипции может быть “Стармейстер”, “Стернмейстер”, “Стенмейстер”), предлагающий и продающий Клиенту курс обучения на бухгалтера в Германии.
B47: 46 | C47: 46. Звонок после прерывания | D47: Проверь, является ли звонок продолжением предыдущего общения (в том числе после обрыва связи или короткой первой попытки), либо это новый первичный контакт. Оцени только первые 1–3 минуты разговора. Ставь [1], если есть хоть один из признаков: – звонок является продолжением предыдущего общения, даже если в начале есть формальное приветствие. – отсутствует стандартное приветствие и полное представление: Продавец не называет компанию Sternmeister, имя и должность (менеджер приемной комиссии), не поясняет зачем звонит – Продавец сразу переходит к сути, задаёт уточняющие вопросы, обсуждает детали сделки/покупки или проводит презентацию – есть прямые отсылки к прошлому контакту: «давайте продолжим», «на чём мы остановились» – есть упоминания обрыва связи в начале диалога: «нас выбило», «извините, связь оборвалась...», «связь прервалась, давайте продолжим» – Клиент подтверждает вначале диалога, что уже было какое-то общение: «да-да, давайте продолжим», «да, что-то видимо со связью» [0] – звонок является первичным контактом. Все признаки нового общения: – Присутствует стандартное приветствие и полное представление: Продавец говорит, что звонит из компании Sternmeister, называвт свое имя и должность, поясняет зачем звонит – Продавец уточняет, удобно ли Клиенту говорить – Озвучивает план разговора, просит клиента рассказать о себе – нет отсылок к прошлому разговору, обрыву связи или общению в прошлом, Продавец общается с этим Клиентом впервые Важно: перед оценкой проверь корректность ролей. Продавец — сотрудник компании Sternmeister (в транскрипции может быть Стармейстер, Стернмейстер, Стенмейстер), предлагающий и продающий Клиенту курс обучения на бухгалтера в Германии.
B48: 47 | C48: 47. Продавец не слышит или затягивает разговор | D48: [1] – если Клиент сообщил, что хочет пройти обучение через государственную субсидию (например, через Gutschein / Jobcenter), или упомянул процесс оформления через Berater-а (консультанта), или сказал, что ему нужно предложение (Angebot) для подачи заявки. Всё это признаки, что он не хочет оплачивать курс сам, а рассчитывает на финансирование через государственные программы. Допустимые формулировки (могут звучать с ошибками, допускается транскрипционная неточность): – Клиент упоминает Gutschein (может звучать как гутшайн, гудшайн, гучайн и т. п.) – Упоминается Jobcenter (центр занятости, может быть сказано по-немецки или в вольной форме) – Упоминается Berater (бератор — консультант, куратор от Jobcenter) – Прозвучала фраза «мне нужно предложение / Angebot», «мне нужно подтверждение для бератора», «мой бератор ждёт от вас оффер» и т. п. [0] – если ни одна из тем выше не поднималась: – Клиент не говорил о субсидиях, Jobcenter, Gutschein – В разговоре не было упоминаний Berater-а, предложения (Angebot) или оформления через государственную программу – Клиент явно говорит, что будет оплачивать самостоятельно, или обсуждение идёт только про оплату и рассрочку от самой компании Важно: даже если Продавец упоминает Gutschein сам, но Клиент не подтверждает интерес, это не считается [1]. Важно: перед оценкой проверь корректность ролей. Продавец — сотрудник компании Sternmeister (в транскрипции может быть “Стармейстер”, “Стернмейстер”, “Стенмейстер”), предлагающий и продающий Клиенту курс обучения на бухгалтера в Германии.
A49: Скоринг | B49: 48 | C49: 48. Срочность | D49: Проверь, готов ли Клиент начать обучение в ближайшие 2 недели. Оцени выраженность готовности на основе всего диалога, включая подтверждения, уверенные ответы и мотивацию. [0-10] — Присвой оценку по шкале от 0 до 10: – [10] — если Клиент явно выражает готовность приступить в ближайшие 2 недели (например, "да, я хочу начать как можно скорее", "готов прямо сейчас"). – [5-9] — если Клиент говорит об этом с осторожностью или обсуждает, что пока рассматривает, но настроен позитивно. – [1-4] — если Клиент сомневается, говорит о необходимости подумать, обсудить с кем-то, но не закрывает вариант обучения. – [0] — если Клиент явно говорит, что не готов начинать в ближайшее время или категорически отказывается. – [Пусто] — если вопрос срочности не обсуждался в разговоре. В reasons укажи: – Примеры реплик Клиента, указывающие на его готовность или отсутствие готовности. – Контекст, в котором прозвучали эти слова. – Твой вывод, почему именно такая оценка. Важно: перед оценкой проверь корректность ролей. Продавец — сотрудник компании Sternmeister (в транскрипции может быть “Стармейстер”, “Стернмейстер”, “Стенмейстер”), предлагающий и продающий Клиенту курс обучения на бухгалтера в Германии.
B50: 49 | C50: 49. Платежеспособность | D50: Проверь, готов ли Клиент оплачивать курс самостоятельно (полная оплата или рассрочка), или он намерен использовать только гос. субсидии (Gutschein, Jobcenter). [0-10] — Присвой оценку по шкале от 0 до 10: – [10] — если Клиент готов оплачивать полностью или через рассрочку, демонстрируя уверенность в этом. – [5-9] — если обсуждалась рассрочка или другие способы оплаты, но Клиент не выразил полной уверенности. – [1-4] — если Клиент неуверенно говорит о возможности оплатить, обсуждает Jobcenter, но рассматривает и личную оплату. – [0] — если Клиент явно заявляет, что не сможет оплатить или хочет только через гос. субсидию. – [Пусто] — если тема оплаты вообще не обсуждалась в разговоре. В reasons укажи: – Реплики Клиента, указывающие на готовность или отсутствие готовности оплатить. – Контекст, в котором обсуждались способы оплаты. – Твой вывод, почему именно такая оценка. Важно: перед оценкой проверь корректность ролей. Продавец — сотрудник компании Sternmeister (в транскрипции может быть “Стармейстер”, “Стернмейстер”, “Стенмейстер”), предлагающий и продающий Клиенту курс обучения на бухгалтера в Германии.
B51: 50 | C51: 50. Потребность | D51: Проверь, понимает ли Клиент ценность обучения для себя и готов ли учиться. Оцени выраженность потребности на основе диалога. [0-10] — Присвой оценку по шкале от 0 до 10: – [10] — если Клиент явно понимает, зачем ему обучение, говорит об этом уверенно и мотивированно. – [5-9] — если обсуждает обучение, но с сомнениями или осторожностью. – [1-4] — если говорит о возможной потребности, но не уверен в необходимости обучения. – [0] — если явно говорит, что не видит ценности или не хочет учиться. – [Пусто] — если вопрос необходимости обучения не поднимался в разговоре. В reasons укажи: – Цитаты Клиента, которые раскрывают его отношение к обучению. – Контекст обсуждения этой темы. – Твой вывод, почему именно такая оценка. Важно: перед оценкой проверь корректность ролей. Продавец — сотрудник компании Sternmeister (в транскрипции может быть “Стармейстер”, “Стернмейстер”, “Стенмейстер”), предлагающий и продающий Клиенту курс обучения на бухгалтера в Германии.
B52: 51 | C52: 51. Итоговый скоринг | D52: [0-30] — Суммарное значение оценки по критериям 47,48 и 49. Если в каком-то из критериев 47-49 оценка "Пусто", то она суммируется как 0. Для примера приведу расчет, считаем сумму трех оценок 47,48,49 критерия: 5 + 2 + Пусто = 5 + 2 + 0 = 7, тогда оценка данного критерия итогового скоринга - 7 В reasons укажи: – Сумму оценок по каждому критерию. – Примеры реплик, которые повлияли на общую оценку. – Общий вывод по скорингу клиента в формате: "Высокая готовность / Средняя готовность / Низкая готовность". Важно: перед оценкой проверь корректность ролей. Продавец — сотрудник компании Sternmeister (в транскрипции может быть “Стармейстер”, “Стернмейстер”, “Стенмейстер”), предлагающий и продающий Клиенту курс обучения на бухгалтера в Германии.

Sheet Лист2
A1: number | B1: call_name | C1: transcription | D1: default_call_week | E1: id_item_set | F1: real_file_duration | G1: item_set_created_at | H1: item_set_updated_at | I1: month_of_processing | J1: call_parts_count | K1: call_date | L1: call_duration | M1: call_id | N1: call_phone | O1: call_source | P1: call_time | Q1: call_type | R1: call_week | S1: contact_id | T1: contact_name | U1: contact_type | V1: lead_created_at | W1: lead_id | X1: field_866934 | Y1: lead_name | Z1: lead_pipeline | AA1: lead_status | AB1: lead_url | AC1: user_id | AD1: user_name | AE1: score_0 | AF1: reason_0 | AG1: quote_0 | AH1: score_1 | AI1: reason_1 | AJ1: quote_1 | AK1: score_2 | AL1: reason_2 | AM1: quote_2 | AN1: score_3 | AO1: reason_3 | AP1: quote_3 | AQ1: score_4 | AR1: reason_4 | AS1: quote_4 | AT1: score_5 | AU1: reason_5 | AV1: quote_5 | AW1: score_6 | AX1: reason_6 | AY1: quote_6 | AZ1: score_7 | BA1: reason_7 | BB1: quote_7 | BC1: score_8 | BD1: reason_8 | BE1: quote_8 | BF1: score_9 | BG1: reason_9 | BH1: quote_9 | BI1: score_10 | BJ1: reason_10 | BK1: quote_10 | BL1: score_11 | BM1: reason_11 | BN1: quote_11 | BO1: score_12 | BP1: reason_12 | BQ1: quote_12 | BR1: score_13 | BS1: reason_13 | BT1: quote_13 | BU1: score_14 | BV1: reason_14 | BW1: quote_14 | BX1: score_15 | BY1: reason_15 | BZ1: quote_15 | CA1: score_16 | CB1: reason_16 | CC1: quote_16 | CD1: score_17 | CE1: reason_17 | CF1: quote_17 | CG1: score_18 | CH1: reason_18 | CI1: quote_18 | CJ1: score_19 | CK1: reason_19 | CL1: quote_19 | CM1: score_20 | CN1: reason_20 | CO1: quote_20 | CP1: score_21 | CQ1: reason_21 | CR1: quote_21 | CS1: score_22 | CT1: reason_22 | CU1: quote_22 | CY1: score_23 | CZ1: reason_23 | DA1: quote_23 | DB1: score_24 | DC1: reason_24 | DD1: quote_24 | DE1: score_25 | DF1: reason_25 | DG1: quote_25 | DH1: score_26 | DI1: reason_26 | DJ1: quote_26 | DK1: score_27 | DL1: reason_27 | DM1: quote_27 | DN1: score_28 | DO1: reason_28 | DP1: quote_28 | DQ1: score_29 | DR1: reason_29 | DS1: quote_29 | DT1: score_30 | DU1: reason_30 | DV1: quote_30 | DW1: score_31 | DX1: reason_31 | DY1: quote_31 | DZ1: score_32 | EA1: reason_32 | EB1: quote_32 | EC1: score_33 | ED1: reason_33 | EE1: quote_33 | EF1: score_34 | EG1: reason_34 | EH1: quote_34 | EI1: score_35 | EJ1: reason_35 | EK1: quote_35 | EL1: score_36 | EM1: reason_36 | EN1: quote_36 | EO1: score_37 | EP1: reason_37 | EQ1: quote_37 | ER1: score_38 | ES1: reason_38 | ET1: quote_38 | EU1: score_39 | EV1: reason_39 | EW1: quote_39 | EX1: score_40 | EY1: reason_40 | EZ1: quote_40 | FA1: score_41 | FB1: reason_41 | FC1: quote_41 | FD1: score_42 | FE1: reason_42 | FF1: quote_42 | FG1: score_43 | FH1: reason_43 | FI1: quote_43 | FJ1: score_44 | FK1: reason_44 | FL1: quote_44 | FM1: score_45 | FN1: reason_45 | FO1: quote_45 | FP1: score_46 | FQ1: reason_46 | FR1: quote_46 | FS1: score_47 | FT1: reason_47 | FU1: quote_47 | FV1: score_48 | FW1: reason_48 | FX1: quote_48 | FY1: score_49 | FZ1: reason_49 | GA1: quote_49 | GB1: score_50 | GC1: reason_50 | GD1: quote_50
A2: 175 // CL 46, PR 82___94c64a | B2: =COUNTA(UNIQUE(B4:B1000)) -> 7 | C2: =COUNTA(UNIQUE(C4:C1000)) -> 7 | D2: 61 с 27 | E2: 153 тот | F2: =SUM(F4:F1000)/60 -> 0 | K2: CRM | L2: =SUM(L4:L1000)/60 -> 158.93333 | M2: =roundup(sum(L585:L823)/60,0) -> 0 | N2: =roundup(sum(L824:L1103)/60,0) -> 0 | O2: =roundup(sum(L1000:L1104)/60,0) -> 0 | AE2: Установление контакта | AQ2: Выявление потребностей | BL2: Презентация продукта | BR2: Предзакрытие и ФОМО | CA2: Отработка возражений | CP2: Этап оплаты | DE2: Стандарты общения | DQ2: Критические ошибки | DZ2: Экспертный блок | EU2: Рекомендации | FJ2: Фильтры | FS2: Скоринг | GQ2: =COUNTA(GQ4:GQ1000) -> 7
A3: Номер | B3: Название файла звонка | C3: Транскрипция | D3: Неделя звонка | E3: Item Set ID | F3: Real File Duration | G3: Дата создания сета | H3: Дата анализа | I3: Месяц анализа | J3: Количество частей | K3: Дата звонка | L3: Длительность | M3: ID звонка | N3: Телефон | O3: Источник | P3: Время звонка | Q3: Тип звонка | R3: Номер недели | S3: ID контакта | T3: ФИО контакта | U3: Тип контакта | V3: Дата создания сделки | W3: ID сделки | X3: Категория | Y3: Название сделки | Z3: Воронка сделки | AA3: Этап сделки | AB3: Ссылка на сделку | AC3: ID менеджера | AD3: ФИО менеджера | AE3: 1 1. Приветствие и установление контакта | AF3: 1 1. Приветствие и установление контакта ПРИЧИНА | AG3: 1 Цитата | AH3: 2 2. Озвучен план разговора (программирование) | AI3: 2 2. Озвучен план разговора (программирование) Причина | AJ3: 2 Цитата | AK3: 3 3. Корректная отработка вопроса о стоимости (если он прозвучал) | AL3: 2 2. Озвучен план разговора (программирование) Причина | AM3: 3 Цитата | AN3: 4 4. Корректная отработка вопроса о JobCenter (если он прозвучал) | AO3: 4 4. Корректная отработка вопроса о JobCenter (если он прозвучал) Причина | AP3: 4 Цитата | AQ3: 5 5. Small talk и установление контакта | AR3: 5 Причина | AS3: 5 Цитата | AT3: 6 6. Точка А (выявить и усилить боль) | AU3: 6 Причина | AV3: 6 Цитата | AW3: 7 7. Ситуативные вопросы в Точке А | AX3: 7 Причина | AY3: 7 Цитата | AZ3: 8 8. Точка В (ожидания, готовность, срочность) | BA3: 8 Причина | BB3: 8 Цитата | BC3: 9 9. Уточнение SMART-целей Клиента | BD3: 9 Причина | BE3: 9 Цитата | BF3: 10 10. Преимущества профессии Бухгалтера | BG3: 10 Причина | BH3: 10 Цитата | BI3: 11 11. Резюмирование целей и сроков перед презентацией | BJ3: 11 Причина | BK3: 11 Цитата | BL3: 12 12. Презентация проведена с опорой на цели и запрос Клиента | BM3: 12 Причина | BN3: 12 Цитата | BO3: 13 13. Презентация проведена в формате диалога, с вовлечением Клиента | BP3: 13 Причина | BQ3: 13 Цитата | BR3: 14 14. Что откликнулось Клиенту в презентации и готовность клиента начать | BS3: 14 Причина | BT3: 14 Цитата | BU3: 15. Предзакрытие, FOMO и тактика дефицита | BV3: 15 Причина | BW3: 15 Цитата | BX3: 16. Реферальная программа | BY3: 16 Причина | BZ3: 16 Цитата | CA3: 16 16. Какие возражения озвучил Клиент (теги) | CB3: 16 Причина | CC3: 16 Цитата | CD3: 17 17. Сколько возражений отработал Продавец и насколько корректно | CE3: 17 Причина | CF3: 17 Цитата | CG3: 18 18. Продавец корректно отработал ложные возражения (“подумаю”, “посоветуюсь”, “не сейчас”) | CH3: 18 Причина | CI3: 18 Цитата | CJ3: 19 19. Какие техники отработки возражений стоило бы применить Продавцу | CK3: 19 Причина | CL3: 19 Цитата | CM3: 20 20. Как Продавец отработал вопросы Клиента (не только возражения) | CN3: 20 Причина | CO3: 20 Цитата | CP3: 21 21. Продавец порекомендовал вариант оплаты и дал аргументацию | CQ3: 21 Причина | CR3: 21 Цитата | CS3: 22 22. Продавец узнал, подходит ли предложенный вариант оплаты Клиенту | CT3: 22 Причина | CU3: 22 Цитата | CV3: 23 23. Продавец рассказал о способах оплаты | CW3: 23 Причина | CX3: 23 Цитата | CY3: 24. Продавец предложил приступить к обучению | CZ3: 24 Причина | DA3: 24 Цитата | DB3: 25 25. Следующие шаги | DC3: 25 Причина | DD3: 25 Цитата | DE3: 26 26. Применение сторителлинга | DF3: 26 Причина | DG3: 26 Цитата | DH3: 27 27. Общая доброжелательность и вежливость Продавца | DI3: 27 Причина | DJ3: 27 Цитата | DK3: 28 28. Продавец использовал активное слушание и отзеркаливание Клиента | DL3: 28 Причина | DM3: 28 Цитата | DN3: 29 29. Продавец был корректен и сохранял самоконтроль | DO3: 29 Причина | DP3: 29 Цитата | DQ3: 30 30. Критические ошибки с точки зрения компании | DR3: 30 Причина | DS3: 30 Цитата | DT3: 31 31. Критические ошибки с точки зрения клиента | DU3: 31 Причина | DV3: 31 Цитата | DW3: 32 32. Критические ошибки с точки зрения закона | DX3: 32 Причина | DY3: 32 Цитата | DZ3: 33 33. Talk ratio Продавца | EA3: 33 Причина | EB3: 33 Цитата | EC3: 34 34. Оценка звонка по международным методологиям | ED3: 34 Причина | EE3: 34 Цитата | EF3: 35 35. Структура звонка: фактический скрипт, который применил Продавец | EG3: 35 Причина | EH3: 35 Цитата | EI3: 36 36. Что заставит этого Клиента купить (тип, реакция и болеутоляющая формула) | EJ3: 36 Причина | EK3: 36 Цитата | EL3: 37 37. Неиспользованные УТП, которые могли бы повлиять | EM3: 37 Причина | EN3: 37 Цитата | EO3: 38 38. Потеря клиента на этапе оплаты | EP3: 38 Причина | EQ3: 38 Цитата | ER3: 39. Экспертный стиль установновления раппорта | ES3: 39 Причина | ET3: 39 Цитата | EU3: 40 40. Краткое резюме звонка | EV3: 39 Причина | EW3: 39 Цитата | EX3: 40 40. Упоминание конкурентов и реакция Продавца | EY3: 40 Причина | EZ3: 40 Цитата | FA3: 41 41. Рекомендации Продавцу: зоны роста | FB3: 41 Причина | FC3: 41 Цитата | FD3: 42 42. Рекомендации Продавцу: лучшие практики | FE3: 42 Причина | FF3: 42 Цитата | FG3: 43 43. Портрет клиента | FH3: 43 Причина | FI3: 43 Цитата | FJ3: 44 44. Сбой или прерывание разговора | FK3: 44 Причина | FL3: 44 Цитата | FM3: 45 45. Звонок после прерывания | FN3: 45 Причина | FO3: 45 Цитата | FP3: 46 46. Продавец не слышит или затягивает разговор | FQ3: 46 Причина | FR3: 46 Цитата | FS3: 47 47. Срочность | FT3: 47 Причина | FU3: 47 Цитата | FV3: 48 48. Платежеспособность | FW3: 48 Причина | FX3: 48 Цитата | FY3: 49 49. Потребность | FZ3: 49 Причина | GA3: 49 Цитата | GB3: 50 50. Итоговый скоринг | GC3: 50 Причина | GD3: 50 Цитата | GE3: =IFERROR(SUM(R[0]C[-156],R[0]C[-153],R[0]C[-150],R[0]C[-147])/COUNT(R[0]C[-156],R[0]C[-153],R[0]C[-150],R[0]C[-147]),"Установление контакта") -> #ERROR! | GF3: =IFERROR(SUM(R[0]C[-145],R[0]C[-142],R[0]C[-139],R[0]C[-136],R[0]C[-133],R[0]C[-130],R[0]C[-127])/COUNT(R[0]C[-145],R[0]C[-142],R[0]C[-139],R[0]C[-136],R[0]C[-133],R[0]C[-130],R[0]C[-127]),"Выявление потребностей") -> #ERROR! | GG3: =IFERROR(SUM(R[0]C[-125],R[0]C[-122])/COUNT(R[0]C[-125],R[0]C[-122]),"Презентация продукта") -> #ERROR! | GH3: =IFERROR(SUM(R[0]C[-120],R[0]C[-117])/COUNT(R[0]C[-120],R[0]C[-117]),"Предзакрытие и ФОМО") -> #ERROR! | GI3: =IFERROR(SUM(R[0]C[-112],R[0]C[-109],R[0]C[-106],R[0]C[-103],R[0]C[-100])/COUNT(R[0]C[-112],R[0]C[-109],R[0]C[-106],R[0]C[-103],R[0]C[-100]),"Отработка возражений") -> #ERROR! | GJ3: =IFERROR(SUM(R[0]C[-98],R[0]C[-95],R[0]C[-92],R[0]C[-89],R[0]C[-86])/COUNT(R[0]C[-98],R[0]C[-95],R[0]C[-92],R[0]C[-89],R[0]C[-86]),"Этап оплаты") -> #ERROR! | GK3: =IFERROR(SUM(R[0]C[-84],R[0]C[-81],R[0]C[-78],R[0]C[-75])/COUNT(R[0]C[-84],R[0]C[-81],R[0]C[-78],R[0]C[-75]),"Стандарты общения") -> #ERROR! | GL3: =IFERROR(SUM(R[0]C[-73],R[0]C[-70],R[0]C[-67])/COUNT(R[0]C[-73],R[0]C[-70],R[0]C[-67]),"Критические ошибки") -> #ERROR! | GM3: =IFERROR(SUM(R[0]C[-65],R[0]C[-62],R[0]C[-59],R[0]C[-56],R[0]C[-53],R[0]C[-50])/COUNT(R[0]C[-65],R[0]C[-62],R[0]C[-59],R[0]C[-56],R[0]C[-53],R[0]C[-50]),"Экспертный блок") -> #ERROR! | GN3: =IFERROR(SUM(R[0]C[-45],R[0]C[-42],R[0]C[-39],R[0]C[-36],R[0]C[-33])/COUNT(R[0]C[-45],R[0]C[-42],R[0]C[-39],R[0]C[-36],R[0]C[-33]),"Рекомендации") -> #ERROR! | GO3: =IFERROR(SUM(R[0]C[-31],R[0]C[-28],R[0]C[-25])/COUNT(R[0]C[-31],R[0]C[-28],R[0]C[-25]),"Фильтры") -> #ERROR! | GP3: =IFERROR(SUM(R[0]C[-23],R[0]C[-20],R[0]C[-17],R[0]C[-14])/COUNT(R[0]C[-23],R[0]C[-20],R[0]C[-17],R[0]C[-14]),"Скоринг") -> #ERROR! | GQ3: Итоговый процент за звонок | GR3: Длительность (мин) | GS3: Группы Итог скоринга | GT3: Группы Срочность | GU3: Группы Платежеспособность | GV3: Группы Потребность | GW3: Месяц
A4: 1 | B4: 172471940_1816745793_1f2ee2 | C4: https://docs.google.com/document/d/1wi9p93DNcOQ93kH_4AzYMf40jy5CTXDeq5KrBEOG2NA/edit?usp=drivesdk | D4: 2025-06-30 - 2025-07-06 | I4: 2025.07 | K4: 2025-07-05 | L4: 1092 | M4: 172471940_1816745793 | N4: +491754495379, Статус: Разговор состоялся | O4: CallGear | P4: 11:02:00+02:00 | Q4: Исходящий | R4: 28 | S4: 15237002 | T4: Ulya Alakbarova | U4: Контакт | V4: 2025-07-05T10:43:28+02:00 | W4: 12651206 | Y4: Lead from: https://sternmeister.de/education?utm_source=facebook&utm_id=lp_short&utm_medium=site_nikita&utm_campaign=nikita_mainfunnel_education_3&utm_term=lal2_qual_noage_noint_nolang_3&utm_content=video5_newcreo_main&fbclid=PAZXh0bgNhZW0BMABhZGlkAasgu16 | Z4: Pipeline | AA4: Новый лид | AB4: https://sternmeister.kommo.com/leads/detail/12651206 | AC4: 13271835 | AD4: Антон Громов | AE4: 1 | AF4: Продавец полностью соблюдает структуру приветствия. Он поздоровался, представился (Антон), назвал компанию (Штермейстер), указал причину звонка (по поводу бухгалтерии) и получил подтверждение от клиента. Все необходимые элементы присутствуют. | AG4: 00:00:02.97 - Продавец: Здравствуйте, это Антон из Штермейстера. По поводу бухгалтерии звоню. Интересовались учебой, верно?, 00:00:08.81 - Клиент: Да. | AH4: 1 | AI4: Продавец четко озвучил план разговора, включив все необходимые смысловые блоки: уточнил удобство времени, объяснил структуру беседы (познакомимся, обсудим цели, расскажу про обучение), и подготовил к принятию решения (если подойдем друг к другу, помогу зачислиться). | AJ4: 00:00:10.03 - Продавец: Вам сейчас удобно побеседовать? Примерно? Хорошо. Тогда познакомимся, обсудим ваши цели, задачи. Я подробнее расскажу про обучение, про все наши условия. Если друг к другу подойдем, тогда помогу зачислиться. Вот такой формат, договорились?, 00:00:31.40 - Клиент: Да. | AL4: Клиент задал вопрос о стоимости только в самом конце разговора (17:44), когда уже была проведена презентация и выяснены потребности. Вопрос прозвучал не в начале разговора, поэтому данный критерий неприменим. | AM4: 00:17:44.00 - Клиент: И еще, пожалуйста, скажите, а сколько будет за 7 месяцев? | AO4: Тема JobCenter и финансирования через субсидии не поднималась в разговоре. Клиент не задавал вопросов о Gutschein, Berater или других формах государственного финансирования. | AQ4: 1 | AR4: Продавец успешно выяснил ключевую информацию о клиенте: сколько лет живет в Германии (10 лет), уровень языка (B1), предыдущий опыт работы (25 лет бухгалтером в Азербайджане), текущую деятельность (клининговая фирма). Контакт установлен эффективно. | AS4: 00:00:32.50 - Продавец: Так, Ульяна, а вы вообще давно в Германии живете?, 00:00:38.58 - Клиент: Десять лет., 00:00:54.24 - Клиент: У меня 25 лет работала. Но не... не в Германии., 00:01:29.34 - Клиент: Ну, у нас своя фирма небольшая, клининговая. | AT4: 1 | AU4: Продавец получил информацию по всем элементам Точки А: опыт (25 лет бухгалтером), текущая ситуация (работает в клининге, что ей не нравится), попытки изменить ситуацию (поэтому обратилась к ним), видение решения (вернуться в бухгалтерию). Боль клиента четко выявлена - она устала от неподходящей работы. | AV4: 00:01:53.00 - Клиент: Ну, это не мое. Убираю., 00:02:20.30 - Клиент: Я не люблю., 00:02:36.50 - Клиент: Поэтому я решила к вам написать., 00:02:55.05 - Клиент: Не хочу больше. | AW4: 1 | AX4: Продавец задал уточняющие вопросы о влиянии текущей ситуации на жизнь клиента. Он спросил 'как это сказывается на жизни, на вас, на самой?' и 'что значит не мое', выясняя глубину проблемы и ее влияние на клиента. | AY4: 00:02:08.00 - Продавец: А как это сказывается на жизни, на вас, на самой?, 00:02:10.42 - Продавец: Ну, я не совсем понимаю, что значит не мое. Это может быть физически тяжело, или денег мало, или вот что мне не нравится. | AZ4: 1 | BA4: Продавец получил информацию по всем элементам SMART: цель (вернуться в бухгалтерию), доход (4 тысячи в месяц), значимость (работать в любимой сфере), срок (чем быстрее, тем лучше). Также обсуждалось, что клиент в любом случае будет менять ситуацию. | BB4: 00:05:16.80 - Клиент: Хотелось бы и 4 тысячи в месяц., 00:04:10.30 - Клиент: Чем быстрее, тем лучше., 00:04:40.50 - Клиент: Я в любом случае меняю., 00:04:47.00 - Клиент: хочу в своей любимой работе быть. | BC4: 0 | BD4: Хотя клиент дал расплывчатый ответ по срокам ('чем быстрее, тем лучше'), продавец не помог ему сформулировать более конкретные временные рамки. Продавец принял ответ и сам предложил сроки (7 месяцев + 1 месяц на трудоустройство), но не добился от клиента четкого определения желаемых сроков. | BE4: 00:04:10.30 - Клиент: Чем быстрее, тем лучше., 00:04:12.30 - Продавец: Чем быстрее, тем лучше. Но у нас обучение занимает 7 месяцев и трудоустройство примерно в течение еще одного месяца. | BF4: 1 | BG4: Продавец упомянул важные преимущества профессии бухгалтера: средний годовой доход (47 тысяч евро), что соответствует требуемым фразам о зарплатах. Хотя он не использовал все возможные фразы о социальном пакете, он применил ключевую информацию о доходах. | BH4: 00:05:36.60 - Продавец: Бухгалтер, который только начинает в Германии, в год в среднем 47 тысяч евро получается. Получается на вычет налогов. | BI4: 1 | BJ4: Продавец четко резюмировал ключевые моменты: текущую ситуацию клиента (10 лет в Германии, B1, 25 лет опыта, работает в клининге), цели (вернуться в бухгалтерию как можно быстрее), и получил подтверждение правильности понимания от клиента. | BK4: 00:05:46.50 - Продавец: В целом, на самом деле, ключевые моменты мне более-менее понятны. Тогда давайте я кратенько подрезюмирую... Вы мне рассказали про себя, что 10 лет живете в Германии, язык у вас B1, и до этого 25 лет работали бухгалтером... И сейчас работаете в клининговой сфере... и задача стоит вернуться в любимую сферу как можно быстрее. Правильно я вас слышал? | BL4: 1 | BM4: Продавец адаптировал презентацию под цели клиента, делая прямые отсылки к ее ситуации: 'У вас стаж 25 лет, прекрасно, вы на 100% подходите', 'мы идем до трудоустройства', 'именно ради работы'. Презентация была четко связана с потребностями клиента. | BN4: 00:07:05.60 - Продавец: У вас стаж 25 лет, прекрасно, вы на 100% подходите., 00:07:05.60 - Продавец: То есть наша задача дать полноценную профессиональную переподготовку, все время сопровождать и помочь с трудоустройством. | BO4: 1 | BP4: Продавец вовлекал клиента в диалог, задавая вопросы: 'Вам вообще для себя, как думаете, что важно в преподавателях?', 'Вы с ними знакомы?', 'Вот здесь по языку все ли понятно, все ли подходит?'. Презентация шла в живом формате с активным участием клиента. | BQ4: 00:08:00.67 - Продавец: Вам вообще для себя, как думаете, что важно в преподавателях? Какие это должны быть люди?, 00:09:52.90 - Продавец: У нас дверственная программа «Датов» и «Лексус». Вы с ними знакомы?, 00:11:41.33 - Продавец: Вот здесь по языку все ли понятно, все ли подходит? | BR4: 0 | BS4: Продавец не задал вопрос о том, что клиенту особенно понравилось в презентации, и не уточнил готовность начать при подходящей стоимости. Клиент сама задала вопрос о стоимости в конце, но продавец не проверил реакцию на презентацию и готовность к началу. | BT4: 00:17:29.42 - Продавец: Мы называемся Штермейстер и обучаем профессии финансового бухгалтера в Германии., 00:17:44.00 - Клиент: И еще, пожалуйста, скажите, а сколько будет за 7 месяцев? | BU4: 0 | BV4: Продавец не создал FOMO-эффект. Презентация была завершена без создания ощущения упущенной выгоды или ограниченности предложения. Клиент сразу перешла к вопросу о стоимости без какого-либо воздействия срочности со стороны продавца. | BW4: 00:17:25.25 - Продавец: Также у нас проходит стажировка в реальной компании... Всему этому обучаем., 00:17:44.00 - Клиент: И еще, пожалуйста, скажите, а сколько будет за 7 месяцев? | CA4: 0 | CB4: В разговоре клиент не выдвинул возражений против обучения. Единственный вопрос касался стоимости в самом конце разговора, но это был информационный запрос, а не возражение. Разговор прервался до обсуждения цены и потенциальных возражений. | CC4: 00:17:44.00 - Клиент: И еще, пожалуйста, скажите, а сколько будет за 7 месяцев? | CE4: Возражения в разговоре не прозвучали, поэтому данный критерий неприменим. | CH4: Ложных возражений не было в разговоре. | CJ4: 0 | CK4: А) В данном звонке возражения не прозвучали, поскольку разговор прервался до этапа обсуждения стоимости и принятия решения. Б) Анализ с точки зрения методик продаж: - SPIN-продажи: Продавец хорошо выявил ситуацию (S) и проблему (P), но не развил импликации (I) - как текущая ситуация влияет на жизнь клиента в долгосрочной перспективе. - Challenger Sale: Отсутствовал вызов - продавец не показал клиенту новую перспективу или скрытые проблемы. - NEAT: Need (потребность) выявлена, Economic impact (экономическое влияние) затронуто поверхностно, Authority (полномочия) и Timeline (временные рамки) проработаны слабо. В) Примеры фраз для будущих случаев: 1. Для методики SPIN: 'Если ситуация не изменится в следующие 2-3 года, как это повлияет на ваше финансовое положение и самооценку?' 2. Для Challenger: 'Многие думают, что опыт 25 лет - это преимущество, но работодатели в Германии часто видят это как риск устаревших методов' 3. Для создания срочности: 'Каждый месяц без смены профессии - это потеря 3000+ евро потенциального дохода' Эти подходы помогли бы: укрепить эмоциональную мотивацию, выявить скрытые страхи и создать ощущение важности быстрого решения. | CM4: 0 | CN4: А) Вопросы клиента по ходу разговора: 1. 00:09:45.47 - о названии программы ('А какая программа? Как называется программа?') 2. 00:13:12.59 - о названии компании ('как называется, ваша программа... ваша фирма') 3. 00:13:20.80 - о подтверждении в Германии ('И вы прошедшиеся подтвержденные в Германии, да?') 4. 00:16:00.68 - уточнение о стажировке ('Типа как практика, что ли?') 5. 00:17:44.00 - о стоимости ('сколько будет за 7 месяцев?') Б) Качество ответов: 1. На вопрос о программах - дал четкий ответ: 'Датов и Лексус' 2. О названии компании - ответил полно: 'Штермейстер' 3. О подтверждении - ответ был корректным но кратким 4. О стажировке - подтвердил как практику 5. О стоимости - разговор прервался до ответа В) Неотвеченные вопросы: Вопрос о стоимости остался без ответа из-за прерывания разговора. Лучший ответ: 'Стоимость 3500 евро при полной оплате со скидкой 400 евро, или рассрочка без процентов. Но сначала давайте убедимся, что программа вам подходит' Влияние: Отсутствие ответа о цене не позволило перейти к этапу закрытия сделки. | CO4: 00:09:45.47 - Клиент: А какая программа? Как называется программа?, 00:17:44.00 - Клиент: И еще, пожалуйста, скажите, а сколько будет за 7 месяцев? | CQ4: Разговор не дошёл до этапа обсуждения оплаты. Клиент задал вопрос о стоимости в самом конце, но разговор прервался до того, как продавец смог представить варианты оплаты. | CT4: Обсуждение оплаты не началось или прервалось до этого момента. | CW4: Разговор не дошёл до обсуждения способов оплаты или клиент не выражал согласия оплачивать. | CZ4: Разговор прервался до попытки закрытия сделки. | DB4: 1 | DC4: Продавец зафиксировал следующий шаг - договорился о повторном звонке через полчаса, когда у клиента освободится время для завершения разговора. | DD4: 00:17:59.75 - Оператор: Хорошо, давайте., 00:18:00.98 - Клиент: Ага, наполовину ставим, потому что у него срочное дело здесь вышло. | DE4: 0 | DF4: Продавец не применил сторителлинг и не рассказал ни одной истории успеха клиентов курса. Презентация была информативной, но без примеров конкретных людей, которые прошли обучение. | DH4: 1 | DI4: Продавец обращался к клиенту по имени (Ульяна), использовал вежливые выражения ('спасибо', 'пожалуйста'), поддерживал уважительный тон, подстраивался под темп клиента, проявлял терпение при уточняющих вопросах. | DJ4: 00:00:32.50 - Продавец: Так, Ульяна, а вы вообще давно в Германии живете?, 00:18:06.57 - Оператор: Хорошо, ладно, спасибо. | DK4: 1 | DL4: Продавец активно слушал, использовал подтверждающие фразы ('понятно', 'хорошо', 'угу'), перефразировал важные мысли клиента в резюмировании, реагировал на реплики клиента уточняющими вопросами, поддерживал живой диалог. | DM4: 00:01:23.50 - Продавец: Понятно., 00:01:44.80 - Продавец: Хорошо. Понятно., 00:05:46.50 - Продавец: Правильно я вас слышал? | DN4: 1 | DO4: Продавец не перебивал клиента, сохранял спокойный профессиональный тон, терпеливо отвечал на вопросы, не проявлял признаков раздражения даже когда клиент просила о переносе звонка. | DP4: 00:17:59.75 - Оператор: Хорошо, давайте., 00:18:06.57 - Оператор: Хорошо, ладно, спасибо. | DQ4: 0 | DR4: Продавец не допустил критических ошибок: не высказывался негативно о компании, не отговаривал клиента от покупки, зафиксировал следующий шаг (повторный звонок через полчаса) с конкретикой по времени. | DS4: 00:17:59.75 - Оператор: Хорошо, давайте. | DT4: 0 | DU4: Продавец не допустил критических ошибок: информация о курсе была корректной (7 месяцев, онлайн формат, русский язык, программы Datev и Lexware), поведение было уважительным, ответы корректные. Все данные соответствовали официальной информации о курсе Sternmeister. | DW4: 0 | DX4: Критических нарушений с точки зрения закона не зафиксировано. Продавец не давал ложных гарантий трудоустройства, не разглашал внутреннюю информацию, не делал неправомерных обещаний по лицензиям. Рассказ о курсе соответствовал допустимым рамкам B2C-продажи образовательных услуг. | DZ4: 83 | EA4: Диалог длился 1078 секунд. Продавец говорил 894 секунды, Клиент — 184 секунды. У Продавца — 35 реплик, у Клиента — 33 реплики. Соотношение: 894 / 1078 = 83%. | EC4: 35 | ED4: 1. Консультативные продажи 2.0 - 7/10: Продавец хорошо выявил потребности и построил доверие, но слишком много говорил сам вместо активного слушания. Нужно было больше вопросов типа 'Что для вас самое важное в выборе курса?' 2. Эмоциональный резонанс - 8/10: Отлично выявил эмоциональную боль клиента (усталость от неподходящей работы), но не использовал сторителлинг. Добавить: 'Представьте: через 8 месяцев вы приходите на работу бухгалтером с улыбкой' 3. Продажи на основе потребностей - 7/10: Четко выявил потребности, но не приоритизировал их. Нужно было спросить: 'Что важнее - быстрый старт или минимальная цена?' 4. Story-Based Selling - 4/10: Полностью отсутствовали истории успеха. Нужно было: 'У нас была Виктория, тоже 20+ лет опыта, сейчас работает финансовым директором' 5. Модель 4P - 9/10: Отлично определил проблему, пообещал результат, но не хватало доказательств и конкретного предложения. Итого: 7 + 8 + 7 + 4 + 9 = 35 | EF4: 0 | EG4: А) Фактический скрипт продавца: 1. Приветствие и подтверждение заявки 2. Программирование разговора 3. Small talk - выяснение базовой информации 4. Точка А - выявление текущей ситуации и боли 5. Точка В - выяснение целей и желаемых результатов 6. Резюмирование 7. Презентация курса с вовлечением клиента 8. Обрыв на вопросе о стоимости Б) Особенности: Продавец следовал классической структуре, но не дошел до этапа закрытия сделки из-за внешних обстоятельств. В) Сработавшие элементы: Клиент активно участвовала в диалоге, отвечала на вопросы, проявила интерес к программам обучения, задавала уточняющие вопросы о курсе. Г) Не сработавшие элементы: Разговор прервался до получения решения. Клиент не выразила явной готовности к покупке, разговор завершился без конкретного результата по продаже. | EI4: 0 | EJ4: А) Что уже сработало: - Четкая структура презентации и логичные объяснения - Конкретная информация о программах (Datev, Lexware) - Данные о доходах бухгалтеров (47 тысяч евро) - Подтверждение соответствия её опыта требованиям Б) Что могло бы сработать сильнее: - Больше фактов и статистики о трудоустройстве - Сравнительный анализ с конкурентами - Четкий план пошагового обучения - Гарантии и сертификации В) Pain-killer line: 'Ульяна, за 3 года в клининге вы потеряли около 120 тысяч евро разницы в зарплате по сравнению с бухгалтером. Каждый месяц промедления - это еще минус 3000 евро. Стоимость курса окупится за 1 месяц работы.' Эта фраза сработает для рационального типа, так как оперирует конкретными цифрами и экономической логикой. Лучший момент - перед обсуждением стоимости. Г) На следующем контакте: - Начать с цифр и фактов - Предоставить детальную программу курса - Показать примеры сертификатов и документов - Не давить эмоционально, дать время на анализ | EL4: 0 | EM4: А) Боли и интересы клиента vs УТП: - Языковой барьер → не раскрыт УТП 'Немецкий язык для бухгалтеров' - Неуверенность в трудоустройстве → слабо презентован 'Карьерный центр + бот для тренировок интервью' - Желание быстрого результата → не упомянута 'Персонализированная система мотивации' Б) Поверхностно раскрытые УТП: - Стажировка упомянута кратко, не раскрыта ценность реального опыта - Сертификат AZAV не объяснен как государственное признание - 70% практики названо, но не показано на конкретных примерах В) Пропущенные УТП для этого клиента: 1. GPT Co-pilot: 'У вас есть помощник ИИ, который поможет с домашними заданиями и подготовкой к собеседованиям' 2. Группа поддержки: 'Вы будете общаться с такими же людьми, которые меняют профессию' 3. Современные AI-инструменты: 'Изучите технологии, которые используют ведущие компании' Г) Недостающий УТП: Клиент выражал беспокойство по поводу возраста и возвращения в профессию. Нужен УТП: 'Специальная поддержка для специалистов 45+ с большим опытом - как правильно презентовать себя работодателю' | EP4: Разговор не дошел до полноценного обсуждения оплаты - он прервался сразу после вопроса клиента о стоимости. Невозможно оценить, была ли потеря на этапе оплаты, так как этот этап не состоялся. | EU4: 0 | EV4: А) Содержание звонка: Обсуждены блоки: знакомство, выявление мотивации и текущей ситуации (Точка А), выяснение целей и желаемого результата (Точка В), презентация курса бухгалтерии. Разговор структурированный, последовательный, прерван на этапе обсуждения стоимости. Б) Реакция клиента: Заинтересованная и позитивная на протяжении всего разговора. Клиент активно участвовала в диалоге, задавала уточняющие вопросы о программах обучения (Datev, Lexware), названии компании, подтверждении курса в Германии. Проявляла искренний интерес к возможности смены профессии. В) Достигнутые договоренности: Зафиксирован следующий шаг - повторный звонок через полчаса для завершения обсуждения (включая вопрос о стоимости). Продавец корректно отреагировал на просьбу клиента о переносе времени разговора из-за срочных дел. | EX4: 0 | EY4: Упоминаний конкурентов в разговоре не было. Клиент не сравнивал с другими курсами или компаниями, не упоминал альтернативные варианты обучения. | FA4: 0 | FB4: 1. Отсутствие проверки реакции на презентацию: Продавец не спросил 'Что вам особенно понравилось?' или 'Готовы ли начать, если подойдет стоимость?' Как следовало: 'Ульяна, что из услышанного показалось вам наиболее ценным?' Эффект: Помогло бы выявить горячие точки интереса и подготовить к обсуждению стоимости. 2. Не создан FOMO-эффект: Продавец сразу перешел к обсуждению программы без создания срочности. Как следовало: 'Сейчас набирается последняя группа перед перерывом, следующий поток только через 3 месяца.' Эффект: Увеличило бы мотивацию к быстрому решению. 3. Недостаток конкретики по срокам: Не уточнил конкретные временные рамки клиента. Как следовало: 'К какому месяцу вы хотели бы уже работать бухгалтером?' Эффект: Помогло бы создать четкий план и усилить мотивацию. | FD4: 0 | FE4: 1. Качественное резюмирование перед презентацией: Фраза: 'давайте я кратенько подрезюмирую... Правильно я вас слышал?' Контекст: После выявления потребностей, перед презентацией Почему сработало: Показал внимательное слушание и получил подтверждение понимания Техника: Активное слушание + проверка понимания Тип: Массовая техника 2. Адаптация презентации под опыт клиента: Фраза: 'У вас стаж 25 лет, прекрасно, вы на 100% подходите' Контекст: В начале презентации, после резюмирования Почему сработало: Создал уверенность в подходящности программы Техника: Персонализация + подтверждение соответствия Тип: Массовая техника 3. Интерактивная презентация с вовлечением: Фраза: 'Что важно в преподавателях? Какие это должны быть люди?' Контекст: Во время презентации блока о преподавателях Почему сработало: Клиент сама сформулировала требования, затем продавец показал соответствие Техника: Вовлекающие вопросы + подстройка под ответ Тип: Массовая техника | FG4: 0 | FH4: А) Психологический портрет: Ульяна - рациональный, аналитический тип. Задает конкретные уточняющие вопросы, внимательно слушает, принимает решения обдуманно. Проявляет сдержанность, но заинтересованность. Уверенно говорит о своих потребностях ('не хочу больше', 'в любом случае меняю'). Темперамент спокойный, деловой. Б) Цели и приоритеты: Главная цель - вернуться в любимую профессию бухгалтера. Мотивация: усталость от неподходящей работы в клининге ('это не мое', 'я не люблю'). Финансовая цель - 4000 евро в месяц. Временные рамки - как можно быстрее. Сильная эмоциональная составляющая: 'хочу в своей любимой работе быть'. В) Дополнительные характеристики: Для маркетинга: использовать рациональные аргументы, статистику, четкие факты. Триггеры: 'профессиональность', 'признанные программы', 'гарантированный результат'. Каналы: скорее всего ответит на email с подробной информацией. УТП которые сработают: конкретные цифры трудоустройства, примеры успешных кейсов коллег 45+, государственная сертификация. Сегмент: опытные специалисты 45+ с высшим образованием, желающие вернуться в профессию. | FJ4: 1 | FK4: Звонок был прерван до логического завершения. Клиент попросила перенести разговор из-за срочных дел ('у меня здесь срочное дело вышло'), и разговор завершился договоренностью о повторном звонке через полчаса, а не естественным окончанием диалога. | FL4: 00:17:59.75 - Клиент: Если можно, через полчаса свяжитесь со мной, если можно., 00:18:00.98 - Клиент: потому что у него срочное дело здесь вышло. | FM4: 0 | FN4: Звонок начинается с нового контакта: есть полноценное приветствие ('Здравствуйте, это Антон из Штермейстера'), представление компании, уточнение причины звонка, программирование разговора. Клиент впервые говорит с этим продавцом, нет отсылок к предыдущим диалогам. | FO4: 00:00:02.97 - Продавец: Здравствуйте, это Антон из Штермейстера. По поводу бухгалтерии звоню. Интересовались учебой, верно? | FP4: 0 | FQ4: Клиент не упоминал государственные субсидии. В разговоре не прозвучало упоминаний Gutschein, Jobcenter, Berater или просьб о предложении (Angebot) для подачи заявки на государственное финансирование. | FS4: 8 | FT4: Клиент выражает высокую готовность начать быстро. Примеры реплик: 'чем быстрее, тем лучше' (04:10), 'я в любом случае меняю' (04:40), 'не хочу больше' (02:55). На вопрос о сроках дала четкий ответ о желании начать как можно скорее. Контекст показывает усталость от текущей ситуации и решимость к переменам. Оценка 8/10, так как готовность высокая, но без фанатизма. | FU4: 00:04:10.30 - Клиент: Чем быстрее, тем лучше., 00:04:40.50 - Клиент: Я в любом случае меняю., 00:02:55.05 - Клиент: Не хочу больше. | FV4: 7 | FW4: Клиент проявляет готовность к оплате, задав прямой вопрос о стоимости: 'сколько будет за 7 месяцев?' (17:44). У неё есть собственная фирма, что указывает на финансовую состоятельность. Не упоминала государственные субсидии или финансовые затруднения. Контекст показывает практичный подход к инвестициям в образование. Оценка 7/10 - готовность есть, но окончательное решение будет зависеть от суммы. | FX4: 00:17:44.00 - Клиент: И еще, пожалуйста, скажите, а сколько будет за 7 месяцев?, 00:01:29.34 - Клиент: Ну, у нас своя фирма небольшая, клининговая. | FY4: 9 | FZ4: Клиент четко понимает ценность обучения и высоко мотивирована. Примеры: 'хочу в своей любимой работе быть' (04:47), 'поэтому я решила к вам написать' (02:36). Имеет 25-летний опыт в бухгалтерии и осознает необходимость адаптации к немецким стандартам. Контекст показывает осознанный выбор професиональной переподготовки. Оценка 9/10 - потребность очень высокая и осознанная. | GA4: 00:04:47.00 - Клиент: хочу в своей любимой работе быть., 00:02:36.50 - Клиент: Поэтому я решила к вам написать. | GB4: 24 | GC4: Сумма оценок: Срочность (8) + Платежеспособность (7) + Потребность (9) = 24. Примеры ключевых реплик: 'чем быстрее, тем лучше', 'сколько будет за 7 месяцев?', 'хочу в своей любимой работе быть'. Общий вывод: Высокая готовность. Клиент демонстрирует сильную мотивацию к смене профессии, финансовую готовность и срочность в принятии решения. | GE4: =IFERROR(SUM(R[0]C[-156],R[0]C[-153],R[0]C[-150],R[0]C[-147])/COUNT(R[0]C[-156],R[0]C[-153],R[0]C[-150],R[0]C[-147]),"Установление контакта") -> #ERROR! | GF4: =IFERROR(SUM(R[0]C[-145],R[0]C[-142],R[0]C[-139],R[0]C[-136],R[0]C[-133],R[0]C[-130],R[0]C[-127])/COUNT(R[0]C[-145],R[0]C[-142],R[0]C[-139],R[0]C[-136],R[0]C[-133],R[0]C[-130],R[0]C[-127]),"Выявление потребностей") -> #ERROR! | GG4: =IFERROR(SUM(R[0]C[-125],R[0]C[-122])/COUNT(R[0]C[-125],R[0]C[-122]),"Презентация продукта") -> #ERROR! | GH4: =IFERROR(SUM(R[0]C[-120],R[0]C[-117])/COUNT(R[0]C[-120],R[0]C[-117]),"Предзакрытие и ФОМО") -> #ERROR! | GI4: =IFERROR(SUM(R[0]C[-109],R[0]C[-106])/COUNT(R[0]C[-109],R[0]C[-106]),"Отработка возражений") -> #ERROR! | GJ4: =IFERROR(SUM(R[0]C[-98],R[0]C[-95],R[0]C[-92],R[0]C[-89],R[0]C[-86])/COUNT(R[0]C[-98],R[0]C[-95],R[0]C[-92],R[0]C[-89],R[0]C[-86]),"Этап оплаты") -> #ERROR! | GK4: =IFERROR(SUM(R[0]C[-84],R[0]C[-81],R[0]C[-78],R[0]C[-75])/COUNT(R[0]C[-84],R[0]C[-81],R[0]C[-78],R[0]C[-75]),"Стандарты общения") -> #ERROR! | GL4: =IFERROR(SUM(R[0]C[-73],R[0]C[-70],R[0]C[-67])/COUNT(R[0]C[-73],R[0]C[-70],R[0]C[-67]),"Критические ошибки") -> #ERROR! | GM4: =IFERROR(R[0]C[-62]/50,"Экспертный блок 🧠 стратегический слой: методологии 🧰 тактический: структура и фразы 🧍 поведенческий: мотивация клиента 💳 финансовый: дожим и потери") -> #ERROR! | GN4: =IFERROR(SUM(R[0]C[-45],R[0]C[-42],R[0]C[-39],R[0]C[-36],R[0]C[-33])/COUNT(R[0]C[-45],R[0]C[-42],R[0]C[-39],R[0]C[-36],R[0]C[-33]),"Рекомендации") -> #ERROR! | GO4: =IFERROR(SUM(R[0]C[-31],R[0]C[-28],R[0]C[-25])/COUNT(R[0]C[-31],R[0]C[-28],R[0]C[-25]),"Фильтры") -> #ERROR! | GP4: =IFERROR(SUM(R[0]C[-23],R[0]C[-20],R[0]C[-17])/COUNT(R[0]C[-23],R[0]C[-20],R[0]C[-17]),"Скоринг") -> #ERROR! | GQ4: =IFERROR( SUM(IF({R[0]C[-168],R[0]C[-165],R[0]C[-162],R[0]C[-159],R[0]C[-156],R[0]C[-153],R[0]C[-150],R[0]C[-147],R[0]C[-144],R[0]C[-141],R[0]C[-138],R[0]C[-135],R[0]C[-132],R[0]C[-129],R[0]C[-126],R[0]C[-117],R[0]C[-114],R[0]C[-105],R[0]C[-102],R[0]C[-99],R[0]C[-96],R[0]C[-93],R[0]C[-90],R[0]C[-87],R[0]C[-84],R[0]C[-81]}="",hidden!R[0]C[-187],{R[0]C[-168],R[0]C[-165],R[0]C[-162],R[0]C[-159],R[0]C[-156],R[0]C[-153],R[0]C[-150],R[0]C[-147],R[0]C[-144],R[0]C[-141],R[0]C[-138],R[0]C[-135],R[0]C[-132],R[0]C[-129],R[0]C[-126],R[0]C[-117],R[0]C[-114],R[0]C[-105],R[0]C[-102],R[0]C[-99],R[0]C[-96],R[0]C[-93],R[0]C[-90],R[0]C[-87],R[0]C[-84],R[0]C[-81]}+hidden!R[0]C[-186])) / COUNT(IF({R[0]C[-168],R[0]C[-165],R[0]C[-162],R[0]C[-159],R[0]C[-156],R[0]C[-153],R[0]C[-150],R[0]C[-147],R[0]C[-144],R[0]C[-141],R[0]C[-138],R[0]C[-135],R[0]C[-132],R[0]C[-129],R[0]C[-126],R[0]C[-117],R[0]C[-114],R[0]C[-105],R[0]C[-102],R[0]C[-99],R[0]C[-96],R[0]C[-93],R[0]C[-90],R[0]C[-87],R[0]C[-84],R[0]C[-81]}="",hidden!R[0]C[-187],{R[0]C[-168],R[0]C[-165],R[0]C[-162],R[0]C[-159],R[0]C[-156],R[0]C[-153],R[0]C[-150],R[0]C[-147],R[0]C[-144],R[0]C[-141],R[0]C[-138],R[0]C[-135],R[0]C[-132],R[0]C[-129],R[0]C[-126],R[0]C[-117],R[0]C[-114],R[0]C[-105],R[0]C[-102],R[0]C[-99],R[0]C[-96],R[0]C[-93],R[0]C[-90],R[0]C[-87],R[0]C[-84],R[0]C[-81]}+hidden!R[0]C[-186])) ,"") -> #ERROR! | GR4: =L4/hidden!A3 -> #REF! | GS4: =IF((R[0]C[-26]+R[0]C[-23]+R[0]C[-20])<hidden!R[-1]C[-199],hidden!R[-1]C[-197], IF((R[0]C[-26]+R[0]C[-23]+R[0]C[-20])<hidden!R[-1]C[-198],hidden!R[-1]C[-196],hidden!R[-1]C[-195])) -> #ERROR! | GT4: =IF(R[0]C[-27]<=hidden!R[-1]C[-195],hidden!R[-1]C[-193], IF(R[0]C[-27]<=hidden!R[-1]C[-194],hidden!R[-1]C[-192],hidden!R[-1]C[-191])) -> #ERROR! | GU4: =IF(R[0]C[-25]<=hidden!R[-1]C[-196],hidden!R[-1]C[-194], IF(R[0]C[-25]<=hidden!R[-1]C[-195],hidden!R[-1]C[-193],hidden!R[-1]C[-192])) -> #ERROR! | GV4: =IF(R[0]C[-23]<=hidden!R[-1]C[-197],hidden!R[-1]C[-195], IF(R[0]C[-23]<=hidden!R[-1]C[-196],hidden!R[-1]C[-194],hidden!R[-1]C[-193])) -> #ERROR! | GW4: =TEXT(R[0]C[-194], "yyyy.mm") -> #ERROR!
A5: 2 | B5: 149264788_1816427109_d580d2 | C5: https://docs.google.com/document/d/11qvTi7jlaDPybiamxKyhhnWDwhnk82AGlOCNBXS9B3w/edit?usp=drivesdk | D5: 2025-06-30 - 2025-07-06 | I5: 2025.07 | K5: 2025-07-04 | L5: 774 | M5: 149264788_1816427109 | N5: +491732547425, Статус: Разговор состоялся | O5: CallGear | P5: 14:07:44+02:00 | Q5: Исходящий | R5: 28 | S5: 15205969 | T5: Evelina Storm | U5: Контакт | V5: 2025-07-04T11:56:37+02:00 | W5: 12622903 | Y5: Lead from: https://sternmeister.de/education?utm_source=facebook&utm_id=lp_short&utm_medium=site_nikita&utm_campaign=nikita_education_dynamic_creative_3&utm_term=de_W_2555_wide_nolang_int_5&utm_content=dynamic_creative_teaser&fbclid=PAZXh0bgNhZW0BMABhZGlk | Z5: Pipeline | AA5: Рассрочка | AB5: https://sternmeister.kommo.com/leads/detail/12622903 | AC5: 13271835 | AD5: Антон Громов | AE5: 0 | AF5: В транскрипции отсутствует начало разговора с приветствием и представлением. Продавец не представился, не назвал компанию Sternmeister и не получил подтверждения от клиента о том, что тот оставлял заявку на курс бухгалтерии. Разговор начинается сразу с вопроса о том, удобно ли побеседовать, без должного приветствия и идентификации. | AG5: 00:00:24.97 - Продавец: Вам сейчас удобно побеседовать? | AH5: 1 | AI5: Продавец корректно озвучил план разговора, включив все четыре необходимых смысловых блока: уточнил удобность времени (20 минут), объяснил структуру разговора (познакомиться, обсудить задачи, рассказать про учебу), и подготовил к принятию решения (если подойдем друг другу, поможет зачислить). | AJ5: 00:00:26.30 - Продавец: Отлично. Тогда давайте познакомимся, обсудим ваши задачи, вообще, что хотите. И я расскажу подробнее про учебу, про условия все. Если друг друга подойдем, помогу зачислить. Во время где-то минут на 20. Нормально? | AK5: 0 | AL5: Вопрос о стоимости не поднимался клиентом в начале разговора до этапа выяснения потребностей. | AN5: 0 | AO5: Тема JobCenter и финансирования через субсидии не поднималась в разговоре. | AQ5: 1 | AR5: Продавец успешно выяснил базовую информацию о клиенте: как давно живет в Германии (почти 10 лет), уровень языка (С2, свободный), и основную деятельность (есть свой бизнес онлайн и оффлайн). Это помогло установить контакт и понять контекст клиента. | AS5: 00:00:42.30 - Продавец: Я готова. Так, а вы вообще в Германии давно живете?, 00:00:46.82 - Клиент: Да, почти 10 лет., 00:00:48.94 - Продавец: Ого, ничего себе. А язык указали как С2, свободный. Да, все верно. Замечательно. Хорошо. | AT5: 1 | AU5: Продавец получил полную информацию по всем четырем элементам Точки А: опыт клиента (свой бизнес), текущая ситуация (не понимает многие моменты в работе бухгалтера, что его не устраивает), попытки решения (пробовал изучать самостоятельно по книгам), идеальное решение (хочет понимать и контролировать своего бухгалтера, найти истину среди противоречивых ответов разных бухгалтеров). | AV5: 00:01:02.87 - Клиент: В первую очередь для себя. У меня свой бизнес, и бизнес включается как онлайн, так и оффлайн. Я хочу больше понимать и, наверное, грубо будет сказано, но, наверное, в какой-то степени контролировать своего бухгалтера, потому что многие моменты я не понимаю, и меня это не устраивает., 00:01:49.78 - Клиент: Нет, такого не бывает, но интересный факт в том, что каждый бухгалтер говорит разное. То есть их вообще ответы полностью разнятся, и мне хочется найти ту самую истину, наверное., 00:03:09.20 - Клиент: Всё именно в Германии немного всё равно отличается от того, что знаю я, и поэтому, я уже пробовалась просто с книгами, покупала себе книги, но мне кажется, это всё равно немножко по-другому. | AW5: 0 | AX5: Продавец не задавал уточняющих вопросов о влиянии текущей ситуации клиента на его жизнь или отношения с семьей. Хотя клиент рассказал о своих проблемах с пониманием бухгалтерии, продавец не углубился в то, как это сказывается на жизни клиента. | AZ5: 0 | BA5: Продавец не получил полную информацию по SMART-структуре. Конкретная цель была выяснена (понимать и контролировать бухгалтерию), но не были получены ответы по измеримому результату (уровень дохода), значимости цели (вторичные мотивы) и срокам достижения (клиент сказал 'неограниченно'). | BB5: 00:02:28.40 - Продавец: Хорошо. Какие-то цели по времени, по срокам, то есть за сколько обучиться вы себе ставите?, 00:02:34.58 - Клиент: Неограниченно, нет. | BC5: 0 | BD5: Продавец получил расплывчатый ответ по срокам ('неограниченно'), но не помог клиенту сформулировать более конкретную цель и не уточнил другие аспекты SMART-структуры. | BE5: 00:02:34.58 - Клиент: Неограниченно, нет. | BF5: 0 | BG5: Продавец не рассказал о преимуществах профессии бухгалтера в Германии, не упомянул зарплаты, социальный пакет или карьерный рост. Не применил ни одной из необходимых фраз о доходах, льготах или перспективах профессии. | BI5: 0 | BJ5: Продавец не резюмировал ключевые моменты перед переходом к презентации. Он сразу перешел к рассказу о программе без подведения итогов обсуждения ситуации и целей клиента, и не получил подтверждения от клиента. | BK5: 00:02:56.43 - Продавец: То есть, соответственно, у вас запрос только конкретно для получения знаний, для того, чтобы лучше контролировать, понимать свой бизнес, свои финансовые потоки, вести учет и понимать, что там делает ваш бухгалтер. | BL5: 1 | BM5: Продавец адаптировал презентацию под выявленные потребности клиента. Он сначала выяснил запрос клиента (контроль бухгалтерии своего бизнеса), а затем в презентации делал отсылки к этим задачам, объясняя как курс поможет именно в ситуации клиента. | BN5: 00:03:24.69 - Продавец: Тогда я вам предложу нестандартный вариант, потому что большинство людей у нас всё-таки приходят за трудоустройством в первую очередь. У вас есть уже бизнес и основная деятельность, поэтому, как я понимаю, это не особо сейчас в плане вам куда-то устраиваться, правильно?, 00:05:52.73 - Продавец: Для вас это особенно актуально будет, потому что все преподаватели – действующие бухгалтеры. | BO5: 1 | BP5: Презентация проходила в живом диалоге. Продавец задавал вопросы по ходу рассказа, уточнял интерес клиента к отдельным аспектам программы и получал обратную связь, создавая ощущение диалога, а не монолога. | BQ5: 00:07:20.59 - Продавец: По формату пока всё ли подходит?, 00:07:22.75 - Клиент: Да, конечно., 00:08:08.60 - Клиент: А я смогу потом сама выдавать зарплату людям?, 00:09:24.44 - Клиент: А как экзамены проходят? | BR5: 0 | BS5: Продавец не задал вопрос о том, что из презентации оказалось наиболее важным или интересным для клиента, и не спросил о готовности начать сегодня, если подойдет стоимость. Клиент проявлял интерес вопросами, но продавец не зафиксировал это и не переходил к закрытию. | BU5: 1 | BV5: Продавец создал FOMO-эффект, сообщив о том, что группа уже стартовала 29 июня, следующее занятие завтра, а следующий запуск только в августе. Это создало ощущение ограниченности по времени и необходимости принять решение быстро. | BW5: 00:10:08.28 - Продавец: Хороший вопрос. И здесь какой у нас момент. На самом деле мы уже стартанули. 29 июня было вводное занятие. Ну там чисто все перезнакомились и всё. То есть контент вы ещё не пропустили. И следующее занятие будет завтра. А следующий запуск будет, наверное, где-то в августе. | CA5: 0 | CB5: Возражение 'подумаю' прозвучало в конце разговора на этапе принятия решения - клиент попросил дать время до вечера для размышлений (00:11:32.70). Возражение 'мало информации' проявилось через запрос клиента о примере документа и необходимости понять свои права и возможности для принятия решения (00:11:46.63). | CC5: 00:11:32.70 - Клиент: Дайте мне время до вечера., 00:11:46.63 - Клиент: Можете мне скинуть пример, как выглядит документ, который по завершению получают? Пример, что там у него написано. Мне это очень важно. | CD5: 0 | CE5: Прозвучало 2 возражения: 'подумаю' и 'мало информации'. Продавец частично отработал возражение 'мало информации' - пообещал прислать образец документа, но не следовал полной структуре отработки (присоединение → уточнение → аргумент → призыв к действию). По возражению 'подумаю' продавец не провел отработку - согласился дать время до вечера без уточнения причин сомнений. | CF5: 00:11:32.70 - Клиент: Дайте мне время до вечера., 00:11:35.03 - Продавец: Хорошо., 00:11:54.62 - Продавец: Хорошо. А вам для чего он нужен? Вы вроде не планируете? | CG5: 0 | CH5: Прозвучало ложное возражение 'подумаю' - клиент попросил дать время до вечера. Продавец не применил технику 'искренность', не задал уточняющий вопрос о том, что именно смущает или что нужно для принятия решения сейчас. Он просто согласился дать время и не попытался вывести на настоящее возражение. Также не сделал персонализированный призыв к действию. | CI5: 00:11:32.70 - Клиент: Дайте мне время до вечера., 00:11:35.03 - Продавец: Хорошо. | CJ5: 0 | CK5: А) Продавец отрабатывал возражения поверхностно: на 'мало информации' предложил прислать материалы без глубокого выяснения сути сомнений, на 'подумаю' сразу согласился без уточнений. Отсутствовали присоединение, полное уточнение и сильные аргументы. Б) С точки зрения методик SPIN (вопросы о ситуации и потребностях) и Challenger (обучение клиента) продавец упустил возможности. По SPIN не хватало проблемных вопросов для усиления боли. По Challenger не было попытки дать клиенту новое видение ситуации или показать скрытые риски откладывания решения. В) Примеры фраз: - SPIN: 'А что именно в документе поможет вам принять решение? Какие конкретно права вас больше всего волнуют?' (для возражения 'мало информации') - Challenger: 'Понимаю потребность подумать. Скажите, а сколько времени вы уже думаете над решением этого вопроса с бухгалтерией?' (для возражения 'подумаю') Эти подходы помогли бы укрепить доверие через демонстрацию понимания ситуации клиента, выявить настоящие причины сомнений и продвинуть диалог к принятию решения через создание ощущения срочности и понимания последствий откладывания. | CL5: 00:11:32.70 - Клиент: Дайте мне время до вечера., 00:11:46.63 - Клиент: Можете мне скинуть пример, как выглядит документ | CM5: 0 | CN5: А) Вопросы клиента: 1) Сможет ли сама выдавать зарплату сотрудникам (00:08:08.60) - на этапе презентации 2) Как проходят экзамены (00:09:24.44) - на этапе презентации 3) Когда старты курса (00:10:01.61) - при обсуждении сроков 4) Стоимость курса (00:10:44.39) - при переходе к коммерческим условиям 5) Пример документа об окончании (00:11:46.63) - при возражениях Б) Продавец дал понятные и прямые ответы на вопросы 1-4. На вопрос о зарплате подтвердил возможность, об экзаменах объяснил онлайн-формат, о стартах дал конкретные даты, о стоимости назвал цифры. Однако на вопрос о документе ответ был неполным - пообещал прислать, но не объяснил сразу суть документа. В) На вопрос о примере документа стоило ответить более развернуто: 'Это сертификат AZAV о профессиональной переподготовке, который дает право работать бухгалтером в Германии. Документ государственного образца, признается всеми работодателями. Я пришлю образец, но главное - с ним вы сможете полноценно вести бухгалтерию своего бизнеса и при желании работать на других компании.' Неотвеченные вопросы существенно не повлияли на ход разговора, так как основная информация была предоставлена. | CO5: 00:08:08.60 - Клиент: А я смогу потом сама выдавать зарплату людям?, 00:09:24.44 - Клиент: А как экзамены проходят?, 00:11:46.63 - Клиент: Можете мне скинуть пример, как выглядит документ | CP5: 1 | CQ5: Продавец соблюдал алгоритм презентации цены: сначала озвучил ценность курса (полная переподготовка, включая карьерный трек), затем предложил варианты от большего к меньшему (3090 евро стандартная стоимость, 2500 евро укороченный формат без трудоустройства), и аргументировал выбор, объяснив почему в данном случае подходит укороченный вариант. | CR5: 00:11:02.77 - Продавец: Смотрите, у нас стандартная стоимость, включая карьерный трек, 3 тысячи 90 евро. Но в вашем случае, потому что такой острой необходимости нет, здесь укороченный формат без трудоустройства, это 2 500 евро. | CS5: 1 | CT5: Продавец задал прямой вопрос о том, подходит ли предложенная стоимость клиенту и получил подтверждение. Выслушал ответ и перешел к следующему этапу приглашения к участию. | CU5: 00:11:06.77 - Продавец: То есть можно либо единоразово платить, либо, например, двумя платежами. Насколько для вас это благоподъемно?, 00:11:15.65 - Клиент: Подъемно, конечно. | CV5: 0 | CW5: Продавец упомянул возможность оплаты единоразово или двумя платежами, но не уточнил тип банковской карты клиента и не объяснил детально, как именно проходит процесс оплаты (по ссылке, на счет и т.д.). | CX5: 00:11:06.77 - Продавец: То есть можно либо единоразово платить, либо, например, двумя платежами. | CY5: 1 | CZ5: Продавец сделал прямое предложение участвовать в курсе ('Тогда в целом я приглашаю к вам участие'), узнал о готовности клиента, и когда клиент попросил время подумать, не предложил предоплату, но зафиксировал следующий шаг связи. | DA5: 00:11:18.43 - Продавец: Тогда в целом я приглашаю к вам участие. Как раз таки в эту группу вы ещё успеете войти. И к концу зимы уже обучение по сути своей закончите. Что скажете?, 00:11:32.70 - Клиент: Дайте мне время до вечера. | DB5: 1 | DC5: Продавец закрепил четкие договоренности о следующих шагах: пообещал прислать программу и образец документа, договорился о звонке вечером или на следующее утро, предоставив клиенту возможность связаться раньше если решение будет принято. | DD5: 00:12:23.56 - Продавец: Хорошо, я пришлю, да, без проблем, образец. Так, это будет сертификат формата CETA-FAL по профильной переподготовке. Всё, тогда в WhatsApp мы с вами на связи, я сейчас всё туда скину. Если вопросы появляются, пишите, и где-нибудь часиков в 18 я вам наберу, либо можем это сделать завтра утром. | DE5: 0 | DF5: Продавец не применил сторителлинг и не рассказал успешных историй других клиентов курсов Sternmeister в качестве примера и мотивации. | DH5: 1 | DI5: Продавец демонстрировал вежливость и доброжелательность: использовал вежливые слова ('хорошо', 'отлично', 'замечательно'), подстраивался под тональность клиента, общался уважительно без снисходительности. Однако не обращался к клиенту по имени в течение разговора. | DJ5: 00:00:26.30 - Продавец: Отлично. Тогда давайте познакомимся, 00:00:48.94 - Продавец: Ого, ничего себе. А язык указали как С2, свободный. Да, все верно. Замечательно. Хорошо., 00:11:35.03 - Продавец: Хорошо. | DK5: 1 | DL5: Продавец активно слушал клиента, использовал фразы активного слушания ('хорошо', 'понял', 'так'), реагировал на высказывания клиента комментариями и уточнениями, перефразировал важные мысли клиента и поддерживал живой диалог. | DM5: 00:01:27.10 - Продавец: Понял. А какие-то проблемы, связанные, может быть, с ошибками бухгалтера, штрафы, просчеты, что-то бывает?, 00:01:59.78 - Продавец: Хорошо. Хорошо, я понял вас., 00:03:23.78 - Продавец: Хорошо, я понял. | DN5: 1 | DO5: Продавец не перебивал клиента, не проявлял раздражения или агрессии, не использовал фразы типа 'я уже объяснял', сохранял спокойный и профессиональный тон на протяжении всего разговора. | DQ5: 0 | DR5: Продавец не допустил критических ошибок: не высказывался негативно о компании, не отговаривал клиента, и закрепил конкретные следующие шаги с указанием времени звонка (вечером в 18 часов или завтра утром) и способа связи (WhatsApp). | DS5: 00:12:23.56 - Продавец: где-нибудь часиков в 18 я вам наберу, либо можем это сделать завтра утром. Но если вдруг решение будет раньше, то можете мне написать спокойно. | DT5: 0 | DU5: Продавец не допустил критических ошибок с точки зрения клиента: предоставлял корректную информацию о курсе, не грубил, отвечал на вопросы по существу. Информация о длительности курса (7 месяцев), формате обучения (онлайн) и документах соответствовала официальным данным. | DV5: 00:02:36.80 - Продавец: У нас учеба занимает 7 месяцев., 00:05:33.40 - Продавец: Всё в формате онлайн. | DW5: 0 | DX5: Критических нарушений с точки зрения закона не зафиксировано. Продавец не давал ложных гарантий трудоустройства, не утверждал, что лицензия AZAV уже получена, и не вводил клиента в заблуждение относительно документов. | DZ5: 81 | EA5: Диалог длился 408 секунд. Продавец говорил 330 секунд, Клиент — 78 секунд. У Продавца — 35 реплик, у Клиента — 24. Соотношение: 330 / 408 = 81%. | EC5: 29 | ED5: 1. Консультативные продажи 2.0 - 6/10: Продавец выявил потребности клиента и адаптировал предложение, но говорил больше чем слушал (81% времени). Не хватило глубины в выяснении эмоциональных драйверов. 2. Эмоциональный резонанс - 4/10: Продавец не выявил глубинную эмоциональную мотивацию, не использовал сторителлинг, не создал яркие образы будущего результата. 3. Продажи на основе потребностей - 7/10: Четко выявил основную потребность (контроль бухгалтерии), адаптировал предложение под задачи клиента, но не выделил приоритеты среди потребностей. 4. Сторителлинг - 2/10: Не использовал истории успеха других клиентов, не создал релевантные кейсы для убеждения. 5. Модель 4P - 10/10: Четко определил проблему (непонимание работы бухгалтера), дал обещание результата (полный контроль), привел доказательства (опытные преподаватели), сделал конкретное предложение. Итог: 6+4+7+2+10 = 29 | EE5: 00:01:02.87 - Клиент: многие моменты я не понимаю, и меня это не устраивает, 00:05:52.73 - Продавец: все преподаватели – действующие бухгалтеры, 00:11:18.43 - Продавец: Тогда в целом я приглашаю к вам участие | EF5: 0 | EG5: А) Фактический скрипт: 1) Программирование разговора (время, структура) 2) Small talk (время в Германии, язык) 3) Выявление Точки А (текущие проблемы с бухгалтером) 4) Частичное выявление Точки Б (цели использования знаний) 5) Презентация курса с адаптацией под потребности 6) Создание FOMO (ограниченность по времени) 7) Презентация цены 8) Попытка закрытия без отработки возражений Б) Особенности: пропустил резюмирование перед презентацией, не углубился в эмоциональные мотивы, поверхностно отработал возражения В) Сработавшие элементы: адаптация предложения под бизнес-потребности клиента, создание срочности через даты запуска Г) Не сработавшие элементы: отсутствие глубокой отработки возражения 'подумаю', недостаточное усиление мотивации Разговор не привел к покупке - клиент попросил время подумать и остался в сомнении. | EH5: 00:11:32.70 - Клиент: Дайте мне время до вечера. | EI5: 0 | EJ5: А) Что сработало: адаптация предложения под конкретные бизнес-задачи, объяснение практических навыков (выдача зарплаты), конкретная структура программы Б) Что могло сработать сильнее: кейсы успешного применения знаний в бизнесе, расчет экономии от самостоятельного ведения учета, риски неправильного понимания бухгалтерии В) Pain-killer line: 'Каждый месяц неточности в понимании бухгалтерского учета могут стоить вашему бизнесу от 500 до 2000 евро штрафов и упущенной выгоды. Наш курс окупится уже через 2 месяца.' Эта фраза сработает для рационального типа, так как дает конкретные цифры потерь и выгод. Г) На следующем контакте: сфокусироваться на ROI обучения, привести конкретные кейсы экономии, не давить эмоционально, предоставить максимум фактов. | EK5: 00:08:08.60 - Клиент: А я смогу потом сама выдавать зарплату людям?, 00:11:46.63 - Клиент: Мне это очень важно | EL5: 0 | EM5: А) Клиент выразил боль от противоречивых советов бухгалтеров и желание контролировать процессы. УТП 'GPT Co-pilot для консультаций' и 'Персонализированная система мотивации' могли бы закрыть эти запросы. Б) УТП '70% практики' упомянут поверхностно, не раскрыта значимость для бизнес-задач. УТП 'Немецкий для бухгалтеров' упомянут как менее актуальный, хотя мог быть полезен для работы с документами. В) Стоило добавить: - Экономическое обоснование: 'Курс окупится за 2 месяца за счет экономии на услугах бухгалтера' - Кейсы предпринимателей: 'Участники экономят 800-1200 евро в месяц, ведя учет самостоятельно' - Безопасность: 'Снижение рисков штрафов на 95% благодаря пониманию требований' Г) Не хватает УТП: 'Персональная консультация по оптимизации учета именно вашего бизнеса' - многие предприниматели нуждаются в индивидуальном разборе их специфики. | EN5: 00:01:49.78 - Клиент: каждый бухгалтер говорит разное, 00:08:52.45 - Продавец: много практики | EO5: 1 | EP5: А) Разговор завершился отложенным решением - клиент попросил время до вечера для размышлений Б) Клиент сказал: 'Дайте мне время до вечера' и попросил дополнительную информацию о документах В) Продавец не углубился в причины сомнений, не выяснил, что именно нужно клиенту для принятия решения сейчас, не создал достаточную срочность, не показал риски откладывания Г) Тактика, которая могла бы изменить ситуацию: 'Понимаю потребность в дополнительной информации. Скажите, если документ соответствует вашим ожиданиям, что еще может повлиять на ваше решение? Давайте разберем все сомнения сейчас, чтобы вы могли спокойно начать уже завтра.' | EQ5: 00:11:32.70 - Клиент: Дайте мне время до вечера., 00:11:46.63 - Клиент: Можете мне скинуть пример, как выглядит документ | EU5: 0 | EV5: А) Содержание звонка: Продавец провел полный цикл продаж - программирование разговора, выявление потребностей (контроль бухгалтерии собственного бизнеса), презентацию курса с адаптацией под задачи предпринимателя, обсуждение стоимости (2500 евро за укороченную программу) и попытку закрытия. Б) Реакция клиента: Заинтересованная и позитивная на протяжении всего разговора. Клиент активно задавал вопросы о практических аспектах (выдача зарплат, экзамены), подтвердил финансовую возможность оплаты. В конце проявил осторожность, попросив время на размышления и дополнительную информацию о документах. В) Достигнутые договоренности: Зафиксирован следующий звонок на вечер того же дня (в 18:00) или на следующее утро. Продавец пообещал прислать программу курса и образец документа об окончании. Оставлена возможность для клиента связаться раньше при принятии решения. | EW5: 00:11:18.43 - Продавец: Тогда в целом я приглашаю к вам участие, 00:12:23.56 - Продавец: где-нибудь часиков в 18 я вам наберу | EX5: 0 | EY5: Упоминаний конкурентов в разговоре не было. | FA5: 0 | FB5: 1. Поверхностная отработка возражения 'подумаю' - Продавец сразу согласился: 'Хорошо' без выяснения причин сомнений. Следовало сказать: 'Понимаю. А что именно хотелось бы уточнить для принятия решения сейчас?' Это помогло бы выявить истинные возражения. 2. Отсутствие резюмирования перед презентацией - Продавец сразу перешел к рассказу о курсе без подведения итогов. Нужно было: 'Итак, если я правильно понял, вы хотите контролировать бухгалтерию своего бизнеса и разобраться в противоречивых советах специалистов. Верно?' Это усилило бы понимание ценности предложения. 3. Недостаточное создание срочности - Упомянул старт группы, но не показал конкретные потери от откладывания. Следовало: 'Каждый месяц без понимания бухгалтерии - это риск штрафов и упущенная прибыль. Начав сейчас, к новому году вы полностью контролируете финансы.' Это мотивировало бы к быстрому решению. | FC5: 00:11:32.70 - Клиент: Дайте мне время до вечера., 00:11:35.03 - Продавец: Хорошо. | FD5: 0 | FE5: 1. Адаптация предложения под бизнес-контекст - 'Тогда я вам предложу нестандартный вариант, потому что большинство людей у нас всё-таки приходят за трудоустройством в первую очередь. У вас есть уже бизнес...' - Сработало через признание уникальности ситуации и персонализацию. Техника: градация приоритетов. Массовая техника. 2. Создание FOMO через конкретные даты - 'На самом деле мы уже стартанули. 29 июня было вводное занятие... следующее занятие будет завтра. А следующий запуск будет, наверное, где-то в августе.' - Создало ощущение упущенной возможности и необходимости решать быстро. Техника: ограниченность по времени. Массовая техника. 3. Активное выяснение практических деталей - Когда клиент спросил о выдаче зарплат, продавец четко подтвердил возможность и объяснил значимость. Это укрепило доверие и показало понимание бизнес-потребностей. Техника: консультативная продажа. Массовая техника. | FF5: 00:03:24.69 - Продавец: Тогда я вам предложу нестандартный вариант, 00:10:14.28 - Продавец: мы уже стартанули | FG5: 0 | FH5: А) Психологический и демографический портрет: Рациональный предприниматель с аналитическим складом ума, живет в Германии 10 лет, свободно владеет немецким (С2). Проявляет осторожность в принятии решений, требует дополнительной информации для анализа. Инициативен - задает конкретные вопросы, фокусируется на практической применимости. Цитаты: 'мне хочется найти ту самую истину', 'Мне это очень важно'. Б) Цели и приоритеты: Главная цель - контроль и понимание бухгалтерского учета собственного бизнеса (онлайн и оффлайн). Боль - противоречивые советы разных бухгалтеров, отсутствие понимания процессов. Мотивация: 'я хочу больше понимать и контролировать своего бухгалтера, потому что многие моменты я не понимаю'. Сроки не критичны - 'неограниченно'. В) Выводы для бизнеса: Сегмент предпринимателей нуждается в УТП 'экономия на услугах бухгалтера' и 'снижение рисков'. Триггеры: 'контроль', 'понимание', 'истина'. Канал: вероятно digital. Нужны кейсы ROI и конкретная практика для бизнеса. Возможна упаковка отдельного продукта 'Бухгалтерия для предпринимателей'. | FI5: 00:01:02.87 - Клиент: я хочу больше понимать и контролировать своего бухгалтера, 00:01:49.78 - Клиент: мне хочется найти ту самую истину | FJ5: 0 | FK5: Разговор завершился логично с взаимными договоренностями о следующем контакте. Участники попрощались ('До свидания'), не было технических сбоев или резких обрывов. | FL5: 00:12:51.30 - Продавец: До свидания. | FM5: 0 | FN5: Звонок начинается с нового контакта без отсылок к предыдущим диалогам. Продавец сразу спрашивает об удобности времени и переходит к знакомству, что характерно для первичного контакта. | FO5: 00:00:24.97 - Продавец: Вам сейчас удобно побеседовать?, 00:00:26.30 - Продавец: Тогда давайте познакомимся | FP5: 0 | FQ5: Клиент не упоминал Gutschein, Jobcenter, Berater или потребность в предложении (Angebot) для государственного финансирования. Обсуждалась только самостоятельная оплата и рассрочка от компании. | FS5: 8 | FT5: Клиент проявил высокую готовность начать обучение. На вопрос о сроках ответил 'неограниченно', что показывает отсутствие временного давления, но при этом интересовался конкретными датами старта и активно обсуждал возможность попасть в текущую группу. Фраза 'Супер' на предложение 20-минутного разговора демонстрирует позитивный настрой и готовность к быстрому принятию решений. | FU5: 00:02:34.58 - Клиент: Неограниченно, нет., 00:10:01.61 - Клиент: Пока достаточно. На самом деле всё очень интересно. Расскажите, когда старт? | FV5: 9 | FW5: Клиент четко подтвердил финансовую готовность: 'Подъемно, конечно' на вопрос о стоимости 2500 евро. Обсуждал варианты оплаты (единоразово или двумя платежами) без возражений по цене. Не упоминал потребность в государственном финансировании или сложности с оплатой. | FX5: 00:11:15.65 - Клиент: Подъемно, конечно., 00:10:44.39 - Клиент: Ну, в зависимости, во-первых, от оплаты | FY5: 9 | FZ5: Клиент ясно понимает ценность обучения для себя и мотивирован учиться. Четко сформулировал цели: контроль и понимание работы бухгалтера, решение проблемы противоречивых советов специалистов. Проявлял активный интерес, задавая практические вопросы о применении знаний в своем бизнесе. | GA5: 00:01:02.87 - Клиент: Я хочу больше понимать и, наверное, грубо будет сказано, но, наверное, в какой-то степени контролировать своего бухгалтера, потому что многие моменты я не понимаю, и меня это не устраивает., 00:03:09.20 - Клиент: мне хочется найти ту самую истину | GB5: 26 | GC5: Сумма оценок: Срочность (8) + Платежеспособность (9) + Потребность (9) = 26. Клиент демонстрирует высокую готовность: четко понимает зачем ему обучение, готов оплатить предложенную стоимость, заинтересован в быстром старте. Примеры: 'Подъемно, конечно', 'мне хочется найти ту самую истину', 'всё очень интересно'. Общий вывод: Высокая готовность. | GD5: 00:11:15.65 - Клиент: Подъемно, конечно., 00:01:49.78 - Клиент: мне хочется найти ту самую истину, 00:10:01.61 - Клиент: всё очень интересно | GE5: =IFERROR(SUM(R[0]C[-156],R[0]C[-153],R[0]C[-150],R[0]C[-147])/COUNT(R[0]C[-156],R[0]C[-153],R[0]C[-150],R[0]C[-147]),"Установление контакта") -> #ERROR! | GF5: =IFERROR(SUM(R[0]C[-145],R[0]C[-142],R[0]C[-139],R[0]C[-136],R[0]C[-133],R[0]C[-130],R[0]C[-127])/COUNT(R[0]C[-145],R[0]C[-142],R[0]C[-139],R[0]C[-136],R[0]C[-133],R[0]C[-130],R[0]C[-127]),"Выявление потребностей") -> #ERROR! | GG5: =IFERROR(SUM(R[0]C[-125],R[0]C[-122])/COUNT(R[0]C[-125],R[0]C[-122]),"Презентация продукта") -> #ERROR! | GH5: =IFERROR(SUM(R[0]C[-120],R[0]C[-117])/COUNT(R[0]C[-120],R[0]C[-117]),"Предзакрытие и ФОМО") -> #ERROR! | GI5: =IFERROR(SUM(R[0]C[-109],R[0]C[-106])/COUNT(R[0]C[-109],R[0]C[-106]),"Отработка возражений") -> #ERROR! | GJ5: =IFERROR(SUM(R[0]C[-98],R[0]C[-95],R[0]C[-92],R[0]C[-89],R[0]C[-86])/COUNT(R[0]C[-98],R[0]C[-95],R[0]C[-92],R[0]C[-89],R[0]C[-86]),"Этап оплаты") -> #ERROR! | GK5: =IFERROR(SUM(R[0]C[-84],R[0]C[-81],R[0]C[-78],R[0]C[-75])/COUNT(R[0]C[-84],R[0]C[-81],R[0]C[-78],R[0]C[-75]),"Стандарты общения") -> #ERROR! | GL5: =IFERROR(SUM(R[0]C[-73],R[0]C[-70],R[0]C[-67])/COUNT(R[0]C[-73],R[0]C[-70],R[0]C[-67]),"Критические ошибки") -> #ERROR! | GM5: =IFERROR(R[0]C[-62]/50,"Экспертный блок 🧠 стратегический слой: методологии 🧰 тактический: структура и фразы 🧍 поведенческий: мотивация клиента 💳 финансовый: дожим и потери") -> #ERROR! | GN5: =IFERROR(SUM(R[0]C[-45],R[0]C[-42],R[0]C[-39],R[0]C[-36],R[0]C[-33])/COUNT(R[0]C[-45],R[0]C[-42],R[0]C[-39],R[0]C[-36],R[0]C[-33]),"Рекомендации") -> #ERROR! | GO5: =IFERROR(SUM(R[0]C[-31],R[0]C[-28],R[0]C[-25])/COUNT(R[0]C[-31],R[0]C[-28],R[0]C[-25]),"Фильтры") -> #ERROR! | GP5: =IFERROR(SUM(R[0]C[-23],R[0]C[-20],R[0]C[-17])/COUNT(R[0]C[-23],R[0]C[-20],R[0]C[-17]),"Скоринг") -> #ERROR! | GQ5: =IFERROR( SUM(IF({R[0]C[-168],R[0]C[-165],R[0]C[-162],R[0]C[-159],R[0]C[-156],R[0]C[-153],R[0]C[-150],R[0]C[-147],R[0]C[-144],R[0]C[-141],R[0]C[-138],R[0]C[-135],R[0]C[-132],R[0]C[-129],R[0]C[-126],R[0]C[-117],R[0]C[-114],R[0]C[-105],R[0]C[-102],R[0]C[-99],R[0]C[-96],R[0]C[-93],R[0]C[-90],R[0]C[-87],R[0]C[-84],R[0]C[-81]}="",hidden!R[0]C[-187],{R[0]C[-168],R[0]C[-165],R[0]C[-162],R[0]C[-159],R[0]C[-156],R[0]C[-153],R[0]C[-150],R[0]C[-147],R[0]C[-144],R[0]C[-141],R[0]C[-138],R[0]C[-135],R[0]C[-132],R[0]C[-129],R[0]C[-126],R[0]C[-117],R[0]C[-114],R[0]C[-105],R[0]C[-102],R[0]C[-99],R[0]C[-96],R[0]C[-93],R[0]C[-90],R[0]C[-87],R[0]C[-84],R[0]C[-81]}+hidden!R[0]C[-186])) / COUNT(IF({R[0]C[-168],R[0]C[-165],R[0]C[-162],R[0]C[-159],R[0]C[-156],R[0]C[-153],R[0]C[-150],R[0]C[-147],R[0]C[-144],R[0]C[-141],R[0]C[-138],R[0]C[-135],R[0]C[-132],R[0]C[-129],R[0]C[-126],R[0]C[-117],R[0]C[-114],R[0]C[-105],R[0]C[-102],R[0]C[-99],R[0]C[-96],R[0]C[-93],R[0]C[-90],R[0]C[-87],R[0]C[-84],R[0]C[-81]}="",hidden!R[0]C[-187],{R[0]C[-168],R[0]C[-165],R[0]C[-162],R[0]C[-159],R[0]C[-156],R[0]C[-153],R[0]C[-150],R[0]C[-147],R[0]C[-144],R[0]C[-141],R[0]C[-138],R[0]C[-135],R[0]C[-132],R[0]C[-129],R[0]C[-126],R[0]C[-117],R[0]C[-114],R[0]C[-105],R[0]C[-102],R[0]C[-99],R[0]C[-96],R[0]C[-93],R[0]C[-90],R[0]C[-87],R[0]C[-84],R[0]C[-81]}+hidden!R[0]C[-186])) ,"") -> #ERROR! | GR5: =L5/hidden!A4 -> #REF! | GS5: =IF((R[0]C[-26]+R[0]C[-23]+R[0]C[-20])<hidden!R[-1]C[-199],hidden!R[-1]C[-197], IF((R[0]C[-26]+R[0]C[-23]+R[0]C[-20])<hidden!R[-1]C[-198],hidden!R[-1]C[-196],hidden!R[-1]C[-195])) -> #ERROR! | GT5: =IF(R[0]C[-27]<=hidden!R[-1]C[-195],hidden!R[-1]C[-193], IF(R[0]C[-27]<=hidden!R[-1]C[-194],hidden!R[-1]C[-192],hidden!R[-1]C[-191])) -> #ERROR! | GU5: =IF(R[0]C[-25]<=hidden!R[-1]C[-196],hidden!R[-1]C[-194], IF(R[0]C[-25]<=hidden!R[-1]C[-195],hidden!R[-1]C[-193],hidden!R[-1]C[-192])) -> #ERROR! | GV5: =IF(R[0]C[-23]<=hidden!R[-1]C[-197],hidden!R[-1]C[-195], IF(R[0]C[-23]<=hidden!R[-1]C[-196],hidden!R[-1]C[-194],hidden!R[-1]C[-193])) -> #ERROR! | GW5: =TEXT(R[0]C[-194], "yyyy.mm") -> #ERROR!
A6: 3 | B6: 149248986_1816373914_32b5ac | C6: https://docs.google.com/document/d/1rOH_FqBJFmPGtCNUL1YT4MAKLXevk_cSislZzlkKlTM/edit?usp=drivesdk | D6: 2025-06-30 - 2025-07-06 | I6: 2025.07 | K6: 2025-07-04 | L6: 1026 | M6: 149248986_1816373914 | N6: +4915152903198, Статус: Разговор состоялся | O6: CallGear | P6: 12:30:43+02:00 | Q6: Исходящий | R6: 28 | S6: 15155136 | T6: Kateryna Buina | U6: Контакт | V6: 2025-07-03T15:00:21+02:00 | W6: 12594494 | Y6: Lead from: https://sternmeister.de/tg-application | Z6: Pipeline | AA6: Контакт установлен | AB6: https://sternmeister.kommo.com/leads/detail/12594494 | AC6: 13271835 | AD6: Антон Громов | AE6: 0 | AF6: Продавец не соблюл полную структуру приветствия. Он поприветствовался и представился как 'Антон, эштермейстер, бухгалтерия', но не назвал компанию Sternmeister и не получил подтверждение от клиента о том, что тот оставлял заявку на обучение. Вместо этого сразу перешел к вопросу об удобности времени для разговора. | AG6: 00:00:03.87 - Продавец: Здравствуйте, это Антон, эштермейстер, бухгалтерия. Да. Так, вам сейчас удобно побеседовать будет? Минут на 20 примерно? | AH6: 1 | AI6: Продавец озвучил план разговора, включив все четыре смысловых блока: уточнил удобность времени (20 минут), предложил познакомиться и обсудить задачи клиента, рассказать про учебу и условия, подобрать вариант, и если все подойдет - зачислить. | AJ6: 00:00:23.66 - Продавец: Тогда давайте сейчас как поступим. Мы познакомимся, осудим ваши задачи, что хотите получить, и я расскажу про учебы, про условия, подберем вариант подходящий. Если всем все подойдет, могу зачислить. Хорошо? | AK6: 0 | AL6: Вопрос о стоимости в начале разговора не поднимался клиентом. | AN6: 1 | AO6: Продавец корректно отреагировал на интерес клиента к обучению через джоб-центр. Он не сказал, что не работает с JobCenter, а предложил подготовить предложение для джоб-центра и уточнил возможность самостоятельной оплаты как альтернативы. | AP6: 00:03:46.81 - Клиент: Ну, конечно, желательно через джоб-центр. Ну, если... ну, знать хотя бы, сколько стоит, если это самостоятельно., 00:15:32.87 - Продавец: Поэтому мы сможем подготовить предложение для оператора примерно в течение 2-3 недель. | AQ6: 1 | AR6: Продавец выяснил ключевую информацию о клиенте: как долго живет в Германии (с 2022 года), уровень немецкого языка (В1 не сдала), текущую работу (мини-джоб хаус-хильфы), семейную ситуацию и опыт работы бухгалтером в Украине. | AS6: 00:00:43.56 - Продавец: А вы давно в Германии живете?, 00:00:49.39 - Продавец: Я понял, хорошо. А уровень языка какой у вас?, 00:01:46.78 - Продавец: а интерес к бухгалтерии с чем связан? Для чего вы обучились?, 00:03:25.86 - Продавец: Так, а вы сейчас кем работаете? | AT6: 1 | AU6: Продавец получил информацию по всем ключевым элементам Точки А: опыт клиента (бухгалтер в Украине), текущая ситуация (мини-джоб, на джоб-центре, 3 года без движения), что не устраивает (нет карьерного роста, низкий доход), попытки изменить ситуацию (изучение языка, подготовка к В1), идеальное решение (работа бухгалтером с нормальной зарплатой). | AV6: 00:02:29.87 - Клиент: Я в Украине была бухгалтером..., 00:03:38.72 - Клиент: У меня маленький мини-джоб, хаус-хильфы..., 00:05:05.93 - Клиент: три года, как говорится, мы не движемся ни туда, ни сюда, 00:05:51.07 - Клиент: в принципе, если я даже буду зарабатывать, я не знаю, хотя бы 25 евро в час начально | AW6: 0 | AX6: Продавец не задавал углубляющих вопросов о влиянии текущей ситуации на жизнь клиента или отношения с семьей. Он не выяснял, как эмоционально переживается застой и готова ли клиент к долгому ожиданию. | AZ6: 1 | BA6: Продавец получил информацию по всем элементам SMART: конкретная цель (работа бухгалтером), измеримый результат (25 евро в час, 3000 евро в месяц), значимость (финансовая независимость, самостоятельность), срок (в ближайшее время, не растягивать на год-два). | BB6: 00:05:51.07 - Клиент: в принципе, если я даже буду зарабатывать, я не знаю, хотя бы 25 евро в час начально, 00:05:56.20 - Продавец: По опыту бухгалтер начинающий зарабатывает от 3000 евро в месяц, 00:06:27.41 - Продавец: И обучение вы планируете уже в ближайшее время? То есть растягивать на год, на два желания нет, правильно? | BC6: 0 | BD6: Клиент дала конкретные ответы по всем пунктам SMART-структуры, поэтому необходимости в уточнении не было. | BF6: 0 | BG6: Продавец упомянул только зарплату начинающего бухгалтера (от 3000 евро в месяц), но не рассказал о социальном пакете, карьерном росте, стабильности занятости, оплачиваемых больничных, премиях и других преимуществах профессии. Также не спросил, какие эмоции клиент будет испытывать при достижении цели. | BH6: 00:05:56.20 - Продавец: По опыту бухгалтер начинающий зарабатывает от 3000 евро в месяц. | BI6: 1 | BJ6: Продавец подытожил ключевые моменты перед презентацией: текущую ситуацию клиента (в Германии, есть опыт бухгалтера, на джоб-центре, В1 не сдала, на выплатах), цель (работать бухгалтером), временные рамки (не откладывать) и попросил поправить, если что не так. | BK6: 00:07:08.83 - Продавец: Тогда давайте сейчас я подрезюмирую, что услышал от вас. Поправьте меня, если что не так. И дальше по самой программе, я про нее расскажу. Вот вы мне про себя сказали, что сначала вы устроились в Германии, и у вас есть опыт, есть образование бухгалтером, работали в этой сфере... | BL6: 1 | BM6: Продавец адаптировал презентацию под потребности клиента: делал отсылки к ее опыту ('У вас опыт есть, поэтому вы нам подходите'), к языковым проблемам ('курс профессионального немецкого языка... поможет разговорный навык до уровня В2 подтянуть'), к необходимости трудоустройства ('ведем до трудоустройства'). | BN6: 00:07:49.42 - Продавец: У вас опыт есть, поэтому вы нам подходите, 00:09:48.41 - Продавец: потому что я честно скажу, что в этой сфере язык имеет ключевое значение для работы, но вот В1 – это прям супер минимум, 00:12:49.10 - Продавец: Мы работаем до трудоустройства | BO6: 1 | BP6: Презентация проходила в диалоге: продавец задавал уточняющие вопросы ('Здесь по формату все ли пока подходит?', 'Насколько подходит?'), получал подтверждения от клиента ('Ну, да', 'Не очень хорошо, да, не узко', 'Да, это тоже искусство'), создавая ощущение живого диалога, а не монолога. | BQ6: 00:10:15.92 - Продавец: Здесь по формату все ли пока подходит?, 00:10:18.98 - Клиент: Ну, да., 00:11:03.72 - Клиент: Не очень хорошо, да, не узко., 00:12:49.10 - Продавец: Насколько подходит? | BR6: 0 | BS6: Продавец не задал вопрос о том, что именно из презентации показалось клиенту наиболее важным или интересным. Также не уточнил готовность клиента начать сегодня, если подойдет стоимость. Клиент давала короткие подтверждения по ходу презентации, но специального обсуждения реакции не было. | BU6: 1 | BV6: Продавец создал FOMO-эффект, сообщив о льготной цене на последнее место в третьей группе со скидкой 50% (3900 евро вместо 7800), подчеркнув ограниченность предложения. Это мотивировало клиента к быстрому принятию решения. | BW6: 00:14:24.90 - Продавец: Там последнее место осталось, мы его по льготной цене отдаем. Скидка 50% – 3900 евро. Там уже первое занятие было в воскресенье, но такое чисто знакомство, и все. По сути, контент не пропущен. | CA6: 0 | CB6: Дорого: на этапе обсуждения стоимости клиент сказала '600 евро в месяц. Пока сложно сказать, что прям так горячим пирожком я...' (неуверенно, с сомнением). Посоветуюсь: 'Надо с мужем поговорить' (спокойно, как необходимость). Не сейчас: 'За сколько я в поезд не впрыгну, к сожалению' (с сожалением, объясняя текущую ситуацию). Джоб-центр: в начале разговора выразила предпочтение обучению через джоб-центр (уверенно, как приоритет). | CC6: 00:14:24.90 - Клиент: 600 евро в месяц. Пока сложно сказать, что прям так горячим пирожком я..., 00:14:41.03 - Клиент: Надо с мужем поговорить, 00:16:25.13 - Клиент: За сколько я в поезд не впрыгну, к сожалению, 00:03:46.81 - Клиент: Ну, конечно, желательно через джоб-центр | CD6: 0 | CE6: Продавец отработал менее 3 возражений и нарушил структуру. При возражении 'дорого' он сразу предложил варианты оплаты без присоединения и уточнения. При возражении 'посоветуюсь' не углубился в выяснение истинных причин. При возражении о джоб-центре корректно перенес на подготовку предложения. Структура отработки (присоединение → уточнение → аргумент → призыв к действию) не соблюдалась. | CF6: 00:14:47.63 - Продавец: А какой бюджет был бы подъемен, как думаете?, 00:15:15.27 - Продавец: максимум, который можем предложить, могу строго согласовать, на 10 месяцев разбивается по 390 евро в месяц | CG6: 0 | CH6: При ложном возражении 'посоветуюсь' ('Надо с мужем поговорить') продавец не использовал технику искренности, не задал уточняющих вопросов типа 'в чем именно хотите посоветоваться', не попытался выявить настоящую причину сомнений. Быстро закрыл тему переходом к джоб-центру. Не делал персонализированного призыва к действию в конце отработки. | CI6: 00:14:41.03 - Клиент: Надо с мужем поговорить., 00:14:47.63 - Продавец: А какой бюджет был бы подъемен, как думаете? | CJ6: 0 | CK6: А) Анализ отработки возражений: Продавец столкнулся с возражениями 'дорого', 'посоветуюсь', 'не сейчас' и 'джоб-центр'. Ошибки: отсутствие присоединения, поверхностное уточнение, слабые аргументы, быстрый переход к альтернативам без глубокого понимания причин. Б) Методики: SPIN (ситуативные, проблемные, извлекающие, направляющие вопросы) - не были использованы для выявления скрытых потребностей. Challenger Sale - продавец не оспаривал предположения клиента о невозможности оплаты. NEAT (потребности, экономическое влияние, доступ к полномочиям, временные рамки) - не выяснил влияние отсрочки решения. В) Примеры фраз: SPIN: 'Что именно в семейном бюджете мешает принять решение сейчас?' Challenger: 'Многие думают, что дорого, но потеря 4 месяцев до следующей группы = потеря 16000 евро дохода'. NEAT: 'Если не начнете сейчас, когда планируете решить вопрос с карьерой?' Эти подходы помогли бы укрепить доверие, выявить настоящие причины и продвинуть к решению. | CM6: 0 | CN6: А) Вопросы клиента: На раннем этапе клиент спросила о стоимости при самостоятельной оплате. На этапе обсуждения оплаты уточняла формат платежей и возможности. Б) Качество ответов: Продавец дал конкретные ответы по стоимости (7800/3900 евро, рассрочка), объяснил варианты оплаты. Ответы были по сути, но без развернутой аргументации ценности. В) Рекомендации для улучшения ответов: На вопрос о стоимости лучше было бы сначала подчеркнуть ценность: 'Полный курс с сертификацией, трудоустройством и языком стоит 7800, но с учетом вашего опыта и текущей акции...' Это усилило бы восприятие выгодности предложения. Неотвеченные вопросы не повлияли критично на ход разговора, но более развернутые ответы могли бы укрепить ценность предложения. | CO6: 00:03:55.12 - Клиент: сколько стоит, если это самостоятельно, 00:14:24.90 - Продавец: Стандартная стоимость обычно 7800 евро... скидка 50% – 3900 евро | CP6: 0 | CQ6: Продавец не соблюдал алгоритм презентации цены. Он не озвучил ценность курса до называния цены, не рекомендовал оплату от большего к меньшему (сразу предложил рассрочку), не дал развернутой аргументации выбора. Просто назвал стандартную цену 7800 евро, льготную 3900 евро и варианты рассрочки без обоснования преимуществ каждого варианта. | CR6: 00:14:24.90 - Продавец: Стандартная стоимость обычно 7800 евро. Профессиональная переподготовка по средней зарплате. Но сейчас условия отличаются... Скидка 50% – 3900 евро., 00:15:15.27 - Продавец: максимум, который можем предложить, могу строго согласовать, на 10 месяцев разбивается по 390 евро в месяц | CS6: 1 | CT6: Продавец задавал вопросы о подходящем варианте оплаты: 'Насколько такой бюджет у вас был?' и 'какой бюджет был бы подъемен'. Когда клиент выразила сомнения, он предложил альтернативный вариант на 10 месяцев. Выслушивал ответы клиента и адаптировался под ее возможности. | CU6: 00:14:24.90 - Продавец: Насколько такой бюджет у вас был?, 00:14:47.63 - Продавец: А какой бюджет был бы подъемен, как думаете?, 00:15:15.27 - Продавец: 390 евро более подъемный вариант или вообще? | CV6: 0 | CW6: Клиент не выразил согласие оплачивать, поэтому обсуждение конкретных способов оплаты не происходило. | CY6: 0 | CZ6: Продавец не сделал прямого предложения оплатить и приступить к обучению. Когда стало очевидно, что клиент не готов оплачивать сейчас, он не предложил внести предоплату. Вместо попытки закрытия сделки сразу перешел к предложению подготовить документы для джоб-центра. | DA6: 00:15:32.87 - Продавец: Поэтому мы сможем подготовить предложение для оператора примерно в течение 2-3 недель | DB6: 1 | DC6: Продавец зафиксировал четкие следующие шаги: отправить программу на почту для ознакомления, подготовить предложение для джоб-центра в течение 2-3 недель, связаться ближе к 20-м числам для подготовки документов на августовский поток. | DD6: 00:16:16.07 - Продавец: Я включу вам программу, чтобы вы могли посмотреть, что это, как устроено изнутри, конкретно темы, которые изучаются. Когда документы будут готовы, я с вами свяжусь, где-то ближе к 20-м числам, и подготовим предложение | DE6: 0 | DF6: Продавец не применил сторителлинг в разговоре. Не рассказал ни одной успешной истории клиентов компании Sternmeister в качестве примера и мотивации для данного клиента. | DH6: 0 | DI6: Продавец не обращался к клиенту по имени ни разу, не использовал вежливые слова типа 'пожалуйста', 'спасибо', 'извините'. Общался достаточно сухо и механически. Хотя не был грубым, но отсутствовала доброжелательность и индивидуальный подход. | DK6: 1 | DL6: Продавец использовал фразы активного слушания ('Я понял', 'хорошо', 'угу'), реагировал на высказывания клиента уточнениями, перефразировал важные моменты ('Правильно понимаю, что это единственное, что вас останавливает'), поддерживал диалог в живом темпе. | DM6: 00:00:49.39 - Продавец: Я понял, хорошо., 00:03:09.50 - Продавец: У них задачи как можно быстрее., 00:04:36.31 - Продавец: Так, я понял | DN6: 1 | DO6: Продавец не перебивал клиента, не проявлял раздражения, не использовал фразы типа 'я уже объяснял'. Сохранял спокойный, профессиональный тон до конца разговора даже при отказе клиента от оплаты. | DQ6: 0 | DR6: Продавец не допустил критических ошибок. Не высказывался негативно о компании, не отговаривал от покупки, закрепил конкретные следующие шаги с указанием времени связи (2-3 недели, ближе к 20-м числам) и формата (подготовка предложения для джоб-центра). | DS6: 00:15:32.87 - Продавец: Поэтому мы сможем подготовить предложение для оператора примерно в течение 2-3 недель, 00:16:16.07 - Продавец: Когда документы будут готовы, я с вами свяжусь, где-то ближе к 20-м числам | DT6: 0 | DU6: Продавец не допустил критических ошибок с точки зрения клиента. Информация о курсе соответствовала действительности (7 месяцев, онлайн, русский язык, практика, стажировка, трудоустройство), поведение было уважительным, ответы корректными. Не давал ложной информации о лицензиях или сертификатах. | DW6: 0 | DX6: Продавец не допустил юридически опасных действий. Не разглашал внутреннюю информацию, не давал неправомерных гарантий трудоустройства (говорил 'помогаем', 'ведем до трудоустройства'), корректно говорил о сертификатах и не утверждал, что лицензия AZAV уже получена. | DY6: 00:08:21.42 - Продавец: Мы ведем до трудоустройства, 00:12:11.67 - Продавец: получаете документы, наш вайтер Гугл для подготовки к государственным образцам | DZ6: 72 | EA6: Диалог длился 1020 секунд (с 00:00:01 по 00:17:01). Продавец говорил 730 секунд, Клиент — 290 секунд. У Продавца — 25 реплик, у Клиента — 22 реплики. Соотношение: 730 / 1020 = 72%. | EC6: 28 | ED6: 1. Консультативные продажи 2.0: 6/10. Продавец выявлял потребности и связывал решение с задачами клиента, но говорил больше, чем слушал. Для 10/10 нужно было больше вопросов типа 'Как эта ситуация влияет на вашу семью?'. 2. Эмоциональный резонанс: 4/10. Выявил мотивацию (финансовая независимость), но не использовал сторителлинг и не работал с эмоциями. Для 10/10 нужны истории успеха и визуализация результата. 3. Потребностная продажа: 7/10. Четко выявил потребности и классифицировал запрос, связал характеристики с приоритетами. Для 10/10 не хватало устранения сомнений. 4. Story-Based Selling: 2/10. Не рассказывал историй клиентов. Для 10/10 нужны кейсы похожих украинок-бухгалтеров. 5. 4P модель: 9/10. Четко определил проблему (застой в карьере), обещал результат (3000 евро), дал доказательства (опыт других), сделал предложение. Сумма: 6+4+7+2+9=28 | EF6: 0 | EG6: А) Фактический скрипт: 1) Приветствие и программирование (озвучил план встречи) 2) Small talk (выяснение ситуации клиента) 3) Точка А (текущие проблемы и боли) 4) Точка Б (цели и желания) 5) Резюмирование 6) Презентация курса (формат, содержание, трудоустройство) 7) Обсуждение стоимости и рассрочки 8) Работа с возражениями 9) Переход к джоб-центру 10) Фиксация следующих шагов. Б) Особенности: пропустил этап создания срочности, не использовал сторителлинг, быстро согласился на джоб-центр вместо дожима. В) Сработавшие элементы: структурированная презентация вызвала понимание формата, резюмирование создало ясность, конкретные цифры по зарплате заинтересовали. Г) Не сработавшие: отсутствие эмоциональных историй не создало мотивации, слабая работа с возражениями не сняла сомнения по деньгам. Результат: клиент остался в подвешенном состоянии, не приблизился к покупке. | EI6: 0 | EJ6: А) Сработало: конкретные цифры зарплаты, структурированная программа, гибкость в вариантах оплаты, понимание языковых проблем. Б) Могло сработать сильнее: истории успеха украинских бухгалтеров, подчеркивание стабильности профессии, эмоциональная картина лучшего будущего для детей. В) Pain-killer line: 'Представьте: через 8 месяцев вы работаете немецким бухгалтером с зарплатой 3000 евро, ваши дети видят, что мама не убирает офисы, а занимается интеллектуальной работой - вы снова почувствуете себя профессионалом'. Сказать после выявления целей. Г) На следующем контакте: сфокусироваться на безопасности решения, привести конкретные примеры трудоустроенных мам-бухгалтеров, обсудить план 'безболезненного' старта. Не повторять давление по деньгам. | EL6: 0 | EM6: А) Неиспользованные УТП под запросы клиента: для языковых сомнений - GPT Co-pilot и бот для интервью; для неуверенности в трудоустройстве - карьерный центр с шаблонами резюме; для мам с детьми - гибкий график и LMS-платформа; для украинцев - поддержка соотечественников в группе. Б) Поверхностно раскрытые: немецкий язык (не объяснил про разговорные клубы), сертификация (не подчеркнул государственный образец). В) Рекомендации по подаче: 'У нас есть ИИ-помощник, который поможет подготовиться к собеседованиям на немецком', 'Персональный трекер покажет ваш прогресс - никто не останется позади', 'Группа поддержки включает многих мам из Украины'. Г) Недостающие УТП: 'Специальная поддержка для мам' (гибкая система занятий под детский график), 'Украинское комьюнити' (менторство от выпускниц-соотечественниц), 'Гарантированная социализация' (профессиональные контакты в немецкой среде). | EO6: 1 | EP6: А) Разговор шел позитивно до этапа оплаты, клиент проявляла интерес к формату и программе. На этапе оплаты дала отказ/отложение. Б) Клиент сказала: 'Пока сложно сказать, что прям так горячим пирожком я... Надо с мужем поговорить... Не могу сейчас... За сколько я в поезд не впрыгну, к сожалению'. В) Ошибки продавца: не создал достаточной срочности, не отработал глубоко возражение 'посоветуюсь', быстро согласился на джоб-центр вместо дожима, не предложил предоплату или мини-коммитмент. Г) Изменяющая тактика: 'Понимаю потребность посоветоваться. В чем именно муж может помочь принять решение? Может, стоит ему тоже прослушать нашу презентацию?' - это могло выявить настоящие причины и вовлечь семью в решение. | EQ6: 00:14:24.90 - Клиент: Пока сложно сказать, что прям так горячим пирожком я..., 00:14:41.03 - Клиент: Надо с мужем поговорить | EU6: 0 | EV6: А) Содержание: Обсуждались мотивация (смена сферы с уборки на бухгалтерию), текущие сложности (застой 3 года, мини-джоб, языковой барьер), цели (финансовая независимость, 3000 евро зарплаты), презентация курса (7 месяцев онлайн, немецкий язык, трудоустройство), этап оплаты (7800/3900 евро, рассрочка), возражения (дорого, посоветуюсь, джоб-центр). Б) Реакция клиента: заинтересованная на этапе выявления потребностей, понимающая при презентации формата, сомневающаяся при обсуждении стоимости, отстраненная при попытке закрытия. На УТП реагировала позитивно, на цену - негативно. В) Договоренности: зафиксирован следующий звонок через 2-3 недели для подготовки предложения джоб-центру, отправка программы на изучение. Продавец проявил инициативу в фиксации шагов. | EX6: 0 | EY6: В разговоре не было упоминаний конкурентов ни прямо, ни косвенно. | FA6: 0 | FB6: 1. Отсутствие обращения по имени. Контекст: на протяжении всего разговора ни разу не назвал клиента по имени. Как следовало: 'Здравствуйте, [имя]', '[имя], а как долго вы в Германии?'. Эффект: создается личный контакт и доверие. 2. Поверхностная отработка возражения 'посоветуюсь'. Фраза: 'Надо с мужем поговорить' → 'А какой бюджет был бы подъемен?'. Как следовало: 'Понимаю. В чем именно хотите с ним посоветоваться? Может, есть что-то конкретное, что его беспокоит?'. Эффект: выявление истинных причин сопротивления. 3. Быстрая сдача позиций на джоб-центр. Контекст: при первых денежных сомнениях сразу предложил путь через субсидии. Как следовало: 'Понимаю ваши сомнения по деньгам. Но подумайте: каждый месяц отсрочки - это потеря 3000 евро будущего дохода. Может, стоит найти способ начать сейчас?'. Эффект: удержание на коммерческом треке и создание срочности. | FD6: 0 | FE6: 1. Структурное резюмирование. Фраза: 'Тогда давайте сейчас я подрезюмирую, что услышал от вас...'. Контекст: после выявления потребностей, перед презентацией. Почему сработало: создал ощущение понимания и структурности, клиент подтвердила правильность понимания. Техника: консультативные продажи. Тип: массовая техника. 2. Конкретизация зарплатных ожиданий. Фраза: 'По опыту бухгалтер начинающий зарабатывает от 3000 евро в месяц'. Контекст: после вопроса клиента о доходах. Почему сработало: дал конкретную цифру выше ожиданий клиента (она говорила о 25 евро/час). Техника: якорение цифрами. Тип: массовая техника. 3. Создание FOMO через ограниченность. Фраза: 'последнее место осталось, мы его по льготной цене отдаем'. Контекст: при презентации стоимости. Почему сработало: создало ощущение уникальности предложения и необходимости быстрого решения. Техника: дефицит и эксклюзивность. Тип: массовая техника. | FG6: 0 | FH6: А) Психологический портрет: Осторожная, ответственная женщина средних лет. Принимает решения обдуманно, консультируясь с семьей. Проявляет инициативу в обучении, но боится финансовых рисков. Темперамент спокойный, речь размеренная. Особенности: уточняет детали, ищет гарантии. Имя не было озвучено. Б) Цели и мотивация: Главная цель - вернуться к профессии бухгалтера и финансовая независимость ('не быть вечной уборщицей'). Боли: застой 3 года, низкий статус работы, зависимость от соцвыплат. Мотивация: самореализация, стабильность для детей, профессиональная гордость. Срок: готова начать, но не торопится с решением об оплате. В) Маркетинговые выводы: Сегмент - образованные украинские мамы 35-45 лет. Триггеры: профессиональная самореализация, финансовая стабильность семьи, достойная работа. Эффективные фичи: гибкий график для мам, поддержка украинского комьюнити, государственное финансирование. Канал - социальные сети украинских сообществ в Германии. | FJ6: 0 | FK6: Разговор был полноценным и завершился логично попрощанием 'Все, хорошо, отлично. Спасибо большое. До свидания' без технических сбоев или резких прерываний. | FL6: 00:17:01.78 - Клиент: Все, хорошо, отлично. Спасибо большое. До свидания. | FM6: 0 | FN6: Звонок начинается с приветствия и представления. Продавец знакомится с клиентом, задает базовые вопросы о ситуации, не ссылается на предыдущие контакты. Это первичный контакт. | FO6: 00:00:03.87 - Продавец: Здравствуйте, это Антон, эштермейстер, бухгалтерия, 00:00:43.56 - Продавец: А вы давно в Германии живете? | FP6: 1 | FQ6: Клиент упомянул желание обучения через джоб-центр и просил предложение (Angebot) для подачи заявки. Также говорил о 'биратор' (искаженно - берратор/консультант от джоб-центра). Это признаки ориентации на государственное финансирование через Gutschein/Jobcenter. | FR6: 00:03:46.81 - Клиент: Ну, конечно, желательно через джоб-центр, 00:02:42.45 - Клиент: биратор, как говорится, они на это начали, что пока вы не сделаете В1 | FS6: 6 | FT6: Клиент выразила готовность не растягивать обучение на год-два and хочет начать 'в ближайшее время', но показала осторожность при обсуждении конкретных сроков оплаты. Говорила 'не сейчас' относительно финансового решения, но проявляла интерес к августовскому потоку. Оценка 6 отражает положительную мотивацию при умеренной готовности к быстрому старту. | FU6: 00:06:27.41 - Продавец: И обучение вы планируете уже в ближайшее время? То есть растягивать на год, на два желания нет, правильно?, 00:06:29.33 - Клиент: Нет, нет., 00:16:25.13 - Клиент: За сколько я в поезд не впрыгну, к сожалению, 00:16:20.65 - Клиент: это будет нормально (про августовский поток) | FV6: 3 | FW6: Клиент выразила сомнения в возможности самостоятельной оплаты ('Пока сложно сказать, что прям так горячим пирожком я', 'мне желательно джоб-центр'), но рассматривала варианты рассрочки и интересовалась стоимостью. Семейный бюджет ограничен, зависят от соцвыплат, но муж работает тайль-цайт. Оценка 3 отражает низкую, но не нулевую готовность к самофинансированию. | FX6: 00:14:24.90 - Клиент: Пока сложно сказать, что прям так горячим пирожком я..., 00:03:46.81 - Клиент: желательно через джоб-центр, 00:04:06.38 - Клиент: мы все равно, как семья, ну, по общему доходу мы на джоб-центре | FY6: 8 | FZ6: Клиент четко понимает ценность обучения, мотивированно говорит о смене сферы деятельности ('не сильно бы хотелось быть вечной уборщицей'), видит обучение как путь к профессиональной самореализации и финансовой независимости. Уверенно артикулирует свои цели и понимает необходимость переподготовки для работы в Германии. | GA6: 00:02:29.87 - Клиент: здесь не сильно бы хотелось быть вечной уборщицей, 00:02:29.87 - Клиент: проще пройти курсы как бы и просто искать там работу там на бухгалтер, 00:05:51.07 - Клиент: Мы уже будем совершенно самостоятельные, как говорится, люди | GB6: 17 | GC6: Сумма оценок: Срочность (47) = 6, Платежеспособность (48) = 3, Потребность (49) = 8. Итого: 6 + 3 + 8 = 17. Примеры ключевых реплик: 'не растягивать на год-два' (срочность), 'желательно через джоб-центр' (платежеспособность), 'не хотелось быть вечной уборщицей' (потребность). Общий вывод: Средняя готовность - клиент мотивирован и понимает ценность, но ограничен финансово и осторожен в принятии решений. | GD6: 00:06:29.33 - Клиент: Нет, нет (про растягивание), 00:03:46.81 - Клиент: желательно через джоб-центр, 00:02:29.87 - Клиент: не сильно бы хотелось быть вечной уборщицей | GE6: =IFERROR(SUM(R[0]C[-156],R[0]C[-153],R[0]C[-150],R[0]C[-147])/COUNT(R[0]C[-156],R[0]C[-153],R[0]C[-150],R[0]C[-147]),"Установление контакта") -> #ERROR! | GF6: =IFERROR(SUM(R[0]C[-145],R[0]C[-142],R[0]C[-139],R[0]C[-136],R[0]C[-133],R[0]C[-130],R[0]C[-127])/COUNT(R[0]C[-145],R[0]C[-142],R[0]C[-139],R[0]C[-136],R[0]C[-133],R[0]C[-130],R[0]C[-127]),"Выявление потребностей") -> #ERROR! | GG6: =IFERROR(SUM(R[0]C[-125],R[0]C[-122])/COUNT(R[0]C[-125],R[0]C[-122]),"Презентация продукта") -> #ERROR! | GH6: =IFERROR(SUM(R[0]C[-120],R[0]C[-117])/COUNT(R[0]C[-120],R[0]C[-117]),"Предзакрытие и ФОМО") -> #ERROR! | GI6: =IFERROR(SUM(R[0]C[-109],R[0]C[-106])/COUNT(R[0]C[-109],R[0]C[-106]),"Отработка возражений") -> #ERROR! | GJ6: =IFERROR(SUM(R[0]C[-98],R[0]C[-95],R[0]C[-92],R[0]C[-89],R[0]C[-86])/COUNT(R[0]C[-98],R[0]C[-95],R[0]C[-92],R[0]C[-89],R[0]C[-86]),"Этап оплаты") -> #ERROR! | GK6: =IFERROR(SUM(R[0]C[-84],R[0]C[-81],R[0]C[-78],R[0]C[-75])/COUNT(R[0]C[-84],R[0]C[-81],R[0]C[-78],R[0]C[-75]),"Стандарты общения") -> #ERROR! | GL6: =IFERROR(SUM(R[0]C[-73],R[0]C[-70],R[0]C[-67])/COUNT(R[0]C[-73],R[0]C[-70],R[0]C[-67]),"Критические ошибки") -> #ERROR! | GM6: =IFERROR(R[0]C[-62]/50,"Экспертный блок 🧠 стратегический слой: методологии 🧰 тактический: структура и фразы 🧍 поведенческий: мотивация клиента 💳 финансовый: дожим и потери") -> #ERROR! | GN6: =IFERROR(SUM(R[0]C[-45],R[0]C[-42],R[0]C[-39],R[0]C[-36],R[0]C[-33])/COUNT(R[0]C[-45],R[0]C[-42],R[0]C[-39],R[0]C[-36],R[0]C[-33]),"Рекомендации") -> #ERROR! | GO6: =IFERROR(SUM(R[0]C[-31],R[0]C[-28],R[0]C[-25])/COUNT(R[0]C[-31],R[0]C[-28],R[0]C[-25]),"Фильтры") -> #ERROR! | GP6: =IFERROR(SUM(R[0]C[-23],R[0]C[-20],R[0]C[-17])/COUNT(R[0]C[-23],R[0]C[-20],R[0]C[-17]),"Скоринг") -> #ERROR! | GQ6: =IFERROR( SUM(IF({R[0]C[-168],R[0]C[-165],R[0]C[-162],R[0]C[-159],R[0]C[-156],R[0]C[-153],R[0]C[-150],R[0]C[-147],R[0]C[-144],R[0]C[-141],R[0]C[-138],R[0]C[-135],R[0]C[-132],R[0]C[-129],R[0]C[-126],R[0]C[-117],R[0]C[-114],R[0]C[-105],R[0]C[-102],R[0]C[-99],R[0]C[-96],R[0]C[-93],R[0]C[-90],R[0]C[-87],R[0]C[-84],R[0]C[-81]}="",hidden!R[0]C[-187],{R[0]C[-168],R[0]C[-165],R[0]C[-162],R[0]C[-159],R[0]C[-156],R[0]C[-153],R[0]C[-150],R[0]C[-147],R[0]C[-144],R[0]C[-141],R[0]C[-138],R[0]C[-135],R[0]C[-132],R[0]C[-129],R[0]C[-126],R[0]C[-117],R[0]C[-114],R[0]C[-105],R[0]C[-102],R[0]C[-99],R[0]C[-96],R[0]C[-93],R[0]C[-90],R[0]C[-87],R[0]C[-84],R[0]C[-81]}+hidden!R[0]C[-186])) / COUNT(IF({R[0]C[-168],R[0]C[-165],R[0]C[-162],R[0]C[-159],R[0]C[-156],R[0]C[-153],R[0]C[-150],R[0]C[-147],R[0]C[-144],R[0]C[-141],R[0]C[-138],R[0]C[-135],R[0]C[-132],R[0]C[-129],R[0]C[-126],R[0]C[-117],R[0]C[-114],R[0]C[-105],R[0]C[-102],R[0]C[-99],R[0]C[-96],R[0]C[-93],R[0]C[-90],R[0]C[-87],R[0]C[-84],R[0]C[-81]}="",hidden!R[0]C[-187],{R[0]C[-168],R[0]C[-165],R[0]C[-162],R[0]C[-159],R[0]C[-156],R[0]C[-153],R[0]C[-150],R[0]C[-147],R[0]C[-144],R[0]C[-141],R[0]C[-138],R[0]C[-135],R[0]C[-132],R[0]C[-129],R[0]C[-126],R[0]C[-117],R[0]C[-114],R[0]C[-105],R[0]C[-102],R[0]C[-99],R[0]C[-96],R[0]C[-93],R[0]C[-90],R[0]C[-87],R[0]C[-84],R[0]C[-81]}+hidden!R[0]C[-186])) ,"") -> #ERROR! | GR6: =L6/hidden!A5 -> #REF! | GS6: =IF((R[0]C[-26]+R[0]C[-23]+R[0]C[-20])<hidden!R[-1]C[-199],hidden!R[-1]C[-197], IF((R[0]C[-26]+R[0]C[-23]+R[0]C[-20])<hidden!R[-1]C[-198],hidden!R[-1]C[-196],hidden!R[-1]C[-195])) -> #ERROR! | GT6: =IF(R[0]C[-27]<=hidden!R[-1]C[-195],hidden!R[-1]C[-193], IF(R[0]C[-27]<=hidden!R[-1]C[-194],hidden!R[-1]C[-192],hidden!R[-1]C[-191])) -> #ERROR! | GU6: =IF(R[0]C[-25]<=hidden!R[-1]C[-196],hidden!R[-1]C[-194], IF(R[0]C[-25]<=hidden!R[-1]C[-195],hidden!R[-1]C[-193],hidden!R[-1]C[-192])) -> #ERROR! | GV6: =IF(R[0]C[-23]<=hidden!R[-1]C[-197],hidden!R[-1]C[-195], IF(R[0]C[-23]<=hidden!R[-1]C[-196],hidden!R[-1]C[-194],hidden!R[-1]C[-193])) -> #ERROR! | GW6: =TEXT(R[0]C[-194], "yyyy.mm") -> #ERROR!
