Workbook

Sheet AI
A1: number | B1: call_name | C1: transcription | D1: default_call_week | E1: id_item_set | F1: item_set_created_at | G1: item_set_updated_at | H1: month_of_processing | I1: real_file_duration | J1: call_parts_count | K1: call_date | L1: call_duration | M1: call_id | N1: call_phone | O1: call_source | P1: call_time | Q1: call_type | R1: call_week | S1: contact_id | T1: contact_name | U1: contact_type | V1: lead_created_at | W1: lead_id | X1: lead_name | Y1: lead_pipeline | Z1: lead_status | AA1: lead_url | AB1: user_id | AC1: user_name | AD1: score_0 | AE1: reason_0 | AF1: quote_0 | AG1: score_1 | AH1: reason_1 | AI1: quote_1 | AJ1: score_2 | AK1: reason_2 | AL1: quote_2 | AM1: score_3 | AN1: reason_3 | AO1: quote_3 | AP1: score_4 | AQ1: reason_4 | AR1: quote_4 | AS1: score_5 | AT1: reason_5 | AU1: quote_5 | AV1: score_6 | AW1: reason_6 | AX1: quote_6 | AY1: score_7 | AZ1: reason_7 | BA1: quote_7 | BB1: score_8 | BC1: reason_8 | BD1: quote_8 | BE1: score_9 | BF1: reason_9 | BG1: quote_9 | BH1: score_10 | BI1: reason_10 | BJ1: quote_10 | BK1: score_11 | BL1: reason_11 | BM1: quote_11 | BN1: score_12 | BO1: reason_12 | BP1: quote_12 | BQ1: score_13 | BR1: reason_13 | BS1: quote_13 | BT1: score_14 | BU1: reason_14 | BV1: quote_14 | BW1: score_15 | BX1: reason_15 | BY1: quote_15 | BZ1: score_16 | CA1: reason_16 | CB1: quote_16 | CC1: score_17 | CD1: reason_17 | CE1: quote_17 | CF1: score_18 | CG1: reason_18 | CH1: quote_18 | CI1: score_19 | CJ1: reason_19 | CK1: quote_19 | CL1: score_20 | CM1: reason_20 | CN1: quote_20 | CO1: score_21 | CP1: reason_21 | CQ1: quote_21 | CR1: score_22 | CS1: reason_22 | CT1: quote_22 | CU1: score_23 | CV1: reason_23 | CW1: quote_23 | CX1: score_24 | CY1: reason_24 | CZ1: quote_24 | DA1: score_25 | DB1: reason_25 | DC1: quote_25 | DD1: score_26 | DE1: reason_26 | DF1: quote_26 | DG1: score_27 | DH1: reason_27 | DI1: quote_27 | DJ1: score_28 | DK1: reason_28 | DL1: quote_28 | DM1: score_29 | DN1: reason_29 | DO1: quote_29 | DP1: score_30 | DQ1: reason_30 | DR1: quote_30 | DS1: score_31 | DT1: reason_31 | DU1: quote_31 | EH1: total_score | EI1: total_score_mandatory | EJ1: duration_min | EK1: group_score_1 | EL1: group_score_1_mandatory | EO1: field_866934
K2: CRM | AD2: Приветствие | AJ2: Снятие первичного волнения | AP2: Презентация предстоящего термина | AY2: Отправка материалов | BH2: Вопросы и возражения Клиента | BQ2: Следующие шаги | BW2: Завершение разговора | CI2: Стандарты общения | CO2: Критические ошибки | CX2: Экспертный блок | DD2: Рекомендации | DP2: Фильтры
A3: № | B3: Call file name | C3: Transcription | D3: Week of the call | E3: Item Set ID | F3: Item Set Created At | G3: Date of Analyze | H3: Month of Analyze | I3: Real File Duration | J3: количество частей | K3: Дата звонка | L3: Длительность | M3: ID звонка | N3: Телефон | O3: Источник | P3: Время звонка | Q3: Тип звонка | R3: Номер недели | S3: ID контакта | T3: ФИО контакта | U3: Тип контакта | V3: Дата создания сделки | W3: ID сделки | X3: Название сделки | Y3: Воронка сделки | Z3: Этап сделки | AA3: Ссылка на сделку | AB3: ID менеджера | AC3: ФИО менеджера | AD3: 1. Приветствие и представление менеджера | AE3: 1. Приветствие и представление менеджера – Reason | AF3: 1. Приветствие и представление менеджера – Quote | AG3: 2. Программирование разговора | AH3: 2. Программирование разговора – Reason | AI3: 2. Программирование разговора – Quote | AJ3: 3. Уточнение эмоционального состояния клиента перед термином | AK3: 3. Уточнение эмоционального состояния клиента перед термином – Reason | AL3: 3. Уточнение эмоционального состояния клиента перед термином – Quote | AM3: 4. Снятие волнения и поддержка клиента | AN3: 4. Снятие волнения и поддержка клиента – Reason | AO3: 4. Снятие волнения и поддержка клиента – Quote | AP3: 5. Объяснение формата встречи с бератером | AQ3: 5. Объяснение формата встречи с бератером – Reason | AR3: 5. Объяснение формата встречи с бератером – Quote | AS3: 6. Объяснение типичных вопросов бератера | AT3: 6. Объяснение типичных вопросов бератера – Reason | AU3: 6. Объяснение типичных вопросов бератера – Quote | AV3: 7. Снижение страха перед термином | AW3: 7. Снижение страха перед термином – Reason | AX3: 7. Снижение страха перед термином – Quote | AY3: 8. Отправка памятки для подготовки к термину | AZ3: 8. Отправка памятки для подготовки к термину – Reason | BA3: 8. Отправка памятки для подготовки к термину – Quote | BB3: 9. Объяснение содержания памятки | BC3: 9. Объяснение содержания памятки – Reason | BD3: 9. Объяснение содержания памятки – Quote | BE3: 10. Отправка тренажёра для подготовки | BF3: 10. Отправка тренажёра для подготовки – Reason | BG3: 10. Отправка тренажёра для подготовки – Quote | BH3: 11. Теги возражений | BI3: 11. Теги возражений – Reason | BJ3: 11. Теги возражений – Quote | BK3: 12. Корректность отработки возражений Клиента | BL3: 12. Корректность отработки возражений Клиента – Reason | BM3: 12. Корректность отработки возражений Клиента – Quote | BN3: 13. Вопросы Клиента | BO3: 13. Вопросы Клиента – Reason | BP3: 13. Вопросы Клиента – Quote | BQ3: 14. Договорённость о следующем контакте | BR3: 14. Договорённость о следующем контакте – Reason | BS3: 14. Договорённость о следующем контакте – Quote | BT3: 15. Открытый канал связи и поддержка Клиента | BU3: 15. Открытый канал связи и поддержка Клиента – Reason | BV3: 15. Открытый канал связи и поддержка Клиента – Quote | BW3: 16. Проверка уверенности Клиента после разговора | BX3: 16. Проверка уверенности Клиента после разговора – Reason | BY3: 16. Проверка уверенности Клиента после разговора – Quote | BZ3: 17. Объяснение процесса после успешного термина | CA3: 17. Объяснение процесса после успешного термина – Reason | CB3: 17. Объяснение процесса после успешного термина – Quote | CC3: 18. Инструкция на случай отказа в финансировании | CD3: 18. Инструкция на случай отказа в финансировании – Reason | CE3: 18. Инструкция на случай отказа в финансировании – Quote | CF3: 19. Сопровождение Клиента после термина | CG3: 19. Сопровождение Клиента после термина – Reason | CH3: 19. Сопровождение Клиента после термина – Quote | CI3: 20. Общая доброжелательность и вежливость Продавца | CJ3: 20. Общая доброжелательность и вежливость Продавца – Reason | CK3: 20. Общая доброжелательность и вежливость Продавца – Quote | CL3: 21. Продавец использовал активное слушание и отзеркаливание Клиента | CM3: 21. Продавец использовал активное слушание и отзеркаливание Клиента – Reason | CN3: 21. Продавец использовал активное слушание и отзеркаливание Клиента – Quote | CO3: 22. Критические ошибки с точки зрения компании | CP3: 22. Критические ошибки с точки зрения компании – Reason | CQ3: 22. Критические ошибки с точки зрения компании – Quote | CR3: 23. Критические ошибки с точки зрения клиента | CS3: 23. Критические ошибки с точки зрения клиента – Reason | CT3: 23. Критические ошибки с точки зрения клиента – Quote | CU3: 24. Критические ошибки с точки зрения закона | CV3: 24. Критические ошибки с точки зрения закона – Reason | CW3: 24. Критические ошибки с точки зрения закона – Quote | CX3: 25. Структура звонка: фактический скрипт, который применил Продавец | CY3: 25. Структура звонка: фактический скрипт, который применил Продавец – Reason | CZ3: 25. Структура звонка: фактический скрипт, который применил Продавец – Quote | DA3: 26. Потеря клиента на этапе закрытия | DB3: 26. Потеря клиента на этапе закрытия – Reason | DC3: 26. Потеря клиента на этапе закрытия – Quote | DD3: 27. Краткое резюме звонка | DE3: 27. Краткое резюме звонка – Reason | DF3: 27. Краткое резюме звонка – Quote | DG3: 28. Рекомендации Продавцу: зоны роста | DH3: 28. Рекомендации Продавцу: зоны роста – Reason | DI3: 28. Рекомендации Продавцу: зоны роста – Quote | DJ3: 29. Рекомендации Продавцу: лучшие практики | DK3: 29. Рекомендации Продавцу: лучшие практики – Reason | DL3: 29. Рекомендации Продавцу: лучшие практики – Quote | DM3: 30. Портрет клиента | DN3: 30. Портрет клиента – Reason | DO3: 30. Портрет клиента – Quote | DP3: 31. Сбой или прерывание разговора | DQ3: 31. Сбой или прерывание разговора – Reason | DR3: 31. Сбой или прерывание разговора – Quote | DS3: 32. Полезный звонок | DT3: 32. Полезный звонок – Reason | DU3: 32. Полезный звонок – Quote | DV3: =IFERROR(SUM(AD2,AG2)/COUNT(AD2,AG2),"Приветствие") -> Приветствие | DW3: =IFERROR(SUM(AJ2,AM2)/COUNT(AJ2,AM2),"Снятие первичного волнения") -> Снятие первичного волнения | DX3: =IFERROR(SUM(AP2,AS2,AV2)/COUNT(AP2,AS2,AV2),"Презентация предстоящего термина") -> Презентация предстоящего термина | DY3: =IFERROR(SUM(AY2,BB2,BE2)/COUNT(AY2,BB2,BE2),"Отправка материалов") -> Отправка материалов | DZ3: =IFERROR(SUM(BH2,BK2,BN2)/COUNT(BH2,BK2,BN2),"Вопросы и возражения Клиента") -> Вопросы и возражения Клиента | EA3: =IFERROR(SUM(BQ2,BT2)/COUNT(BQ2,BT2),"Следующие шаги") -> Следующие шаги | EB3: =IFERROR(SUM(BW2,BZ2,CC2,CF2)/COUNT(BW2,BZ2,CC2,CF2),"Завершение разговора") -> Завершение разговора | EC3: =IFERROR(SUM(CI2,CL2)/COUNT(CI2,CL2),"Стандарты общения") -> Стандарты общения | ED3: =IFERROR(SUM(CO2,CR2,CU2)/COUNT(CO2,CR2,CU2),"Критические ошибки") -> Критические ошибки | EE3: =IFERROR(SUM(CX2,DA2)/COUNT(CX2,DA2),"Экспертный блок") -> Экспертный блок | EF3: =IFERROR(SUM(DD2,DG2,DJ2,DM2)/COUNT(DD2,DG2,DJ2,DM2),"Рекомендации") -> Рекомендации | EG3: =IFERROR(SUM(DP2,DS2)/COUNT(DP2,DS2),"Фильтры") -> Фильтры | EH3: total_score | EI3: total_score_mandatory | EJ3: duration_min | EK3: group_score_1 | EL3: group_score_1_mandatory | EM3: Итоговый процент за звонок | EN3: Длительность (мин) | EO3: Категория
A4: 4 | B4: 172422187_1887961834_d98a01 | C4: https://docs.google.com/document/d/1iXoK0aGGJsISwZGbnQRnKIw9zvdErJqWrIckgLxefJk/edit?usp=drivesdk | D4: 2026-03-09 - 2026-03-15 | E4: 54506 | F4: 2026-03-10 18:47:10 | G4: 2026-03-10 18:56:16 | H4: 2026.03 | I4: 563.544 | J4: 1 | K4: 2026-03-09 | L4: 564 | M4: 172422187_1887961834 | N4: +4915115887174, Статус: Разговор состоялся | O4: CallGear | P4: 16:29:09+01:00 | Q4: Исходящий | R4: 11 | S4: 20567538 | T4: Lavrentieva Viktoriia | U4: Контакт | V4: 2026-02-18T17:25:15+01:00 | W4: 18053858 | X4: Автосделка: New lead form Typeform 1769898488 | Y4: Бух Бератер | Z4: Доведение | AA4: https://sternmeister.kommo.com/leads/detail/18053858 | AB4: 14817967 | AC4: Кристина Никоненко | AD4: 1 | AE4: Менеджер поприветствовала клиента, представилась и назвала компанию. | AF4: [00:00:00.031] – Продавец – Виктория, добрый вечер. Здравствуйте. Меня зовут Кристина, я менеджер сопровождения компании Шторммастеры. | AG4: 1 | AH4: Менеджер обозначила цель звонка (узнать про термин), предложила обсудить дальнейшие шаги и подготовку к термину. Также уточнила, есть ли у клиента 5-10 минут для разговора. | AI4: [00:00:00.031] – Продавец – Виктория, добрый вечер. Здравствуйте. Меня зовут Кристина, я менеджер сопровождения компании Шторммастеры. Звоню узнать, как у вас обстоят с термином. Удалось ли вам новый термин оформить у бирайтера?, [00:00:19.512] – Продавец – Я вас поздравляю. Подскажите, пожалуйста, есть ли у вас буквально 5-10 минут для того, чтобы мы дальнейшие шаги, например, обсудили, подготовку к термину? | AJ4: 1 | AK4: Менеджер прямо спросил клиента о его эмоциональном состоянии и наличии волнения перед предстоящим термином. | AL4: [00:01:07.130] – Продавец – Подскажите, пожалуйста, как себя в целом чувствуете? Есть ли волнение перед предстоящим термином? | AM4: 1 | AN4: Клиент сказал, что пока не испытывает волнения. Менеджер одобрила такой настрой и перешла к объяснениям, подразумевая, что это поможет избежать волнения в будущем. | AO4: [00:01:10.520] – Клиент – Пока что нет. [00:01:13.238] – Продавец – Это хороший настрой. В любом случае, главное, что смысл встреч понимаете, какие вопросы будет бирайтер задавать: почему именно данные курсы выбрали, как это поможет вам выйти на рынок труда, почему выбрали именно бухгалтерию, знаете ли вы содержание курса, сколько он длится. То есть все-таки стандартные вопросы будет задавать бирайтер на встрече с вами. | AP4: 1 | AQ4: Менеджер объяснила, что бератер будет задавать стандартные вопросы, касающиеся выбора курса и планов после обучения, что указывает на роль бератера как проверяющего целесообразность. | AR4: [00:01:13.238] – Продавец – Это хороший настрой. В любом случае, главное, что смысл встреч понимаете, какие вопросы будет бирайтер задавать: почему именно данные курсы выбрали, как это поможет вам выйти на рынок труда, почему выбрали именно бухгалтерию, знаете ли вы содержание курса, сколько он длится. То есть все-таки стандартные вопросы будет задавать бирайтер на встрече с вами. | AS4: 1 | AT4: Менеджер привела примеры вопросов, которые бератер обычно задает, касающиеся мотивации выбора курса, его содержания и планов клиента. | AU4: [00:01:13.238] – Продавец – В любом случае, главное, что смысл встреч понимаете, какие вопросы будет бирайтер задавать: почему именно данные курсы выбрали, как это поможет вам выйти на рынок труда, почему выбрали именно бухгалтерию, знаете ли вы содержание курса, сколько он длится. То есть все-таки стандартные вопросы будет задавать бирайтер на встрече с вами. | AV4: 1 | AW4: Менеджер снизила страх, предложив тренировку произношения и понимания логики ответов через бота, а также отметив, что можно говорить простыми фразами и не нужно ничего зубрить. | AX4: [00:02:04.260] – Продавец – И можете прям по памятке почитать в спокойном для себя темпе. Время у нас много, не нужно ничего зубрить, главное понять логику ответов и несколько раз проговорить ключевые фразы. И как раз можно потренировать произношение по памятке и аудирование за счет бота. Это вам поможет говорить уверенно, четко и пусть даже простыми фразами., [00:02:32.600] – Клиент – Да, мне лучше простыми фразами, я потом запутываюсь. | AY4: 0 | AZ4: Менеджер не сообщила об отправке памятки, но спросила, присылали ли ее коллеги. Памятка уже была у клиента, но менеджер не предложила ее продублировать или отправить еще раз для удобства. | BA4: [00:00:31.466] – Продавец – Замечательно. Подскажите, пожалуйста, помните, возможно, прислали ли вам мои коллеги памятку по вопросам, которые обычно берут?, [00:00:40.480] – Клиент – Да, есть. | BB4: 1 | BC4: Менеджер не объяснила содержание памятки, но клиент подтвердил, что она у него есть и он ее "тогда смотрел" и пересмотрит позже. Менеджер упомянула, что по памятке можно "почитать в спокойном для себя темпе", и это поможет "понять логику ответов". | BD4: [00:00:44.426] – Клиент – Ну, я тогда смотрела, когда ходила первый раз на встречу. Вот поэтому я еще пересмотрю перед тем, как идти. Ну, просто это 24 марта, я все забуду, я поэтому посмотрю., [00:02:04.260] – Продавец – И можете прям по памятке почитать в спокойном для себя темпе. Время у нас много, не нужно ничего зубрить, главное понять логику ответов и несколько раз проговорить ключевые фразы. | BE4: 1 | BF4: Менеджер сообщила об отправке бота-тренажера G5 на e-mail и объяснила, как он поможет тренировать произношение и аудирование. | BG4: [00:01:48.620] – Клиент – Нет. [00:01:50.240] – Продавец – Я вам его тогда отправлю на e-mail. Он работает достаточно... Включить?, [00:02:04.260] – Продавец – И можете прям по памятке почитать в спокойном для себя темпе. Время у нас много, не нужно ничего зубрить, главное понять логику ответов и несколько раз проговорить ключевые фразы. И как раз можно потренировать произношение по памятке и аудирование за счет бота. Это вам поможет говорить уверенно, четко и пусть даже простыми фразами. | BH4: Тегов нет. | BI4: Клиент не озвучивал явных возражений или сомнений по отношению к курсу или процессу, только небольшое беспокойство по поводу того, что забудет информацию из памятки из-за срока до термина и медлительности Job Center. | BJ4: [00:00:44.426] – Клиент – Ну, я тогда смотрела, когда ходила первый раз на встречу. Вот поэтому я еще пересмотрю перед тем, как идти. Ну, просто это 24 марта, я все забуду, я поэтому посмотрю., [00:05:10.000] – Клиент – Ой, я не думаю, что 30 марта. У меня такой же центр, они очень медленные. Если у меня 24-го только будет термин, то вряд ли, говорю сразу. | BL4: Клиент не озвучивал явных возражений или сомнений, которые требовали бы отработки. Единственное, что можно отнести к сомнениям, – это беспокойство о том, что клиент забудет информацию к дате термина, на что Менеджер отреагировала понимающе, но без конкретного предложения, которое могло бы снять это сомнение. Также клиент выразил сомнение в своевременном начале курса из-за медлительности Job Center, на что Менеджер предложила запасные варианты. | BM4: [00:00:44.426] – Клиент – Ну, я тогда смотрела, когда ходила первый раз на встречу. Вот поэтому я еще пересмотрю перед тем, как идти. Ну, просто это 24 марта, я все забуду, я поэтому посмотрю., [00:01:00.660] – Продавец – Я понимаю, да, когда оно далеко. Да. | BN4: 1 | BO4: Клиент задавал несколько вопросов, и Менеджер корректно на них ответила. Были вопросы по поводу бота ('как его включить?') и по поводу даты ангибота/следующего курса. | BP4: [00:01:57.800] – Клиент – Ну да, как его включить?, [00:02:00.560] – Продавец – А просто его запускаете, он открывается в браузере., [00:05:00.740] – Клиент – А когда следующий курс? В мае или когда вы говорили? | BQ4: 1 | BR4: Менеджер договорилась о следующем звонке с клиентом на 16 число в 12:30, чтобы ответить на возможные вопросы. | BS4: [00:03:12.800] – Клиент – Давайте, может, позже немножко, может, числа 16-го., [00:03:18.020] – Продавец – Давайте попробуем хорошо 16-го тогда. Во 2-й, в 1-й половине, как вам будет удобно?, [00:03:39.800] – Клиент – Сейчас я подумаю. Лучше где-то в 12:30. | BT4: 1 | BU4: Менеджер явно сообщила клиенту, что он может писать, если появятся вопросы до следующего звонка. | BV4: [00:09:13.800] – Продавец – Хорошо, если будут вопросы, то тоже пишите обязательно, буду вам отправлю. | BW4: 1 | BX4: Менеджер прямо спросила клиента о том, как он себя чувствует после разговора, стало ли ему понятнее и появилась ли уверенность. | BY4: [00:03:47.460] – Продавец – Я так и поставлю, у меня сейчас расписание свободно. Подскажите, пожалуйста, как вы себя чувствуете после нашего разговора? Более понятно, может быть, появилась какая-то уверенность в предстоящем вашем решении? | BZ4: 1 | CA4: Менеджер подробно объяснила дальнейший процесс после успешного термина, включая передачу документов в агентство РБА, назначение нового термина и важность запроса на ускорение этого процесса. | CB4: [00:04:18.000] – Продавец – Я вас поняла. К любым результатам действительно нужно быть готовым. И по поводу результатов хотелось бы проговорить еще также важный момент. Если термин в Job Center пройдет успешно, ваши документы должны передать в агентство РБА. Обиратель вам об этом скажет. Далее они назначают новый термин уже. И тут нужно попросить сделать это как можно быстрее, чтобы не пропустить начало потока. | CC4: 1 | CD4: Менеджер дала четкие инструкции на случай отказа в финансировании, подчеркнув важность выяснения причины и возможности повлиять на ситуацию. | CE4: [00:07:07.780] – Продавец – И также, если вдруг, если по каким-либо причинам бирайтер не одобрит финансирование нашего курса, хотя у вас достаточно хороший шанс на получение финансирования, однако хочу отметить, что вам нужно во время термина выяснить причину, спросить, как он видит ваше развитие и чего, по его мнению, вам не хватает, чтобы получить финансирование. То есть важность термина с полным пониманием, какое решение принято и как можно на это повлиять, если потребуется. | CF4: 0 | CG4: Менеджер не сообщила о том, что свяжется с клиентом после термина для обсуждения дальнейших действий. Была договоренность о звонке до термина, но не после. | CI4: 1 | CJ4: Продавец обращалась к клиенту по имени ("Виктория", [00:00:00.031]), использовала вежливые слова ("здравствуйте", "пожалуйста", "спасибо"). Общалась уважительно и доброжелательно, подстраивая тон под спокойное состояние клиента. | CK4: [00:00:00.031] – Продавец – Виктория, добрый вечер. Здравствуйте. Меня зовут Кристина, я менеджер сопровождения компании Шторммастеры., [00:00:19.512] – Продавец – Я вас поздравляю. Подскажите, пожалуйста, есть ли у вас буквально 5-10 минут для того, чтобы мы дальнейшие шаги, например, обсудили, подготовку к термину?, [00:09:18.720] – Клиент – Спасибо большое. | CL4: 1 | CM4: Продавец активно слушала клиента, реагировала на его реплики ("Я понимаю", "Я вас поняла"), поддерживала диалог и даже перефразировала ("Мне главное, чтобы сертификат котировался в Германии. - Я так поняла, что он официальный.") | CN4: [00:01:00.660] – Продавец – Я понимаю, да, когда оно далеко. Да., [00:02:38.220] – Продавец – Ну, я вас прекрасно понимаю., [00:04:18.000] – Продавец – Я вас поняла. К любым результатам действительно нужно быть готовым., [00:08:41.740] – Продавец – Я так поняла, что он официальный. | CO4: 1 | CP4: Критических ошибок с точки зрения компании не было. Продавец не высказывалась негативно, не отговаривала клиента, не дезинформировала. Разговор завершился с фиксацией следующего шага - запланированного звонка. | CQ4: [00:09:12.640] – Клиент – Хорошо, да., [00:09:13.800] – Продавец – Хорошо, если будут вопросы, то тоже пишите обязательно, буду вам отправлю. | CR4: 1 | CS4: Продавец не допустила критических ошибок. Информация, касающаяся курса и процессов, была корректной. Поведение было уважительным, ответы ясные. Менеджер грамотно пояснила статус сертификата, что он "официальный" и "государство одобрило". | CT4: [00:08:45.240] – Клиент – Да, это официальное. [00:08:46.000] – Продавец – Государство одобрило, то есть оно финансирует именно то, что нужно для трудоустройства вам. Другого оно финансировать не будет. Кто бы этого не хотел, может быть, и к лучшему, зато все максимально официально. | CU4: 1 | CV4: Критических нарушений с точки зрения закона не зафиксировано. Продавец не давала ложных гарантий, не разглашала внутреннюю информацию и корректно комментировала статус сертификации, не заявляя о наличии AZAV, но говоря об официальности и одобрении государством. | CW4: [00:08:46.000] – Продавец – Государство одобрило, то есть оно финансирует именно то, что нужно для трудоустройства вам. Другого оно финансировать не будет. Кто бы этого не хотел, может быть, и к лучшему, зато все максимально официально. | CX4: 1 | CY4: А) Фактический скрипт:1. Приветствие и представление: Менеджер поздоровалась, представилась и назвала компанию. [00:00:00.031]2. Уточнение статуса термина: Менеджер спросила, оформлен ли новый термин. [00:00:06.666]3. Программирование разговора: Спросила об удобстве 5-10 минут для обсуждения дальнейших шагов. [00:00:19.512]4. Проверка наличия памятки: Уточнила, получал ли клиент памятку. [00:00:31.466]5. Проверка эмоционального состояния: Спросила о волнении перед термином. [00:01:07.130]6. Объяснение формата встречи с бератером: Рассказала о стандартных вопросах. [00:01:13.238]7. Предложение тренажера: Спросила, отправляли ли бота G5, и при отрицательном ответе предложила отправить. [00:01:48.620]8. Ценность тренажера: Объяснила, как бот поможет в подготовке. [00:02:04.260]9. Планирование следующего контакта: Предложила созвониться, чтобы ответить на вопросы. [00:02:45.380]10. Уточнение после разговора: Спросила о настроении клиента после звонка. [00:03:47.460]11. Объяснение процесса после успешного термина: Рассказала о передаче документов и важности быстрого назначения следующего термина. [00:04:18.000]12. Уточнение даты ангибота: Спросила, на какую дату был ангибот. [00:04:50.760]13. Инструкция на случай отказа: Рассказала, что делать, если бератер не одобрит финансирование. [00:07:07.780]14. Завершение разговора: Договоренность о следующем звонке и предложении писать с вопросами. [00:09:12.640]Б) Особенности скрипта: Продавец довольно последовательно шла по скрипту, охватывая ключевые моменты подготовки к термину. Нестандартным шагом можно назвать предложение бота G5. Пропущено было активное предложение отправить памятку повторно, хотя клиент упоминал, что пересмотрит её.В) Элементы скрипта сработали: Клиент подтвердил наличие термина, согласился на разговор, проявил интерес к боту G5, согласился на следующий звонок, задавал уточняющие вопросы по срокам и документам.Г) Элементы не сработали: Возможно, недостаточно активно была отработана фраза клиента о том, что "она все забудет", на что менеджер просто ответила: "Я понимаю, да, когда оно далеко". | CZ4: [00:00:00.031] – Продавец – Виктория, добрый вечер. Здравствуйте. Меня зовут Кристина, я менеджер сопровождения компании Шторммастеры., [00:00:19.512] – Продавец – Я вас поздравляю. Подскажите, пожалуйста, есть ли у вас буквально 5-10 минут для того, чтобы мы дальнейшие шаги, например, обсудили, подготовку к термину?, [00:00:31.466] – Продавец – Замечательно. Подскажите, пожалуйста, помните, возможно, прислали ли вам мои коллеги памятку по вопросам, которые обычно берут?, [00:01:07.130] – Продавец – Подскажите, пожалуйста, как себя в целом чувствуете? Есть ли волнение перед предстоящим термином?, [00:01:13.238] – Продавец – В любом случае, главное, что смысл встреч понимаете, какие вопросы будет бирайтер задавать: почему именно данные курсы выбрали, как это поможет вам выйти на рынок труда, почему выбрали именно бухгалтерию, знаете ли вы содержание курса, сколько он длится., [00:01:48.620] – Клиент – Нет. [00:01:50.240] – Продавец – Я вам его тогда отправлю на e-mail., [00:02:04.260] – Продавец – И можете прям по памятке почитать в спокойном для себя темпе. , [00:02:45.380] – Продавец – Подскажите, пожалуйста, также могу с вами позвонить где-нибудь, например, 12-го числа, 13-го числа, для того, чтобы, если у вас появятся вопросы по памятке, либо вообще в целом, может быть, про обучение какие-то вопросы появятся, я на них отвечу, в какое время вам будет удобно?, [00:03:47.460] – Продавец – Подскажите, пожалуйста, как вы себя чувствуете после нашего разговора? Более понятно, может быть, появилась какая-то уверенность в предстоящем вашем решении?, [00:04:18.000] – Продавец – Я вас поняла. К любым результатам действительно нужно быть готовым. И по поводу результатов хотелось бы проговорить еще также важный момент. Если термин в Job Center пройдет успешно, ваши документы должны передать в агентство РБА., [00:04:50.760] – Клиент – Сейчас скажу., [00:07:07.780] – Продавец – И также, если вдруг, если по каким-либо причинам бирайтер не одобрит финансирование нашего курса, хотя у вас достаточно хороший шанс на получение финансирования, однако хочу отметить, что вам нужно во время термина выяснить причину, спросить, как он видит ваше развитие и чего, по его мнению, вам не хватает, чтобы получить финансирование., [00:09:12.640] – Клиент – Хорошо, да. [00:09:13.800] – Продавец – Хорошо, если будут вопросы, то тоже пишите обязательно, буду вам отправлю. | DA4: 1 | DB4: Разговор завершился позитивно, с конкретной договоренностью о следующем шаге: запланирован звонок на 16 число в 12:30. Клиент проявил готовность к последующим действиям. | DC4: [00:09:12.640] – Клиент – Хорошо, да., [00:09:13.800] – Продавец – Хорошо, если будут вопросы, то тоже пишите обязательно, буду вам отправлю., [00:09:20.020] – Продавец – До свидания., [00:09:21.040] – Клиент – До свидания.. | DD4: Резюме | DE4: А) Содержание звонка: Звонок был посвящен подготовке клиента к предстоящему термину в Job Center. Были затронуты темы: подтверждение даты термина, обсуждение возможных вопросов бератера, важность понимания логики ответов, предложение бота-тренажера для практики, инструкции на случай успешного/неуспешного прохождения термина, а также планирование следующего звонка для ответа на вопросы клиента. Мотивация клиента, презентация курса или этап оплаты не обсуждались, так как это был звонок сопровождения.Б) Реакция Клиента: Клиент была спокойна и в целом позитивно настроена. Она подтвердила наличие термина, выразила согласие на предложенный план подготовки (обсуждение, бот, следующий звонок) и задала уточняющие вопросы по срокам и документам. Не было выражено явных сомнений или негатива.В) Достигнутые договорённости: Были зафиксированы следующие шаги: отправка бота-тренажера на e-mail клиента, а также следующий звонок 16 марта в 12:30 для обсуждения вопросов. Продавец зафиксировала следующий шаг. | DG4: Рекомендация | DH4: 1. Фраза Продавца: "Я понимаю, да, когда оно далеко". Контекст: Клиент сказала, что все забудет к 24 марта, потому что это долго. Продавец отреагировала этой фразой. Как следовало сказать: "Я прекрасно понимаю, что так бывает. Именно поэтому у нас есть памятка и бот-тренажер, которые можно использовать ближе к дате термина, чтобы освежить память и быть уверенной в ответах. Мы также созвонимся с вами ближе к дате, чтобы еще раз все проговорить." Ожидаемый эффект: Это позволило бы сразу же снять беспокойство клиента, подкрепить ценность предложенных инструментов и подтвердить дальнейшую поддержку, усилив уверенность клиента. 2. Фраза Продавца: Отсутствие активного предложения продублировать памятку. Контекст: Продавец спросила, присылали ли коллеги памятку, клиент ответила "да, есть", но также сказала, что "тогда смотрела" и "еще пересмотрит перед тем, как идти". Как следовало сказать: "Отлично, что памятка у вас есть. Я могу продублировать ее вам на почту вместе с ботом, чтобы она точно была под рукой, когда вы решите ее пересмотреть." Ожидаемый эффект: Это показало бы дополнительную заботу о клиенте, гарантировало бы наличие актуальной версии памятки и упростило бы для клиента доступ к ней, что также могло бы снизить беспокойство о том, что она "все забудет". | DI4: [00:00:44.426] – Клиент – Ну, я тогда смотрела, когда ходила первый раз на встречу. Вот поэтому я еще пересмотрю перед тем, как идти. Ну, просто это 24 марта, я все забуду, я поэтому посмотрю., [00:01:00.660] – Продавец – Я понимаю, да, когда оно далеко. Да. | DJ4: Рекомендация | DK4: 1. Фраза Продавца: "Я вам его тогда отправлю на e-mail. Он работает достаточно... Включить? ... И можете прям по памятке почитать в спокойном для себя темпе. ... И как раз можно потренировать произношение по памятке и аудирование за счет бота. Это вам поможет говорить уверенно, четко и пусть даже простыми фразами." Контекст: Клиент не знала о боте G5. Продавец предложила его отправить и подробно объяснила его пользу. Почему это сработало: Продавец предложила конкретный инструмент для решения возможной проблемы (страх перед экзаменом, плохой немецкий), подробно объяснила его функционал и преимущества, а также сняла возможное опасение клиента о сложности ("пусть даже простыми фразами"). Техника: Презентация решения потребностей (Feature-Advantage-Benefit), снижение барьеров. Тип практики: Массовая техника. 2. Фраза Продавца: "...вам нужно во время термина выяснить причину, спросить, как он видит ваше развитие и чего, по его мнению, вам не хватает, чтобы получить финансирование. То есть важность термина с полным пониманием, какое решение принято и как можно на это повлиять, если потребуется. К примеру, бывали такие моменты, что бирайтер отправляет на работу... В таком случае можно договориться с бирайтером о том, что на повторный термин вы ему принесете отклики... Если будут в виде отказа, то уже можно будет еще раз повторно рассмотреть обучение." Контекст: Продавец дала инструкцию, что делать в случае отказа в финансировании. Почему это сработало: Продавец не только подготовила клиента к возможному негативному исходу, но и предложила конкретный, пошаговый план действий для преодоления препятствия, придавая клиенту уверенность в том, что даже в случае отказа есть пути решения. Техника: Работа с возражениями на опережение, предоставление алгоритма действий, усиление позиции клиента. Тип практики: Массовая техника. | DL4: [00:01:50.240] – Продавец – Я вам его тогда отправлю на e-mail. Он работает достаточно... Включить?, [00:02:04.260] – Продавец – И можете прям по памятке почитать в спокойном для себя темпе. Время у нас много, не нужно ничего зубрить, главное понять логику ответов и несколько раз проговорить ключевые фразы. И как раз можно потренировать произношение по памятке и аудирование за счет бота. Это вам поможет говорить уверенно, четко и пусть даже простыми фразами., [00:07:07.780] – Продавец – И также, если вдруг, если по каким-либо причинам бирайтер не одобрит финансирование нашего курса, хотя у вас достаточно хороший шанс на получение финансирования, однако хочу отметить, что вам нужно во время термина выяснить причину, спросить, как он видит ваше развитие и чего, по его мнению, вам не хватает, чтобы получить финансирование. То есть важность термина с полным пониманием, какое решение принято и как можно на это повлиять, если потребуется. | DM4: Рекомендация | DN4: А) Психологический и демографический портрет Клиента: Клиент - Виктория, спокойная, не склонная к панике, как она сама говорит "всегда спокойная, готова к любым результатам". [00:04:06.980] Проявляет небольшое беспокойство по поводу запоминания информации к далекой дате термина и скорости работы Job Center. Уточняющая, задает вопросы по процессу. Не проявляет инициативу в поиске информации, но готова следовать рекомендациям.Б) Цели и приоритеты Клиента: Главная цель клиента - получить сертификат, который котируется в Германии. [00:08:34.520] Возможно, ищет стабильность и возможность трудоустройства в Германии. Страх потерять время зря или получить недействительный документ. Нет ярко выраженных болей или страхов, кроме общих беспокойств по поводу бюрократических процессов.В) Дополнительные характеристики и предложения:Для маркетинга: Использовать формулировки, подчеркивающие официальность, государственную поддержку и признание сертификата в Германии. Акцент на пошаговое сопровождение и снятие бюрократических сложностей.УТП, которые сработали бы сильнее: Гарантии официального признания сертификата, подробное объяснение всех этапов взаимодействия с Job Center и Agentur für Arbeit, поддержка в случае отказа.Фичи/бонусы/способы оплаты: Важно акцентировать на полном сопровождении до трудоустройства, включая помощь с резюме и собеседованиями.Сегмент/персона/рынок: Клиент не ищет "быстрых" решений, а ориентирован на легальность и официальность, что характерно для людей, переехавших в Германию и стремящихся к интеграции на рынок труда. Этот сегмент ценит надежность и понятные процессы, готовность к бюрократии, но нуждается в поддержке. | DO4: [00:04:06.980] – Клиент – Нет, я спокойная всегда, я готова к любым результатам, поэтому я не могу., [00:08:34.520] – Клиент – Нет, мне главное, чтобы сертификат котировался в Германии. | DP4: 1 | DQ4: Разговор был полноценным, завершился логично, участники попрощались. | DR4: [00:09:20.020] – Продавец – До свидания., [00:09:21.040] – Клиент – До свидания.. | DS4: 1 | DT4: Звонок относится к этапу первого контакта сопровождения. Признаки первого контакта включают: поздравление с назначенным термином, объяснение цели звонка как первичной подготовки, разговор о том, как проходит встреча с бератером, обещание отправить тренажер и договоренность о следующем контакте для дальнейшей подготовки.Все эти пункты были соблюдены. | DU4: [00:00:15.160] – Клиент – Да, сегодня удалось на 24 марта., [00:00:19.512] – Продавец – Я вас поздравляю. Подскажите, пожалуйста, есть ли у вас буквально 5-10 минут для того, чтобы мы дальнейшие шаги, например, обсудили, подготовку к термину?, [00:01:13.238] – Продавец – В любом случае, главное, что смысл встреч понимаете, какие вопросы будет бирайтер задавать..., [00:01:50.240] – Продавец – Я вам его тогда отправлю на e-mail., [00:02:45.380] – Продавец – Подскажите, пожалуйста, также могу с вами позвонить где-нибудь, например, 12-го числа, 13-го числа, для того, чтобы, если у вас появятся вопросы по памятке, либо вообще в целом, может быть, про обучение какие-то вопросы появятся, я на них отвечу, в какое время вам будет удобно? | DV4: =IFERROR(SUM(AC4,AF4)/COUNT(AC4,AF4),"Приветствие") -> Приветствие | DW4: =IFERROR(SUM(AI4,AL4)/COUNT(AI4,AL4),"Снятие первичного волнения") -> Снятие первичного волнения | DX4: =IFERROR(SUM(AO4,AR4,AU4)/COUNT(AO4,AR4,AU4),"Презентация предстоящего термина") -> Презентация предстоящего термина | DY4: =IFERROR(SUM(AX4,BA4,BD4)/COUNT(AX4,BA4,BD4),"Отправка материалов") -> Отправка материалов | DZ4: =IFERROR(SUM(BG4,BJ4,BM4)/COUNT(BG4,BJ4,BM4),"Вопросы и возражения Клиента") -> Вопросы и возражения Клиента | EA4: =IFERROR(SUM(BP4,BS4)/COUNT(BP4,BS4),"Следующие шаги") -> Следующие шаги | EB4: =IFERROR(SUM(BV4,BY4,CB4,CE4)/COUNT(BV4,BY4,CB4,CE4),"Завершение разговора") -> Завершение разговора | EC4: =IFERROR(SUM(CH4,CK4)/COUNT(CH4,CK4),"Стандарты общения") -> Стандарты общения | ED4: =IFERROR(SUM(CN4,CQ4,CT4)/COUNT(CN4,CQ4,CT4),"Критические ошибки") -> Критические ошибки | EE4: =IFERROR(SUM(#REF!,#REF!)/COUNT(#REF!,#REF!),"Экспертный блок") -> Экспертный блок | EF4: =IFERROR(SUM(#REF!,#REF!,#REF!,#REF!)/COUNT(#REF!,#REF!,#REF!,#REF!),"Рекомендации") -> Рекомендации | EG4: =IFERROR(SUM(#REF!,#REF!)/COUNT(#REF!,#REF!),"Фильтры") -> Фильтры | EH4: 0.92307692 | EI4: 0.875 | EJ4: 9.3924 | EK4: 1 | EL4: 1 | EM4: {=IFERROR( SUM(IF({AD4,AG4,AJ4,AM4,AP4,AS4,AV4,AY4,BB4,BE4,BK4,BN4,BQ4,BT4,BW4,BZ4,CC4,CF4,CI4,CL4}="",hidden!C4,{AD4,AG4,AJ4,AM4,AP4,AS4,AV4,AY4,BB4,BE4,BK4,BN4,BQ4,BT4,BW4,BZ4,CC4,CF4,CI4,CL4}+hidden!D4)) / COUNT(IF({AD4,AG4,AJ4,AM4,AP4,AS4,AV4,AY4,BB4,BE4,BK4,BN4,BQ4,BT4,BW4,BZ4,CC4,CF4,CI4,CL4}="",hidden!C4,{AD4,AG4,AJ4,AM4,AP4,AS4,AV4,AY4,BB4,BE4,BK4,BN4,BQ4,BT4,BW4,BZ4,CC4,CF4,CI4,CL4}+hidden!D4)) ,"")} -> 0.9 | EN4: =I4/hidden!A1 -> 9.3924
A5: 5 | B5: 195627662_1888425111_b89574 | C5: https://docs.google.com/document/d/1Pst-TCISMQXFmZEMYrmqtQcdR7F-wMwwL_D4cqn5iDg/edit?usp=drivesdk | D5: 2026-03-09 - 2026-03-15 | E5: 54740 | F5: 2026-03-11 15:00:20 | G5: 2026-03-11 15:10:31 | H5: 2026.03 | I5: 861.624 | J5: 1 | K5: 2026-03-11 | L5: 862 | M5: 195627662_1888425111 | N5: +491606896909, Статус: Разговор состоялся | O5: CallGear | P5: 11:35:40+01:00 | Q5: Исходящий | R5: 11 | S5: 14900444 | T5: Hanna Bielokon | U5: Контакт | V5: 2026-03-11T11:31:07+01:00 | W5: 18379056 | X5: Автосделка: Lead from: https://sternmeister.de/education?utm_source=facebook&utm_medium=video_diana_gipnoz&utm_id=lp_short&utm_campaign=%7Ccntry%3DGermany%7Creg%3Dall%7Cgls%3Dqual_lead%7Caid%7C120225303723160678&utm_content=cid%7C120224919600550678%7Cgid% | Y5: Бух Бератер | Z5: Принято от первой линии | AA5: https://sternmeister.kommo.com/leads/detail/18379056 | AB5: 14817967 | AC5: Кристина Никоненко | AD5: 1 | AE5: Менеджер поприветствовала клиента, представилась и обозначила название компании. Это соответствует критерию: приветствие было вежливым, менеджер назвала себя Кристиной и уточнила название компании Штернмастер. | AF5: [00:00:04.334] – Продавец – Здравствуйте, меня зовут Кристина, я менеджер сопровождения компании Штернмастер. | AG5: 1 | AH5: Менеджер кратко объяснила цель звонка — обсудить дальнейшие шаги перед термином, обозначила примерную длительность разговора (5-10 минут) и уточнила, удобно ли клиенту сейчас говорить. Это полностью отвечает критерию. | AI5: [00:00:12.907] – Продавец – Подскажите, пожалуйста, есть ли у вас буквально 5-10 минут для того, чтобы мы обсудили дальнейшие шаги перед термином? | AJ5: 0 | AK5: Менеджер не спросила напрямую о волнении клиента или его самочувствии перед термином. Вопросы и поддержка были связаны с процессом, но прямого уточнения эмоционального состояния не было. | AM5: 1 | AN5: Клиент была немного обеспокоена процессом (например из-за новой земли, экзаменов и статуса), и менеджер выразила поддержку, при этом попыталась снизить волнение, заверив в своей поддержке перед термином и мотивируя, что всё получится. | AO5: [00:00:43.070] – Продавец – Ну, значит, нужно себя хорошо презентовать ему., [00:00:49.778] – Продавец – Моя задача помочь вам подготовиться, ответить на все вопросы и сделать так, чтобы вы пришли на встречу с берайтером спокойно, уверенно. | AP5: 1 | AQ5: Менеджер объяснила, что встреча нужна для проверки мотивации и понимания курса, а также упомянула роль берайтера. По формату встречи она указала, что берайтер будет задавать вопросы о курсе, мотивации, и конечной целью должно быть трудоустройство. | AR5: [00:05:35.944] – Продавец – Ну, в принципе, вы знаете уже, да, как встреча с берайтером проходит по поводу обучения., [00:05:49.444] – Продавец – чтобы берайтер понимал, что, конечно, ваша финальная точка будет трудоустройство. | AS5: 1 | AT5: Менеджер привела примеры типичных вопросов: почему выбрали бухгалтерию, какой курс, что есть в курсе, финальная цель — трудоустройство. Это отвечает критерию. | AU5: [00:05:39.488] – Продавец – Это вопрос про вашу мотивацию, почему вы брали именно бухгалтерию, что за курс, какой курс, да, там, что есть в этом курсе, да, и чтобы берайтер понимал, что, конечно, ваша финальная точка будет трудоустройство. | AV5: 1 | AW5: Менеджер неоднократно поддерживала клиента, говорила, что не нужно бояться отвечать простыми фразами, отмечала, что главное — стратегия ответов и понимание логики, и что уровень немецкого уже хороший. Это снижает страх перед термином. | AX5: [00:06:15.279] – Продавец – От слова идет на уровень простыми фразами, но тут главное понять логику, как и что отвечать берайтеру, в каком варианте ответ, соответственно, на немецком языке., [00:08:29.199] – Продавец – Он будет у меня хороший, господи, этот уровень языка., [00:08:37.990] – Продавец – И то, что вы добились уже сейчас хороших результатов, это только ваша заслуга, ваше стремление и желание. | AY5: 1 | AZ5: Менеджер прямо сообщила, что отправит памятку по подготовке к термину. О канале отправки сказано, что 'в любом случае напишет в WhatsApp', что подразумевает отправку памятки тоже этим каналом. | BA5: [00:06:11.014] – Продавец – Я вам отправлю на всякий случай памятку, подготовку к терминам., [00:10:42.268] – Продавец – Еще в WhatsApp обязательно. | BB5: 1 | BC5: Менеджер объяснила, что в памятке: список типичных фраз, логика ответов берайтеру, типичные ловушки, правильная стратегия ответов — что поможет подготовиться к встрече. | BD5: [00:06:14.098] – Продавец – Это такой костыль. От слова идет на уровень простыми фразами, но тут главное понять логику, как и что отвечать берайтеру, в каком варианте ответ, соответственно, на немецком языке., [00:06:25.000] – Продавец – Там есть фразы типичные ловушки от берайтера, правильная стратегия ответов. | BE5: 1 | BF5: Менеджер сообщила о тренажёре и разъяснила его назначение — для отработки ответов от имени берайтера, аналог бота-тренажёра. | BG5: [00:08:14.641] – Продавец – И также отправлю вам этот пятичат-бот. Он задает вопросы от имени берайтера и сможете проговорить как раз-таки ответы. | BH5: Тегов нет | BI5: В течение разговора клиент проявлял ряд опасений и сомнений, среди которых: Страх отказа в финансировании (финансы семьи, смена статуса), Сомнение в курсе (нет опыта бухгалтера), Недостаточная подготовка (уровень немецкого, практика). | BJ5: [00:01:43.289] – Клиент – Я надеюсь на то, что это уже будет в новой земле, правильно понимаю?, [00:03:44.349] – Клиент – Скажут ли мне сейчас, что, фрау, не многовато ли обучения?, [00:07:46.310] – Клиент – И если сумма подходит под программу, то одобрение, случайно, возможно?, [00:11:33.852] – Клиент – Не пожалею ли я, что я без опыта вообще макнулась в это дело, и мне не хватит просто понимания процессов, не то что языка. | BK5: 1 | BL5: Менеджер корректно реагировала на озвученные опасения (финансы, опыт, подготовка): подробно объясняла процесс, снижала волнение и поддерживала клиента. | BM5: [00:05:56.915] – Продавец – Я вам... Ну, ранее вы проходили... А как давно проходили на лучшей?, [00:08:37.990] – Продавец – И то, что вы добились уже сейчас хороших результатов, это только ваша заслуга, ваше стремление и желание., [00:12:35.609] – Продавец – Здесь с нуля спокойно обучаются, потому что материалы программы охватывают. ... Тут разберется любой. | BN5: 1 | BO5: Клиент задавала комплексные вопросы по поводу процесса финансирования, формальностей, курса бухгалтерии и необходимости опыта. Менеджер дала исчерпывающие и понятные ответы на все вопросы. | BP5: [00:01:50.659] – Клиент – Я надеюсь на то, что это уже будет в новой земле, правильно понимаю? — [00:01:50.659] – Продавец – Да, это будет уже в новой земле., [00:11:16.004] – Клиент – У меня 17 лет было свое частное предприятие...., [00:12:15.515] – Клиент – Это я поняла, это с нуля материал? — [00:12:19.302] – Продавец – Да. | BQ5: 1 | BR5: Менеджер согласовала следующий контакт на 15 или 16 число, с объяснением даты и цели контакта (подготовка к встрече с берайтером и уточнение деталей после консультации с другом супруга, бывшим сотрудником Jobcenter). | BS5: [00:09:48.614] – Продавец – Он ранее тоже работал в джоб-центре и подготовит вас к встрече с берайтером в агентуре Фарбайки., [00:10:08.057] – Продавец – Или даже давайте в воскресенье, 15-го числа. Будет еще лучше. | BT5: 1 | BU5: Менеджер указала, что будет на связи с клиентом на всём этапе до термина и что коллега напишет в WhatsApp, создавая ощущение открытого взаимодействия. | BV5: [00:00:47.034] – Продавец – И я буду с вами на связи до самого дня термина., [00:10:37.379] – Продавец – Она вам в любом случае напишет в WhatsApp. | BW5: 0 | BX5: Менеджер не уточнила в явной форме, стало ли клиенту понятнее и увереннее после разговора, не задала вопрос о текущем состоянии клиента после консультации. | BZ5: 1 | CA5: Менеджер объясняла про дальнейший процесс (например, получения документов после прохождения термина), а также консультирование с коллегой после прохождения. | CB5: [00:09:19.746] – Продавец – Также хотелось бы поговорить важный момент, если термин в джоб-центре пройдет успешно, ваши документы также придут., [00:09:25.316] – Продавец – У вас будет в агентуре термин или в джоб-центре? | CC5: 0 | CD5: Менеджер не объяснила, что делать в случае отказа в финансировании и как себя вести при неудаче с берайтером. | CF5: 1 | CG5: Менеджер указала, что после консультации с другом будет следующий контакт (разбор с ведущим специалистом до и после термина), создав иллюзию постоянного сопровождения. | CH5: [00:10:31.368] – Продавец – Она вам в любом случае напишет в WhatsApp., [00:11:02.604] – Продавец – У нас уже будет полная картина, как действовать дальше. | CI5: 1 | CJ5: Менеджер неоднократно обращалась к клиенту по имени, использовала вежливые слова (спасибо, пожалуйста, поздравляю, хорошо), вела разговор искренне, доброжелательно, с поддержкой и похвалой (даже с самооценочной поддержкой), имела позитивный тон. | CK5: [00:00:26.469] – Продавец – Хорошо, поздравляю вас с ремонтом., [00:08:29.199] – Продавец – Он будет у меня хороший, господи, этот уровень языка., [00:08:59.115] – Продавец – Ты с ума сошла, надо себя хвалить. | CL5: 1 | CM5: Менеджер многократно показывала, что слушает и понимает клиента, перефразировала вопросы, поддерживала прямой диалог (например, по финансовому статусу, смене статуса, вопросам экзамена). Темп был живым, много реплик поддержки и перефразирования. | CN5: [00:01:50.659] – Продавец – Да, это будет уже в новой земле., [00:05:07.636] – Продавец – Вижу, что вам нужно еще сдать на права., [00:12:01.216] – Продавец – Ваш вопрос. Хочу отметить, что мы не готовим теоретиков... | CO5: 1 | CP5: Ни одной критической ошибки, вредной для компании, не зафиксировано. Диалог вёлся уважительно, следующие шаги зафиксированы, не было введения в заблуждение, отказа от клиента или некорректного обсуждения лицензий/процессов. | CR5: 1 | CS5: В разговоре не было ни грубости, ни дезинформации, ни агрессии. Информация про курс соответствовала действительности, никакой ложной или опасной информации не прозвучало. | CU5: 1 | CV5: Менеджер не давала ложных обещаний (например, гарантии трудоустройства), не разглашала внутреннюю конфиденциальную информацию, не вводила в заблуждение относительно AZAV/сертификата и в целом соблюдала допустимые рамки коммуникации. | CX5: 1 | CY5: А) Продавец начал с приветствия, представления и поздравления клиента, далее уточнил удобство разговора, объяснил цель диалога. Затем последовательно обсуждался статус клиента (экзамены, новый берайтер, смена земли), далее проговаривались детали финансирования, возможных сложностей, затем был дан обзор формата встречи с берайтером и курса, отправка памятки, договорённость о следующем контакте. Б) Особенность: продавец много слушал, адаптировался под клиента, приводил конкретные советы. В) У клиента появился интерес, он задал ряд вопросов, открылся и делился деталями ситуации. Г) Клиент не ушёл в сомнение, но не было финального вопроса по уверенности/готовности. | CZ5: [00:00:04.334] – Продавец – Здравствуйте, меня зовут Кристина, я менеджер сопровождения компании Штернмастер., [00:06:11.014] – Продавец – Я вам отправлю на всякий случай памятку, подготовку к терминам., [00:10:08.057] – Продавец – Или даже давайте в воскресенье, 15-го числа. | DA5: 1 | DB5: Разговор завершился позитивно, клиент согласилась на дальнейший контакт (дата обсуждена), материалы согласованы. Продавец корректно довёл до фиксации следующего шага. | DC5: [00:10:31.368] – Продавец – Она вам в любом случае напишет в WhatsApp., [00:14:13.961] – Продавец – Ну, хорошо, вам удачного, доброго дня. | DD5: Резюме | DE5: А) Темы звонка: приветствие, поздравление с термином, обсуждение текущей ситуации (экзамены, переезд, смена статуса), детали финансирования, обсуждение возможных сложностей, объяснение формата встречи с берайтером, отправка памятки, обсуждение курса и этапов, договорённость о следующем контакте. Б) Реакция клиента: заинтересованная, иногда озабоченная (финансы, статус), охотно делилась деталями и задавала вопросы, проявляла интерес к курсу, но также открыто обсуждала страхи и неопределённость. В) Зафиксировано: отправка памятки и тренажёра, обсуждение даты следующего созвона (15-16 числа), согласие на продолжение диалога, обмен контактами. | DG5: Рекомендация | DH5: 1. Не уточнено прямо эмоциональное состояние/уровень понятности после консультации. Лучше спросить: 'Анна, стало ли вам спокойнее после разговора? Всё ли теперь понятно про встречу с берайтером?' — Это снизит тревожность и повысит доверие. 2. Не озвучены шаги на случай отказа берайтера в финансировании. Рекомендация: 'Если вдруг получите отказ, обязательно узнаете причину и дайте знать нам, мы поможем подготовить обоснование.' — Это уменьшает страх отказа. 3. Можно было бы чуть подробнее дать вводный обзор по формату курса и преимуществам именно Sternmeister, чтобы усилить мотивацию и УТП. Пример: 'Наш курс выделяется тем, что...'. Ожидаемый эффект — рост уверенности и доверия клиента на старте. | DJ5: Рекомендация | DK5: 1. Поддержка и похвала клиента — 'И то, что вы добились уже сейчас хороших результатов, это только ваша заслуга...' — укрепляет доверие и позитивное отношение, массовая техника. 2. Персонализированный подход с учётом индивидуальных сложностей клиента (семья, статус, экзамены) — пример адаптации под клиента, индивидуальная техника. 3. Чёткость и структурность в доведении до следующего шага — фиксация даты следующего контакта и открытый канал в WhatsApp. Это массовая практика управления ожиданиями. | DM5: Рекомендация | DN5: А) Психологический и демографический портрет: Женщина, имя Анна, переехала в Германию, недавно вышла замуж, опыт работы воспитателем и предпринимателем, ответственный и тревожный стиль принятия решений, склонна к сомнениям (страх отказа, недостаточная подготовка), проявляет инициативу в уточнениях ('А мне Оля сейчас выслала'). Б) Цели: интеграция в немецкий рынок, смена профессии ('Я, в принципе, не бухгалтер...'), получение финансирования, уверенность в будущем ('Я шла по этому пути, потому что пыталась остаться в Мангелисте'). Переживает о фин. критериях, статусе в джоб-центре. В) Для маркетинга: важно подчеркивать поддержку на всех этапах, пошаговую структуру курса, простоту материала, возможность стартовать с нуля, организацию сопровождения по смене статуса. Для таких клиентов нужны подробные инструкции, список типовых ошибок и частые контакты. Каналы: WhatsApp, email, много практики в курсе, реальные кейсы. | DP5: 1 | DQ5: Разговор завершился естественно, участники попрощались, диалог был полноразмерным, технических сбоев не было. | DR5: [00:14:13.961] – Продавец – Ну, хорошо, вам удачного, доброго дня., [00:14:18.894] – Клиент – До свидания. | DS5: 1 | DT5: Это первый контакт сопровождения — менеджер поздравила с термином, обозначила себя как куратора до дня встречи, впервые подробно рассказала о формате термина, отправила памятку и договорилась о подготовке. Нет тематики промежуточной или финального контакта. | DU5: [00:00:09.021] – Продавец – Поздравляю вас с назначенным термином., [00:00:47.034] – Продавец – И я буду с вами на связи до самого дня термина., [00:06:11.014] – Продавец – Я вам отправлю на всякий случай памятку, подготовку к терминам., [00:10:08.057] – Продавец – Или даже давайте в воскресенье, 15-го числа. | DV5: =IFERROR(SUM(AC5,AF5)/COUNT(AC5,AF5),"Приветствие") -> Приветствие | DW5: =IFERROR(SUM(AI5,AL5)/COUNT(AI5,AL5),"Снятие первичного волнения") -> Снятие первичного волнения | DX5: =IFERROR(SUM(AO5,AR5,AU5)/COUNT(AO5,AR5,AU5),"Презентация предстоящего термина") -> Презентация предстоящего термина | DY5: =IFERROR(SUM(AX5,BA5,BD5)/COUNT(AX5,BA5,BD5),"Отправка материалов") -> Отправка материалов | DZ5: =IFERROR(SUM(BG5,BJ5,BM5)/COUNT(BG5,BJ5,BM5),"Вопросы и возражения Клиента") -> Вопросы и возражения Клиента | EA5: =IFERROR(SUM(BP5,BS5)/COUNT(BP5,BS5),"Следующие шаги") -> Следующие шаги | EB5: =IFERROR(SUM(BV5,BY5,CB5,CE5)/COUNT(BV5,BY5,CB5,CE5),"Завершение разговора") -> Завершение разговора | EC5: =IFERROR(SUM(CH5,CK5)/COUNT(CH5,CK5),"Стандарты общения") -> Стандарты общения | ED5: =IFERROR(SUM(CN5,CQ5,CT5)/COUNT(CN5,CQ5,CT5),"Критические ошибки") -> Критические ошибки | EE5: =IFERROR(SUM(#REF!,#REF!)/COUNT(#REF!,#REF!),"Экспертный блок") -> Экспертный блок | EF5: =IFERROR(SUM(#REF!,#REF!,#REF!,#REF!)/COUNT(#REF!,#REF!,#REF!,#REF!),"Рекомендации") -> Рекомендации | EG5: =IFERROR(SUM(#REF!,#REF!)/COUNT(#REF!,#REF!),"Фильтры") -> Фильтры | EH5: 0.88888889 | EI5: 0.8125 | EJ5: 14.3604 | EK5: 1 | EL5: 1 | EM5: {=IFERROR( SUM(IF({AD5,AG5,AJ5,AM5,AP5,AS5,AV5,AY5,BB5,BE5,BK5,BN5,BQ5,BT5,BW5,BZ5,CC5,CF5,CI5,CL5}="",hidden!C5,{AD5,AG5,AJ5,AM5,AP5,AS5,AV5,AY5,BB5,BE5,BK5,BN5,BQ5,BT5,BW5,BZ5,CC5,CF5,CI5,CL5}+hidden!D5)) / COUNT(IF({AD5,AG5,AJ5,AM5,AP5,AS5,AV5,AY5,BB5,BE5,BK5,BN5,BQ5,BT5,BW5,BZ5,CC5,CF5,CI5,CL5}="",hidden!C5,{AD5,AG5,AJ5,AM5,AP5,AS5,AV5,AY5,BB5,BE5,BK5,BN5,BQ5,BT5,BW5,BZ5,CC5,CF5,CI5,CL5}+hidden!D5)) ,"")} -> 0.85 | EN5: =I5/hidden!A2 -> 14.3604
A6: 6 | B6: 195004316_1886502851_12674b | C6: https://docs.google.com/document/d/1adfg6MlGj-9lwxy_xZLs48LqHhmSJ6UqTSaTOt1q4V4/edit?usp=drivesdk | D6: 2026-03-02 - 2026-03-08 | E6: 54814 | F6: 2026-03-11 16:44:20 | G6: 2026-03-11 16:53:55 | H6: 2026.03 | I6: 506.952 | J6: 1 | K6: 2026-03-03 | L6: 507 | M6: 195004316_1886502851 | N6: +380507739471, Статус: Разговор состоялся | O6: CallGear | P6: 14:38:09+01:00 | Q6: Исходящий | R6: 11 | S6: 19433123 | T6: Olesya Berkovska | U6: Контакт | V6: 2026-03-03T14:01:16+01:00 | W6: 18249004 | X6: Автосделка: Lead from: https://sternmeister.de/education?utm_source=google&utm_medium=cpc&utm_campaign=cid|23273193589|aid|&utm_content=gid||phr||dvc|m|pos||mch||src||reg|9196572|rin|9196572|kw|&gclid=Cj0KCQiAubrJBhCbARIsAHIdxD8vtzdEXU3hVVAcpaEBVFn7H9avFB | Y6: Бух Бератер | Z6: Принято от первой линии | AA6: https://sternmeister.kommo.com/leads/detail/18249004 | AB6: 14817967 | AC6: Кристина Никоненко | AD6: 1 | AE6: Менеджер корректно поприветствовала Клиента, представилась и назвала компанию. Приветствие было формальным, и с самого начала прозвучала чёткая идентификация личности и компании. Для улучшения — стоит добавить уточнение имени Клиента (если оно известно). | AF6: [00:00:04.50] – Продавец – Здравствуйте. Меня зовут Кристина, я менеджер отдела сопровождения компании Штернмастер. | AG6: 1 | AH6: Менеджер сразу обозначила цель звонка (помощь в подготовке к термину) и примерную длительность (10 минут), а также уточнила, удобно ли сейчас говорить. Всё сделано корректно. | AI6: [00:00:13.96] – Продавец – Подскажите, пожалуйста, есть ли у вас буквально 10 минут для того, чтобы мы с вами обсудили наши дальнейшие с вами шаги? | AJ6: 1 | AK6: Менеджер прямо уточнила эмоциональное состояние Клиента перед предстоящим термином, спросила о возможном волнении. | AL6: [00:00:33.49] – Продавец – Подскажите, пожалуйста, есть ли у вас сейчас волнение по поводу предстоящего термина? | AM6: 1 | AN6: Клиент сообщил о спокойствии, что всё хорошо. Продавец отреагировала позитивно, поддержала и отметила, что это хороший настрой, тем самым усилив уверенность Клиента. | AO6: [00:00:39.02] – Клиент – Нет, нет, наоборот, спокойно, что все документы хорошо, что все в порядке., [00:00:44.13] – Продавец – Отлично, это хороший настрой. | AP6: 1 | AQ6: Менеджер объяснила, кто такой дирайтер (бератер) и какова цель встречи – проверка, насколько выбранный курс повышения квалификации поможет выйти на рынок труда. | AR6: [00:00:53.00] – Продавец – Дирайтер – это ваш консультант в Jobcenter, и его задача убедиться, что выбранный вами курс повышения квалификации действительно поможет вам выйти на рынок труда. | AS6: 1 | AT6: Менеджер привела примеры типичных вопросов дирайтера: про мотивацию, опыт, содержание курса, длительность, планы работы, уровень языка и пояснила цель этих вопросов. | AU6: [00:01:09.20] – Продавец – Типичные вопросы, которые задают бирайтеры: почему выбрали именно бухгалтерию, знаете ли вы содержание самого курса, что там в нем находится, сколько он длится, где планируете работать после обучения, какой у вас уровень языка. | AV6: 1 | AW6: Менеджер пояснила, что встреча – не экзамен, дирайтер не ставит оценок за язык и главное — мотивация. Успокоила Клиента, что достаточно говорить простыми фразами. | AX6: [00:01:30.01] – Продавец – Тут хочу сразу сказать, важно понимать, бирайтер – это не экзаменатор, и он не ставит вам оценок, тем более за язык., [00:01:44.09] – Продавец – Главное – говорить четко, пусть даже простыми фразами. | AY6: 1 | AZ6: Менеджер сообщила, что отправит памятку «Подготовка к термину» и уточнила у Клиента удобный канал отправки, остановились на e-mail. | BA6: [00:01:54.13] – Продавец – Первый этап – это самостоятельная часть, и я вам сейчас отправлю информацию., [00:01:59.09] – Продавец – Подготовка к термину называется, вам лучше на WhatsApp или отправить на e-mail?, [00:02:07.66] – Клиент – Может, давайте на e-mail., [00:02:09.37] – Продавец – Хорошо, давайте на e-mail. | BB6: 1 | BC6: Менеджер подробно объяснила содержание памятки: 19 часто задаваемых вопросов с вариантами ответов, транскрипции, перевод, фразы-помощники и типичные ловушки. Чётко раскрыта польза. | BD6: [00:02:16.66] – Продавец – В нем собраны 19 самых частых вопросов от бирайтера с готовыми вариантами ответов на немецком языке, транскрипцией и переводом на русский язык, чтобы вы могли на немецком языке к ним подготовиться., [00:02:32.10] – Продавец – Это фразы, которые помогут вам, если вы не поняли вопрос с дирайтером или вам нужно время подумать., [00:02:44.14] – Продавец – Там написаны каверзные вопросы, которые дирайтер иногда задает, и правильная должна быть стратегия ответа. | BE6: 1 | BF6: Менеджер сообщила, что отправит тренажёр для тренировки перед термином (eBoot), и объяснила его назначение, чтобы Клиент смог потренироваться отвечать на вопросы бератера. | BG6: [00:03:17.71] – Продавец – И еще я бы хотела вам отправить разработанный в нашей компании тренажер, чтобы вы могли более уверенно чувствовать себя на предстоящем терминe., [00:03:25.69] – Продавец – Это eBoot, который выступает в роли самого бирайтера, задает вопросы, почему вы выбрали этот курс, и вы можете прямо по памятке ему отвечать. | BH6: Тегов нет. | BI6: Клиент не высказывал прямых возражений, страхов или сомнений по поводу программы, терминов, курса или процесса. Высказывания были преимущественно позитивные и уверенные. | BJ6: [00:00:39.02] – Клиент – Нет, нет, наоборот, спокойно, что все документы хорошо, что все в порядке., [00:03:49.89] – Клиент – Ну, я думаю, должна помочь, но в любом случае будем стараться, подготовимся, потому что мы сами заинтересованы, во-первых, и поучиться, это нам, и отсрочка, что нас не дергает бирайтер, и мы учимся, и мы получаем реально какую-то диплома, то есть это, ну, мы только за, мы наоборот хотим получить бонусы с этого. | BL6: Возражения или явные сомнения Клиент не озвучивал, соответственно рассмотрение отработки не требуется. | BO6: Клиент не задавал прямых вопросов, а лишь соглашался, предлагал варианты коммуникации и высказывал согласие на предложенные действия. | BP6: [00:02:03.02] – Клиент – Может, так и так, может., [00:02:07.66] – Клиент – Может, давайте на e-mail. | BQ6: 1 | BR6: Менеджер озвучила конкретный следующий контакт (созвон 9 числа, после обеда) для обсуждения возможных вопросов по материалам и подготовке к термину. | BS6: [00:04:19.79] – Продавец – Также подскажите, пожалуйста, если, к примеру, я с вами 9-го числа свяжусь... и сможем с вами их обсудить 9-го числа. Как вам такой вариант?, [00:04:53.76] – Клиент – Да, хорошо, набирайте, все это набирайте, да., [00:04:59.90] – Клиент – Ну, давайте после обеда, желательно после обеда., [00:05:06.55] – Продавец – Хорошо, после обеда тогда с вами свяжусь я. | BT6: 1 | BU6: Менеджер в финале звонка сообщила, что всегда на связи и, если возникнут вопросы, Клиент может писать в чат. | BV6: [00:08:17.68] – Продавец – Если есть вопросы, пишите в чат, я с вами на связи. | BW6: 1 | BX6: Менеджер в явной форме спросила, стало ли Клиенту понятнее, чего ждать на термине, и как он себя чувствует после разговора. | BY6: [00:05:28.26] – Продавец – Скажите, пожалуйста, как вы себя чувствуете после нашего разговора? Стало ли вам более понятно, чего ждать на самом термине? | BZ6: 1 | CA6: Менеджер подробно объяснила дальнейшие шаги после успешного термина: передача документов в агентство Arbeit, назначение нового термина, важность оперативности. | CB6: [00:05:56.92] – Продавец – Если термин в Jobcenter пройдет успешно, ваши документы должны передать в агентство Fur Arbeitet. Агентство вам об этом скажет на своем термине. Далее они назначают уже новый термин. И важно попросить делать это как можно быстрее, чтобы не пропустить начало потока. Они идут всегда навстречу. Здесь можете не переживать. Главное, это не забыть сообщить. | CC6: 1 | CD6: Менеджер объяснила, что при отказе важно выяснить причину решения сразу во время термина и получить рекомендации для будущей попытки (возможность апелляции). | CE6: [00:06:48.79] – Продавец – И также, если по каким-либо причинам дирайтер не одобрит финансирование нашего курса обучения, во время термина нужно сразу выяснить причину и спросить, как он видит ваше развитие и чему, по его мнению, вам не хватает, чтобы получить финансирование. Более четкое понимание того, что вам нужно делать дальше. | CF6: 1 | CG6: Менеджер не только зафиксировала повторный контакт до термина, но и описала дальнейшее сопровождение, включая информирование о помощи с апелляцией, если потребуется. Ожидается дальнейшая поддержка. | CH6: [00:06:48.79] – Продавец – И также, если по каким-либо причинам дирайтер не одобрит финансирование нашего курса обучения... Более четкое понимание того, что вам нужно делать дальше. Ну и в целом, да, если… Также это нам поможет подать на апелляцию в дальнейшем. | CI6: 1 | CJ6: Весь диалог построен очень доброжелательно, с вежливой инициативой, использованием "пожалуйста", "благодарю вас", "добрый день" и отсутствием любой негативной интонации. Обращения по имени не было из-за отсутствия этой информации. Открытый, поддерживающий, позитивный стиль сохранялся. | CK6: [00:00:13.96] – Продавец – Подскажите, пожалуйста, есть ли у вас буквально 10 минут для того, чтобы мы с вами обсудили наши дальнейшие с вами шаги?, [00:00:22.35] – Продавец – Благодарю вас., [00:08:13.86] – Продавец – Хорошо, тогда, да, доброго дня вам. | CL6: 1 | CM6: Продавец слушал Клиента, реагировал на его слова подтверждением, делал мини-рефреймы (подчеркивал позитивное отношение к учебе и мотивацию). В общении есть "согласна", "отлично", "это хороший настрой" – признаки активного слушания. | CN6: [00:00:44.13] – Продавец – Отлично, это хороший настрой., [00:04:12.21] – Продавец – Ну, я тут согласна, уже хочется выйти, да, что-то новое для себя открыть в этой жизни, новую профессию тоже получить. | CO6: 1 | CP6: Критических ошибок не зафиксировано: Продавец не говорил негативно о компании или продукте, не отговаривал, не вводил в заблуждение по процессам и сертификату. Следующий контакт закреплён чётко (дата, время), намерение работать с клиентом подтверждено. | CQ6: [00:04:19.79] – Продавец – Также подскажите, пожалуйста, если, к примеру, я с вами 9-го числа свяжусь..., [00:04:53.76] – Клиент – Да, хорошо, набирайте, все это набирайте, да., [00:05:06.55] – Продавец – Хорошо, после обеда тогда с вами свяжусь я. | CR6: 1 | CS6: Не выявлено недостоверной информации о курсе, лицензии или сертификате. Все ответы уважительны и соответствуют реальности. Не было грубости, перебиваний или недальновидных формулировок. Ошибки, нарушающие доверие или желания продолжать, отсутствуют. | CT6: [00:02:16.66] – Продавец – В нем собраны 19 самых частых вопросов от бирайтера с готовыми вариантами ответов на немецком языке..., [00:03:49.89] – Клиент – Ну, я думаю, должна помочь, но в любом случае будем стараться, подготовимся, потому что мы сами заинтересованы... | CU6: 1 | CV6: Не было сообщений, нарушающих законодательство или презентующих запрещённые гарантии. Не поднимались вопросы официальных ограничений по лицензии, не было упоминаний внутренних документов, нарушений сохранности данных/обещаний трудоустройства и т. д. | CW6: [00:03:17.71] – Продавец – И еще я бы хотела вам отправить разработанный в нашей компании тренажер, чтобы вы могли более уверенно чувствовать себя на предстоящем терминe. | CX6: 1 | CY6: А) Скрипт: Приветствие, представление, поздравление с достижением этапа. Запрограммировала формат разговора, цель и длительность. Сразу подключила мотивацию и атмосферу поддержки. Уточнила эмоциональное состояние. Далее — объяснение, кто такой дирайтер, каких вопросов ждать (с конкретикой). Успокоила по поводу языка/мотивации. Дальше — переход к памятке и материалам, обсуждение способов отправки (email). Подробное объяснение памятки и тренажёра. Проговорила режим работы с материалами, обозначила второй этап подготовки. Зафиксировала следующий контакт с датой и временем. Обсудила дальнейший процесс после термина. Финал — открытый канал связи и поддержка. Б) Особенности: Очень структурированный, понятный темп, много поддерживающих фраз, отсутствует продажа по необходимости дополнительной записи онлайн — обсуждается подготовка к уже назначенному термину. В) Сработало: Клиент открылся, с готовностью шёл на контакт, поддерживал позитивную линию, согласился с датой следующего созвона. Г) Не было: Клиент не давал возражений, иногда был не очень инициативен, вопросы не задавал. | CZ6: [00:00:04.50] – Продавец – Здравствуйте. Меня зовут Кристина... | DA6: 1 | DB6: А) Звонок завершился позитивно: Клиент согласился на следующий контакт 9-го числа после обеда, не выражал сомнений или возражений. Б) Клиент сказал: «Да, хорошо, набирайте», «Хорошо, хорошо, договорились. Спасибо.» В) Продавец четко договорился о времени, подтвердил этапы, поддержал доброжелательный финал. Г) Для усиления можно было добавить вопрос о том, удобно ли Клиенту подготовить конкретные вопросы к следующему звонку (ещё больше раскрыть потребности). | DC6: [00:04:53.76] – Клиент – Да, хорошо, набирайте, все это набирайте, да., [00:08:10.76] – Клиент – Хорошо, хорошо, договорились. Спасибо. | DD6: Резюме | DE6: А) Продавец поприветствовала, представилась и поздравила, что назначен термин. Объяснила суть и формат термина с дирайтером, расписала тип вопросов, успокоила по поводу требований, акцентировала мотивацию. Предложила памятку и тренажёр, подробно рассказала о структуре и материалах. Описала дальнейшие этапы после термина и что делать при отказе. Закончила договорённостью о следующем звонке (конкретная дата и время). Б) Клиент реагировал позитивно, без тревожности или возражений, был в целом заинтересован и мотивирован. В) Достигнута договорённость о повторном созвоне 9 числа после обеда, клиент готовился к собеседованию и ждал материалов. | DF6: [00:04:19.79] – Продавец – Также подскажите, пожалуйста, если, к примеру, я с вами 9-го числа свяжусь... | DG6: Рекомендация | DH6: 1. Не прозвучало обращение по имени клиента. Контекст: Продавец использует только формальное обращение. Следовало бы хотя бы один раз уточнить имя и обращаться лично — это бы усилило персонализацию и доверие. Ожидаемый эффект: Повышение вовлечённости и лояльности. 2. Недостаточно сильный дожим по выявлению индивидуальных интересов. Продавец не уточнил, чего конкретно больше всего опасается или ожидает клиент. Следовало: «А что для вас самое важное на этом курсе/термине?», «Есть ли что-то, что вызывает беспокойство?» Ожидаемый эффект: Глубже раскрыть настоящие мотивы и потенциальные боли клиента. 3. Не проговорены дополнительные УТП курса (например, про карьерный центр, формат сертификации). Следовало: «После курса вам доступен карьерный центр», «Сертификат оформляется по гос. стандарту». Ожидаемый эффект: Укрепить ценность предложения и конкурентные преимущества. 4. Нет формулировки срочности (почему важно не затягивать с обучением или стартом). Следовало: «Потоков не так много, лучше не тянуть, чтобы не потерять место.» Ожидаемый эффект: Повышает вероятность активации клиента к действию. | DJ6: Рекомендация | DK6: 1. Поддержка и нормализация (массовая техника). Фраза: «Это хороший настрой», «Главное говорить четко, пусть даже простыми фразами». Сняло лишнее волнение, дало чувство уверенности. Почему это сработало: уменьшает тревожность, поддерживает позитивную атмосферу. 2. Подробное описание памятки и тренажёра (массовая техника). Вовлекает клиента в процесс подготовки и даёт инструментарий, а не только сухую инструкцию. Суть: «В памятке 19 самых частых вопросов…» и «еBoot выступает в роли бирайтера». Почему сработало: клиент понял, что получит реальные инструменты, повысится шанс усвоения материала. 3. Привязка к следующему звонку с уточнением времени (массовая техника). Суть: «9-го числа, после обеда, я вам наберу, и мы сможем обсудить вопросы…» Почему сработало: снимает страх, что клиент останется один с материалом, и закрепляет контакт. | DM6: Рекомендация | DN6: А) Клиент спокоен, конструктивен, открыт, инициативу проявляет в пределах диалога («может на e-mail», «после обеда»). Волнений или страхов не декларирует, готов учиться. Пол, возраст и имя в явном виде не сообщались. Поведенчески – готов к взаимодействию, проявляет доверие, но не очень разговорчив. Б) Приоритеты: получение новой профессии и отложение давления по поиску работы («мы хотим получить бонусы с этого»), ценит упорядоченность процесса, нацелен на официальный диплом. Цели: повысить профессиональную квалификацию, перейти на новый этап в жизни. В) Формулировки: хорошо сработают сообщения о том, что программа помогает выйти на рынок труда, сертификат официального образца (вайтербилдунг/абшлусццертификат). Для сегмента значимы гарантированная поддержка, материалы для подготовки, индивидуальные разъяснения. УТП: карьерный центр, поддержка после выпуска, помощь с документами, тренажёры, кураторы. Можно масштабировать на других клиентов с похожей мотивацией и уровнем доверия. | DO6: [00:03:49.89] – Клиент – Ну, я думаю, должна помочь, но в любом случае будем стараться, подготовимся, потому что мы сами заинтересованы... , [00:04:12.21] – Продавец – Ну, я тут согласна, уже хочется выйти, да, что-то новое для себя открыть в этой жизни, новую профессию тоже получить. | DP6: 1 | DQ6: Разговор завершился логично и полно, участники попрощались, диалог дошёл до естественного завершения без технических сбоев. | DR6: [00:08:21.82] – Клиент – Хорошо, да, спасибо., [00:08:23.56] – Продавец – До свидания. | DS6: 1 | DT6: Разговор полностью соответствует первому контакту: менеджер поздравляет с назначением термина, объясняет цель контакта и структуру термина, впервые отправляет памятку и тренажёр, фиксирует следующий шаг для подготовки. Признаки второго или финального контакта отсутствуют. | DU6: [00:00:10.05] – Продавец – Мне хотелось бы поздравить вас с назначенным термином., [00:00:23.37] – Продавец – Я буду с вами на связи до самого дня термина, и моя задача помочь вам подготовиться..., [00:01:54.13] – Продавец – Первый этап – это самостоятельная часть, и я вам сейчас отправлю информацию., [00:04:19.79] – Продавец – Также подскажите, пожалуйста, если, к примеру, я с вами 9-го числа свяжусь... | DV6: =IFERROR(SUM(AC6,AF6)/COUNT(AC6,AF6),"Приветствие") -> Приветствие | DW6: =IFERROR(SUM(AI6,AL6)/COUNT(AI6,AL6),"Снятие первичного волнения") -> Снятие первичного волнения | DX6: =IFERROR(SUM(AO6,AR6,AU6)/COUNT(AO6,AR6,AU6),"Презентация предстоящего термина") -> Презентация предстоящего термина | DY6: =IFERROR(SUM(AX6,BA6,BD6)/COUNT(AX6,BA6,BD6),"Отправка материалов") -> Отправка материалов | DZ6: =IFERROR(SUM(BG6,BJ6,BM6)/COUNT(BG6,BJ6,BM6),"Вопросы и возражения Клиента") -> Вопросы и возражения Клиента | EA6: =IFERROR(SUM(BP6,BS6)/COUNT(BP6,BS6),"Следующие шаги") -> Следующие шаги | EB6: =IFERROR(SUM(BV6,BY6,CB6,CE6)/COUNT(BV6,BY6,CB6,CE6),"Завершение разговора") -> Завершение разговора | EC6: =IFERROR(SUM(CH6,CK6)/COUNT(CH6,CK6),"Стандарты общения") -> Стандарты общения | ED6: =IFERROR(SUM(CN6,CQ6,CT6)/COUNT(CN6,CQ6,CT6),"Критические ошибки") -> Критические ошибки | EE6: =IFERROR(SUM(#REF!,#REF!)/COUNT(#REF!,#REF!),"Экспертный блок") -> Экспертный блок | EF6: =IFERROR(SUM(#REF!,#REF!,#REF!,#REF!)/COUNT(#REF!,#REF!,#REF!,#REF!),"Рекомендации") -> Рекомендации | EG6: =IFERROR(SUM(#REF!,#REF!)/COUNT(#REF!,#REF!),"Фильтры") -> Фильтры | EH6: 1 | EI6: 1 | EJ6: 8.4492 | EK6: 1 | EL6: 1 | EM6: {=IFERROR( SUM(IF({AD6,AG6,AJ6,AM6,AP6,AS6,AV6,AY6,BB6,BE6,BK6,BN6,BQ6,BT6,BW6,BZ6,CC6,CF6,CI6,CL6}="",hidden!C6,{AD6,AG6,AJ6,AM6,AP6,AS6,AV6,AY6,BB6,BE6,BK6,BN6,BQ6,BT6,BW6,BZ6,CC6,CF6,CI6,CL6}+hidden!D6)) / COUNT(IF({AD6,AG6,AJ6,AM6,AP6,AS6,AV6,AY6,BB6,BE6,BK6,BN6,BQ6,BT6,BW6,BZ6,CC6,CF6,CI6,CL6}="",hidden!C6,{AD6,AG6,AJ6,AM6,AP6,AS6,AV6,AY6,BB6,BE6,BK6,BN6,BQ6,BT6,BW6,BZ6,CC6,CF6,CI6,CL6}+hidden!D6)) ,"")} -> 1 | EN6: =I6/hidden!A6 -> 8.4492
A7: 7 | B7: 171984639_1888209517_364bf8 | C7: https://docs.google.com/document/d/1qFCXTgDKSfibGkkl_gAAiS4N5bTV4XTOVhPnR-rv72Q/edit?usp=drivesdk | D7: 2026-03-09 - 2026-03-15 | E7: 54907 | F7: 2026-03-11 18:55:05 | G7: 2026-03-11 19:03:02 | H7: 2026.03 | I7: 707.4 | J7: 1 | K7: 2026-03-10 | L7: 707 | M7: 171984639_1888209517 | N7: +380637167878, Статус: Разговор состоялся | O7: CallGear | P7: 14:54:18+01:00 | Q7: Исходящий | R7: 11 | S7: 20845698 | T7: Anastasiia Bykovets | U7: Контакт | V7: 2026-02-17T17:52:19+01:00 | W7: 18038794 | X7: Lead from: https://sternmeister.de/education#rec999749301 | Y7: Бух Бератер | Z7: Доведение | AA7: https://sternmeister.kommo.com/leads/detail/18038794 | AB7: 14817967 | AC7: Кристина Никоненко | AD7: 0 | AE7: Менеджер поздоровался с клиентом, но не назвал компанию SternMeister/Штернмейстер либо её производные, и сначала назвал другое имя. Представление было: 'Анастасия, добрый день, здравствуйте.' Затем 'Прошу прощения... Представлюсь, меня зовут Кристина.' — компании не было названо ни в начале, ни далее. Для полного соответствия стандарту необходимо чётко представиться и назвать компанию. | AF7: [00:00:00.03] – Продавец – Анастасия, добрый день, здравствуйте., [00:00:18.75] – Продавец – Да, еще раз прошу прощения. Представлюсь, меня зовут Кристина. | AG7: 1 | AH7: Менеджер обозначила цель звонка (обсуждение дальнейших шагов перед термином), озвучила примерную длительность ('буквально 5-10 минут') и спросила про возможность поговорить — что эквивалентно уточнению удобства разговора. Можно формулировать ещё точнее, но по факту стандарт выполнен. | AI7: [00:00:08.51] – Продавец – Подскажите, пожалуйста, будет у вас буквально 5-10 минут, для того, чтобы мы обсудили дальнейшие шаги перед термином? | AJ7: 1 | AK7: Менеджер прямо поинтересовалась боязнью/волнением клиента: 'Подскажите, пожалуйста, Анастасия, есть ли у вас какие-то волнения по поводу предстоящего термина? Опасения, возможно?' — формулировка полностью соответствует критерию. | AL7: [00:00:23.57] – Продавец – Подскажите, пожалуйста, Анастасия, есть ли у вас какие-то волнения по поводу предстоящего термина? Опасения, возможно? | AM7: 1 | AN7: Клиент озвучила опасения, что не оплатят ('Есть опасения одно, что просто не оплатят.'). Менеджер поддержала, нормализовала переживания: 'То, что цена вопроса волнует, я вас поняла. Это абсолютно нормально. Практически все наши студенты переживали перед первым термином. Но я хочу вас успокоить, мы готовим людей к таким встречам каждый день. У нас накоплен огромный опыт, мы будем с вами на протяжении всего этого процесса, то есть вы не будете одна, это очень важно.' — соответствие критерию по всем пунктам. | AO7: [00:00:32.26] – Клиент – Опасения есть одно, что просто не оплатят., [00:00:45.21] – Продавец – То, что цена вопроса волнует, я вас поняла. Это абсолютно нормально. Практически все наши студенты переживали перед первым термином. Но я хочу вас успокоить, ... мы будем с вами на протяжении всего этого процесса, то есть вы не будете одна, это очень важно. | AP7: 1 | AQ7: Менеджер структурно объяснила, кто такой бератер и что происходит на встрече: 'Его задача – это убедиться, что выбранный вами курс повышения квалификации действительно поможет вам выйти на рынок труда. То есть финальная точка после завершения курса – это будет трудоустройство. Он будет задавать вопросы о вашей мотивации, о вашем опыте, о самом курсе будет тоже вопросы задавать.' Стандарт выполнен. | AR7: [00:03:44.28] – Продавец – ...Расскажу, как проходит встреча с бирайтером по данному вопросу. Его задача – это убедиться, что выбранный вами курс повышения квалификации действительно поможет вам выйти на рынок труда... | AS7: 1 | AT7: Менеджер перечислила конкретные типовые вопросы: 'почему выбрали именно бухгалтерию, знаете ли вы содержание курса, сколько он длится, где планируете работать после обучения, то есть для них еще и картина будущего очень важна'. Объяснила, что бератер задает это для проверки мотивации и осознанности выбора. | AU7: [00:04:06.22] – Продавец – Типичные вопросы, которые задают бирайтеры: почему выбрали именно бухгалтерию, знаете ли вы содержание курса, сколько он длится, где планируете работать после обучения, то есть для них еще и картина будущего очень важна. | AV7: 1 | AW7: Менеджер прямо указала, что бератер не экзаменатор, объяснила логичность процесса, подчеркнула несложность требований: 'Здесь важно понимать, что бирайтер – это не экзаменатор, он не будет вам ставить оценки за немецкий, он хочет увидеть ваши мотивации и осознанный выбор.' — всё сделано правильно. | AX7: [00:04:26.30] – Продавец – Здесь важно понимать, что бирайтер – это не экзаменатор, он не будет вам ставить оценки за немецкий, он хочет увидеть ваши мотивации и осознанный выбор. | AY7: 1 | AZ7: Менеджер сообщила о памятке и назвала канал отправки: 'Я прямо сейчас отправлю вам в WhatsApp нашу специальную памятку “Подготовка к термину”.' — все требования соблюдены. | BA7: [00:04:38.89] – Продавец – Я прямо сейчас отправлю вам в WhatsApp нашу специальную памятку «Подготовка к термину». | BB7: 1 | BC7: Содержание памятки раскрыто подробно: 'В нем собрано 19 самых частых вопросов бирайтера с готовыми вариантами ответов на немецком языке, транскрипции, переводом на русский. Также там есть фразы-спасатели, типичные ловушки бирайтера, важный раздел...' и далее про структуру и пользу памятки. | BD7: [00:04:44.70] – Продавец – Это такой скелет... В нем собрано 19 самых частых вопросов бирайтера с готовыми вариантами ответов на немецком языке, транскрипции, переводом на русский. Также там есть фразы-спасатели, типичные ловушки бирайтера, важный раздел... | BE7: 1 | BF7: Менеджер сообщила, что отправит тренажер: 'Также дополнительно направлю вам в WhatsApp разработанный нашей компанией тренажер, чтобы вы могли уверенно чувствовать себя на предстоящем термине. Это и бот: он открывается в браузере, задает вопросы от лица бирайтера. Можно будет потренировать ответы.' Описание соответствует. | BG7: [00:05:46.05] – Продавец – Также дополнительно направлю вам в WhatsApp разработанный нашей компанией тренажер, чтобы вы могли уверенно чувствовать себя на предстоящем термине. Это и бот: он открывается в браузере, задает вопросы от лица бирайтера. Можно будет потренировать ответы. | BH7: Тегов нет | BI7: Возражения/сомнения клиента: 'Опасения есть одно, что просто не оплатят.' — Страх отказа в финансировании. 'Потому что это стоит дорого.' — Недостаточная подготовка к тому, что сумму могут не одобрить. 'Я не уверена, что мне его будут подплачивать еще раз здесь.' — Страх отказа, сомнения в процедуре. 'Я не чувствую себя настолько уверенной, чтобы я могла пойти сдать какие-то экзамены.' — Низкий уровень уверенности, возможно, страх перед сложностью экзаменов/термина. | BJ7: [00:00:32.26] – Клиент – Опасения есть одно, что просто не оплатят., [00:00:41.56] – Клиент – Потому что это стоит дорого., [00:01:37.89] – Клиент – Просто как бы у меня есть уже высшее экономическое образование, поэтому я не уверена, что мне его будут подплачивать еще раз здесь., [00:03:16.19] – Клиент – Я, хоть имею экономическое образование и сейчас учусь как бы на ЦАИС, но все равно я не чувствую себя настолько уверенной, чтобы я могла пойти сдать какие-то экзамены. | BK7: 1 | BL7: Менеджер внимательно отработал сомнения: пояснил механизм финансирования, поддержал нормализацию переживаний по стоимости, прояснил вопросы по типу курса и различию с другими вариантами (аусбилдинг), заверил в поддержке и предоставил подготовочные материалы. Это снижает тревожность клиента. | BM7: [00:00:45.21] – Продавец – То, что цена вопроса волнует, я вас поняла. Это абсолютно нормально... мы будем с вами на протяжении всего этого процесса, то есть вы не будете одна, это очень важно., [00:01:56.44] – Продавец – Обычно сумма за 30 тысяч, что уходит в аусбилдинг, это кто получает полностью на 3 года обучения... если образование в Германии никак не могут подтвердить, то тоже могут аусбилдинг одобрить., [00:04:44.28] – Продавец – В памятке ... фразы-спасатели, ... стратегия ответа. Там максимально простыми фразами написано, как осваивать... | BN7: 1 | BO7: Клиент уточняла: 'А как думаете, с чем оно может быть связано?' (см. по поводу риска не одобрения), 'То есть тысячи людей получают... я все понимаю, просто есть знакомый...' – про суммы и подтверждение образования. Менеджер отвечал по существу, разъяснял разницу между типами финансирования (аусбилдинг), описал логику бератера. Все вопросы клиента обработаны полностью. | BP7: [00:00:36.31] – Продавец – Я вас поняла. А как думаете, с чем оно может быть связано?, [00:01:47.78] – Продавец – Добрый ли, скорее всего, аусбилдинг вашим знакомым, верно?, [00:02:56.44] – Продавец – Обычно сумма за 30 тысяч, ... | BQ7: 1 | BR7: Следующий контакт обозначен и зафиксирован: 'Подскажите, пожалуйста, могу с вами связаться 13 числа, удобное для вас время, для того, чтобы ответить на ваши вопросы, если таковые появятся, и также обсудить с вами материалы, которые я вам сейчас отправлю?... В одиннадцать-двенадцать, хорошо.' — всё по стандарту. | BS7: [00:06:02.29] – Продавец – Подскажите, пожалуйста, могу с вами связаться 13 числа, удобное для вас время, для того, чтобы ответить на ваши вопросы, если таковые появятся, и также обсудить с вами материалы, которые я вам сейчас отправлю?, [00:06:42.09] – Продавец – В одиннадцать-двенадцать, хорошо. | BT7: 0 | BU7: Менеджер сообщил о следующих шагах и отправке материалов, но прямо не озвучил, что всегда можно обращаться, писать, звонить с возникающими вопросами. Лучше уточнять этот момент явно, особенно для тревожных клиентов. | BV7: [00:06:02.29] – Продавец – ...могу с вами связаться 13 числа... чтобы ответить на ваши вопросы, если таковые появятся... (косвенное упоминание, прямого предложения обращаться по мере необходимости не было) | BW7: 1 | BX7: Менеджер явно задал вопрос: 'Также, скажите, пожалуйста, как вы себя чувствуете после нашего разговора? Стало ли вам более понятно, чего ждать на термине? Появилось ли больше уверенности?' — пункт строго соблюден. | BY7: [00:06:42.09] – Продавец – Также, скажите, пожалуйста, как вы себя чувствуете после нашего разговора? Стало ли вам более понятно, чего ждать на термине? Появилось ли больше уверенности? | BZ7: 1 | CA7: Менеджер объяснил следующие шаги: 'Если термин в Jobcenter пройдет успешно, ваши документы должны передать в агентство проработки. Бирайтер вам об этом скажет. Далее они назначают новый термин, и важно попросить сделать его как можно быстрее, чтобы не пропустить начало потока.' — по стандарту. | CB7: [00:07:08.20] – Продавец – Если термин в Jobcenter пройдет успешно... ваши документы должны передать в агентство проработки... Далее они назначают новый термин, и важно попросить сделать его как можно быстрее, чтобы не пропустить начало потока. | CC7: 1 | CD7: Менеджер прямо объяснил: 'Если по каким-то причинам бирайтер не одобрит финансирование нашего курса обучения, во время термина нужно сразу выяснить причину и спросить, как он видит ваше дальнейшее развитие и чего, по его мнению, вам не хватает, чтобы получить финансирование.' — пункт выполнен полностью. | CE7: [00:09:21.40] – Продавец – Также важный момент. Если по каким-то причинам бирайтер не одобрит финансирование нашего курса обучения, во время термина нужно сразу выяснить причину и спросить, как он видит ваше дальнейшее развитие и чего, по его мнению, вам не хватает, чтобы получить финансирование. | CF7: 0 | CG7: В явной форме менеджер не сказал, что свяжется с клиентом после термина для обсуждения дальнейших действий. В разговоре озвучен лишь следующий контакт до термина, далее — нет. | CH7: [00:11:16.48] – Продавец – Хорошо, тогда с вами уже с 13-го числа и там обсудим наши дальнейшие шаги в подготовке. | CI7: 1 | CJ7: Менеджер 3 раза обратился по имени ('Анастасия'), использовал вежливые обращения ('пожалуйста', 'прошу прощения'), не перебивал, проявлял сочувствие и понимание ('я вас поняла'), тон — мягкий, доброжелательный. Клиент был немного тревожен, продавец подстраивался и сохранял спокойствие. | CK7: [00:00:00.03] – Продавец – Анастасия, добрый день, здравствуйте., [00:00:05.16] – Продавец – Прошу прощения..., [00:06:42.09] – Продавец – Также, скажите, пожалуйста, как вы себя чувствуете после нашего разговора? | CL7: 1 | CM7: Менеджер реагировал на опасения клиента ('Я вас поняла', 'То, что цена вопроса волнует, я вас поняла...'), уточнял детали, подстраивался под стиль клиента, перефразировал про её опыт и сомнения, давал обратную связь: | CN7: [00:00:45.21] – Продавец – То, что цена вопроса волнует, я вас поняла. Это абсолютно нормально., [00:01:56.44] – Продавец – Обычно сумма за 30 тысяч, что уходит в аусбилдинг, это кто получает полностью на 3 года обучения., [00:03:44.28] – Продавец – Ну, сам факт того, что вы не уверены, что после них сможете закончить это обучение и поступить на работу, верно? | CO7: 1 | CP7: Критических ошибок не выявлено: продавец не давал негативных оценок курсу, не отговаривал клиента, не сливал без закрепления следующих шагов, не дезинформировал по лицензиям или сертификатам, закрепил следующий шаг. | CQ7: [00:06:42.09] – Продавец – В одиннадцать-двенадцать, хорошо. | CR7: 1 | CS7: Ошибок по этому критерию нет. Вся информация, которую дал продавец, соответствует реальному статусу курса, обсуждение было уважительным, грубости или давления не было. | CT7: [00:00:45.21] – Продавец – То, что цена вопроса волнует, я вас поняла. Это абсолютно нормально. | CU7: 1 | CV7: Юридических рисков или запретных обещаний не было. Информация о лицензии, процессе и сертификатах соответствовала допустимому уровню раскрытия. Никакой внутренней информации или лишних гарантий не озвучено. | CW7: [00:00:45.21] – Продавец – ...стоимость программы утверждается самим государством, и она полностью покрывается. Если бы программа не соответствовала стандартам, она бы просто не получила адаптацию от ЗАФа, от ДЭФа. | CX7: 1 | CY7: А) Скрипт: 1) Приветствие, извинение за задержку, краткое представление (без упоминания компании). 2) Запрос времени для разговора и объяснение цели ('обсудить дальнейшие шаги перед термином'). 3) Вопрос о волнении/опасениях, выявление главного страха — не оплатят. 4) Развернутая поддержка, нормализация чувств, объяснение государственного регламента стоимости. 5) Уточнение кейса клиента (аусбилдинг/образование). 6) Объяснение роли бератера и формата встречи. 7) Перечень типовых вопросов от бератера, пояснение, что бератер — не экзаменатор. 8) Обещание памятки и тренажёра, объяснение их пользы. 9) Подтверждение следующего шага/созвона. 10) Проверка, стало ли спокойнее. 11) Перечень дальнейших шагов после термина. 12) Инструкция на случай отказа. 13) Разбор организационных моментов (ангебот, даты потоков и т.д.). 14) Финальное согласование времени следующего контакта. Б) Особенности: продавец мягко поясняет процесс, не форсирует принятие решения, даёт ключевую инфо заранее, работает на снижение тревоги. В) Работает: шаги с объяснением (структура процесса), предоставление памятки, договоренность о следующем звонке — клиент не прерывает диалог, соглашается на повторный контакт. Г) Не сработал эмоциональный дожим — клиент остался тревожен и на завершающем этапе подтвердил неуверенность ('я ни в чем сейчас не уверена'). Техника эмоционального утепления требует усиления. Рекомендация — усилить финальный мотивирующий аргумент, активнее вытаскивать плюсы персонально для клиента. | CZ7: [00:00:08.51] – Продавец – Подскажите, пожалуйста, будет у вас буквально 5-10 минут, для того, чтобы мы обсудили дальнейшие шаги перед термином?, [00:00:23.57] – Продавец – есть ли у вас какие-то волнения по поводу предстоящего термина?..., [00:04:44.28] – Продавец – ...я прямо сейчас отправлю вам в WhatsApp нашу специальную памятку..., [00:06:02.29] – Продавец – ...могу с вами связаться 13 числа..., [00:06:42.09] – Продавец – Также, скажите, пожалуйста, как вы себя чувствуете после нашего разговора? | DA7: 0 | DB7: А) Разговор завершился фиксацией следующего шага, но клиент прямо сказал: 'Если честно, я ни в чем сейчас не уверена. Когда мне утвердят обучение или скажут, может, искать что-то другое, тогда, в принципе, будет что-то понятно, а пока ничего не понятно.' Б) Клиент ушёл в неопределённость, сомневается. В) Продавец не сделал финального вдохновляющего или мотивирующего дожима, не поддержал аргументами персонально для этой ситуации (либо не подчеркнул персональные плюсы). Г) Техникой, способной переписать ситуацию, было бы детальное разбор заведомо самой вероятной причины отказа и предложение решений ('Давайте подумаем, какой вариант вам подойдет, если согласуют минимальное финансирование...'). | DC7: [00:06:55.53] – Клиент – Если честно, я ни в чем сейчас не уверена. Когда мне утвердят обучение или скажут, может, искать что-то другое, тогда, в принципе, будет что-то понятно, а пока ничего не понятно. | DD7: Резюме | DE7: А) Темы: представление, выявление тревоги клиента, обсуждение страха не получить финансирование, объяснение формата встречи с бератером, типовые вопросы, рассылка памятки и тренажера, узнавании дополнительной информации о курсе, обозначение следующего шага и организационные вопросы по текущим курсам клиента. Б) Реакция: клиент тревожен, местами нейтрален, не проявляет явного позитивного энтузиазма, фиксирует сомнения; реагирует на поддержку, но не вдохновляется. В) Договорённости: следующая встреча согласована на 13 число, 11-12 часов дня; обозначено, что продавец отправит материалы. Финальный интерес — средний, готовность к следующему контакту 'ок', но уверенности у клиента не появилось, уровень тревоги остаётся высоким. | DF7: — | DG7: Рекомендация | DH7: 1. Не назвал компанию при представлении. Фраза: 'Анастасия, добрый день, здравствуйте.' (Не указано — компания SternMeister, ни на старте, ни далее.) Важно чётко вводить бренд, чтобы у клиента не было сомнений, с кем идёт диалог. Лучший вариант: 'Анастасия, добрый день, компания Штернмейстер, меня зовут Кристина.' Ожидаемый эффект — повышение доверия и узнаваемости. — 2. Не проговорил клиенту возможность обращаться с вопросами между контактами. Фраза (отсутствует): Менеджер не заверил, что всегда на связи, не пригласил обратиться любым вопросом или тревогой вне плана-звонка. Нужно добавить: 'Если появятся вопросы до нашего следующего созвона, смело пишите или звоните, я всегда на связи.' Эффект — снижение тревоги, повышение доверия. — 3. Не сделал дожим/мотивационный итог. Клиент прямо сказал, что не уверен ('я ни в чем не уверена...'), менеджер лишь 'понял', но не развернул вдохновляющий или мотивирующий финал ('Для вас открыта реальная возможность... вы сможете...'). Следовало сказать: 'Вы уже сделали многое, а ваш опыт и уровень языка — ваша сильная сторона! Мы поддержим вас на каждом этапе.' Эффект — усиление эмоционального контакта и уверенности клиента. | DI7: — | DJ7: Рекомендация | DK7: 1. Массовая техника — Снятие тревоги через нормализацию: 'То, что цена вопроса волнует, я вас поняла. Это абсолютно нормально. Практически все наши студенты переживали перед первым термином.' — Снижает тревогу клиента, передаёт опыт других. — 2. Массовая техника — Детализация процесса и типовых вопросов: 'Типичные вопросы, которые задают бирайтеры: почему выбрали именно бухгалтерию...' — снимает лишние опасения, увеличивает ощущение контроля, формирует доверие и предсказуемость. — 3. Массовая техника — Обещание памятки и тренажёра: 'Я прямо сейчас отправлю вам в WhatsApp нашу специальную памятку “Подготовка к термину”.' — Предоставление конкретного, материального ресурса для подготовки повышает уверенность и воспринимаемую пользу. | DL7: — | DM7: Рекомендация | DN7: А) Психологический и демографический портрет: Клиент — женщина, Анастасия, настроена рационально, но тревожна, склонна к самоанализу и сомнениям. Имеет опыт высшего образования (экономика), дополнительно учится (ЦАИН/ЦАИС), рассуждает о знакомых и альтернативных вариантах (сравнивает суммы, примеры других). Открывает свои страхи (не оплатят, не утвердят, не справится с экзаменами). Диалог ведёт подробно, отвечает полно, но не проявляет инициативы решения проблем. — Б) Цели и приоритеты: получить финансирование на курс, повысить квалификацию для успешного выхода на рынок труда в Германии, избежать избыточных трат и неудачных шагов (страх зря потратить время и деньги, остаться с неподтвержденной квалификацией). Ищет гарантии, подтверждения возможностей. — В) Доп. характеристики: клиенту требуется больше эмоциональной поддержки и разъяснений. Для маркетинга — акцент на гос. поддержку, гарантии соответствия стандартам, простоту собеседования, помощь на всех этапах, наличие подготовительных инструментов и кейсов. Важно объяснять структурно и чётко: что делать, если возникнет отказ, обязательно упоминать персональную поддержку и возможность обращения. | DO7: [00:00:32.26] – Клиент – Опасения есть одно, что просто не оплатят., [00:01:37.89] – Клиент – Просто как бы у меня есть уже высшее экономическое образование, поэтому я не уверена, что мне его будут подплачивать еще раз здесь., [00:06:55.53] – Клиент – Если честно, я ни в чем сейчас не уверена. | DP7: 1 | DQ7: Разговор завершён логично: участники попрощались, менеджер пожелал хорошего дня, клиент поблагодарил, пауза/сбоя не было. | DR7: [00:11:40.58] – Продавец – Доброго дня вам., [00:11:41.94] – Клиент – Да, спасибо., [00:11:45.16] – Клиент – До свидания. | DS7: 1 | DT7: Звонок — первый контакт сопровождения: впервые рассказывается, как проходит встреча с бератером, озвучивается цель как подготовка к термину, отправляются памятка и тренажёр, согласовывается повторный контакт перед термином, нет признаков промежуточного/финального созвона. | DU7: [00:00:08.51] – Продавец – ...обсудили дальнейшие шаги перед термином, [00:04:38.89] – Продавец – ...отправлю вам в WhatsApp нашу специальную памятку «Подготовка к термину», [00:06:02.29] – Продавец – ...могу с вами связаться 13 числа, ... и также обсудить с вами материалы, которые я вам сейчас отправлю? | DV7: =IFERROR(SUM(AC7,AF7)/COUNT(AC7,AF7),"Приветствие") -> Приветствие | DW7: =IFERROR(SUM(AI7,AL7)/COUNT(AI7,AL7),"Снятие первичного волнения") -> Снятие первичного волнения | DX7: =IFERROR(SUM(AO7,AR7,AU7)/COUNT(AO7,AR7,AU7),"Презентация предстоящего термина") -> Презентация предстоящего термина | DY7: =IFERROR(SUM(AX7,BA7,BD7)/COUNT(AX7,BA7,BD7),"Отправка материалов") -> Отправка материалов | DZ7: =IFERROR(SUM(BG7,BJ7,BM7)/COUNT(BG7,BJ7,BM7),"Вопросы и возражения Клиента") -> Вопросы и возражения Клиента | EA7: =IFERROR(SUM(BP7,BS7)/COUNT(BP7,BS7),"Следующие шаги") -> Следующие шаги | EB7: =IFERROR(SUM(BV7,BY7,CB7,CE7)/COUNT(BV7,BY7,CB7,CE7),"Завершение разговора") -> Завершение разговора | EC7: =IFERROR(SUM(CH7,CK7)/COUNT(CH7,CK7),"Стандарты общения") -> Стандарты общения | ED7: =IFERROR(SUM(CN7,CQ7,CT7)/COUNT(CN7,CQ7,CT7),"Критические ошибки") -> Критические ошибки | EE7: =IFERROR(SUM(#REF!,#REF!)/COUNT(#REF!,#REF!),"Экспертный блок") -> Экспертный блок | EF7: =IFERROR(SUM(#REF!,#REF!,#REF!,#REF!)/COUNT(#REF!,#REF!,#REF!,#REF!),"Рекомендации") -> Рекомендации | EG7: =IFERROR(SUM(#REF!,#REF!)/COUNT(#REF!,#REF!),"Фильтры") -> Фильтры | EH7: 0.85185185 | EI7: 0.8125 | EJ7: 11.79 | EK7: 0.5 | EL7: 0.5 | EM7: {=IFERROR( SUM(IF({AD7,AG7,AJ7,AM7,AP7,AS7,AV7,AY7,BB7,BE7,BK7,BN7,BQ7,BT7,BW7,BZ7,CC7,CF7,CI7,CL7}="",hidden!C7,{AD7,AG7,AJ7,AM7,AP7,AS7,AV7,AY7,BB7,BE7,BK7,BN7,BQ7,BT7,BW7,BZ7,CC7,CF7,CI7,CL7}+hidden!D7)) / COUNT(IF({AD7,AG7,AJ7,AM7,AP7,AS7,AV7,AY7,BB7,BE7,BK7,BN7,BQ7,BT7,BW7,BZ7,CC7,CF7,CI7,CL7}="",hidden!C7,{AD7,AG7,AJ7,AM7,AP7,AS7,AV7,AY7,BB7,BE7,BK7,BN7,BQ7,BT7,BW7,BZ7,CC7,CF7,CI7,CL7}+hidden!D7)) ,"")} -> 0.85 | EN7: =I7/hidden!A7 -> 11.79
A8: 8 | B8: 172234134_1889009273_ef4caf | C8: https://docs.google.com/document/d/19Irkze2C4eC_1MAQSJCB_LAL3RYM0OFiSGgI4PWiTqQ/edit?usp=drivesdk | D8: 2026-03-09 - 2026-03-15 | E8: 59502 | F8: 2026-03-13 23:26:30 | G8: 2026-03-13 23:33:27 | H8: 2026.03 | I8: 728.496 | J8: 1 | K8: 2026-03-13 | L8: 729 | M8: 172234134_1889009273 | N8: +4915118621381, Статус: Разговор состоялся | O8: CallGear | P8: 17:14:03+01:00 | Q8: Исходящий | R8: 11 | S8: 21133414 | T8: Valentyna Sedikova | U8: Контакт | V8: 2026-03-13T17:01:13+01:00 | W8: 18415142 | X8: Автосделка: Заявка - https://sternmeister.de/new_black | Y8: Бух Бератер | Z8: Принято от первой линии | AA8: https://sternmeister.kommo.com/leads/detail/18415142 | AB8: 14817967 | AC8: Кристина Никоненко | AD8: 1 | AE8: Менеджер поприветствовал Клиента, представился по имени и озвучил компанию Sternmeister, что соответствует критериям оценки. Рекомендации: Сохранять четкое и структурное приветствие в каждом звонке. | AF8: [00:00:00.031] – Продавец – Алло, алло. Добрый вечер, здравствуйте. Меня зовут Кристина, я менеджер сопровождения компании Шторммастер. | AG8: 1 | AH8: Менеджер обозначил цель звонка (помочь подготовиться к термину, сопровождать до дня термина), уточнил длительность разговора (буквально 10 минут), но прямо не спросил, удобно ли говорить. Однако клиент добровольно подтвердил готовность к разговору, что частично компенсирует недочёт. Рекомендуется всегда прямо спрашивать о времени для разговора. | AI8: [00:00:22.520] – Продавец – И моя задача, как раз-таки, помочь вам подготовить, соответственно, все вопросы, сделать так, чтобы пришли на встречу с Бирайтером спокойно, уверенно, соответственно. Скажите, пожалуйста, будет у вас буквально 10 минут, чтобы мы обсудили дальнейшие шаги перед самим термином? [00:00:45.223] – Клиент – Да, конечно. | AJ8: 1 | AK8: Менеджер прямо задал вопрос о самочувствии/волнении перед предстоящим термином. Рекомендация: Продолжать такой подход. | AL8: [00:01:01.521] – Продавец – Подскажите, пожалуйста, в целом, как себя чувствуете, есть ли волнения по поводу предстоящего термина? | AM8: 1 | AN8: Менеджер выразила поддержку, сказала что хороший настрой, похвалила клиента и нормализовала переживания («Я уверена, что так и будет», «я уже не волнуюсь», «перестаньте, какой у вас возраст?», «голос молодой и бодрый»). Рекомендация: Всегда находить слова поддержки. | AO8: [00:00:22.520] – Продавец – Я уверена, что так и будет ... [00:01:22.870] – Продавец – Отлично, хороший настрой. [00:01:33.331] – Продавец – У вас достаточно молодой и бодрый голос. В возрасте речи вообще никакой не должно быть. | AP8: 1 | AQ8: Менеджер достаточно подробно описал роль бератера и цель встречи. Объяснила, что бератер — консультант в соццентре, его задача — убедиться в мотивации и целесообразности курса, конечная цель — трудоустройство. | AR8: [00:01:41.989] – Продавец – Давайте я вам расскажу кратко, как обычно проходит с Бирайтером. Бирайтер – это ваш консультант в соццентре. Его задача, главное, это убедиться, что выбранный вами курс повышения квалификации действительно поможет вам выйти на рынок. То есть финальная точка – это трудоустройство. | AS8: 1 | AT8: Менеджер озвучил целый перечень типичных вопросов, которые могут прозвучать на встрече: почему выбрали курс, знаете ли о содержании, длительность обучения, кем работать после курса, уровень немецкого, самочувствие. Объяснила, что это стандартные вопросы. | AU8: [00:01:41.989] – Продавец – И типичные вопросы, которые часто спрашивают, это: почему выбрали именно бухгалтерию, знаете ли вы содержание курса, сколько он длится, где планируете работать после обучения, какой вы сейчас уровень немецкого языка, как себя ощущаете. И все это стандартные вопросы, к которым нам нужно будет с вами подготовиться. | AV8: 1 | AW8: Менеджер объяснила, что бератер не экзаменатор, важно донести мотивацию, даже если немецкий не высокий — это нормально. Предложена поддержка и снятие излишних опасений. | AX8: [00:02:49.169] – Продавец – Здесь важно понимать, что Бирайтер это не экзаменатор, он не ставит вам оценок за немецкий язык, он хочет именно увидеть вашу мотивацию и осознанный выбор. Даже если ваш немецкий не на уровне, да, там, C1, да, это нормально. Главное говорить верно, четко, и пусть даже... | AY8: 1 | AZ8: Менеджер сказала, что отправит памятку для подготовки и указала, что почта будет отправлена (канал — почта и, возможно, WhatsApp). | BA8: [00:02:49.169] – Продавец – И чтобы мы могли с вами начать уже сегодня готовиться, я вам отправлю такой скелет на памятку. ... [00:11:20.938] – Продавец – У вас есть, да? Вот я хочу… Сейчас буквально проверю, чтобы там точно она была. Ага, почты вашей у меня нет. Если будет удобно написать в WhatsApp почту, я вам прямо на почту всё отправлю. | BB8: 1 | BC8: Менеджер подробно объяснила, что будет в памятке: 19 типовых вопросов, готовые варианты ответов, фразы-спасатели, типичные ловушки бератера, стратегия ответов. Отдельно подчеркнула, в чём польза (повторить ключевые фразы и понять логику). | BD8: [00:02:49.169] – Продавец – Здесь очень важно именно, что в документе содержится 19 самых частых вопросов Бирайтера с готовыми вариантами ответа на немецком. Также есть фразы-спасатели, если, допустим, заполнить пустоту. Типичные ловушки Бирайтера, там описаны каверзные вопросы и очень важно, что там описана хорошая стратегия ответа на этот каверзный вопрос. … самое главное, это понять логику ответов и несколько раз просто проговорить ключевые фразы вслух. | BE8: 1 | BF8: Менеджер сказала, что отправит ссылку на тренажёр — бота для практики стандартных вопросов бератера. Чётко описала назначение способ практики. | BG8: [00:02:49.169] – Продавец – А также я вам еще дополнительно направлю, поскольку уровень у вас хороший, разработанный нашей компанией тренажер, сейчас бот, он открывается в браузере и задаёт вопросы от имени Бирайтера. То есть вы, соответственно, с ним можете проговорить для того, чтобы вы могли себя уверенно чувствовать на протяжении всего времени, пока будете на термине. | BH8: Тегов нет | BI8: Клиент не озвучивал явных возражений или страхов. Было легкое сомнение по поводу возраста и возможного отказа, но открытых возражений, страха перед термином или курса нет. | BJ8: [00:00:14.950] – Клиент – Ну, я надеюсь, я надеюсь, что мне дадут, Кристина. [00:09:31.269] – Клиент – Ну, она намекает мне прям, намекнула. | BL8: Явные возражения или сомнения не озвучивались, так что оценка неприменима — менеджер не игнорировал сомнения, но и не было тревоги у клиента. | BN8: 1 | BO8: Клиент спрашивал о деталях даты встречи, процессе оформления, Ангиботе, и Менеджер ответил развернуто и по существу на каждый вопрос. | BP8: [00:00:45.223] – Клиент – Да, конечно. Подскажите, пожалуйста, как только это будет 23-го рано утром, скорее всего, тогда это мы, наверное, в пятницу уже… Потому что 23-е, мне кажется, это понедельник. [00:01:01.521] – Продавец – Да, да, да, все верно, 23-е понедельник, и в пятницу обязательно созвонимся... [00:07:35.524] – Клиент – Термин встречи? ... [00:07:46.387] – Клиент – Она мне сказала, что есть вот такая и такая. Я говорю, я не знаю, на какую вы успеете. [00:07:54.778] – Продавец – Ага, хорошо. Тогда будем отталкиваться уже от Джоб-центра... | BQ8: 1 | BR8: Менеджер озвучила дату следующего контакта (18-го числа), подтверждение регулярной связи и обозначение целей (дальнейшая подготовка к термину). | BS8: [00:04:11.378] – Продавец – Хорошо, тогда 18-го числа с вами свяжусь, если у вас какие-то будут вопросы. Будем с вами. | BT8: 1 | BU8: Менеджер сообщила, что можно обращаться при возникновении любых вопросов до дня термина, открыла канал связи через WhatsApp. | BV8: [00:11:38.878] – Продавец – И если у вас вопросы какие-то вдруг появятся, не откроется памятка по термину, что-то не работает, нужна какая-то дополнительная информация, обязательно пишите в WhatsApp. Я с вами до дня термина по всем вопросам отвечу, помогу, сориентирую вас. | BW8: 1 | BX8: Менеджер прямо поинтересовалась о том, стало ли Клиенту понятнее, чего ожидать на термине, и как он себя чувствует после разговора. | BY8: [00:04:11.378] – Продавец – ...Так же подскажите, пожалуйста, как всё чувствуете после нашего разговора? Стало ли вам более понятно, чего ждать на предстоящем термине? | BZ8: 1 | CA8: Менеджер объяснила, что после успешного термина в Jobcenter документы передаются в Agentur für Arbeit, где будет новая встреча. Уточнила важность быстрого получения новой даты. | CB8: [00:06:28.019] – Продавец – В Джоб-центре. Отлично. Также у вас в целом хороший шанс на получение финансирования. ...если термин в Джоб-центре пройдет успешно, ваши документы должны передать к агентам бюро Арбайта, Бирайтер вам об этом скажет. Далее, они выдают вам новый термин уже туда, и важно попросить это сделать как можно быстрее, чтобы не пропустить начало потока. | CC8: 1 | CD8: Менеджер разъяснил, что нужно делать в случае отказа — выяснить причину отказа, узнать мнение бератера, что требуется для получения финансирования. | CE8: [00:09:06.625] – Продавец – И если вдруг, если вдруг у вас идет отказ… ну такой, ну да, не знаю, да, мало ли. Если по каким-то причинам Бирайтер не одобрит финансирование нашего курса во время термина, нужно выяснить причину и спросить, как он видит ваше дальнейшее развитие и чего, по его мнению, вам не хватает после финансирования. | CF8: 1 | CG8: Менеджер упомянула о постоянном сопровождении Клиента как в период до термина, так и после, обещала реагировать на все вопросы. Однако фразы про отдельный контакт после термина нет — подразумевается постоянное сопровождение. | CH8: [00:11:38.878] – Продавец – Я с вами до дня термина по всем вопросам отвечу, помогу, сориентирую вас. | CI8: 1 | CJ8: Стиль общения мягкий, доброжелательный, местами неформальный (поддержка, похвала возраста, юмор), менеджер использует «пожалуйста», «спасибо», обращается уважительно и тепло. Имя клиента не называлось, но в остальном все признаки вежливости и доброжелательности налицо. | CK8: [00:00:00.031] – Продавец – Добрый вечер, здравствуйте... [00:01:33.331] – Продавец – У вас достаточно молодой и бодрый голос... [00:11:55.341] – Клиент – Хорошо, спасибо, я вам отправлю сейчас почту. [00:12:00.751] – Продавец – Спасибо, спасибо большое. До свидания. | CL8: 1 | CM8: Менеджер слушает внимательно, подчеркивает важные мысли Клиента, реагирует на рассказы, подхватывает реплики (про возраст, опыт работы, переезд); поддерживает диалог, а не монолог. | CN8: [00:01:22.870] – Продавец – Отлично, хороший настрой... [00:01:33.331] – Продавец – У вас достаточно молодой и бодрый голос... [00:05:52.526] – Продавец – То, что у вас энергии много, это факт, что вы готовы работать... | CO8: 1 | CP8: В разговоре нет негативных фраз о компании или курсе, продавец не отговаривал клиента, не допускал дезинформации по сертификату/AZAV и процессам, завершил разговор фиксацией следующего шага (созвон 18-го) и поддержкой. | CQ8: [00:04:11.378] – Продавец – Хорошо, тогда 18-го числа с вами свяжусь, если у вас какие-то будут вопросы. | CR8: 1 | CS8: Вся информация, представленная продавцом, корректна и соответствует действительности; нет искажений, грубости или давления. Стиль уважительный, ответы ясны. | CT8: [00:00:00.031] – Продавец – Меня зовут Кристина, я менеджер сопровождения компании Шторммастер... [00:02:49.169] – Продавец – ...главное говорить верно, четко, ...я вам отправлю такой скелет на памятку. | CU8: 1 | CV8: В разговоре не прозвучало юридически опасных обещаний, разглашений или некорректных формулировок. Менеджер не обещал гарантии трудоустройства, не делал ложных заявлений о лицензии/сертификатах. | CW8: [00:02:49.169] – Продавец – ...это не экзаменатор, он не ставит вам оценок за немецкий язык, он хочет именно увидеть вашу мотивацию и осознанный выбор. | CX8: 1 | CY8: А) Скрипт: Продавец начал с приветствия, знакомства и поздравления с термином, формулировал цель звонка, далее уточнил волнение и настрой, объяснил формат встречи с бератером, подробно перечислил типовые вопросы, снял страх/поддержал, сообщил о памятке и тренажёре, подробно описал содержание памятки, задал вопросы о процессе (Ангибот, даты), зафиксировал следующий контакт и открыл канал связи. Б) Особенность: Скрипт детальный и последовательный, перекрыт всеми ключевыми блоками, пропусков нет. В) Важные этапы: Клиент проявил интерес при обсуждении сопутствующих вопросов и мотивации. Г) Нет провалов: Клиент не уходил в сомнение, не замолчал, вопросов было мало — все раскрыты. | CZ8: [00:00:00.031] – Продавец – Алло, алло. Добрый вечер, здравствуйте... [00:01:21.076] – Клиент – Абсолютно нет... [00:01:41.989] – Продавец – Давайте я вам расскажу кратко, как обычно проходит с Бирайтером... [00:02:49.169] – Продавец – ...я вам отправлю такой скелет на памятку... | DA8: 1 | DB8: А) Разговор завершён договорённостью о следующем шаге (контакт 18-го числа), Клиент дал согласие и проявил готовность. Отказов и сомнений не было. Б) На этапе закрытия — взаимное подтверждение действий по памятке, договор о связи. В) Продавец закрыл звонок корректно, ничего не упуская. Г) Для улучшения можно было спросить: «Когда вам удобнее разобрать памятку — сразу или после изучения?» — для ускорения цикла. | DC8: [00:11:55.341] – Клиент – Хорошо, спасибо, я вам отправлю сейчас почту. [00:12:00.751] – Продавец – Спасибо, спасибо большое. До свидания. | DD8: Резюме | DE8: А) Содержание: Продавец поприветствовал Клиента, представился, объяснил цель первого контакта, подробно рассказал о предстоящей встрече с бератером, типовых вопросах, снял возможные волнения, представил и пообещал отправку материалов (памятка, тренажер), уточнил детали предстоящей встречи и этапы процесса после и в случае отказа, договорился о дальнейшем контакте и открыл канал связи до термина. Б) Реакция Клиента: Заинтересованная, местами с лёгкими сомнениями, вопросы — уточняющего характера, в остальном позитивная. К презентации, УТП и предложениям — реакция благожелательная. В) Достигнутые договорённости: Следующий звонок 18-го числа, отправка памятки и тренажёра по почте/WhatsApp, постоянная поддержка менеджера. Попытка зафиксировать следующий шаг — есть. | DF8: [00:00:00.031] – Продавец – Алло, алло. Добрый вечер, здравствуйте. ... [00:04:11.378] – Продавец – Хорошо, тогда 18-го числа с вами свяжусь... [00:11:38.878] – Продавец – обязательно пишите в WhatsApp. Я с вами до дня термина по всем вопросам отвечу, помогу, сориентирую вас. | DG8: Рекомендация | DH8: 1. Не спросил прямо, удобно ли говорить в начале. – Цитата: «...будет у вас буквально 10 минут, чтобы мы обсудили...» Контекст: Менеджер сразу начал разговор, Клиент не выразил возражения. Лучше: «Скажите, пожалуйста, удобно ли вам сейчас говорить или выберем другое время?» Эффект: Создаёт больше уважения к времени Клиента. 2. Ни разу не обратился к Клиенту по имени (если оно известно). – Контекст: Только представился, имя клиента не использовал. Лучше: Перед фиксацией следующего шага или поддержки использовать имя загружает доверие. 3. Минимизировать длинные монологи — например, при объяснениях, где можно чаще проверять понимание Клиента («Поясните, пожалуйста, есть ли вопросы по этому пункту?»). | DI8: [00:00:22.520] – Продавец – ...будет у вас буквально 10 минут, чтобы мы обсудили дальнейшие шаги перед самим термином? | DJ8: Рекомендация | DK8: 1. Поддержка уверенности и открытие перспектив («Я уверена, что так и будет»). – Контекст: В начале разговора Клиент высказал надежду, Менеджер моментально поддержала. Эффект: Снимает тревожность, создаёт тёплый, доверительный тон. Техника: Эмпатичная поддержка (массовая техника). 2. Подробное описание процесса и снятие страха экзамены («Берайтер это не экзаменатор... хочется именно увидеть вашу мотивацию»). – Контекст: Ожидание встречи у Клиента. Эффект: Снижает стресс у большинства клиентов. Техника: Нормализация страха, storytelling (массовая техника). 3. Подробное объяснение всех содержательных тем (в том числе, что именно будет в памятке). – Контекст: При объяснении подготовки. Эффект: Клиент понимает пользу, меньше рисков «проиграть» термины из-за незнания. Техника: Edu-сопровождение, детализация (массовая техника). | DL8: [00:00:22.520] – Продавец – Я уверена, что так и будет..., [00:02:49.169] – Продавец – Здесь важно понимать, что Бирайтер это не экзаменатор, он не ставит вам оценок за немецкий язык, он хочет именно увидеть вашу мотивацию и осознанный выбор..., [00:02:49.169] – Продавец – Здесь очень важно именно, что в документе содержится 19 самых частых вопросов Бирайтера с готовыми вариантами ответа на немецком... | DM8: Рекомендация | DN8: А) Психологический и демографический портрет: Возраст выше среднего (есть взрослый сын), тип «новичок с опытом», уверенность высокая (не волнуется), доверяет профессионалам, позитивный, с юмором, не конфликтен. Проявил инициативу — уточняет даты, детали процесса. Личных данных (имени) нет. Б) Цели и приоритеты: Работать в Германии по профессии, повысить квалификацию, быть энергичной, хочет стабильности и трудоустройства («...хочется выйти на работу и работу иметь нормальную»), опасения по возрасту, но в целом стремление к саморазвитию. В) Для маркетинга: Упор на снятие страха из-за возраста/рода занятий, подробные описания процессов и выгод курса, кейсы для зрелых учеников, дополнительные (конструктивные) социальные гарантии. Сегмент масштабируем — зрелые эмигранты, ранее работавшие в смежных сферах. | DO8: [00:01:21.076] – Клиент – Абсолютно нет. [00:05:52.526] – Продавец – То, что у вас энергии много, это факт, что вы готовы работать... [00:10:02.292] – Клиент – Понятно, что я же здесь пополнить бюджет, конечно же. Я шучу. В принципе, конечно, хочется выйти на работу и работу иметь нормальную. | DP8: 1 | DQ8: Разговор завершён логично: участники попрощались и подтвердили следующий шаг, технических сбоев или резких обрывов не было. | DR8: [00:12:00.751] – Продавец – Спасибо, спасибо большое. До свидания. | DS8: 1 | DT8: Это звонок первого контакта: Менеджер поздравил с назначенным термином, объяснил свою роль как постоянного сопровождающего до дня термина, описал первый процесс подготовки, впервые сообщил о памятке, тренажёре и договорился о дальнейшей подготовке и следующем звонке. | DU8: [00:00:00.031] – Продавец – ...Поздравляю вас с назначенным термином, это большой уже шаг вперед. ...Я буду с вами на протяжении всего времени до самого дня термина. ...Скажите, пожалуйста, будет у вас буквально 10 минут, чтобы мы обсудили дальнейшие шаги перед самим термином?, [00:02:49.169] – Продавец – ...я вам отправлю такой скелет на памятку..., [00:04:11.378] – Продавец – Хорошо, тогда 18-го числа с вами свяжусь, если у вас какие-то будут вопросы. | DV8: =IFERROR(SUM(AC8,AF8)/COUNT(AC8,AF8),"Приветствие") -> Приветствие | DW8: =IFERROR(SUM(AI8,AL8)/COUNT(AI8,AL8),"Снятие первичного волнения") -> Снятие первичного волнения | DX8: =IFERROR(SUM(AO8,AR8,AU8)/COUNT(AO8,AR8,AU8),"Презентация предстоящего термина") -> Презентация предстоящего термина | DY8: =IFERROR(SUM(AX8,BA8,BD8)/COUNT(AX8,BA8,BD8),"Отправка материалов") -> Отправка материалов | DZ8: =IFERROR(SUM(BG8,BJ8,BM8)/COUNT(BG8,BJ8,BM8),"Вопросы и возражения Клиента") -> Вопросы и возражения Клиента | EA8: =IFERROR(SUM(BP8,BS8)/COUNT(BP8,BS8),"Следующие шаги") -> Следующие шаги | EB8: =IFERROR(SUM(BV8,BY8,CB8,CE8)/COUNT(BV8,BY8,CB8,CE8),"Завершение разговора") -> Завершение разговора | EC8: =IFERROR(SUM(CH8,CK8)/COUNT(CH8,CK8),"Стандарты общения") -> Стандарты общения | ED8: =IFERROR(SUM(CN8,CQ8,CT8)/COUNT(CN8,CQ8,CT8),"Критические ошибки") -> Критические ошибки | EE8: =IFERROR(SUM(#REF!,#REF!)/COUNT(#REF!,#REF!),"Экспертный блок") -> Экспертный блок | EF8: =IFERROR(SUM(#REF!,#REF!,#REF!,#REF!)/COUNT(#REF!,#REF!,#REF!,#REF!),"Рекомендации") -> Рекомендации | EG8: =IFERROR(SUM(#REF!,#REF!)/COUNT(#REF!,#REF!),"Фильтры") -> Фильтры | EH8: 1 | EI8: 1 | EJ8: 12.1416 | EK8: 1 | EL8: 1 | EM8: {=IFERROR( SUM(IF({AD8,AG8,AJ8,AM8,AP8,AS8,AV8,AY8,BB8,BE8,BK8,BN8,BQ8,BT8,BW8,BZ8,CC8,CF8,CI8,CL8}="",hidden!C8,{AD8,AG8,AJ8,AM8,AP8,AS8,AV8,AY8,BB8,BE8,BK8,BN8,BQ8,BT8,BW8,BZ8,CC8,CF8,CI8,CL8}+hidden!D8)) / COUNT(IF({AD8,AG8,AJ8,AM8,AP8,AS8,AV8,AY8,BB8,BE8,BK8,BN8,BQ8,BT8,BW8,BZ8,CC8,CF8,CI8,CL8}="",hidden!C8,{AD8,AG8,AJ8,AM8,AP8,AS8,AV8,AY8,BB8,BE8,BK8,BN8,BQ8,BT8,BW8,BZ8,CC8,CF8,CI8,CL8}+hidden!D8)) ,"")} -> 1 | EN8: =I8/hidden!A8 -> 12.1416
A9: 9 | B9: 172582537_1888448089_d2d5dc | C9: https://docs.google.com/document/d/1xovHUf_PGNn0SoWf8PLfPx-cDaOIVUzk7YhJn20oMbo/edit?usp=drivesdk | D9: 2026-03-09 - 2026-03-15 | E9: 77151 | F9: 2026-03-16 02:28:13 | G9: 2026-03-16 10:04:09 | H9: 2026.03 | I9: 500.544 | J9: 1 | K9: 2026-03-11 | L9: 501 | M9: 172582537_1888448089 | N9: +491608414606, Статус: Разговор состоялся | O9: CallGear | P9: 12:37:08+01:00 | Q9: Исходящий | R9: 12 | S9: 21200922 | T9: Yuliia Postolnik | U9: Контакт | V9: 2026-03-11T12:33:07+01:00 | W9: 18379670 | X9: Автосделка: Заявка - https://sternmeister.de/study | Y9: Бух Бератер | Z9: Доведение | AA9: https://sternmeister.kommo.com/leads/detail/18379670 | AB9: 14817967 | AC9: Кристина Никоненко | AD9: 1 | AE9: Менеджер корректно поздоровалась, представилась по имени и указала компанию: 'Меня зовут Кристина, я менеджер сопровождения компании Штернмастер.' Приветствие и представление были полными и понятными. | AF9: [00:00:02.88] – Продавец – Юлия, добрый день, здравствуйте., [00:00:05.62] – Продавец – Меня зовут Кристина, я менеджер сопровождения компании Штернмастер. | AG9: 1 | AH9: Менеджер обозначила цель звонка – подготовка к термину, назвала длительность ('буквально 5-10 минут') и уточнила, удобно ли клиенту говорить: 'Подскажите, пожалуйста, будет у вас буквально 5-10 минут для этого шага?' | AI9: [00:00:05.62] – Продавец – ...Поздравляю вас с назначенным термином, это уже серьезный шаг вперед. Подскажите, пожалуйста, будет у вас буквально 5-10 минут для этого шага?, [00:00:17.82] – Продавец – ...моя задача помочь вам подготовиться, ответить на вопросы, сделать так, чтобы вы пришли на встречу с драйвом спокойно и уверенно. | AJ9: 1 | AK9: Менеджер прямо спросила про эмоциональное состояние: 'Подскажите, пожалуйста, есть ли какие-то волнения по поводу предстоящего термина?' | AL9: [00:00:17.82] – Продавец – Подскажите, пожалуйста, есть ли какие-то волнения по поводу предстоящего термина? | AM9: 1 | AN9: Клиент сообщил, что волнения нет. Менеджер учла это и продолжила поддерживать клиента, объяснив, что будет помогать на всех этапах, и подкрепила поддержкой: 'моя задача помочь вам подготовиться... сделать так, чтобы вы пришли на встречу с драйвом спокойно и уверенно.' | AO9: [00:00:33.99] – Клиент – Нет., [00:00:17.82] – Продавец – ...моя задача помочь вам подготовиться, ответить на вопросы, сделать так, чтобы вы пришли на встречу с драйвом спокойно и уверенно. | AP9: 1 | AQ9: Менеджер объяснила, кто такой бератер, его задачи и цель встречи: 'Поскольку термин темного обучения, то бирайтер – это ваш консультант в джоб-центре, и его задача – это убедиться, что выбранный вами курс повышения квалификации действительно поможет вам выйти на рынок труда, то есть финальная точка курса – это именно трудоустройство.' | AR9: [00:01:05.68] – Продавец – ...бирайтер – это ваш консультант в джоб-центре, и его задача – это убедиться, что выбранный вами курс повышения квалификации действительно поможет вам выйти на рынок труда, то есть финальная точка курса – это именно трудоустройство. | AS9: 1 | AT9: Менеджер привела примеры вопросов: 'почему вы выбрали именно бухгалтерию? Знаете ли вы содержание курса, сколько он длится? ...где планируете после обучения работать.' Объяснила также, зачем их задают: проверить мотивацию и осознанность выбора. | AU9: [00:01:19.78] – Продавец – ...Типичные вопросы, которые задают бирайтеры: почему вы выбрали именно бухгалтерию? Знаете ли вы содержание курса, сколько он длится?... где планируете после обучения работать. | AV9: 1 | AW9: Менеджер снижала тревожность, говоря, что бератер не экзаменатор: 'он не ставит вам оценки за немецкий, он хочет увидеть вашу мотивацию и осознанность выбора. Поэтому главное говорить уверенно, четко и пусть даже где-то простые фразы.' | AX9: [00:01:42.26] – Продавец – ...бирайтер это не экзаменатор, он не ставит вам оценки за немецкий, он хочет увидеть вашу мотивацию и осознанность выбора. Поэтому главное говорить уверенно, четко и пусть даже где-то простые фразы. | AY9: 1 | AZ9: Менеджер сказала, что отправит памятку и обозначила канал – e-mail: 'Я вам на почту отправлю нашу специальную памятку. Она называется «Подготовка к термину».' | BA9: [00:01:42.26] – Продавец – ...Я вам на почту отправлю нашу специальную памятку. Она называется «Подготовка к термину». | BB9: 1 | BC9: Менеджер подробно описала, что содержит памятка: 19 типовых вопросов, готовые ответы, транскрипции, переводы, фразы-спасатели, раздел с ловушками бератера. Также объяснила пользу: памятка поможет подготовиться к встрече. | BD9: [00:01:42.26] – Продавец – ...В нем собраны 19 самых частых вопросов, подбираются с готовыми вариантами ответов на немецком языке, транскрипциями и переводом на русский язык.[00:02:16.30] – Продавец – В памятке также есть раздел «Фразы-спасатели», ...и еще есть очень важный раздел, это типичные ловушки бирайтера, там написаны каверзные вопросы... и правильная стратегия ответов. | BE9: 1 | BF9: Менеджер сообщила о тренажёре и его назначении: 'Я вам отправлю дополнительно запятый чат-бот. Это разработанный нашей компанией тренажер. Он выступает в роли бирайтера, задает от лица бирайтера вопросы, и можно еще таким образом по памятке отвечать.' | BG9: [00:03:21.12] – Продавец – И еще я вам отправлю дополнительно запятый чат-бот. Это разработанный нашей компанией тренажер. Он выступает в роли бирайтера, задает от лица бирайтера вопросы, и можно еще таким образом по памятке отвечать. | BH9: Тегов нет. | BI9: Клиент напрямую не озвучивал классические возражения, а скорее констатировал мнение о 'тяжелом джоб-центре' и 'берейтере', а также поделился опытом мужа. Прямые страхи или сомнения не были выражены. | BJ9: [00:04:30.84] – Клиент – У нас тяжелый джоб-центр, конечно. И бирайтер тоже очень тяжелый. | BL9: Клиент не озвучивал прямых возражений или тревог, требующих отдельной проработки менеджером. | BO9: Клиент не задавал прямых вопросов продавцу, скорее рассказывал о своем опыте и делился комментариями. | BQ9: 1 | BR9: Менеджер предложила связаться 13-го числа (конкретная дата, перед термином), чтобы обсудить, появились ли вопросы, и согласовала время (вторая половина дня). | BS9: [00:07:46.84] – Продавец – И также, Илья, подскажите, пожалуйста, если мы, например, с вами сядемся 13-го числа, узнать, есть ли у вас какие-то вопросы., [00:07:55.42] – Продавец – Это будет пятница., [00:07:57.82] – Клиент – Да, только во вторую половину дня. | BT9: 1 | BU9: Менеджер сообщила, что клиент может задавать вопросы в любое время: 'Если такие вопросы появятся, вы можете всегда мне написать, спросить, да, в любое время.' | BV9: [00:07:30.38] – Продавец – Если такие вопросы появятся, вы можете всегда мне написать, спросить, да, в любое время. | BW9: 1 | BX9: Менеджер спросила, как клиент себя чувствует после разъяснения процесса: 'Подскажите, пожалуйста, Юлия, вот после того, как я вам рассказала, как будет проходить встреча на термине, как вы себя чувствуете? Стало ли более понятно, чего ждать на самом термине?' | BY9: [00:05:30.29] – Продавец – Подскажите, пожалуйста, Юлия, вот после того, как я вам рассказала, как будет проходить встреча на термине, как вы себя чувствуете? Стало ли более понятно, чего ждать на самом термине? | BZ9: 1 | CA9: Менеджер объяснила дальнейшие шаги: документы передают в Agentur für Arbeit, будет новый термин, важно попросить сделать это быстро, чтобы не пропустить начало потока. | CB9: [00:06:20.98] – Продавец – ...Если термин пройдет успешно, ваши документы должны передать в агент Феррарбайд. Бирайтер вам об этом скажет. Далее они назначат новый термин, и важно попросить сделать это как можно быстрее, чтобы не пропустить начало потока. | CC9: 0 | CD9: Менеджер не озвучила, что делать в случае отказа в финансировании курса, таких инструкций и советов в разговоре не было. | CF9: 0 | CG9: Менеджер не сообщил о дальнейшем сопровождении после термина и не проговорил о планах связаться после прохождения встречи с бератером. | CI9: 1 | CJ9: Менеджер трижды использовал имя клиента ('Юлия'), регулярно употреблял вежливые слова ('пожалуйста', 'спасибо', 'замечательно'), стиль общения был дружелюбным и поддерживающим, диалог шел на позитивной ноте, даже на опасениях о 'тяжелом джоб-центре' менеджер сохраняла спокойствие. | CK9: [00:00:02.88] – Продавец – Юлия, добрый день, здравствуйте., [00:05:30.29] – Продавец – Подскажите, пожалуйста, Юлия, вот после того, как я вам рассказала... , [00:07:46.84] – Продавец – И также, Илья, подскажите, пожалуйста, если мы, например, с вами сядемся 13-го числа... | CL9: 1 | CM9: Менеджер активно поддерживал контакт, часто использовал 'угу', 'замечательно', раскрывал высказывания клиента (про опыт мужа, опасения по джоб-центру) и перефразировал, а также подтверждал, что слышит и понимает позицию клиента. | CN9: [00:01:04.06] – Клиент – Угу., [00:03:44.62] – Клиент – Конечно., [00:05:30.29] – Продавец – ...как вы себя чувствуете?... , [00:04:55.32] – Клиент – Вот... Ну, вот всем предлагают курсы, я же говорю... , [00:05:06.58] – Продавец – Туда всех. Я поняла. Ну, хорошо. | CO9: 1 | CP9: Критических ошибок не зафиксировано: Продавец не критиковал ни курс, ни компанию, не дезинформировал, не склонял к отказу, закрепил следующий шаг. | CQ9: [00:07:54.06] – Продавец – если мы, например, с вами сядемся 13-го числа, узнать, есть ли у вас какие-то вопросы. | CR9: 1 | CS9: Ложной информации не было, грубости и перебивания тоже, Менеджер корректно и вежливо поддерживала диалог, информация соответствовала действительности. | CT9: [00:07:54.06] – Продавец – если мы, например, с вами сядемся 13-го числа, узнать, есть ли у вас какие-то вопросы. | CU9: 1 | CV9: Ни одной фразы, попадающей под юридическую опасность, не прозвучало. Гарантий трудоустройства не давалось, лицензии и сертификаты не упоминались в запрещенном ключе, внутренних сведений не раскрывалось. | CX9: 1 | CY9: A) Скрипт: 1) Приветствие и представление, 2) Программирование разговора (цель, длительность, удобно ли говорить), 3) Уточнение эмоционального состояния, 4) Объяснение сути встречи с бератером, 5) Конкретные типовые вопросы, 6) Снятие страха (бирэйтер не экзамен), 7) Обещание памятки и тренажёра, 8) Договоренность о повторном контакте, 9) Открытый канал для вопросов. Переключения между темами плавные: от технического (термин, вопросы, поддержка), к эмоциональному (опыт мужа, сложности с джоб-центром), затем административное завершение. Б) Особенности: Живое слушание, поддержка клиента, нет давления, много разъяснений. В) Сработали: Клиент соглашался, реагировал 'да', 'конечно', задавал вопросы и комментировал - интерес был. Договорились о повторном контакте. Г) Не сработало: Нет реакции на сомнения по сложностям с центром и отсутствует информация на случай отказа. | CZ9: [00:00:02.88] – Продавец – Юлия, добрый день, здравствуйте., [00:01:05.68] – Продавец – ...бирайтер – это ваш консультант в джоб-центре..., [00:03:21.12] – Продавец – ...я вам отправлю дополнительно запятый чат-бот..., [00:07:54.06] – Продавец – если мы, например, с вами сядемся 13-го числа, узнать, есть ли у вас какие-то вопросы. | DA9: 1 | DB9: А) Разговор завершён с явной договорённостью о дальнейшем контакте – клиент не отказался, не ушёл в сомнения. Б) На этапе закрытия клиент дал согласие на подготовку к термину и подтвердил удобство следующего контакта. В) Продавец закрепил следующий шаг, не допустил ошибок. Г) Дополнительно: если бы продавец уточнил, есть ли технические вопросы или напомнил о преимуществах курса, можно было бы усилить уверенность. | DC9: [00:07:54.06] – Продавец – если мы, например, с вами сядемся 13-го числа, узнать, есть ли у вас какие-то вопросы., [00:08:09.10] – Продавец – Все хорошо, тогда информацию вам отправляю по подготовке к термину на почту и с вами на связи. | DD9: Резюме | DE9: А) Содержание: Звонок посвящён поздравлению клиента с назначением термина, объяснению встреч с бератером, типовых вопросов, снятию волнения, презентации вспомогательных материалов (памятка, тренажёр), обмену опытом о Jobcenter и договорённости о следующем звонке. Б) Реакция клиента: В целом спокойная, временами взволнованная (опыт с 'тяжёлым джоб-центром'), но открыт к поддержке, проявляет участие в диалоге, соглашается на обучение и контакт. В) Договорённости: Согласован следующий созвон (13-е число, вторая половина дня), клиент знает, что может обращаться с вопросами, обещаны материалы для подготовки. | DG9: Рекомендация | DH9: 1. Не дано инструкции на случай отказа: Клиент делится опытом трудностей с мужем и тяжелым джоб-центром – важно было проговорить шаги, что делать при отказе ('Если бератер откажет, важно узнать причину и сразу связаться с нами, мы подскажем, как поступить'). 2. Нет обещания сопровождения после термина: После обсуждения дальнейших шагов не сказано, что менеджер поддержит после встречи ('Я обязательно свяжусь после термина – обсудим, что делать дальше'). 3. Не усилены сильные стороны программы на фоне скепсиса клиента: Когда клиент говорит о малой пользе курсов, следовало акцентировать преимущества, реальную помощь в трудоустройстве и успехи других учеников ('Наши выпускники устраиваются на работу, а программа – максимально практикоориентированная'). Ожидаемый эффект: Больше уверенности у клиента, выше лояльность и снятие страха отказа. | DJ9: Рекомендация | DK9: 1. Акцент на простоту и поддержку: 'Главное говорить уверенно, четко и пусть даже где-то простые фразы.' – Сработало на снижение тревожности, массовая техника. 2. Подробное структурное объяснение памятки: Пролонгация ценности инструмента подготовки до термина, хорошо работает на повышение вовлечённости, массовая техника. 3. Живое активное слушание: Менеджер часто подхватывает, вставляет согласительные реплики, зеркалит опасения ('Я поняла...'). Это помогает удерживать клиента, индивидуальная техника. Вывод: Эти подходы способствуют доверию, пониманию и мотивируют клиента. | DM9: Рекомендация | DN9: A) Психологический и демографический портрет: Юлия — рассудительная, немного тревожная, с опытом в системе Jobcenter (оперирует терминологией, знает, как проходят процессы), склонна доверять опыту близких (мужа), осторожна, но не пессимистична. Поведение — уточняющее, время от времени комментирует, делится опытом, соглашается на предложенные шаги. Б) Цели: Получить профессию (бухгалтер), повысить уровень возможностей на рынке, уйти со статуса Jobcenter, минимизировать риск отказа системы. Болит страх отказа в обучении, переживания из-за 'жёстких' бератеров. Хочет заранее подготовиться и избежать ошибок мужа. В) Для маркетинга: Работают подробные памятки, симуляторы, личная поддержка. Важно заранее объяснять последовательность шагов и показывать реальные кейсы успеха. Триггер: 'тяжёлый центр', 'пример мужа', необходимость сопровождения после одобрения. Важно масштабировать персональное сопровождение и 'чек-листы'. | DP9: 1 | DQ9: Разговор был полноценным, участники попрощались, никаких технических сбоев или резких обрывов не было. Диалог завершен фразами прощания. | DR9: [00:08:16.10] – Продавец – До свидания. | DS9: 1 | DT9: Звонок — первый контакт сопровождения: есть поздравление с термином, обещана поддержка до дня встречи, первичное объяснение процесса, впервые анонсируется памятка и тренажёр, согласуется следующий контакт. Характерные признаки первого контакта налицо. | DU9: [00:00:05.62] – Продавец – Меня зовут Кристина, я менеджер сопровождения компании..., [00:00:17.82] – Продавец – Я буду с вами на связи до самого дня термина..., [00:01:04.06] – Продавец – Тогда кратко расскажу, как обычно проходит встреча с бирайтером именно на тему обучения, хорошо?, [00:07:54.06] – Продавец – если мы, например, с вами сядемся 13-го числа, узнать, есть ли у вас какие-то вопросы. | DV9: =IFERROR(SUM(AC9,AF9)/COUNT(AC9,AF9),"Приветствие") -> Приветствие | DW9: =IFERROR(SUM(AI9,AL9)/COUNT(AI9,AL9),"Снятие первичного волнения") -> Снятие первичного волнения | DX9: =IFERROR(SUM(AO9,AR9,AU9)/COUNT(AO9,AR9,AU9),"Презентация предстоящего термина") -> Презентация предстоящего термина | DY9: =IFERROR(SUM(AX9,BA9,BD9)/COUNT(AX9,BA9,BD9),"Отправка материалов") -> Отправка материалов | DZ9: =IFERROR(SUM(BG9,BJ9,BM9)/COUNT(BG9,BJ9,BM9),"Вопросы и возражения Клиента") -> Вопросы и возражения Клиента | EA9: =IFERROR(SUM(BP9,BS9)/COUNT(BP9,BS9),"Следующие шаги") -> Следующие шаги | EB9: =IFERROR(SUM(BV9,BY9,CB9,CE9)/COUNT(BV9,BY9,CB9,CE9),"Завершение разговора") -> Завершение разговора | EC9: =IFERROR(SUM(CH9,CK9)/COUNT(CH9,CK9),"Стандарты общения") -> Стандарты общения | ED9: =IFERROR(SUM(CN9,CQ9,CT9)/COUNT(CN9,CQ9,CT9),"Критические ошибки") -> Критические ошибки | EE9: =IFERROR(SUM(#REF!,#REF!)/COUNT(#REF!,#REF!),"Экспертный блок") -> Экспертный блок | EF9: =IFERROR(SUM(#REF!,#REF!,#REF!,#REF!)/COUNT(#REF!,#REF!,#REF!,#REF!),"Рекомендации") -> Рекомендации | EG9: =IFERROR(SUM(#REF!,#REF!)/COUNT(#REF!,#REF!),"Фильтры") -> Фильтры | EH9: 0.92 | EI9: 0.875 | EJ9: 8.3424 | EK9: 1 | EL9: 1 | EM9: {=IFERROR( SUM(IF({AD9,AG9,AJ9,AM9,AP9,AS9,AV9,AY9,BB9,BE9,BK9,BN9,BQ9,BT9,BW9,BZ9,CC9,CF9,CI9,CL9}="",hidden!C9,{AD9,AG9,AJ9,AM9,AP9,AS9,AV9,AY9,BB9,BE9,BK9,BN9,BQ9,BT9,BW9,BZ9,CC9,CF9,CI9,CL9}+hidden!D9)) / COUNT(IF({AD9,AG9,AJ9,AM9,AP9,AS9,AV9,AY9,BB9,BE9,BK9,BN9,BQ9,BT9,BW9,BZ9,CC9,CF9,CI9,CL9}="",hidden!C9,{AD9,AG9,AJ9,AM9,AP9,AS9,AV9,AY9,BB9,BE9,BK9,BN9,BQ9,BT9,BW9,BZ9,CC9,CF9,CI9,CL9}+hidden!D9)) ,"")} -> 0.9 | EN9: =I9/hidden!A9 -> 8.3424
A10: 10 | B10: 195647960_1888488554_0dea20 | C10: https://docs.google.com/document/d/1p4wIhZz3YmgC4w6VTDcik3i13vR9Ez85Xn0IPnYN4mA/edit?usp=drivesdk | D10: 2026-03-09 - 2026-03-15 | E10: 77146 | F10: 2026-03-16 02:25:55 | G10: 2026-03-16 10:09:24 | H10: 2026.03 | I10: 1232.064 | J10: 1 | K10: 2026-03-11 | L10: 1232 | M10: 195647960_1888488554 | N10: +491702069627, Статус: Разговор состоялся | O10: CallGear | P10: 15:01:37+01:00 | Q10: Исходящий | R10: 12 | S10: 19689885 | T10: Liudmyla Melnychuk | U10: Контакт | V10: 2026-03-11T11:20:06+01:00 | W10: 18378980 | X10: Автосделка: Lead from: https://sternmeister.de/education?utm_source=facebook&utm_medium=site_nikita&utm_campaign=03-11-2025+%7C+Nikita+%7C+Lead+Optimization%7Caid%7C120233304256270678&utm_content=cid%7C120233194575060678%7Cgid%7C120233194575120678%7Cadsn% | Y10: Бух Бератер | Z10: Консультация перед термином ДЦ | AA10: https://sternmeister.kommo.com/leads/detail/18378980 | AB10: 14817967 | AC10: Кристина Никоненко | AD10: 1 | AE10: Менеджер корректно поприветствовал клиента, представился и обозначил компанию SternMeister. В начале разговора Менеджер сказал: "Меня зовут Кристина, я менеджер сопровождения компании Stern Master." Таким образом, приветствие и представление выполнены полностью. | AF10: [00:00:07.38] – Продавец – Меня зовут Кристина, я менеджер сопровождения компании Stern Master. Подскажите, пожалуйста, вам удобно сейчас разговаривать? | AG10: 1 | AH10: Менеджер объяснил цель звонка (подготовка к термину, помощь перед встречей с бератором) и уточнил, удобно ли клиенту разговаривать. Длительность или формат разговора подробно не были озвучены, но цель и удобство общения обозначены чётко. | AI10: [00:00:07.38] – Продавец – Меня зовут Кристина, я менеджер сопровождения компании Stern Master. Подскажите, пожалуйста, вам удобно сейчас разговаривать?, [00:00:17.86] – Продавец – Отлично. Еще раз поздравлю вас с назначенным термином. Я буду с вами на связи до самого дня термина. Моя задача помочь вам подготовиться, ответить на все вопросы и сделать так, чтобы вы пришли на встречу с бератором спокойно, уверенно. | AJ10: 1 | AK10: Менеджер прямо спросил, как клиент себя чувствует, есть ли волнение по поводу термина. Вопрос был задан полноценно и корректно. | AL10: [00:00:17.86] – Продавец – Подскажите, пожалуйста, Людмила, как вы себя чувствуете перед термином? Есть ли волнение по поводу термина? | AM10: 1 | AN10: Клиент выразил, что нет волнения, но нужны чёткие инструкции и информация. Менеджер поддержал клиента, нормализовал возможные переживания и выразил уверенность в помощи: "Беспокоиться – это нормально, волноваться перед термином. Практически все наши студенты переживают... Вы будете не одна, мы проведем вас через весь этот процесс." Поддержка оказана грамотно. | AO10: [00:00:38.42] – Клиент – У меня нет волнения, мне просто надо четко говорить., [00:01:29.20] – Продавец – Я вас поняла. Ну да, конечно, бухгалтерия, медицина – это достаточно активная физическая работа. На самом деле, тут… Конечно, бухгалтерия вам подойдет гораздо больше. Беспокоиться – это нормально, волноваться перед термином. Практически все наши студенты переживают перед термином по обучению, но я хочу вас успокоить. Мы готовим к таким встречам. Каждый день у нас накоплен огромный опыт. Вы будете не одна, мы проведем вас через весь этот процесс. | AP10: 1 | AQ10: Менеджер подробно объяснил, кто такой бератер, какова цель встречи, и что ожидается от клиента: проверка, поможет ли курс выйти на рынок труда, оценка мотивации и осознанности выбора курса. | AR10: [00:04:38.46] – Продавец – ...Я кратко расскажу, как обычно проходят встречи с бирайтером, чтобы у вас была полная картина. Бирайтер – это консультант, и его задача – убедиться, что выбранный вами курс повышения квалификации действительно поможет вам выйти на рынок труда, то есть конечная точка – трудоустройство. | AS10: 1 | AT10: Менеджер перечислил примеры типичных вопросов, которые может задать бератер: почему выбрана бухгалтерия, содержание курса, длительность, планы на работу, уровень немецкого и пр. Также пояснил, зачем эти вопросы задаются. | AU10: [00:04:38.46] – Продавец – ...Будут задавать вопросы о вашей мотивации, опыте, и в целом даже о самом курсе: что будет на курсе. Типичные вопросы, которые задают: почему вы выбрали именно бухгалтерию, знаете ли вы содержание курса, сколько он длится, где планируете работать после обучения — по ценам будущего обязательно. | AV10: 1 | AW10: Менеджер объяснил, что встреча с бератером не экзамен, а проверка мотивации и осознанности выбора. Подчеркнул, что даже A2 по языку допустим, главное — уверенность и желание учиться. | AX10: [00:04:38.46] – Продавец – Здесь важно понимать, что бирайтер, не экзаменатор, он не ставит оценки за немецкий, он хочет увидеть вашу мотивацию и осознанный выбор, который приведет к результату. Даже если ваш немецкий пока на уровне А2, это нормально. Главное говорить уверенно, четко, пусть даже простыми фразами. | AY10: 1 | AZ10: Менеджер сообщил о намерении отправить памятку с подготовкой к термину и обозначил канал отправки (e-mail). | BA10: [00:04:38.46] – Продавец – Для подготовки к встрече с бирайтером мы можем с вами сделать следующее: я вам отправлю памятку на e-mail. | BB10: 1 | BC10: Менеджер подробно объяснил, что памятка содержит: 19 типовых вопросов с ответами, транскрипцию, перевод, фразы 'спасатели', типичные ловушки, кадровые вопросы, подробную инструкцию по использованию. Проговорил пользу для подготовки. | BD10: [00:04:38.46] – Продавец – Это подготовка к термину, документ, разработанный нами для будущих студентов, где собрано 19 самых частых вопросов от бирайтера с готовыми ответами на немецком языке, транскрипцией и переводом на русский. В памятке есть раздел «Фразы спасателей» — они помогут, если не поняли вопрос или нужно время подумать, что можно вставить между диалогом. Еще раздел – типичные ловушки бирайтера: кадровые вопросы и правильные стратегии ответа. Там есть вопросы на тему охвата языка для работы в бухгалтерии, например, у вас не носитель языка, и стратегия ответа: «Да, мой язык не идеальный, но в курсе есть 86 часов узконаправленного немецкого, я продолжаю совершенствовать языковые навыки». То есть это не просто «развиваюсь и становлюсь лучше», а факт того, что у вас есть 86 часов узконаправленного немецкого с необходимой терминологией. Без немецкого никуда. Мы в Германии, и улучшаем себя постоянно. Поэтому важна правильная формулировка ответов. Рекомендую изучать памятку в спокойном темпе, не надо спешить, главное понять логику ответов и несколько раз проговорить ключевые фразы. В памятке есть подробная инструкция, как с ней работать. | BE10: 1 | BF10: Менеджер сообщил о наличии и отправке тренажера (IGPT-чатбота) для ролевой отработки, проговаривания вслух и закрепления материала. | BG10: [00:08:04.54] – Продавец – Чтобы вы хорошо звучали, я вам также отправлю разработанный нашей компанией тренажер – IGPT-чатбот, который задает вопросы от лица бирайтера, и вы сможете устно проговорить по памятке подготовки к термину, чтобы звучать уверенно и чтобы ваш бирайтер понимал, что у вас становитесь лучше, что для него важно и на это он акцентирует внимание. | BH10: Тегов нет | BI10: Клиент озвучивал следующие сомнения и опасения: Низкий уровень немецкого, Страх отказа в финансировании, Непонимание процесса Jobcenter, Сложность вопросов на термине, Недостаточная подготовка. Цитаты по ним приведены ниже. | BJ10: [00:00:38.42] – Клиент – У меня нет волнения, мне просто надо четко говорить. У меня А2. Мне надо узнать, что я должна ей говорить вообще..., [00:01:29.20] – Клиент – ...Но она говорит, ну у тебя 80 %, как мы должны тебя оплачивать? Ну, обучение, да?..., [00:04:28.28] – Клиент – Она говорит, нет, тебе не подходит, куда тебе учиться., [00:04:28.28] – Клиент – ...Я не знаю, как с ней говорить, чтобы она поняла. А по-другому, у меня А2., [00:12:30.20] – Клиент – Все равно все зависит от них – хотят они это сделать или не хотят. | BK10: 1 | BL10: Менеджер корректно реагировал на озвученные сомнения и опасения Клиента: объяснял процесс, снижал тревожность, давал поддержку, инструменты для уверенности, отдельные разъяснения по языку, пошаговое сопровождение. | BM10: [00:01:29.20] – Продавец – Я вас поняла..., [00:04:38.46] – Продавец – ...он хочет увидеть вашу мотивацию..., [00:08:42.84] – Продавец – Как вы думаете, вам поможет такая памятка?, [00:12:37.86] – Продавец – Давайте так договоримся. Мы со своей школой предоставляем отличный курс, после которого есть реальный шанс трудоустроиться...., [00:14:16.28] – Продавец – Хотелось бы проговорить важный момент: если термин пройдет успешно, документы должны передать в агентство фрербайт, бирайтер об этом скажет, дальше назначат новый термин, важно попросить сделать его как можно быстрее, чтобы не пропустить дату начала потока. | BN10: 1 | BO10: Клиент задавал вопросы по процедуре, по документам и по тому, что говорить бератеру. Менеджер дал развернутые ответы на каждый заданный вопрос. | BP10: [00:10:57.44] – Клиент – Мне надо этот ангибот полностью распечатать, потому что социальный работник сделал термин к ним..., [00:14:34.92] – Клиент – Нужно распечатать 21 лист, дать мотивационное письмо, выучить вопросы и ответы, а потом какие документы приложить и что ей сказать. Передайте, пожалуйста, в агентуру фюрербайт, или я жду вашего ответа, как? | BQ10: 1 | BR10: Менеджер обозначил следующий контакт: позвонит 13-го числа узнать, как дела и как идёт подготовка, что конкретизирует срок и цель следующей связи. | BS10: [00:09:50.20] – Продавец – У вас термин назначен на 17 число. Подскажите, пожалуйста, если я свяжусь с вами 13-го числа, узнать, как у вас идут дела? Удобно будет?, [00:10:03.46] – Клиент – Да, конечно. | BT10: 1 | BU10: В конце разговора Менеджер сообщил, что можно обращаться в WhatsApp при возникновении вопросов, уточняя канал и подтверждая готовность поддержать Клиента. | BV10: [00:19:53.14] – Продавец – Если не придет информация по подготовке к термину, напишите в WhatsApp, что ничего не пришло, я переправлю. | BW10: 1 | BX10: Менеджер прямо спросил, как клиент себя чувствует после разговора, и стало ли ему понятнее, чего ждать на термине и появилось ли больше уверенности. | BY10: [00:12:08.12] – Продавец – Скажите, пожалуйста, как вы себя чувствуете после нашего разговора? Стало ли более понятно, чего ждать на термине? Появилась ли больше уверенности? | BZ10: 1 | CA10: Менеджер объяснил, что происходит после успешной встречи: документы передаются в агентство фюрербайт, назначается новый термин, и важно просить ускорить процесс. | CB10: [00:14:16.28] – Продавец – Хотелось бы проговорить важный момент: если термин пройдет успешно, документы должны передать в агентство фрербайт, бирайтер об этом скажет, дальше назначат новый термин, важно попросить сделать его как можно быстрее, чтобы не пропустить дату начала потока. | CC10: 1 | CD10: Менеджер дал чёткую инструкцию: в случае отказа выяснить причину, узнать позицию бератера, что потребуется для финансирования, и расписал возможные сценарии решения. | CE10: [00:16:07.32] – Продавец – Если трейтер отказывается финансировать, во время термина нужно выяснить причину и спросить, как она видит ваше развитие, чего не хватает для финансирования. Например, не хватает языка – тогда пройдете курсы. Или она скажет, у вас язык достаточный для работы – хорошо, я пойду оставлять отклики и через две недели посмотрим. Если возьмут – отлично, не возьмут – вернемся к ангиботу и обучению. Важно уйти с термином с полной ясностью, какое решение принято и как на него повлиять. | CF10: 1 | CG10: Менеджер сообщил, что будет на связи с Клиентом, и после термина, в случае вопросов, также предложил дополнительный контакт и поддержку со стороны коллег. | CH10: [00:19:53.14] – Продавец – Я отправлю материалы, 13-го числа свяжусь, узнаю, как дела, есть ли вопросы. В дальнейшем у вас будет встреча с моим коллегой перед термином, я сообщу. 16-го с вами свяжется ведущий специалист джоб-центра Максим... | CI10: 1 | CJ10: Менеджер корректно обращался к клиенту по имени, был максимально вежлив, использовал тёплый тон и слова благодарности, поддерживал эмоционально, подстраивался по стилю и не проявлял сухости или высокомерия. | CK10: [00:00:17.86] – Продавец – ...Подскажите, пожалуйста, Людмила... | CL10: 1 | CM10: Менеджер активно слушал, подтверждал понимание, повторял за клиентом уточнения, реагировал на мысли клиента собственным перефразированием, поддерживал живой диалог. | CN10: [00:01:29.20] – Продавец – Я вас поняла...., [00:04:36.72] – Продавец – Пока по уроку именно. Хорошо, я вас поняла. Хотя бы есть четкое понятие, по какой позиции попытаются отказаться, и стратегию мы можем проработать., [00:12:08.12] – Продавец – Скажите, пожалуйста, как вы себя чувствуете после нашего разговора? Стало ли более понятно... | CO10: 1 | CP10: Критических ошибок не выявлено. Продавец не высказывался негативно о курсе или компании, не отговаривал, не "сливал" клиента без шага, не искажал информации о лицензировании/сертификатах, а завершил разговор закреплением следующего шага и поддержкой. | CQ10: [00:09:50.20] – Продавец – У вас термин назначен на 17 число. Подскажите, пожалуйста, если я свяжусь с вами 13-го числа, узнать, как у вас идут дела? Удобно будет? | CR10: 1 | CS10: Ошибок, способных подорвать доверие, не зафиксировано. Информация дана корректно, поведение было уважительным, не было перебиваний или давления. Продавец не вводил в заблуждение по процессам, сертификатам и лицензиям. | CU10: 1 | CV10: Ни одной критической ошибки с точки зрения закона не обнаружено. Продавец не давал ложных гарантий трудоустройства, не раскрывал внутреннюю информацию, по лицензии AZAV не лгал, работу организации описывал корректно. | CX10: 1 | CY10: А) Скрипт: 1. Приветствие, представление, проверка удобства - [00:00:07.38]; 2. Обозначение цели разговора – подготовка к термину, помощь клиенту, 3. Уточнение эмоционального состояния и ожиданий по термин, 4. Прояснение проблем и запроса клиента, 5. Нормализация тревожности, 6. Описание роли бератера, формата встречи, типовых вопросов, 7. Блок о памятке – что это, зачем, предложение отправить, 8. Описание тренажёра, 9. Обсуждение вопросов клиента по документам и процедурам, 10. Резюмирование шагов, 11. Договоренность о следующем звонке и поддержке, 12. Прощание. Б) Особенности: последовательный, логичный, хорошо структурированный путь, без больших отходов от темы; пропусков нет. В) Сработали: клиент стал задавать вопросы, проявил интерес к памятке и тренажёру, согласился на дальнейшие действия. Г) Не сработало: клиент остался неуверен по поводу решения бератера, но это не связано со структурой, а с внешними барьерами. | DA10: 1 | DB10: А) Разговор завершился фиксированием плана действий (что и когда делать), подтверждением готовности, и договорённостью о следующем контакте. Б) На этапе закрытия клиент не озвучил отказ, не проявил сомнения, принял рекомендации и подтвердил готовность двигаться далее. В) Продавец не допустил ошибок: всё резюмировал, повторил шаги и оставил канал связи открытым. Г) Тактика: добавить ещё больше подчеркивания выгод курса, чтобы повысить уверенность клиента, но формально закрытие выполнено. Клиент остался на связи, готов к дальнейшим действиям. | DC10: [00:20:22.68] – Клиент – Хорошо, спасибо большое вам., [00:20:24.62] – Продавец – Хорошо, все хорошо, до свидания. | DD10: Резюме | DE10: А) Содержание: звонок полностью посвящён подготовке к термину с бератером; обсуждались цели встречи, возможные вопросы, опасения клиента, документы и процесс (памятка, тренажёр, мотивация, действия после термина, порядок документов и отказа, сопровождение). Б) Реакция: Клиент информирован, заинтересован, местами выражает беспокойство и скепсис, но принимает рекомендации, уточняет детали. На предложения соглашается, инициативу проявляет умеренно. В) Договорённости: зафиксирован следующий звонок, шаги по документам/памятке/тренажёру, канал связи WhatsApp открыт, подробно проговорен план до/после термина. | DG10: Рекомендация | DH10: 1. Недостаточно акцентировать сильные стороны курса конкретно для кейса клиента: можно было чаще подчёркивать персональные выгоды, связанные с инвалидностью, прошлым опытом клиента (лучшее – внутри мотивационного блока). 2. Иногда не углубляет анализ отказов/барьеров бератора: следовало бы детальнее спросить, какие именно аргументы бератор приводил, где клиент теряет уверенность. 3. Не делал попыток смоделировать ситуация отказа в процессе: мог добавить вопросы — 'Если всё-таки получите отказ, что для вас будет критично?' 4. Не дал пошагового алгоритма: вместо 'можно распечатать 21 лист', дать чёткий чек-лист: 'Документы: памятка, ангибот, мотивационное письмо, что сказать. Следующие действия...'. Ожидаемый эффект: увеличение доверия и восприятия курса как индивидуального решения, снижение тревожности, повышение мотивации к активному участию в процессе, проактивное управление возражениями. | DJ10: Рекомендация | DK10: 1. Снятие тревожности через нормализацию: "Беспокоиться – это нормально, практически все наши студенты переживают..." После этого клиент более открыто делится мыслями – техника массовая, нормализация эмоций. 2. Презентация памятки как готового решения: "Я вам отправлю памятку... где собрано 19 самых частых вопросов с ответами..." Это создало для клиента ощущение структуры и уверенности – техника массовая, value presentation. 3. Открыть канал и резюмировать поддержку: "Если не придет информация... напишите в WhatsApp..." – индивидуальная техника, подчёркивает вовлечённость и готовность помогать. Все техники можно обучать массово. Они повышают лояльность, снижают тревожность и делают компанию более клиентоориентированной. | DM10: Рекомендация | DN10: А) Клиентка Людмила, зрелого возраста, ориентирована на получение понятных, структурированных инструкций, умеренно уверена, склонна к сомнениям относительно успешности процесса из-за медицинских ограничений и языка. Требует поддержки и ясности во всех шагах, чётко объясняет свои боли (здоровье, язык, непонимание процесса Jobcenter). Инициативна в вопросах, но склонна перекладывать ответственность на бератора. Б) Цели: переобучение на бухгалтера в Германии (медицинский труд невозможен), желание работать по менее физически активной профессии, снизить риски отказа, получить подтверждение своих возможностей, интегрироваться в рынок. Боли: низкий язык, страх отказа, недоверие к работникам институций. Сроки — как можно быстрее, чтобы использовать шанс сейчас. Мотивация: "Я бы хотела быть бухгалтером...", "Я не могу физический труд выполнять..." В) Для маркетинга: использовать чёткие инструкции, шаги, кейсы клиентов-женщин 60+ с инвалидностью, рамки A2–B1, подчёркивать сопровождение и помощь в документах, отдельное внимание психологическому сопровождению. Каналы: WhatsApp, печатные памятки. Сегмент — уязвимые группы, для которых важен психоэмоциональный сервис и подстройка под медлительный/вдумчивый пользовательский путь. | DP10: 1 | DQ10: Разговор завершился логично и полноценно: участники попрощались, диалог дошёл до конца, технических сбоев не было. | DR10: [00:20:24.62] – Продавец – Хорошо, все хорошо, до свидания., [00:20:28.88] – Клиент – До свидания. | DS10: 1 | DT10: Звонок явно относится к этапу первого контакта сопровождения: прозвучали поздравления с назначением термина, менеджер объяснил формат встречи с бератером, впервые подробно описал памятку, а также договорился о следующем контакте. Обсуждается основная цель – подготовка к термину, работа с возражениями и тревожностями клиента. | DU10: [00:00:17.86] – Продавец – Отлично. Еще раз поздравлю вас с назначенным термином. Я буду с вами на связи до самого дня термина. Моя задача помочь вам подготовиться... | DV10: =IFERROR(SUM(AC10,AF10)/COUNT(AC10,AF10),"Приветствие") -> Приветствие | DW10: =IFERROR(SUM(AI10,AL10)/COUNT(AI10,AL10),"Снятие первичного волнения") -> Снятие первичного волнения | DX10: =IFERROR(SUM(AO10,AR10,AU10)/COUNT(AO10,AR10,AU10),"Презентация предстоящего термина") -> Презентация предстоящего термина | DY10: =IFERROR(SUM(AX10,BA10,BD10)/COUNT(AX10,BA10,BD10),"Отправка материалов") -> Отправка материалов | DZ10: =IFERROR(SUM(BG10,BJ10,BM10)/COUNT(BG10,BJ10,BM10),"Вопросы и возражения Клиента") -> Вопросы и возражения Клиента | EA10: =IFERROR(SUM(BP10,BS10)/COUNT(BP10,BS10),"Следующие шаги") -> Следующие шаги | EB10: =IFERROR(SUM(BV10,BY10,CB10,CE10)/COUNT(BV10,BY10,CB10,CE10),"Завершение разговора") -> Завершение разговора | EC10: =IFERROR(SUM(CH10,CK10)/COUNT(CH10,CK10),"Стандарты общения") -> Стандарты общения | ED10: =IFERROR(SUM(CN10,CQ10,CT10)/COUNT(CN10,CQ10,CT10),"Критические ошибки") -> Критические ошибки | EE10: =IFERROR(SUM(#REF!,#REF!)/COUNT(#REF!,#REF!),"Экспертный блок") -> Экспертный блок | EF10: =IFERROR(SUM(#REF!,#REF!,#REF!,#REF!)/COUNT(#REF!,#REF!,#REF!,#REF!),"Рекомендации") -> Рекомендации | EG10: =IFERROR(SUM(#REF!,#REF!)/COUNT(#REF!,#REF!),"Фильтры") -> Фильтры | EH10: 1 | EI10: 1 | EJ10: 20.5344 | EK10: 1 | EL10: 1 | EM10: {=IFERROR( SUM(IF({AD10,AG10,AJ10,AM10,AP10,AS10,AV10,AY10,BB10,BE10,BK10,BN10,BQ10,BT10,BW10,BZ10,CC10,CF10,CI10,CL10}="",hidden!C10,{AD10,AG10,AJ10,AM10,AP10,AS10,AV10,AY10,BB10,BE10,BK10,BN10,BQ10,BT10,BW10,BZ10,CC10,CF10,CI10,CL10}+hidden!D10)) / COUNT(IF({AD10,AG10,AJ10,AM10,AP10,AS10,AV10,AY10,BB10,BE10,BK10,BN10,BQ10,BT10,BW10,BZ10,CC10,CF10,CI10,CL10}="",hidden!C10,{AD10,AG10,AJ10,AM10,AP10,AS10,AV10,AY10,BB10,BE10,BK10,BN10,BQ10,BT10,BW10,BZ10,CC10,CF10,CI10,CL10}+hidden!D10)) ,"")} -> 1 | EN10: =I10/hidden!A10 -> 20.5344
A11: 11 | B11: 195632147_1888462211_3a5171 | C11: https://docs.google.com/document/d/1KY5kMVEPyjyCLwzDMr43SctxhfW73oscSFg0rpfYcRs/edit?usp=drivesdk | D11: 2026-03-09 - 2026-03-15 | E11: 77145 | F11: 2026-03-16 02:25:29 | G11: 2026-03-16 10:14:52 | H11: 2026.03 | I11: 1495.584 | J11: 1 | K11: 2026-03-11 | L11: 1496 | M11: 195632147_1888462211 | N11: +4917675746733, Статус: Разговор состоялся | O11: CallGear | P11: 12:59:34+01:00 | Q11: Исходящий | R11: 12 | S11: 20771650 | T11: Anzhelika Mikhalko | U11: Контакт | V11: 2026-03-11T12:44:07+01:00 | W11: 18379788 | X11: Автосделка: Lead from: https://sternmeister.de/education?utm_source=google&utm_medium=cpc&utm_campaign=cid|23263737483|aid|784226841342&utm_content=gid|187111781725|phr|kwd-2346663020134|dvc|m|pos||mch|b|src||reg|9060719|rin||kw|%D0%BA%D1%83%D1%80%D1%81%D | Y11: Бух Бератер | Z11: Консультация перед термином ДЦ проведена | AA11: https://sternmeister.kommo.com/leads/detail/18379788 | AB11: 14817967 | AC11: Кристина Никоненко | AD11: 1 | AE11: Менеджер корректно поприветствовал клиента, представился по имени и назвал компанию. Он начал разговор с приветствия и обозначил свою роль и компанию. | AF11: [00:00:02.107] – Продавец – Анжелика, добрый день, здравствуйте., [00:00:06.974] – Продавец – Меня зовут Кристина, я менеджер сопровождения компании Штернмастер. | AG11: 1 | AH11: Менеджер обозначил цель звонка (помощь в подготовке к термину), упомянул длительность разговора (5-10 минут), уточнил возможность обсуждения дальнейших шагов. Однако не спросил прямо, удобно ли клиенту говорить, но клиент сам подтвердил готовность и выделил время. | AI11: [00:00:13.865] – Продавец – Подскажите, пожалуйста, будет у вас буквально 5-10 минут для того, чтобы мы с вами дальнейшие шаги обсудили? | AJ11: 1 | AK11: Менеджер прямо спросил о самочувствии клиента и волнении перед встречей с бератером. | AL11: [00:00:39.638] – Продавец – Подскажите, пожалуйста, в первую очередь, как вы себя чувствуете, есть ли волнение перед встречей с бирайтером? | AM11: 1 | AN11: Менеджер поддержал клиента и нормализовал его переживания, объяснив, что волнение типично и что у компании есть опыт поддержки клиентов на этом этапе. | AO11: [00:01:13.686] – Продавец – Ничего страшного, это абсолютно нормально., [00:01:16.810] – Продавец – Почти все наши ближайшие студенты переживают перед термином по поводу обучения, но я хочу вас успокоить., [00:01:27.281] – Продавец – Вы будете не одна, мы пройдем вас через весь этот путь. | AP11: 1 | AQ11: Менеджер подробно объяснил, кто такой бератер, его роль и цель встречи, а также финальную задачу курса. | AR11: [00:01:40.625] – Продавец – Бирайтер – это ваш консультант, соответственно, в JobCenter, и его задача – убедиться, что выбранный вами курс повышения квалификации действительно поможет вам выйти на рынок труда, то есть именно трудоустройство – финальная точка курса. | AS11: 1 | AT11: Менеджер перечислил типичные вопросы от бератера: о мотивации, содержании курса, длительности, планах работы после курса. | AU11: [00:01:59.388] – Продавец – Типичные вопросы, которые задают бирайтеры: почему вы выбрали именно бухгалтерию, знаете ли вы содержание курса, сколько он длится, где планируете работать после обучения, то есть картину будущего спросить. | AV11: 1 | AW11: Менеджер объяснил, что встреча не экзамен, оценок за немецкий не ставят, и важно говорить уверенно даже простыми фразами, что заметно снижает страх клиента. | AX11: [00:02:17.840] – Продавец – важно обратить внимание, что бирайтер, да, то есть он не ваш экзаменатор, то есть он не будет ставить вам оценок за немецкий язык, он хочет увидеть вашу мотивацию..., [00:02:39.053] – Продавец – Даже если ваш немецкий не на уровне носителя, это нормально., [00:02:42.217] – Продавец – Главное говорить уверенно и четко, пусть даже простыми фразами. | AY11: 1 | AZ11: Менеджер сообщил об отправке памятки и указал канал (e-mail). | BA11: [00:03:31.509] – Продавец – чтобы вы могли начать уже готовиться сегодня, я прямо сейчас отправлю вам на e-mail нашу специальную памятку. | BB11: 1 | BC11: Менеджер подробно объяснил структуру и разделы памятки: типовые вопросы, варианты ответов, транскрипция, фразы-спасатели, ловушки от бератера, стратегии ответов. | BD11: [00:03:38.224] – Продавец – Называется она «Подготовка к термину»., [00:03:43.615] – Продавец – В нем собраны 19 самых частых вопросов, подобраны варианты ответов на немецком языке и транскрипции с переводом на русский язык., [00:03:56.482] – Продавец – Также в памятке есть раздел «Фразы спасателей»..., [00:04:06.556] – Продавец – И еще один важный раздел – это типичные ловушки от бирайтера. | BE11: 1 | BF11: Менеджер сообщил об отправке тренажёра (чат-бот ЧапиТи) для практики подготовки к термину, описал его суть и назначение. | BG11: [00:05:49.033] – Продавец – Это разработанный в нашей компании тренажер., [00:05:51.177] – Продавец – Это и ЧапиТи чат-бот., [00:05:55.482] – Продавец – Он задает вопросы от имени бирайтера., [00:05:57.764] – Продавец – И вы сможете вслух как раз-таки проговорить там всю памятку, от себя что-то добавить на немецком. | BH11: Страх перед термином, Низкий уровень немецкого, Страх отказа в финансировании, Другое | BI11: Клиент озвучивал страх и волнение перед термином, сомнение по поводу уровня немецкого, опасение по поводу возможного отказа из-за возраста/квалификации, также приводил примеры дискриминации. | BJ11: [00:00:45.425] – Клиент – Честно говоря, да. (про волнение), [00:02:47.283] – Клиент – У меня совсем не так, бэ анси..., [00:08:11.003] – Клиент – Если они не понимают по-русски, я бы там рассказала..., [00:11:48.746] – Клиент – Я только единственное, что волнуюсь, потому что у нас тут тоже девчонка, но она младше меня на два года, он мне сказал, что ты сильно старая..., [00:14:35.486] – Клиент – Не будет времени. | BK11: 1 | BL11: На каждое сомнение Менеджер подробно реагировал: поддерживал, объяснял нормативность волнения, снимал страх оценки языка, объяснял процесс в случае отказа, уверял, что возраст не аргумент. Это снижало тревожность и проясняло ситуацию для Клиента. | BM11: [00:01:16.810] – Продавец – Почти все наши ближайшие студенты переживают перед термином по поводу обучения, но я хочу вас успокоить..., [00:02:39.053] – Продавец – Даже если ваш немецкий не на уровне носителя, это нормально., [00:12:41.312] – Продавец – У них там есть градация по возрасту, тут можете не переживать., [00:13:26.674] – Продавец – Вы в любом случае должны уйти с термина с полным пониманием того, что для вас играют термин и как вам дальше развиваться в стране. | BN11: 1 | BO11: Клиент задавала вопросы по поводу писем, мотивационного письма, действий при отказе, возможности запроса официального письма об отказе и получения финансирования. Менеджер на все вопросы отвечал подробно и разъяснял, как поступить. | BP11: [00:13:13.072] – Клиент – А как называется вот это письмо, что если они мне отказывают?... , [00:13:24.312] – Клиент – Да, можно, нужно. – ответ Продавца..., [00:20:41.878] – Продавец – Подскажите, пожалуйста, может быть, у вас есть какие-то вопросы об учении, сертификате, расписании?, [00:20:49.730] – Клиент – Нет, смотрите, я распечатала сертификаты, распечатала всё, что прислали. | BQ11: 1 | BR11: Менеджер договорился о следующем контакте: в пятницу перед термином будет звонок для проверки подготовки и обсуждения вопросов. | BS11: [00:07:21.581] – Продавец – Если с вами свяжется, например, в пятницу узнать, как у вас проходит подготовка к термину, если какие-то вопросы по обучению, удобно будет принять звонок?, [00:07:31.213] – Клиент – Конечно, конечно, да, в пятницу, да. | BT11: 1 | BU11: Менеджер сообщил о возможности обращаться при возникновении вопросов, а также предложил писать в чатах. | BV11: [00:13:13.528] – Продавец – Если у вас какие-то вопросы появятся, вы можете написать в чатах. | BW11: 1 | BX11: Менеджер спросил, стало ли понятнее, чего ждать на термине, и появилось ли больше уверенности. | BY11: [00:07:41.144] – Продавец – Стало ли вам более понятно, чего ждать на термине?, [00:07:43.586] – Продавец – Появилась ли больше уверенности? | BZ11: 1 | CA11: Менеджер подробно объяснил дальнейший процесс, что будет передача документов в агентство, необходимость быстро получить следующий термин, на что обратить внимание. | CB11: [00:08:22.036] – Продавец – Также я хотела бы проговорить важный момент. Если термин в JobCenter пройдет успешно, ваши документы должны передать агентам фюрарбайт... | CC11: 1 | CD11: Менеджер дал четкие инструкции, что делать в случае отказа — выяснить причину, узнать мнение бератера, что делать для получения финансирования, и предложил стратегию повторного обращения. | CE11: [00:08:49.934] – Продавец – если по каким-либо причинам бирайтер не одобрит финансирование нашего курса обучения, во время термина нужно выяснить причину и спросить, как он видит ваше развитие, чего, по его мнению, вам не хватает, чтобы получить финансирование. | CF11: 1 | CG11: Менеджер сообщил, что свяжется с клиентом после предстоящего созвона и будет сопровождать в дальнейшем — прямых фраз именно после термина нет, но по логике сопровождение обозначено. | CH11: [00:23:10.904] – Продавец – Хорошо, тогда 13-го мы продолжим. Я расскажу про дальнейшие наши шаги. | CI11: 1 | CJ11: Менеджер постоянно использовал вежливые слова (благодарю, пожалуйста, конечно), был доброжелателен, ни разу не был резок, цеплялся к деталям, проявлял уважение и искренний интерес, эмоционально поддерживал клиента. | CK11: [00:00:26.776] – Продавец – Хорошо, благодарю вас., [00:00:39.638] – Продавец – Подскажите, пожалуйста..., [00:21:10.279] – Продавец – Вот те два письма, которые мы вам отправили? Скорее всего, мотивационное письмо..., [00:23:00.067] – Продавец – Познакомьтесь с материалами, которые я отправила, у вас действительно все шансы на одобрение. | CL11: 1 | CM11: Менеджер активно слушал и реагировал на реплики Клиента, перефразировал, уточнял детали из речи Клиента, разбирал ситуации, проявлял эмпатию, оценивал опасения — всё это признаки активного слушания и отзеркаливания. | CN11: [00:01:13.686] – Продавец – Ничего страшного, это абсолютно нормально., [00:03:12.508] – Продавец – Самое главное, да., [00:23:00.067] – Продавец – Познакомьтесь с материалами, которые я отправила, у вас действительно все шансы на одобрение. | CO11: 1 | CP11: Ни одной из критических ошибок (негатив о курсе/компании, отговор, "слив" клиента, дезинформация по лицензиям или сертификату) не было допущено. Все шаги отработаны: фиксирован новый этап и следующие действия. | CQ11: [00:07:31.213] – Клиент – Конечно, конечно, да, в пятницу, да., [00:23:10.904] – Продавец – Хорошо, тогда 13-го мы продолжим. Я расскажу про дальнейшие наши шаги. | CR11: 1 | CS11: Менеджер давал корректные сведения о курсе и процессах, не вводил в заблуждение, не грубил, не обвинял, отвечал вежливо, без давления и высокомерия. | CT11: [00:12:41.312] – Продавец – У них там есть градация по возрасту, тут можете не переживать., [00:13:24.312] – Продавец – Да, можно, нужно. Вы в любом случае должны уйти с термина с полным пониманием. | CU11: 1 | CV11: Менеджер не делал юридически опасных заявлений, не давал гарантий, не разглашал внутреннюю информацию, не говорил о лицензии AZAV как о полностью имеющейся на момент звонка, не обещал 100% трудоустройство. | CW11: [00:16:13.190] – Продавец – У нас по трудоустройству, когда ребята устраивались, у нас идет 83-85% трудоустройства. | CX11: 1 | CY11: А) Продавец начал с приветствия и представления, затем озвучил цель звонка (подготовка к термину), уточнил, есть ли время у клиента. Далее снял волнение, объяснил формат встречи с бератером и ответил на волнующие вопросы по подготовке. Подробно описал памятку и тренажёр, обозначил, как они помогут, объяснил варианты развития событий после термина и в случае отказа. Зафиксировал дату следующего контакта и предложил поддержку. Б) Скрипт близок к идеальному: последовательность, построение диалога, высокая детализация, поддержка клиента. Не было пропусков этапов; нестандартных действий не выявлено. В) Клиент активно взаимодействовал, задал вопросы, уточнял детали, благодарил. Г) Клиент иногда высказывал опасения по возрасту, времени, языку, но получал корректную поддержку. Провалов или замалчиваний не было. Итог: вся модель поведения продавца была четко выстроена, клиент остался в процессе и с интересом. | CZ11: [00:00:02.107] – Продавец – Анжелика, добрый день, здравствуйте., [00:07:31.213] – Клиент – Конечно, конечно, да, в пятницу, да., [00:08:49.934] – Продавец – если по каким-либо причинам бирайтер не одобрит финансирование нашего курса обучения, во время термина нужно выяснить причину и спросить, как он видит ваше развитие... | DA11: 1 | DB11: А) Разговор завершился с зафиксированной договорённостью: клиент согласился на повторный контакт. Б) На этапе закрытия клиент сказал: "Конечно, конечно, да, в пятницу, да." В) Продавец не допустил ошибок: уточнил все детали, не было недостатка аргументов или поддержки. Г) В качестве дополнительной тактики можно использовать призыв к подготовке к собеседованию для закрепления уверенности клиента: "Давайте вместе пройдем парочку типовых вопросов до пятницы — вам будет еще спокойнее!". | DC11: [00:07:31.213] – Клиент – Конечно, конечно, да, в пятницу, да., [00:23:10.904] – Продавец – Хорошо, тогда 13-го мы продолжим. Я расскажу про дальнейшие наши шаги. | DD11: Резюме | DE11: А) Продавец представился и поздравил клиента с назначением термина, объяснил цель звонка — подготовка к собеседованию с бератером. Описал структуру встречи, типовые вопросы, отправил памятку и тренажёр для подготовки. Обсудил, что делать при отказе, и что делать после одобрения термином. Б) Клиент проявлял интерес, иногда высказывал сомнения (по возрасту, языку), живо участвовал, активно задавал вопросы. В) Были зафиксированы следующие шаги: дата созвона перед термином и открытый канал связи. Следующий контакт согласован. Интерес клиента явно присутствует, отказа не было. | DF11: [00:00:06.974] – Продавец – Меня зовут Кристина..., [00:07:31.213] – Клиент – Конечно, конечно, да, в пятницу, да., [00:23:10.904] – Продавец – Хорошо, тогда 13-го мы продолжим... | DG11: Рекомендация | DH11: 1. Уточнять удобство времени для разговора прямым вопросом. Цитата: "будет у вас буквально 5-10 минут..." — Лучше: "Скажите, удобно ли вам сейчас говорить?" Это поможет ещё точнее подстроиться под клиента. Ожидаемый эффект: меньшее напряжение, клиент чувствует уважение ко времени. 2. Чётко объяснять ценообразование и юридические формулировки по лицензиям и сертификатам (если клиент спросит). Фразы, связанных с AZAV и сертификатами, не было, но если бы клиент их затронул — стоит сделать подготовленный блок с официальными формулировками. 3. Призывать клиента к активному пробному озвучиванию ответов уже в ходе звонка — "Давайте прямо сейчас попробуем озвучить один из вопросов из памятки, я вам подскажу!" Ожидаемый эффект: закрепление уверенности, переход к действию во время звонка. | DI11: будет у вас буквально 5-10 минут для того, чтобы мы с вами дальнейшие шаги обсудили? | DJ11: Рекомендация | DK11: 1. Снятие тревоги и нормализация страхов (массовая техника). Фраза: "Ничего страшного, это абсолютно нормально. Почти все наши ближайшие студенты переживают перед термином по поводу обучения, но я хочу вас успокоить..." Контекст: после признания клиента в волнении. Это снижает сопротивление через нормализацию. 2. Детальное объяснение структуры и содержания памятки (массовая техника): "В нем собраны 19 самых частых вопросов, подобраны варианты ответов на немецком языке и транскрипции с переводом на русский язык..." Это формирует у клиента ощущение безопасности — он видит, что подготовка устроена системно. 3. Поддержка инициативы, акцент на успехах клиента (индивидуальная техника): "Познакомьтесь с материалами, которые я отправила, у вас действительно все шансы на одобрение. Ну, я не вижу пока причин для переживания." — позволяет клиенту почувствовать себя способным и успешным, что фиксирует его мотивацию и продолжение диалога. | DL11: [00:01:13.686] – Продавец – Ничего страшного, это абсолютно нормально..., [00:03:43.615] – Продавец – В нем собраны 19 самых частых вопросов..., [00:23:00.067] – Продавец – Познакомьтесь с материалами, которые я отправила, у вас действительно все шансы на одобрение. | DM11: Рекомендация | DN11: А) Клиент — женщина, Анжелика, вероятно 40+ лет (по упоминанию младших коллег и опасениям по возрасту), иммигрант, уровень немецкого: B1-B2. Темперамент — волнительный, но инициативный, ответственная (записывает информацию, самостоятельно печатает документы). Проявляет страхи и сомнения — по возрасту, по языку, боится отказа. Проявляет открытость поддержке, иногда иронизирует. Б) Цели — повысить квалификацию и получить финансирование курса, выйти на новую работу в Германии, интегрироваться в рынок труда. Боли — страх дискриминации по возрасту, страх не справиться из-за языка, боязнь потерять шанс на финансирование. Мотивация подтверждена фразами: "Я найду, что сразу я буду работать, это 100%". В) Для маркетинга работает упор на системную поддержку, гарантированную подготовку, подробные памятки, развернутую обратную связь; канал — телефон, e-mail. Бонусы типа дополнительных симуляторов, подробные инструкции, уверяющий подход — важны. Масштабировать можно: сегмент — женщины-иммигранты 35+. Триггеры — страх остаться без работы, желание интегрироваться, стремление к самостоятельности. | DO11: [00:00:20.045] – Клиент – Да, да, да, я уже приготовила тетрадочку, фручечку, я вас еще буду записывать., [00:11:48.746] – Клиент – Я только единственное, что волнуюсь, потому что у нас тут тоже девчонка, но она младше меня на два года..., [00:16:01.096] – Клиент – Это ощущение просто... Я найду, что сразу я буду работать, это 100%. | DP11: 1 | DQ11: Разговор был полноценным, завершен договоренностью, явного прерывания или сбоев не было. Участники не попрощались явно, но остановились на логичной фазе — передача к другому специалисту и следующее взаимодействие. | DR11: [00:23:42.708] – Клиент – Хорошо... | DS11: 1 | DT11: Это первый контакт сопровождения. Менеджер поздравил с назначением термина; объяснил, что его задача — вести клиента до встречи; подробно рассказал о формате термина; впервые по сути направил памятку и тренажер для подготовки; договорились о следующем контакте. Признаки: первичная консультация, обсуждение переживаний, знакомство с предстоящим процессом. | DU11: [00:00:10.179] – Продавец – Поздравляю вас с назначенным термином, это большой шаг вперед., [00:00:29.261] – Продавец – Я буду с вами на связи до самого дня термина, и моя задача помочь вам подготовиться..., [00:03:31.509] – Продавец – Я прямо сейчас отправлю вам на e-mail нашу специальную памятку., [00:07:21.581] – Продавец – Если с вами свяжется, например, в пятницу узнать, как у вас проходит подготовка к термину... | DV11: =IFERROR(SUM(AC11,AF11)/COUNT(AC11,AF11),"Приветствие") -> Приветствие | DW11: =IFERROR(SUM(AI11,AL11)/COUNT(AI11,AL11),"Снятие первичного волнения") -> Снятие первичного волнения | DX11: =IFERROR(SUM(AO11,AR11,AU11)/COUNT(AO11,AR11,AU11),"Презентация предстоящего термина") -> Презентация предстоящего термина | DY11: =IFERROR(SUM(AX11,BA11,BD11)/COUNT(AX11,BA11,BD11),"Отправка материалов") -> Отправка материалов | DZ11: =IFERROR(SUM(BG11,BJ11,BM11)/COUNT(BG11,BJ11,BM11),"Вопросы и возражения Клиента") -> Вопросы и возражения Клиента | EA11: =IFERROR(SUM(BP11,BS11)/COUNT(BP11,BS11),"Следующие шаги") -> Следующие шаги | EB11: =IFERROR(SUM(BV11,BY11,CB11,CE11)/COUNT(BV11,BY11,CB11,CE11),"Завершение разговора") -> Завершение разговора | EC11: =IFERROR(SUM(CH11,CK11)/COUNT(CH11,CK11),"Стандарты общения") -> Стандарты общения | ED11: =IFERROR(SUM(CN11,CQ11,CT11)/COUNT(CN11,CQ11,CT11),"Критические ошибки") -> Критические ошибки | EE11: =IFERROR(SUM(#REF!,#REF!)/COUNT(#REF!,#REF!),"Экспертный блок") -> Экспертный блок | EF11: =IFERROR(SUM(#REF!,#REF!,#REF!,#REF!)/COUNT(#REF!,#REF!,#REF!,#REF!),"Рекомендации") -> Рекомендации | EG11: =IFERROR(SUM(#REF!,#REF!)/COUNT(#REF!,#REF!),"Фильтры") -> Фильтры | EH11: 1 | EI11: 1 | EJ11: 24.9264 | EK11: 1 | EL11: 1 | EM11: {=IFERROR( SUM(IF({AD11,AG11,AJ11,AM11,AP11,AS11,AV11,AY11,BB11,BE11,BK11,BN11,BQ11,BT11,BW11,BZ11,CC11,CF11,CI11,CL11}="",hidden!C11,{AD11,AG11,AJ11,AM11,AP11,AS11,AV11,AY11,BB11,BE11,BK11,BN11,BQ11,BT11,BW11,BZ11,CC11,CF11,CI11,CL11}+hidden!D11)) / COUNT(IF({AD11,AG11,AJ11,AM11,AP11,AS11,AV11,AY11,BB11,BE11,BK11,BN11,BQ11,BT11,BW11,BZ11,CC11,CF11,CI11,CL11}="",hidden!C11,{AD11,AG11,AJ11,AM11,AP11,AS11,AV11,AY11,BB11,BE11,BK11,BN11,BQ11,BT11,BW11,BZ11,CC11,CF11,CI11,CL11}+hidden!D11)) ,"")} -> 1 | EN11: =I11/hidden!A11 -> 24.9264
A12: 12 | B12: 172077384_1888526478_5542ce | C12: https://docs.google.com/document/d/1v8XxAgDquXoiuwPCAcvZe-5-qjRiGruoINwj78q0UGw/edit?usp=drivesdk | D12: 2026-03-09 - 2026-03-15 | E12: 77150 | F12: 2026-03-16 02:27:48 | G12: 2026-03-16 10:01:26 | H12: 2026.03 | I12: 779.544 | J12: 1 | K12: 2026-03-11 | L12: 780 | M12: 172077384_1888526478 | N12: +491715543440, Статус: Разговор состоялся | O12: CallGear | P12: 17:22:06+01:00 | Q12: Исходящий | R12: 12 | S12: 20872070 | T12: Varvara | U12: Контакт | V12: 2026-02-24T13:51:14+01:00 | W12: 18141910 | X12: Автосделка: Facebook №3055911667938036 | Y12: Бух Бератер | Z12: Доведение | AA12: https://sternmeister.kommo.com/leads/detail/18141910 | AB12: 14817967 | AC12: Кристина Никоненко | AD12: 0 | AE12: Менеджер поприветствовал клиента по имени: 'Варвара, добрый день', однако не представился и не назвал компанию SternMeister. Клиенту не была обозначена ни должность, ни организация, из которой поступает звонок. Это критично, так как клиент должен чётко понимать, кто, откуда и с какой целью ему звонит. Рекомендация: всегда представляться полностью и сразу обозначать компанию. | AF12: [00:00:02.677] – Продавец – Варвара, добрый день. | AG12: 0 | AH12: Менеджер не обозначил цель звонка и не сообщил о предполагаемой длительности или формате разговора. Хотя он уточнил у клиента, удобно ли говорить ('Подскажите, пожалуйста, удобно вам разговаривать?'), цели и задачи звонка явно не обозначал, что снижает прозрачность коммуникации. Рекомендация: при начале разговора обязательно кратко объяснить цель звонка, возможно — примерное время. | AI12: [00:00:06.925] – Продавец – Подскажите, пожалуйста, удобно вам разговаривать? | AJ12: 1 | AK12: Менеджер прямо поинтересовался, как клиент себя чувствует перед термином, уточнил наличие волнительных моментов или опасений: 'Как у вас тут стоят дела с подготовкой?', 'Как себя чувствуете перед термином? Уже практически через неделю есть какие-то волнения, опасения, может быть, у вас?'. Это соответствует требованию критерия. | AL12: [00:01:13.909] – Продавец – Подскажите, пожалуйста, в целом, как себя чувствуете перед термином? Уже практически через неделю есть какие-то волнения, опасения, может быть, у вас? | AM12: 1 | AN12: Клиент прямо заявил, что не волнуется и чувствует себя уверенно, на что менеджер одобрительно и поддерживающе отреагировал: 'Это замечательно, что чувствуете себя хорошо, потому что главное — это все-таки мотивация и уверенность в себе.' Менеджер закрепил положительный настрой клиента. | AO12: [00:01:29.405] – Продавец – Это замечательно, что чувствуете себя хорошо, потому что главное — это все-таки мотивация и уверенность в себе. | AP12: 0 | AQ12: Менеджер не объяснил, кто такой бератер, не описал его роль или цель встречи. В разговоре отсутствует пояснение, что за встреча ожидает клиента, зачем она назначается или какую роль выполняет бератер. Рекомендация: четко проговаривать, что это консультант Jobcenter/Agentur für Arbeit и какова цель встречи. | AS12: 0 | AT12: Менеджер не рассказал, какие типичные вопросы можно ожидать от бератера на встрече. Нет приведённых примеров или даже намёков на возможные темы беседы с консультантом. Рекомендация: обязательно назвать 1-2 примера, чтобы клиенту было спокойнее и понятнее, к чему готовиться. | AV12: 0 | AW12: Менеджер не проговорил, что встреча с бератером не является экзаменом, не пояснил требований, не подчеркивал, что главное — мотивация, а не безукоризненное знание языка. Такой поддержки даже 'для протокола' не было озвучено, хотя это уменьшило бы потенциальную тревожность клиента. | AY12: 0 | AZ12: Менеджер не упоминал о такой памятке и не обещал её отправить. Клиент только сам отмечает, что памятка получена и изучена, но менеджер не подтверждает, что отправлял ее лично или через компанию, не проговаривает ни канал, ни содержание. Рекомендация: важно сообщить клиенту, что такая памятка была отправлена или будет отправлена повторно. | BA12: [00:00:45.726] – Продавец – А памятку, которую мы отправляли вам для подготовки перед термином? [00:00:50.757] – Клиент – Да, я тоже с ней ознакомлена. | BB12: 0 | BC12: Менеджер не объяснял, что входит в памятку, как она поможет клиенту, какие вопросы/ответы/подсказки там содержатся. Нет попытки повысить осознанность использования памятки и пользы от неё для подготовки. | BE12: 0 | BF12: Менеджер не говорил клиенту о тренажёре для подготовки к термину и не обещал отправить дополнительный инструмент (ссылку/ресурс/чат-бот и пр.), хотя был упомянут G5 Chatbot, но обсуждение его исходит от клиента. Важно проактивно предлагать такие инструменты. | BG12: [00:00:54.442] – Продавец – Ну и тоже G5 Chatbot немножко, да, тоже открывали, верно понимаю? | BH12: Тегов нет. | BI12: Клиент в разговоре не озвучивал никаких существенных возражений или страхов относительно процесса, финансирования, уровня знания немецкого и так далее. Основные вопросы клиента были о графике и специфике программ, но не в формате возражений. | BL12: Клиент не озвучивал возражений или сомнений в разговоре. Значимых волнений и страхов не зафиксировано, а вопрос о программе не нес формат возражения. | BN12: 1 | BO12: Клиент задавал вопросы и Менеджер давал развернутые и понятные ответы. Например, на вопросы о расписании ('А почему такой разрыв, например, с 9 до 15, а потом перерыв из 6 до 19?'), о возможностях пропуска занятий ('ну, вот у меня там термин к стоматологу, образно говоря, там на 12 часов, в такой ситуации?'), об используемых программах и разнице между ними для разных категорий бухгалтеров. На все вопросы клиен получил ясные ответы. | BP12: [00:01:50.066] – Клиент – А почему такой разрыв, например, с 9 до 15, а потом перерыв из 6 до 19? | BQ12: 1 | BR12: Менеджер согласовал с клиентом дату и примерное время следующего созвона, обозначил, что 19 числа в промежутке с 16 до 17 часов клиенту будет удобно, а также проговорил промежуточные и вспомогательные меры (например, выйти на связь 16 числа). Цель — финальная подготовка и обсуждение оставшихся вопросов до термина. | BS12: [00:10:36.240] – Клиент – Где-то в 16:30, после 16 часов, с 16 до 17 я свободна. | BT12: 1 | BU12: Менеджер сообщил клиенту о возможности писать в чат (WhatsApp), если понадобится помощь или появятся вопросы, потерялись какие-то материалы. Это поддерживает ощущение постоянной поддержки и снижает тревожность клиента. | BV12: [00:12:24.211] – Продавец – ...Если будут вопросы, пожалуйста, пишите также в чат, в WhatsApp, можете написать, что-то потеряли, какие-то материалы, Angebot, мало ли, какие-то сертификаты. Пишите, я с вами пришлю. | BW12: 0 | BX12: Менеджер не уточнил в конце разговора, стало ли клиенту понятнее, чего ожидать от предстоящего термина и чувствует ли он больше уверенности после диалога. Отсутствует финальный опрос о внутреннем состоянии клиента. | BZ12: 1 | CA12: Менеджер четко объяснил, что после успешного прохождения термина документы передаются в агентство по трудоустройству (Agentur für Arbeit), и что важно попросить назначить следующий термин как можно скорее, чтобы не пропустить начало курса. | CB12: [00:11:14.740] – Продавец – Да, все верно. После того, как вам одобрят термин в джоб-центре, придется успешно, ваши документы будут передаваться в агентство Феррабайт... | CC12: 0 | CD12: Менеджер не объяснил клиенту, что делать, если бератер не одобрит финансирование. Не прозвучала ни рекомендация выяснить причину, ни четкий план действий на случай отказа в выдаче Gutschein. Эта информация важна для полной подготовки к термину. | CF12: 1 | CG12: Менеджер сообщил, что будут сопровождать клиента не только до, но и после встречи с бератором, помогут подготовиться к следующему этапу, поддержат при необходимости получения Gutschein. | CH12: [00:11:56.640] – Продавец – ...По поводу термина в агентстве Феррабайт, также мы будем вас сопровождать, поможем подготовиться к встрече с агентством Феррабайт. У нас есть специалисты в этом направлении, кто поможет вам получить Gutschein. | CI12: 1 | CJ12: Менеджер не менее 3 раз обращался по имени ('Варвара'), постоянно использовал вежливую лексику ('прошу прощения', 'пожалуйста', 'я вас поняла'), был доброжелателен и чуток к эмоциям клиента. Эмоциональный фон был тёплым и поддерживающим, особенно с учетом спокойствия клиента. | CK12: [00:00:02.677] – Продавец – Варвара, добрый день. | CL12: 1 | CM12: Менеджер внимательно реагировал на реплики клиента ('Я вас поняла', 'Замечательно', 'То есть вы ничего не пропустите'), уточнял и отзеркаливал мысли ('Правильно понимаю...', 'То есть если идти на главного бухгалтера уже, то...'), диалог шёл в активной манере, не было длинных монологов. | CN12: [00:00:59.869] – Продавец – Ну да, то есть годовой отчет мы учим готовить, и там действительно разные окна, на обучении вам все это более подробно. | CO12: 1 | CP12: В разговоре не было негативных высказываний о компании/курсе, не было отговоров или потерь клиента без закрепления шага, не было ложной информации о лицензии AZAV и сертификатах. Менеджер предложил и зафиксировал следующий шаг, всё корректно. | CQ12: [00:12:24.211] – Продавец – Тогда 16 числа я с вами сижу. ... и уже Максим, тоже ведущий наш специалист, в это же время 19-го с вами свяжется. | CR12: 1 | CS12: Менеджер не допускал грубости, перебиваний, ошибок в подаче информации по курсу, сертификации или структуре. Все сведения были даны корректно и уважительно, негативного впечатления для клиента не возникло. | CU12: 1 | CV12: Нарушений законодательства замечено не было; менеджер не раскрывал внутренней информации, не давал гарантий трудоустройства, корректно выражался по вопросам лицензии и структуры курса. Все в рамках B2C-продажи услуг в Германии. | CX12: 1 | CY12: A) Скрипт: 1) Приветствие и прощение за задержку. 2) Проверка, удобно ли говорить. 3) Проверка готовности и ознакомления с материалами ('Удалось ли материалы открыть, посмотреть?'). 4) Проверка эмоционального состояния ('Как себя чувствуете, волнения, опасения?'). 5) Ответы на интересующие вопросы (расписание, специфика программы, перспективы). 6) Разъяснения по обучению, профессиональным перспективам. 7) Проговаривание логистики будущих шагов, согласование даты следующего контакта и открытого канала. 8) Поддержка, завершение разговора. Б) Не было явного роликалинга по этапам собеседования с бератором, не проговорены памятки и тренажёры. Был нестандартный акцент на личных историях клиентки. В целом, удерживал клиента в структуре процесса. В) Сработали: вопросы клиента по графику четко проработаны, позитивные реакции на гибкость; поддержка выбора клиента, обсуждение книги/опыта. Г) Не сработало — не проговорены детали по памятке, тренажеру, нет снятия тревожности (подробнее) о термине (хотя клиент не выражал волнения). | CZ12: [00:00:02.677] – Продавец – Варвара, добрый день. | DA12: 1 | DB12: А) Разговор завершился достижением договорённости о следующем контакте, клиент выразил согласие, отказов или неопределённости не было. Б) Клиент согласился с предложенным временем контакта, подтвердил готовность. В) Продавец закрепил шаг и предложил дополнительную возможность поддержки. Г) Эффективно: менеджер контролировал этап закрытия, сразу фиксировал следующее касание. | DC12: [00:12:50.220] – Клиент – Хорошо, спасибо вам большое. | DD12: Резюме | DE12: А) Содержание: В ходе звонка обсудили подготовку к предстоящему термину (встреча с бератором), проверили работу с обучающими материалами, книги, памятки, специфику расписания, ключевых программ, вопросы про карьерный путь, перспективы главного бухгалтера; затронули этапы после успешного термина и логику дальнейших контактов. Б) Реакция клиента: Клиент был спокоен, уверен, проявлял интерес, задавал уточняющие вопросы по расписанию, содержанию курса, карьерным перспективам, проявлял позитивное и открытое отношение. В) Достигнуты договоренности: Согласованы дата и время следующего контакта, закреплён канал связи для дополнительных вопросов, подтверждена поддержка до и после термина. | DG12: Рекомендация | DH12: Ошибка 1: Не определил и не сообщил цель звонка в начале. Лучше: 'Варвара, звоню из SternMeister — хочу помочь вам подготовиться к встрече с бератором, расскажу, на что обратить внимание.' Ожидаемый эффект: больше доверия, ощущение заботы. Ошибка 2: Не объяснил формат и цели встречи с бератором. Следовало бы кратко рассказать: 'Вас ждёт встреча с консультантом из Jobcenter, который оценит вашу мотивацию и знания о профессии.' Эффект: уменьшение тревожности, прояснение значимости этапа. Ошибка 3: Не рассказал и не предложил памятку или тренажёр проактивно. Лучше: 'Мы подготовили для вас чек-лист и тренажёр — отправлю в WhatsApp. Они помогут отрепетировать ответы.' Эффект: растёт лояльность и чувство поддержки. Ошибка 4: Не уточнил состояние клиента после разговора. Следовало бы завершить вопросом: 'Скажите, стало ли понятнее, что будет на встрече, уменьшилось ли волнение?' Эффект: более глубокий контакт, повышение уровня готовности клиента. Все пункты повышают вовлечённость и ощущение чёткого сопровождения клиента. | DJ12: Рекомендация | DK12: 1. Вежливое обращение и человеческое отношение — 'Прошу прощения', 'Я вас поняла', тёплое завершение. Сработало потому, что укрепляет расположение клиента (массовая техника). 2. Фокус на карьерной перспективе: разъяснение различий по программам, перспектив роста ('для главного бухгалтера отдельное обучение, карьерный путь до трёх лет') — работает на сохранение интереса тем, кто хочет дальше расти (массовая техника). 3. Открытый канал связи: предложение писать в чат при вопросах или проблемах ('пишите также в чат, в WhatsApp...') — снижает стресс и мотивирует к сотрудничеству (массовая техника). Индивидуальных техник, уникальных находок или ярких нестандартных ходов не наблюдается. | DM12: Рекомендация | DN12: А) Психологический/демографический портрет: Имя — Варвара. Клиент спокойна, аккуратна, рациональна, заранее изучила материалы, задаёт структурированные вопросы, не поддаётся волнению ('Нет, у меня нет волнений, опасений. Я всегда уверенно чувствую.'). Проявляет инициативу к уточнению технических (расписание), профессиональных (программы, перспективы карьерного роста) и процессных (этапы взаимодействия с бюраторами) аспектов. Б) Цели/приоритеты: Для неё важна системность, карьерные перспективы, возможно, стремится к стабильности и развитию — упоминает о возможностях дорасти до главбуха, стремится чётко разобраться в содержании обучения. Мотивация: профессиональное развитие, готова вникать в немецкую терминологию. В) Маркетинг/характеристики: Этим клиентам важно логичное построение коммуникации, детальные ответы, поддержка на каждом этапе, возможность обсуждать профессиональные нюансы и перспективы роста; УТП: гибкость расписания, разъяснения карьерных треков, поддержка с немецкой терминологией, безопасность (чёткие сценарии перехода между этапами бюрократии). В целом, сегмент зрелых, мотивированных, хорошо подготовленных клиентов, готовых вкладываться в развитие с расчётом на долгосрочные результаты. | DP12: 1 | DQ12: Разговор завершился полностью: участники попрощались, обменялись добрыми пожеланиями, выключились на позитивной ноте. Не было технических сбоев или резкого завершения — всё логично и структурировано. | DR12: [00:12:52.180] – Продавец – Хорошо, тогда доброго вам дня, до свидания. | DS12: 0 | DT12: По содержанию это не первый, а уже промежуточный контакт: Менеджер уточняет, что материалы уже были отправлены и изучены, памятка была получена и рассмотрена, вопросы по форматам и расписанию обсуждаются детально; обсуждены дальнейшие шаги с Jobcenter и Agentur für Arbeit. Признаков первого контакта нет, так как клиент уже разобрался в памятке, знаком с материалами и программой ('Да, удалось ознакомиться, я все материалы отправила', 'А памятку, которую мы отправляли вам для подготовки перед термином?', 'Да, я тоже с ней ознакомлена.'). | DU12: [00:00:35.397] – Клиент – Да, удалось ознакомиться, я все материалы отправила, те, которые прилагались для Jobcenter, я все отправила дураторам. | DV12: =IFERROR(SUM(AC12,AF12)/COUNT(AC12,AF12),"Приветствие") -> Приветствие | DW12: =IFERROR(SUM(AI12,AL12)/COUNT(AI12,AL12),"Снятие первичного волнения") -> Снятие первичного волнения | DX12: =IFERROR(SUM(AO12,AR12,AU12)/COUNT(AO12,AR12,AU12),"Презентация предстоящего термина") -> Презентация предстоящего термина | DY12: =IFERROR(SUM(AX12,BA12,BD12)/COUNT(AX12,BA12,BD12),"Отправка материалов") -> Отправка материалов | DZ12: =IFERROR(SUM(BG12,BJ12,BM12)/COUNT(BG12,BJ12,BM12),"Вопросы и возражения Клиента") -> Вопросы и возражения Клиента | EA12: =IFERROR(SUM(BP12,BS12)/COUNT(BP12,BS12),"Следующие шаги") -> Следующие шаги | EB12: =IFERROR(SUM(BV12,BY12,CB12,CE12)/COUNT(BV12,BY12,CB12,CE12),"Завершение разговора") -> Завершение разговора | EC12: =IFERROR(SUM(CH12,CK12)/COUNT(CH12,CK12),"Стандарты общения") -> Стандарты общения | ED12: =IFERROR(SUM(CN12,CQ12,CT12)/COUNT(CN12,CQ12,CT12),"Критические ошибки") -> Критические ошибки | EE12: =IFERROR(SUM(#REF!,#REF!)/COUNT(#REF!,#REF!),"Экспертный блок") -> Экспертный блок | EF12: =IFERROR(SUM(#REF!,#REF!,#REF!,#REF!)/COUNT(#REF!,#REF!,#REF!,#REF!),"Рекомендации") -> Рекомендации | EG12: =IFERROR(SUM(#REF!,#REF!)/COUNT(#REF!,#REF!),"Фильтры") -> Фильтры | EH12: 0.57692308 | EI12: 0.375 | EJ12: 12.9924 | EK12: 0 | EL12: 0 | EM12: {=IFERROR( SUM(IF({AD12,AG12,AJ12,AM12,AP12,AS12,AV12,AY12,BB12,BE12,BK12,BN12,BQ12,BT12,BW12,BZ12,CC12,CF12,CI12,CL12}="",hidden!C12,{AD12,AG12,AJ12,AM12,AP12,AS12,AV12,AY12,BB12,BE12,BK12,BN12,BQ12,BT12,BW12,BZ12,CC12,CF12,CI12,CL12}+hidden!D12)) / COUNT(IF({AD12,AG12,AJ12,AM12,AP12,AS12,AV12,AY12,BB12,BE12,BK12,BN12,BQ12,BT12,BW12,BZ12,CC12,CF12,CI12,CL12}="",hidden!C12,{AD12,AG12,AJ12,AM12,AP12,AS12,AV12,AY12,BB12,BE12,BK12,BN12,BQ12,BT12,BW12,BZ12,CC12,CF12,CI12,CL12}+hidden!D12)) ,"")} -> 0.5 | EN12: =I12/hidden!A12 -> 12.9924
